Workbook

Sheet 新初一数据看板
B2: 暑假整体汇总 | D2: =SUM(D4:D16)/2 | E2: =E8+E12+E16 | F2: =E2/(25*D2) | G2: =G8+G12+G16 | H2: =G2/E2 | I2: =SUM(I4:I16)/2 | J2: =I2/(E2+I2) | K2: =(K8*$E$8+K12*$E$12+K16*$E$16)/$E$2 | L2: =(L8*$E$8+L12*$E$12+L16*$E$16)/$E$2 | M2: =(M8*$E$8+M12*$E$12+M16*$E$16)/$E$2 | O2: 一期顾问转化合计 | Q2: =Q8+Q12+Q16 | R2: =SUM(R4:R16)/2 | S2: =Q2-R2 | T2: =S2*55% | U2: =SUM(U4:U16)/2 | V2: =U2/S2 | W2: =U2/T2 | X2: 学员意向分层(UV) | AL2: 零期顾问转化合计 | AN2: =AN8+AN12+AN16 | AO2: =SUM(AO4:AO16)/2 | AP2: =AN2-AO2 | AQ2: =AP2*55% | AR2: =SUM(AR4:AR16)/2 | AS2: =AR2/AP2 | AT2: =AR2/AQ2
B3: 老师看板 | C3: 学科 | D3: 班量 | E3: 在读PV | F3: 满班率 | G3: 暑续秋PV | H3: 转化率 | I3: 课前退PV | J3: 课前退率 | K3: 加微率 | L3: 首联率 | M3: vip入群率 | O3: 所属校区 | P3: 顾问 | Q3: 一期总PV | R3: 已转PV | S3: 应转PV | T3: 转化目标 | U3: 实际转化PV | V3: 实际转化率 | W3: 达成率 | X3: S | Y3: 占比 | Z3: A | AA3: 占比 | AB3: B | AC3: 占比 | AD3: C | AE3: 占比 | AL3: 所属校区 | AM3: 顾问 | AN3: 零期总PV | AO3: 已转PV | AP3: 应转PV | AQ3: 转化目标 | AR3: 实际转化PV | AS3: 实际转化率 | AT3: 达成率
B4: 陈中帅 | C4: 数学 | D4: 7 | E4: =COUNTIFS('UV台帐'!N:N,B4,'UV台帐'!S:S,"在读") | F4: =E4/(D4*25) | G4: =SUMPRODUCT(('UV台帐'!N:N=B4)*('UV台帐'!T:T="是")) | H4: =G4/E4 | I4: =COUNTIFS('UV台帐'!N:N,B4,'UV台帐'!S:S,"课前退") | J4: =I4/(E4+I4) | K4: =COUNTIF('陈中帅'!T:T,"是")/E4 | L4: =COUNTIF('陈中帅'!U:U,"是")/E4 | M4: =COUNTIF('陈中帅'!V:V,"是")/E4 | O4: 天成 | P4: 陈亮延 | Q4: =SUMIF('一期·UV电访分配'!BF:BF,P4,'一期·UV电访分配'!BR:ATS) | R4: 0 | S4: =Q4-R4 | T4: =S4*55% | U4: =SUMIF('一期·UV电访分配'!BF:BF,P4,'一期·UV电访分配'!BW:BW)-R4 | V4: =U4/S4 | W4: =U4/T4 | X4: =COUNTIFS('一期·UV电访分配'!BF:BF,P4,'一期·UV电访分配'!AJ:AJ,"*S*") | Y4: =X4/(Z4+AB4+AD4+X4) | Z4: =COUNTIFS('一期·UV电访分配'!BF:BF,P4,'一期·UV电访分配'!AJ:AJ,"*A*") | AA4: =Z4/(Z4+AB4+AD4+X4) | AB4: =COUNTIFS('一期·UV电访分配'!BF:BF,P4,'一期·UV电访分配'!AJ:AJ,"*B*") | AC4: =AB4/(Z4+AB4+AD4+X4) | AD4: =COUNTIFS('一期·UV电访分配'!BF:BF,P4,'一期·UV电访分配'!AJ:AJ,"*C*") | AE4: =AD4/(Z4+AB4+AD4+X4) | AL4: 天成 | AM4: 陈亮延 | AN4: =SUMIF('零期·UV电访分配'!AE:AE,AM4,'零期·UV电访分配'!AS:AS) | AP4: =AN4-AO4 | AQ4: =AP4*55% | AR4: =SUMIF('零期·UV电访分配'!AE:AE,AM4,'零期·UV电访分配'!AX:AX)-AO4 | AS4: =AR4/AP4 | AT4: =AR4/AQ4
B5: 何咏04 | C5: 数学 | D5: 4 | E5: =COUNTIFS('UV台帐'!N:N,B5,'UV台帐'!S:S,"在读") | F5: =E5/(D5*25) | G5: =SUMPRODUCT(('UV台帐'!N:N=B5)*('UV台帐'!T:T="是")) | H5: =G5/E5 | I5: =COUNTIFS('UV台帐'!N:N,B5,'UV台帐'!S:S,"课前退") | J5: =I5/(E5+I5) | K5: =COUNTIF('何咏04'!T:T,"是")/E5 | L5: =COUNTIF('何咏04'!U:U,"是")/E5 | M5: =COUNTIF('何咏04'!V:V,"是")/E5 | P5: 王达04 | Q5: =SUMIF('一期·UV电访分配'!BF:BF,P5,'一期·UV电访分配'!BR:BR) | R5: 5 | S5: =Q5-R5 | T5: =S5*55% | U5: =SUMIF('一期·UV电访分配'!BF:BF,P5,'一期·UV电访分配'!BW:BW)-R5 | V5: =U5/S5 | W5: =U5/T5 | X5: =COUNTIFS('一期·UV电访分配'!BF:BF,P5,'一期·UV电访分配'!AJ:AJ,"*S*") | Y5: =X5/(Z5+AB5+AD5+X5) | Z5: =COUNTIFS('一期·UV电访分配'!BF:BF,P5,'一期·UV电访分配'!AJ:AJ,"*A*") | AA5: =Z5/(Z5+AB5+AD5+X5) | AB5: =COUNTIFS('一期·UV电访分配'!BF:BF,P5,'一期·UV电访分配'!AJ:AJ,"*B*") | AC5: =AB5/(Z5+AB5+AD5+X5) | AD5: =COUNTIFS('一期·UV电访分配'!BF:BF,P5,'一期·UV电访分配'!AJ:AJ,"*C*") | AE5: =AD5/(Z5+AB5+AD5+X5) | AM5: 王达04 | AN5: =SUMIF('零期·UV电访分配'!AE:AE,AM5,'零期·UV电访分配'!AS:AS) | AP5: =AN5-AO5 | AQ5: =AP5*55% | AR5: =SUMIF('零期·UV电访分配'!AE:AE,AM5,'零期·UV电访分配'!AX:AX)-AO5 | AS5: =AR5/AP5 | AT5: =AR5/AQ5
B6: 田雨涵01 | C6: 数学 | D6: 5 | E6: =COUNTIFS('UV台帐'!N:N,B6,'UV台帐'!S:S,"在读") | F6: =E6/(D6*25) | G6: =SUMPRODUCT(('UV台帐'!N:N=B6)*('UV台帐'!T:T="是")) | H6: =G6/E6 | I6: =COUNTIFS('UV台帐'!N:N,B6,'UV台帐'!S:S,"课前退") | J6: =I6/(E6+I6) | K6: =COUNTIF('田雨涵01'!T:T,"是")/E6 | L6: =COUNTIF('田雨涵01'!U:U,"是")/E6 | M6: =COUNTIF('田雨涵01'!V:V,"是")/E6 | P6: 沈思浩 | Q6: =SUMIF('一期·UV电访分配'!BF:BF,P6,'一期·UV电访分配'!BR:BR) | R6: 1 | S6: =Q6-R6 | T6: =S6*55% | U6: =SUMIF('一期·UV电访分配'!BF:BF,P6,'一期·UV电访分配'!BW:BW)-R6 | V6: =U6/S6 | W6: =U6/T6 | X6: =COUNTIFS('一期·UV电访分配'!BF:BF,P6,'一期·UV电访分配'!AJ:AJ,"*S*") | Y6: =X6/(Z6+AB6+AD6+X6) | Z6: =COUNTIFS('一期·UV电访分配'!BF:BF,P6,'一期·UV电访分配'!AJ:AJ,"*A*") | AA6: =Z6/(Z6+AB6+AD6+X6) | AB6: =COUNTIFS('一期·UV电访分配'!BF:BF,P6,'一期·UV电访分配'!AJ:AJ,"*B*") | AC6: =AB6/(Z6+AB6+AD6+X6) | AD6: =COUNTIFS('一期·UV电访分配'!BF:BF,P6,'一期·UV电访分配'!AJ:AJ,"*C*") | AE6: =AD6/(Z6+AB6+AD6+X6) | AM6: 沈思浩 | AN6: =SUMIF('零期·UV电访分配'!AE:AE,AM6,'零期·UV电访分配'!AS:AS) | AO6: 2 | AP6: =AN6-AO6 | AQ6: =AP6*55% | AR6: =SUMIF('零期·UV电访分配'!AE:AE,AM6,'零期·UV电访分配'!AX:AX)-AO6 | AS6: =AR6/AP6 | AT6: =AR6/AQ6
B7: 宗志鹏 | C7: 数学 | D7: 1 | E7: =COUNTIFS('UV台帐'!N:N,B7,'UV台帐'!S:S,"在读") | F7: =E7/(D7*25) | G7: =SUMPRODUCT(('UV台帐'!N:N=B7)*('UV台帐'!T:T="是")) | H7: =G7/E7 | I7: =COUNTIFS('UV台帐'!N:N,B7,'UV台帐'!S:S,"课前退") | J7: =I7/(E7+I7) | K7: =COUNTIF('宗志鹏'!T:T,"是")/E7 | L7: =COUNTIF('宗志鹏'!U:U,"是")/E7 | M7: =COUNTIF('宗志鹏'!V:V,"是")/E7 | P7: 龙倩敏 | Q7: =SUMIF('一期·UV电访分配'!BF:BF,P7,'一期·UV电访分配'!BR:BR) | R7: 3 | S7: =Q7-R7 | T7: =S7*55% | U7: =SUMIF('一期·UV电访分配'!BF:BF,P7,'一期·UV电访分配'!BW:BW)-R7 | V7: =IFERROR(U7/S7,0) | W7: =IFERROR(U7/T7,0) | X7: =COUNTIFS('一期·UV电访分配'!BF:BF,P7,'一期·UV电访分配'!AJ:AJ,"*S*") | Y7: =IFERROR(X7/(Z7+AB7+AD7+X7),0) | Z7: =COUNTIFS('一期·UV电访分配'!BF:BF,P7,'一期·UV电访分配'!AJ:AJ,"*A*") | AA7: =IFERROR(Z7/(Z7+AB7+AD7+X7),0) | AB7: =COUNTIFS('一期·UV电访分配'!BF:BF,P7,'一期·UV电访分配'!AJ:AJ,"*B*") | AC7: =IFERROR(AB7/(Z7+AB7+AD7+X7),0) | AD7: =COUNTIFS('一期·UV电访分配'!BF:BF,P7,'一期·UV电访分配'!AJ:AJ,"*C*") | AE7: =IFERROR(AD7/(Z7+AB7+AD7+X7),0) | AM7: 龙倩敏 | AN7: =SUMIF('零期·UV电访分配'!AE:AE,AM7,'零期·UV电访分配'!AS:AS) | AP7: =AN7-AO7 | AQ7: =AP7*55% | AR7: =SUMIF('零期·UV电访分配'!AE:AE,AM7,'零期·UV电访分配'!AX:AX)-AO7 | AS7: =AR7/AP7 | AT7: =AR7/AQ7
B8: 数学合计 | D8: =SUM(D4:D7) | E8: =SUM(E4:E7) | F8: =E8/(D8*25) | G8: =SUM(G4:G7) | H8: =G8/E8 | I8: =SUM(I4:I7) | J8: =I8/(E8+I8) | K8: =(K4*$E$4+K5*$E$5+K6*$E$6+K7*$E$7)/$E$8 | L8: =(L4*$E$4+L5*$E$5+L6*$E$6+L7*$E$7)/$E$8 | M8: =(M4*$E$4+M5*$E$5+M6*$E$6+M7*$E$7)/$E$8 | O8: 合计 | Q8: =SUM(Q4:Q7) | R8: =SUM(R4:R7) | S8: =Q8-R8 | T8: =S8*55% | U8: =SUM(U4:U7) | V8: =U8/S8 | W8: =U8/T8 | X8: =SUM(X4:X7) | Y8: =X8/(Z8+AB8+AD8+X8) | Z8: =SUM(Z4:Z7) | AA8: =Z8/(Z8+AB8+AD8+X8) | AB8: =SUM(AB4:AB7) | AC8: =AB8/(Z8+AB8+AD8+X8) | AD8: =SUM(AD4:AD7) | AE8: =AD8/(Z8+AB8+AD8+X8) | AL8: 合计 | AN8: =SUM(AN4:AN7) | AO8: =SUM(AO4:AO7) | AP8: =AN8-AO8 | AQ8: =AP8*55% | AR8: =SUM(AR4:AR7) | AS8: =AR8/AP8 | AT8: =AR8/AQ8
B9: 黄铭怡 | C9: 语文 | D9: 5 | E9: =COUNTIFS('UV台帐'!W:W,B9,'UV台帐'!AB:AB,"在读") | F9: =E9/(D9*25) | G9: =SUMPRODUCT(('UV台帐'!W:W=B9)*('UV台帐'!AC:AC="是")) | H9: =G9/E9 | I9: =COUNTIFS('UV台帐'!W:W,B9,'UV台帐'!AB:AB,"课前退") | J9: =I9/(E9+I9) | K9: =COUNTIF('黄铭怡'!T:T,"是")/E9 | L9: =COUNTIF('黄铭怡'!U:U,"是")/E9 | M9: =COUNTIF('黄铭怡'!V:V,"是")/E9 | O9: 同创汇 | P9: 戎凯01 | Q9: =SUMIF('一期·UV电访分配'!BF:BF,P9,'一期·UV电访分配'!BR:BR) | R9: 8 | S9: =Q9-R9 | T9: =S9*55% | U9: =SUMIF('一期·UV电访分配'!BF:BF,P9,'一期·UV电访分配'!BW:BW)-R9 | V9: =U9/S9 | W9: =U9/T9 | X9: =COUNTIFS('一期·UV电访分配'!BF:BF,P9,'一期·UV电访分配'!AJ:AJ,"*S*") | Y9: =X9/(Z9+AB9+AD9+X9) | Z9: =COUNTIFS('一期·UV电访分配'!BF:BF,P9,'一期·UV电访分配'!AJ:AJ,"*A*") | AA9: =Z9/(Z9+AB9+AD9+X9) | AB9: =COUNTIFS('一期·UV电访分配'!BF:BF,P9,'一期·UV电访分配'!AJ:AJ,"*B*") | AC9: =AB9/(Z9+AB9+AD9+X9) | AD9: =COUNTIFS('一期·UV电访分配'!BF:BF,P9,'一期·UV电访分配'!AJ:AJ,"*C*") | AE9: =AD9/(Z9+AB9+AD9+X9) | AL9: 同创汇 | AM9: 戎凯01 | AN9: =SUMIF('零期·UV电访分配'!AE:AE,AM9,'零期·UV电访分配'!AS:AS) | AO9: 7 | AP9: =AN9-AO9 | AQ9: =AP9*55% | AR9: =SUMIF('零期·UV电访分配'!AE:AE,AM9,'零期·UV电访分配'!AX:AX)-AO9 | AS9: =AR9/AP9 | AT9: =AR9/AQ9
B10: 李润 | C10: 语文 | D10: 7 | E10: =COUNTIFS('UV台帐'!W:W,B10,'UV台帐'!AB:AB,"在读") | F10: =E10/(D10*25) | G10: =SUMPRODUCT(('UV台帐'!W:W=B10)*('UV台帐'!AC:AC="是")) | H10: =G10/E10 | I10: =COUNTIFS('UV台帐'!W:W,B10,'UV台帐'!AB:AB,"课前退") | J10: =I10/(E10+I10) | K10: =COUNTIF('李润'!T:T,"是")/E10 | L10: =COUNTIF('李润'!U:U,"是")/E10 | M10: =COUNTIF('李润'!V:V,"是")/E10 | P10: 王丽 | Q10: =SUMIF('一期·UV电访分配'!BF:BF,P10,'一期·UV电访分配'!BR:BR) | R10: 6 | S10: =Q10-R10 | T10: =S10*55% | U10: =SUMIF('一期·UV电访分配'!BF:BF,P10,'一期·UV电访分配'!BW:BW)-R10 | V10: =U10/S10 | W10: =U10/T10 | X10: =COUNTIFS('一期·UV电访分配'!BF:BF,P10,'一期·UV电访分配'!AJ:AJ,"*S*") | Y10: =X10/(Z10+AB10+AD10+X10) | Z10: =COUNTIFS('一期·UV电访分配'!BF:BF,P10,'一期·UV电访分配'!AJ:AJ,"*A*") | AA10: =Z10/(Z10+AB10+AD10+X10) | AB10: =COUNTIFS('一期·UV电访分配'!BF:BF,P10,'一期·UV电访分配'!AJ:AJ,"*B*") | AC10: =AB10/(Z10+AB10+AD10+X10) | AD10: =COUNTIFS('一期·UV电访分配'!BF:BF,P10,'一期·UV电访分配'!AJ:AJ,"*C*") | AE10: =AD10/(Z10+AB10+AD10+X10) | AM10: 王丽 | AN10: =SUMIF('零期·UV电访分配'!AE:AE,AM10,'零期·UV电访分配'!AS:AS) | AO10: 17 | AP10: =AN10-AO10 | AQ10: =AP10*55% | AR10: =SUMIF('零期·UV电访分配'!AE:AE,AM10,'零期·UV电访分配'!AX:AX)-AO10 | AS10: =AR10/AP10 | AT10: =AR10/AQ10
B11: 陈南05 | C11: 语文 | D11: 4 | E11: =COUNTIFS('UV台帐'!W:W,B11,'UV台帐'!AB:AB,"在读") | F11: =E11/(D11*25) | G11: =SUMPRODUCT(('UV台帐'!W:W=B11)*('UV台帐'!AC:AC="是")) | H11: =G11/E11 | I11: =COUNTIFS('UV台帐'!W:W,B11,'UV台帐'!AB:AB,"课前退") | J11: =I11/(E11+I11) | K11: =COUNTIF('陈南05'!T:T,"是")/E11 | L11: =COUNTIF('陈南05'!U:U,"是")/E11 | M11: =COUNTIF('陈南05'!V:V,"是")/E11 | P11: 苏丽婷 | Q11: =SUMIF('一期·UV电访分配'!BF:BF,P11,'一期·UV电访分配'!BR:BR) | R11: 0 | S11: =Q11-R11 | T11: =S11*55% | U11: =SUMIF('一期·UV电访分配'!BF:BF,P11,'一期·UV电访分配'!BW:BW)-R11 | V11: =U11/S11 | W11: =U11/T11 | X11: =COUNTIFS('一期·UV电访分配'!BF:BF,P11,'一期·UV电访分配'!AJ:AJ,"*S*") | Y11: =X11/(Z11+AB11+AD11+X11) | Z11: =COUNTIFS('一期·UV电访分配'!BF:BF,P11,'一期·UV电访分配'!AJ:AJ,"*A*") | AA11: =Z11/(Z11+AB11+AD11+X11) | AB11: =COUNTIFS('一期·UV电访分配'!BF:BF,P11,'一期·UV电访分配'!AJ:AJ,"*B*") | AC11: =AB11/(Z11+AB11+AD11+X11) | AD11: =COUNTIFS('一期·UV电访分配'!BF:BF,P11,'一期·UV电访分配'!AJ:AJ,"*C*") | AE11: =AD11/(Z11+AB11+AD11+X11) | AM11: 苏丽婷 | AN11: =SUMIF('零期·UV电访分配'!AE:AE,AM11,'零期·UV电访分配'!AS:AS) | AO11: 1 | AP11: =AN11-AO11 | AQ11: =AP11*55% | AR11: =SUMIF('零期·UV电访分配'!AE:AE,AM11,'零期·UV电访分配'!AX:AX)-AO11 | AS11: =AR11/AP11 | AT11: =AR11/AQ11
B12: 语文合计 | D12: =SUM(D9:D11) | E12: =SUM(E9:E11) | F12: =E12/(D12*25) | G12: =SUM(G9:G11) | H12: =G12/E12 | I12: =SUM(I9:I11) | J12: =I12/(E12+I12) | K12: =(K9*$E$9+K10*$E$10+K11*$E$11)/$E$12 | L12: =(L9*$E$9+L10*$E$10+L11*$E$11)/$E$12 | M12: =(M9*$E$9+M10*$E$10+M11*$E$11)/$E$12 | O12: 合计 | Q12: =SUM(Q9:Q11) | R12: =SUM(R9:R11) | S12: =Q12-R12 | T12: =S12*55% | U12: =SUM(U9:U11) | V12: =U12/S12 | W12: =U12/T12 | X12: =SUM(X9:X11) | Y12: =X12/(Z12+AB12+AD12+X12) | Z12: =SUM(Z9:Z11) | AA12: =Z12/(Z12+AB12+AD12+X12) | AB12: =SUM(AB9:AB11) | AC12: =AB12/(Z12+AB12+AD12+X12) | AD12: =SUM(AD9:AD11) | AE12: =AD12/(Z12+AB12+AD12+X12) | AL12: 合计 | AN12: =SUM(AN9:AN11) | AO12: =SUM(AO9:AO11) | AP12: =AN12-AO12 | AQ12: =AP12*55% | AR12: =SUM(AR9:AR11) | AS12: =AR12/AP12 | AT12: =AR12/AQ12
B13: 刘希子 | C13: 英语 | D13: 6 | E13: =COUNTIFS('UV台帐'!AF:AF,B13,'UV台帐'!AK:AK,"在读") | F13: =E13/(D13*25) | G13: =SUMPRODUCT(('UV台帐'!AF:AF=B13)*('UV台帐'!AL:AL="是")) | H13: =G13/E13 | I13: =COUNTIFS('UV台帐'!AF:AF,B13,'UV台帐'!AK:AK,"课前退") | J13: =I13/(E13+I13) | K13: =COUNTIF('刘希子'!T:T,"是")/E13 | L13: =COUNTIF('刘希子'!U:U,"是")/E13 | M13: =COUNTIF('刘希子'!V:V,"是")/E13 | O13: 新宝利 | P13: 杨林33 | Q13: =SUMIF('一期·UV电访分配'!BF:BF,P13,'一期·UV电访分配'!BR:BR) | R13: 1 | S13: =Q13-R13 | T13: =S13*55% | U13: =SUMIF('一期·UV电访分配'!BF:BF,P13,'一期·UV电访分配'!BW:BW)-R13 | V13: =U13/S13 | W13: =U13/T13 | X13: =COUNTIFS('一期·UV电访分配'!BF:BF,P13,'一期·UV电访分配'!AJ:AJ,"*S*") | Y13: =X13/(Z13+AB13+AD13+X13) | Z13: =COUNTIFS('一期·UV电访分配'!BF:BF,P13,'一期·UV电访分配'!AJ:AJ,"*A*") | AA13: =Z13/(Z13+AB13+AD13+X13) | AB13: =COUNTIFS('一期·UV电访分配'!BF:BF,P13,'一期·UV电访分配'!AJ:AJ,"*B*") | AC13: =AB13/(Z13+AB13+AD13+X13) | AD13: =COUNTIFS('一期·UV电访分配'!BF:BF,P13,'一期·UV电访分配'!AJ:AJ,"*C*") | AE13: =AD13/(Z13+AB13+AD13+X13) | AL13: 新宝利 | AM13: 杨林33 | AN13: =SUMIF('零期·UV电访分配'!AE:AE,AM13,'零期·UV电访分配'!AS:AS) | AP13: =AN13-AO13 | AQ13: =AP13*55% | AR13: =SUMIF('零期·UV电访分配'!AE:AE,AM13,'零期·UV电访分配'!AX:AX)-AO13 | AS13: =AR13/AP13 | AT13: =AR13/AQ13
B14: 肖锐03 | C14: 英语 | D14: 7 | E14: =COUNTIFS('UV台帐'!AF:AF,B14,'UV台帐'!AK:AK,"在读") | F14: =E14/(D14*25) | G14: =SUMPRODUCT(('UV台帐'!AF:AF=B14)*('UV台帐'!AL:AL="是")) | H14: =G14/E14 | I14: =COUNTIFS('UV台帐'!AF:AF,B14,'UV台帐'!AK:AK,"课前退") | J14: =I14/(E14+I14) | K14: =COUNTIF('肖锐03'!T:T,"是")/E14 | L14: =COUNTIF('肖锐03'!U:U,"是")/E14 | M14: =COUNTIF('肖锐03'!V:V,"是")/E14 | P14: 林志豪01 | Q14: =SUMIF('一期·UV电访分配'!BF:BF,P14,'一期·UV电访分配'!BR:BR) | R14: 0 | S14: =Q14-R14 | T14: =S14*55% | U14: =SUMIF('一期·UV电访分配'!BF:BF,P14,'一期·UV电访分配'!BW:BW)-R14 | V14: =U14/S14 | W14: =U14/T14 | X14: =COUNTIFS('一期·UV电访分配'!BF:BF,P14,'一期·UV电访分配'!AJ:AJ,"*S*") | Y14: =X14/(Z14+AB14+AD14+X14) | Z14: =COUNTIFS('一期·UV电访分配'!BF:BF,P14,'一期·UV电访分配'!AJ:AJ,"*A*") | AA14: =Z14/(Z14+AB14+AD14+X14) | AB14: =COUNTIFS('一期·UV电访分配'!BF:BF,P14,'一期·UV电访分配'!AJ:AJ,"*B*") | AC14: =AB14/(Z14+AB14+AD14+X14) | AD14: =COUNTIFS('一期·UV电访分配'!BF:BF,P14,'一期·UV电访分配'!AJ:AJ,"*C*") | AE14: =AD14/(Z14+AB14+AD14+X14) | AM14: 林志豪01 | AN14: =SUMIF('零期·UV电访分配'!AE:AE,AM14,'零期·UV电访分配'!AS:AS) | AO14: 12 | AP14: =AN14-AO14 | AQ14: =AP14*55% | AR14: =SUMIF('零期·UV电访分配'!AE:AE,AM14,'零期·UV电访分配'!AX:AX)-AO14 | AS14: =AR14/AP14 | AT14: =AR14/AQ14
B15: 高心怡04 | C15: 英语 | D15: 6 | E15: =COUNTIFS('UV台帐'!AF:AF,B15,'UV台帐'!AK:AK,"在读") | F15: =E15/(D15*25) | G15: =SUMPRODUCT(('UV台帐'!AF:AF=B15)*('UV台帐'!AL:AL="是")) | H15: =G15/E15 | I15: =COUNTIFS('UV台帐'!AF:AF,B15,'UV台帐'!AK:AK,"课前退") | J15: =I15/(E15+I15) | K15: =COUNTIF('高心怡04'!T:T,"是")/E15 | L15: =COUNTIF('高心怡04'!U:U,"是")/E15 | M15: =COUNTIF('高心怡04'!V:V,"是")/E15 | P15: 张敏烨 | Q15: =SUMIF('一期·UV电访分配'!BF:BF,P15,'一期·UV电访分配'!BR:BR) | R15: 1 | S15: =Q15-R15 | T15: =S15*55% | U15: =SUMIF('一期·UV电访分配'!BF:BF,P15,'一期·UV电访分配'!BW:BW)-R15 | V15: =U15/S15 | W15: =U15/T15 | X15: =COUNTIFS('一期·UV电访分配'!BF:BF,P15,'一期·UV电访分配'!AJ:AJ,"*S*") | Y15: =X15/(Z15+AB15+AD15+X15) | Z15: =COUNTIFS('一期·UV电访分配'!BF:BF,P15,'一期·UV电访分配'!AJ:AJ,"*A*") | AA15: =Z15/(Z15+AB15+AD15+X15) | AB15: =COUNTIFS('一期·UV电访分配'!BF:BF,P15,'一期·UV电访分配'!AJ:AJ,"*B*") | AC15: =AB15/(Z15+AB15+AD15+X15) | AD15: =COUNTIFS('一期·UV电访分配'!BF:BF,P15,'一期·UV电访分配'!AJ:AJ,"*C*") | AE15: =AD15/(Z15+AB15+AD15+X15) | AM15: 张敏烨 | AN15: =SUMIF('零期·UV电访分配'!AE:AE,AM15,'零期·UV电访分配'!AS:AS) | AO15: 3 | AP15: =AN15-AO15 | AQ15: =AP15*55% | AR15: =SUMIF('零期·UV电访分配'!AE:AE,AM15,'零期·UV电访分配'!AX:AX)-AO15 | AS15: =AR15/AP15 | AT15: =AR15/AQ15
B16: 英语合计 | D16: =SUM(D13:D14) | E16: =SUM(E13:E15) | F16: =E16/(D16*25) | G16: =SUM(G13:G15) | H16: =G16/E16 | I16: =SUM(I13:I15) | J16: =I16/(E16+I16) | K16: =(K13*$E$13+K14*$E$14+K15*$E$15)/$E$16 | L16: =(L13*$E$13+L14*$E$14+L15*$E$15)/$E$16 | M16: =(M13*$E$13+M14*$E$14+M15*$E$15)/$E$16 | O16: 合计 | Q16: =SUM(Q13:Q15) | R16: =SUM(R13:R15) | S16: =Q16-R16 | T16: =S16*55% | U16: =SUM(U13:U15) | V16: =U16/S16 | W16: =U16/T16 | X16: =SUM(X13:X15) | Y16: =X16/(Z16+AB16+AD16+X16) | Z16: =SUM(Z13:Z15) | AA16: =Z16/(Z16+AB16+AD16+X16) | AB16: =SUM(AB13:AB15) | AC16: =AB16/(Z16+AB16+AD16+X16) | AD16: =SUM(AD13:AD15) | AE16: =AD16/(Z16+AB16+AD16+X16) | AL16: 合计 | AN16: =SUM(AN13:AN15) | AO16: =SUM(AO13:AO15) | AP16: =AN16-AO16 | AQ16: =AP16*55% | AR16: =SUM(AR13:AR15) | AS16: =AR16/AP16 | AT16: =AR16/AQ16
B18: 一期汇总 | D18: 基础信息 | K18: 课前服务 | N18: 课中家长会 | Y18: 一期 | Z18: 学员数 | AB18: vip入群率 | AC18: 课前家长会（UV） | AE18: 课中家长会（UV） | AG18: 转化率 （PV） | AH18: 学员意向分层(PV)
D19: =SUM(D21:D33)/2 | E19: =E25+E29+E33 | F19: =E19/(25*D19) | G19: =G25+G29+G33 | H19: =G19/E19 | I19: =SUM(I21:I33)/2 | J19: =I19/(E19+I19) | K19: =(K25*$E$49+K29*$E$53+K33*$E$57)/$E$43 | L19: =(L25*$E$49+L29*$E$53+L33*$E$57)/$E$43 | M19: =(M25*$E$49+M29*$E$53+M33*$E$57)/$E$43 | N19: =SUM(N21:N33)/2 | O19: =N19/E19 | P19: =SUM(P21:P33)/2 | Q19: =SUM(Q21:Q33)/2 | R19: =Q19/P19 | S19: =SUM(S21:S33)/2 | T19: =SUM(T21:T33)/2 | U19: =T19/S19 | V19: =SUM(V21:V33)/2 | W19: =V19/E19 | Y19: 校区 | Z19: PV | AA19: UV | AC19: 课前诺访 | AD19: 课前确访 | AE19: 课中诺访 | AF19: 课中确访 | AH19: S | AI19: 占比 | AJ19: A | AK19: 占比 | AL19: B | AM19: 占比 | AN19: C | AO19: 占比
B20: 老师看板 | C20: 学科 | D20: 班量 | E20: 在读PV | F20: 满班率 | G20: 暑续秋PV | H20: 转化率 | I20: 课前退PV | J20: 课前退率 | K20: 加微率 | L20: 首联率 | M20: vip入群率 | N20: 课中诺访 | O20: 诺访率PV | P20: 7月18日应到 | Q20: 7月18日实到 | R20: 到场率 | S20: 7月19日应到 | T20: 7月19日实到 | U20: 到场率 | V20: 整体到场 | W20: 到场率 | Y20: 天成大厦 | Z20: =SUMIF('一期·UV电访分配'!A:A,Y20,'一期·UV电访分配'!BR:BR) | AA20: =COUNTIF('一期·UV电访分配'!A:A,Y20) | AB20: =IFERROR(COUNTIFS('一期·UV电访分配'!A:A,Y20,'一期·UV电访分配'!R:R,"是")/AA20,0) | AC20: =IFERROR(COUNTIFS('一期·UV电访分配'!A:A,Y20,'一期·UV电访分配'!AL:AL,"是")/AA20,0) | AD20: =IFERROR(COUNTIFS('一期·UV电访分配'!A:A,Y20,'一期·UV电访分配'!AM:AM,"是")/AA20,0) | AE20: =IFERROR(COUNTIFS('一期·UV电访分配'!A:A,Y20,'一期·UV电访分配'!AY:AY,"是")/AA20,0) | AF20: =IFERROR(COUNTIFS('一期·UV电访分配'!A:A,Y20,'一期·UV电访分配'!BE:BE,"是")/AA20,0) | AG20: =IFERROR(SUMIF('一期·UV电访分配'!A:A,Y20,'一期·UV电访分配'!BW:BW)/Z20,0) | AH20: =COUNTIFS('一期·UV电访分配'!A:A,Y20,'一期·UV电访分配'!AJ:AJ,"*S*") | AI20: =IFERROR(AH20/Z20,0) | AJ20: =COUNTIFS('一期·UV电访分配'!A:A,Y20,'一期·UV电访分配'!AJ:AJ,"*A*") | AK20: =IFERROR(AJ20/Z20,0) | AL20: =COUNTIFS('一期·UV电访分配'!A:A,Y20,'一期·UV电访分配'!AJ:AJ,"*B*") | AM20: =IFERROR(AL20/Z20,0) | AN20: =COUNTIFS('一期·UV电访分配'!A:A,Y20,'一期·UV电访分配'!AJ:AJ,"*C*") | AO20: =IFERROR(AN20/Z20,0)
B21: 陈中帅 | C21: 数学 | D21: 2 | E21: =COUNTIFS('UV台帐'!N:N,B21,'UV台帐'!S:S,"在读",'UV台帐'!R:R,"一期") | F21: =E21/(D21*25) | G21: =SUMPRODUCT(('UV台帐'!N:N=B21)*('UV台帐'!T:T="是")*('UV台帐'!R:R="一期")) | H21: =G21/E21 | I21: =COUNTIFS('UV台帐'!N:N,B21,'UV台帐'!S:S,"课前退",'UV台帐'!R:R,"一期") | J21: =I21/(E21+I21) | K21: =IFERROR(COUNTIFS('陈中帅'!T:T,"是",'陈中帅'!B:B,"一期")/E21,"") | L21: =COUNTIFS('陈中帅'!U:U,"是",'陈中帅'!B:B,"一期")/E21 | M21: =COUNTIFS('陈中帅'!V:V,"是",'陈中帅'!B:B,"一期")/E21 | N21: =COUNTIFS('一期·UV电访分配'!E:E,B21,'一期·UV电访分配'!AY:AY,"是") | O21: =N21/E21 | P21: =COUNTIFS('一期·UV电访分配'!E:E,B21,'一期·UV电访分配'!I:I,"在读",'一期·UV电访分配'!H:H,"一期",'一期·UV电访分配'!A:A,"同创汇") | Q21: =COUNTIFS('一期·UV电访分配'!E:E,B21,'一期·UV电访分配'!I:I,"在读",'一期·UV电访分配'!H:H,"一期",'一期·UV电访分配'!A:A,"同创汇",'一期·UV电访分配'!BE:BE,"是") | R21: =Q21/P21 | S21: =COUNTIFS('一期·UV电访分配'!E:E,B21,'一期·UV电访分配'!I:I,"在读",'一期·UV电访分配'!H:H,"一期",'一期·UV电访分配'!A:A,"新宝利") | T21: =COUNTIFS('一期·UV电访分配'!E:E,B21,'一期·UV电访分配'!I:I,"在读",'一期·UV电访分配'!H:H,"一期",'一期·UV电访分配'!A:A,"新宝利",'一期·UV电访分配'!BE:BE,"是") | U21: =IFERROR(T21/S21,0) | V21: =T21+Q21 | W21: =V21/E21 | Y21: 同创汇 | Z21: =SUMIF('一期·UV电访分配'!A:A,Y21,'一期·UV电访分配'!BR:BR) | AA21: =COUNTIF('一期·UV电访分配'!A:A,Y21) | AB21: =COUNTIFS('一期·UV电访分配'!A:A,Y21,'一期·UV电访分配'!R:R,"是")/AA21 | AC21: =COUNTIFS('一期·UV电访分配'!A:A,Y21,'一期·UV电访分配'!AL:AL,"是")/AA21 | AD21: =COUNTIFS('一期·UV电访分配'!A:A,Y21,'一期·UV电访分配'!AM:AM,"是")/AA21 | AE21: =COUNTIFS('一期·UV电访分配'!A:A,Y21,'一期·UV电访分配'!AY:AY,"是")/AA21 | AF21: =COUNTIFS('一期·UV电访分配'!A:A,Y21,'一期·UV电访分配'!BE:BE,"是")/AA21 | AG21: =SUMIF('一期·UV电访分配'!A:A,Y21,'一期·UV电访分配'!BW:BW)/Z21 | AH21: =COUNTIFS('一期·UV电访分配'!A:A,Y21,'一期·UV电访分配'!AJ:AJ,"*S*") | AI21: =AH21/Z21 | AJ21: =COUNTIFS('一期·UV电访分配'!A:A,Y21,'一期·UV电访分配'!AJ:AJ,"*A*") | AK21: =AJ21/Z21 | AL21: =COUNTIFS('一期·UV电访分配'!A:A,Y21,'一期·UV电访分配'!AJ:AJ,"*B*") | AM21: =AL21/Z21 | AN21: =COUNTIFS('一期·UV电访分配'!A:A,Y21,'一期·UV电访分配'!AJ:AJ,"*C*") | AO21: =AN21/Z21
B22: 何咏04 | C22: 数学 | D22: 2 | E22: =COUNTIFS('UV台帐'!N:N,B22,'UV台帐'!S:S,"在读",'UV台帐'!R:R,"一期") | F22: =IFERROR(E22/(D22*25),"0") | G22: =SUMPRODUCT(('UV台帐'!N:N=B22)*('UV台帐'!T:T="是")*('UV台帐'!R:R="一期")) | H22: =IFERROR(G22/E22,"0") | I22: =COUNTIFS('UV台帐'!N:N,B22,'UV台帐'!S:S,"课前退",'UV台帐'!R:R,"一期") | J22: =IFERROR(I22/(E22+I22),"0") | K22: =IFERROR(COUNTIFS('何咏04'!T:T,"是",'何咏04'!B:B,"一期")/E22,"0") | L22: =IFERROR(COUNTIFS('何咏04'!U:U,"是",'何咏04'!B:B,"一期")/E22,"0") | M22: =IFERROR(COUNTIFS('何咏04'!V:V,"是",'何咏04'!B:B,"一期")/E22,"0") | N22: =COUNTIFS('一期·UV电访分配'!E:E,B22,'一期·UV电访分配'!AY:AY,"是") | O22: =N22/E22 | P22: =COUNTIFS('一期·UV电访分配'!E:E,B22,'一期·UV电访分配'!I:I,"在读",'一期·UV电访分配'!H:H,"一期",'一期·UV电访分配'!A:A,"同创汇") | Q22: =COUNTIFS('一期·UV电访分配'!E:E,B22,'一期·UV电访分配'!I:I,"在读",'一期·UV电访分配'!H:H,"一期",'一期·UV电访分配'!A:A,"同创汇",'一期·UV电访分配'!BE:BE,"是") | R22: =Q22/P22 | T22: 0 | U22: =IFERROR(T22/S22,0) | V22: =T22+Q22 | W22: =V22/E22 | Y22: 新宝利 | Z22: =SUMIF('一期·UV电访分配'!A:A,Y22,'一期·UV电访分配'!BR:BR) | AA22: =COUNTIF('一期·UV电访分配'!A:A,Y22) | AB22: =COUNTIFS('一期·UV电访分配'!A:A,Y22,'一期·UV电访分配'!R:R,"是")/AA22 | AC22: =COUNTIFS('一期·UV电访分配'!A:A,Y22,'一期·UV电访分配'!AL:AL,"是")/AA22 | AD22: =COUNTIFS('一期·UV电访分配'!A:A,Y22,'一期·UV电访分配'!AM:AM,"是")/AA22 | AE22: =COUNTIFS('一期·UV电访分配'!A:A,Y22,'一期·UV电访分配'!AY:AY,"是")/AA22 | AF22: =COUNTIFS('一期·UV电访分配'!A:A,Y22,'一期·UV电访分配'!BE:BE,"是")/AA22 | AG22: =SUMIF('一期·UV电访分配'!A:A,Y22,'一期·UV电访分配'!BW:BW)/Z22 | AH22: =COUNTIFS('一期·UV电访分配'!A:A,Y22,'一期·UV电访分配'!AJ:AJ,"*S*") | AI22: =AH22/Z22 | AJ22: =COUNTIFS('一期·UV电访分配'!A:A,Y22,'一期·UV电访分配'!AJ:AJ,"*A*") | AK22: =AJ22/Z22 | AL22: =COUNTIFS('一期·UV电访分配'!A:A,Y22,'一期·UV电访分配'!AJ:AJ,"*B*") | AM22: =AL22/Z22 | AN22: =COUNTIFS('一期·UV电访分配'!A:A,Y22,'一期·UV电访分配'!AJ:AJ,"*C*") | AO22: =AN22/Z22
B23: 田雨涵01 | C23: 数学 | D23: 1 | E23: =COUNTIFS('UV台帐'!N:N,B23,'UV台帐'!S:S,"在读",'UV台帐'!R:R,"一期") | F23: =E23/(D23*25) | G23: =SUMPRODUCT(('UV台帐'!N:N=B23)*('UV台帐'!T:T="是")*('UV台帐'!R:R="一期")) | H23: =G23/E23 | I23: =COUNTIFS('UV台帐'!N:N,B23,'UV台帐'!S:S,"课前退",'UV台帐'!R:R,"一期") | J23: =I23/(E23+I23) | K23: =COUNTIFS('田雨涵01'!T:T,"是",'田雨涵01'!B:B,"一期")/E23 | L23: =COUNTIFS('田雨涵01'!U:U,"是",'田雨涵01'!B:B,"一期")/E23 | M23: =COUNTIFS('田雨涵01'!V:V,"是",'田雨涵01'!B:B,"一期")/E23 | N23: =COUNTIFS('一期·UV电访分配'!E:E,B23,'一期·UV电访分配'!AY:AY,"是") | O23: =N23/E23 | P23: =COUNTIFS('一期·UV电访分配'!E:E,B23,'一期·UV电访分配'!I:I,"在读",'一期·UV电访分配'!H:H,"一期",'一期·UV电访分配'!A:A,"同创汇") | Q23: =COUNTIFS('一期·UV电访分配'!E:E,B23,'一期·UV电访分配'!I:I,"在读",'一期·UV电访分配'!H:H,"一期",'一期·UV电访分配'!A:A,"同创汇",'一期·UV电访分配'!BE:BE,"是") | R23: =Q23/P23 | S23: =COUNTIFS('一期·UV电访分配'!E:E,B23,'一期·UV电访分配'!I:I,"在读",'一期·UV电访分配'!H:H,"一期",'一期·UV电访分配'!A:A,"新宝利") | T23: =COUNTIFS('一期·UV电访分配'!E:E,B23,'一期·UV电访分配'!I:I,"在读",'一期·UV电访分配'!H:H,"一期",'一期·UV电访分配'!A:A,"新宝利",'一期·UV电访分配'!BE:BE,"是") | U23: =IFERROR(T23/S23,0) | V23: =T23+Q23 | W23: =V23/E23 | Y23: 分校合计 | Z23: =SUM(Z20:Z22) | AA23: =SUM(AA20:AA22) | AB23: =COUNTIF('一期·UV电访分配'!R:R,"是")/AA23 | AC23: =COUNTIF('一期·UV电访分配'!AL:AL,"是")/AA23 | AD23: =COUNTIF('一期·UV电访分配'!AM:AM,"是")/AA23 | AE23: =COUNTIF('一期·UV电访分配'!AY:AY,"是")/AA23 | AF23: =COUNTIF('一期·UV电访分配'!BE:BE,"是")/AA23 | AG23: =SUM('一期·UV电访分配'!BW:BW)/Z23 | AH23: =SUM(AH20:AH22) | AI23: =AH23/Z23 | AJ23: =SUM(AJ20:AJ22) | AK23: =AJ23/Z23 | AL23: =SUM(AL20:AL22) | AM23: =AL23/Z23 | AN23: =SUM(AN20:AN22) | AO23: =AN23/Z23
B24: 宗志鹏 | C24: 数学 | D24: 0 | E24: =COUNTIFS('UV台帐'!N:N,B24,'UV台帐'!S:S,"在读",'UV台帐'!R:R,"一期") | F24: =IFERROR(E24/(D24*25),"0") | G24: =SUMPRODUCT(('UV台帐'!N:N=B24)*('UV台帐'!T:T="是")*('UV台帐'!R:R="一期")) | H24: =IFERROR(G24/E24,"0") | I24: =COUNTIFS('UV台帐'!N:N,B24,'UV台帐'!S:S,"课前退",'UV台帐'!R:R,"一期") | J24: =IFERROR(I24/(E24+I24),"0") | K24: =IFERROR(COUNTIFS('宗志鹏'!T:T,"是",'宗志鹏'!B:B,"一期")/E24,"0") | L24: =IFERROR(COUNTIFS('宗志鹏'!U:U,"是",'宗志鹏'!B:B,"一期")/E24,"0") | M24: =IFERROR(COUNTIFS('宗志鹏'!V:V,"是",'宗志鹏'!B:B,"一期")/E24,"0") | N24: =COUNTIFS('一期·UV电访分配'!E:E,B24,'一期·UV电访分配'!AY:AY,"是") | O24: =N24/E24 | P24: =COUNTIFS('一期·UV电访分配'!E:E,B24,'一期·UV电访分配'!I:I,"在读",'一期·UV电访分配'!H:H,"一期",'一期·UV电访分配'!A:A,"同创汇") | Q24: 0 | R24: =Q24/P24 | T24: 0 | U24: =T24/S24 | V24: =T24+Q24 | W24: =V24/E24
B25: 数学合计 | D25: =SUM(D21:D24) | E25: =SUM(E21:E24) | F25: =E25/(D25*25) | G25: =SUM(G21:G24) | H25: =G25/E25 | I25: =SUM(I21:I24) | J25: =I25/(E25+I25) | K25: =(K21*$E$45+K22*$E$46+K23*$E$47+K24*$E$48)/$E$49 | L25: =(L21*$E$45+L22*$E$46+L23*$E$47+L24*$E$48)/$E$49 | M25: =(M21*$E$45+M22*$E$46+M23*$E$47+M24*$E$48)/$E$49 | N25: =SUM(N21:N23) | O25: =N25/E25 | P25: =SUM(P21:P23) | Q25: =SUM(Q21:Q23) | R25: =Q25/P25 | S25: =SUM(S21:S23) | T25: =SUM(T21:T23) | U25: =IFERROR(T25/S25,0) | V25: =T25+Q25 | W25: =V25/E25
B26: 黄铭怡 | C26: 语文 | D26: 1 | E26: =COUNTIFS('UV台帐'!W:W,B26,'UV台帐'!AB:AB,"在读",'UV台帐'!AA:AA,"一期") | F26: =E26/(D26*25) | G26: =SUMPRODUCT(('UV台帐'!W:W=B26)*('UV台帐'!AC:AC="是")*('UV台帐'!AA:AA="一期")) | H26: =G26/E26 | I26: =COUNTIFS('UV台帐'!W:W,B26,'UV台帐'!AB:AB,"课前退",'UV台帐'!AA:AA,"一期") | J26: =I26/(E26+I26) | K26: =COUNTIFS('黄铭怡'!T:T,"是",'黄铭怡'!B:B,"一期")/E26 | L26: =COUNTIFS('黄铭怡'!U:U,"是",'黄铭怡'!B:B,"一期")/E26 | M26: =COUNTIFS('黄铭怡'!V:V,"是",'黄铭怡'!B:B,"一期")/E26 | N26: =COUNTIFS('一期·UV电访分配'!J:J,B26,'一期·UV电访分配'!AY:AY,"是") | O26: =N26/E26 | P26: =COUNTIFS('一期·UV电访分配'!J:J,B26,'一期·UV电访分配'!M:M,"在读",'一期·UV电访分配'!L:L,"一期",'一期·UV电访分配'!A:A,"同创汇") | Q26: =COUNTIFS('一期·UV电访分配'!J:J,B26,'一期·UV电访分配'!M:M,"在读",'一期·UV电访分配'!L:L,"一期",'一期·UV电访分配'!A:A,"同创汇",'一期·UV电访分配'!BE:BE,"是") | R26: =Q26/P26 | S26: =COUNTIFS('一期·UV电访分配'!J:J,B26,'一期·UV电访分配'!M:M,"在读",'一期·UV电访分配'!L:L,"一期",'一期·UV电访分配'!A:A,"新宝利") | T26: =COUNTIFS('一期·UV电访分配'!J:J,B26,'一期·UV电访分配'!M:M,"在读",'一期·UV电访分配'!L:L,"一期",'一期·UV电访分配'!A:A,"新宝利",'一期·UV电访分配'!BE:BE,"是") | U26: =IFERROR(T26/S26,0) | V26: =T26+Q26 | W26: =V26/E26
B27: 李润 | C27: 语文 | D27: 2 | E27: =COUNTIFS('UV台帐'!W:W,B27,'UV台帐'!AB:AB,"在读",'UV台帐'!AA:AA,"一期") | F27: =E27/(D27*25) | G27: =SUMPRODUCT(('UV台帐'!W:W=B27)*('UV台帐'!AC:AC="是")*('UV台帐'!AA:AA="一期")) | H27: =G27/E27 | I27: =COUNTIFS('UV台帐'!W:W,B27,'UV台帐'!AB:AB,"课前退",'UV台帐'!AA:AA,"一期") | J27: =I27/(E27+I27) | K27: =COUNTIFS('李润'!T:T,"是",'李润'!B:B,"一期")/E27 | L27: =COUNTIFS('李润'!U:U,"是",'李润'!B:B,"一期")/E27 | M27: =COUNTIFS('李润'!V:V,"是",'李润'!B:B,"一期")/E27 | N27: =COUNTIFS('一期·UV电访分配'!J:J,B27,'一期·UV电访分配'!AY:AY,"是") | O27: =N27/E27 | P27: =COUNTIFS('一期·UV电访分配'!J:J,B27,'一期·UV电访分配'!M:M,"在读",'一期·UV电访分配'!L:L,"一期",'一期·UV电访分配'!A:A,"同创汇") | Q27: =COUNTIFS('一期·UV电访分配'!J:J,B27,'一期·UV电访分配'!M:M,"在读",'一期·UV电访分配'!L:L,"一期",'一期·UV电访分配'!A:A,"同创汇",'一期·UV电访分配'!BE:BE,"是") | R27: =IFERROR(Q27/P27,0) | S27: =COUNTIFS('一期·UV电访分配'!J:J,B27,'一期·UV电访分配'!M:M,"在读",'一期·UV电访分配'!L:L,"一期",'一期·UV电访分配'!A:A,"新宝利") | T27: =COUNTIFS('一期·UV电访分配'!J:J,B27,'一期·UV电访分配'!M:M,"在读",'一期·UV电访分配'!L:L,"一期",'一期·UV电访分配'!A:A,"新宝利",'一期·UV电访分配'!BE:BE,"是") | U27: =T27/S27 | V27: =T27+Q27 | W27: =V27/E27
B28: 陈南05 | C28: 语文 | D28: 2 | E28: =COUNTIFS('UV台帐'!W:W,B28,'UV台帐'!AB:AB,"在读",'UV台帐'!AA:AA,"一期") | F28: =E28/(D28*25) | G28: =SUMPRODUCT(('UV台帐'!W:W=B28)*('UV台帐'!AC:AC="是")*('UV台帐'!AA:AA="一期")) | H28: =G28/E28 | I28: =COUNTIFS('UV台帐'!W:W,B28,'UV台帐'!AB:AB,"课前退",'UV台帐'!AA:AA,"一期") | J28: =I28/(E28+I28) | K28: =COUNTIFS('陈南05'!T:T,"是",'陈南05'!B:B,"一期")/E28 | L28: =COUNTIFS('陈南05'!U:U,"是",'陈南05'!B:B,"一期")/E28 | M28: =COUNTIFS('陈南05'!V:V,"是",'陈南05'!B:B,"一期")/E28 | N28: =COUNTIFS('一期·UV电访分配'!J:J,B28,'一期·UV电访分配'!AY:AY,"是") | O28: =N28/E28 | P28: =COUNTIFS('一期·UV电访分配'!J:J,B28,'一期·UV电访分配'!M:M,"在读",'一期·UV电访分配'!L:L,"一期",'一期·UV电访分配'!A:A,"同创汇") | Q28: =COUNTIFS('一期·UV电访分配'!J:J,B28,'一期·UV电访分配'!M:M,"在读",'一期·UV电访分配'!L:L,"一期",'一期·UV电访分配'!A:A,"同创汇",'一期·UV电访分配'!BE:BE,"是") | R28: =Q28/P28 | S28: =COUNTIFS('一期·UV电访分配'!J:J,B28,'一期·UV电访分配'!M:M,"在读",'一期·UV电访分配'!L:L,"一期",'一期·UV电访分配'!A:A,"新宝利") | T28: =COUNTIFS('一期·UV电访分配'!J:J,B28,'一期·UV电访分配'!M:M,"在读",'一期·UV电访分配'!L:L,"一期",'一期·UV电访分配'!A:A,"新宝利",'一期·UV电访分配'!BE:BE,"是") | U28: =IFERROR(T28/S28,0) | V28: =T28+Q28 | W28: =V28/E28
B29: 语文合计 | D29: =SUM(D26:D28) | E29: =SUM(E26:E28) | F29: =E29/(D29*25) | G29: =SUM(G26:G28) | H29: =G29/E29 | I29: =SUM(I26:I28) | J29: =I29/(E29+I29) | K29: =(K26*$E$50+K27*$E$51+K28*$E$52)/$E$53 | L29: =(L26*$E$50+L27*$E$51+L28*$E$52)/$E$53 | M29: =(M26*$E$50+M27*$E$51+M28*$E$52)/$E$53 | N29: =SUM(N26:N28) | O29: =N29/E29 | P29: =SUM(P26:P28) | Q29: =SUM(Q26:Q28) | R29: =Q29/P29 | S29: =SUM(S26:S28) | T29: =SUM(T26:T28) | U29: =T29/S29 | V29: =T29+Q29 | W29: =V29/E29
B30: 刘希子 | C30: 英语 | D30: 1 | E30: =COUNTIFS('UV台帐'!AF:AF,B30,'UV台帐'!AK:AK,"在读",'UV台帐'!AJ:AJ,"一期") | F30: =E30/(D30*25) | G30: =SUMPRODUCT(('UV台帐'!AF:AF=B30)*('UV台帐'!AL:AL="是")*('UV台帐'!AJ:AJ="一期")) | H30: =G30/E30 | I30: =COUNTIFS('UV台帐'!AF:AF,B30,'UV台帐'!AK:AK,"课前退",'UV台帐'!AJ:AJ,"一期") | J30: =I30/(E30+I30) | K30: =COUNTIFS('刘希子'!T:T,"是",'刘希子'!B:B,"一期")/E30 | L30: =COUNTIFS('刘希子'!U:U,"是",'刘希子'!B:B,"一期")/E30 | M30: =COUNTIFS('刘希子'!V:V,"是",'刘希子'!B:B,"一期")/E30 | N30: =COUNTIFS('一期·UV电访分配'!N:N,B30,'一期·UV电访分配'!AY:AY,"是") | O30: =N30/E30 | P30: =COUNTIFS('一期·UV电访分配'!N:N,B30,'一期·UV电访分配'!Q:Q,"在读",'一期·UV电访分配'!P:P,"一期",'一期·UV电访分配'!A:A,"同创汇") | Q30: =COUNTIFS('一期·UV电访分配'!N:N,B30,'一期·UV电访分配'!Q:Q,"在读",'一期·UV电访分配'!P:P,"一期",'一期·UV电访分配'!A:A,"同创汇",'一期·UV电访分配'!BE:BE,"是") | R30: =IFERROR(Q30/P30,0) | S30: =COUNTIFS('一期·UV电访分配'!N:N,B30,'一期·UV电访分配'!Q:Q,"在读",'一期·UV电访分配'!P:P,"一期",'一期·UV电访分配'!A:A,"新宝利") | T30: =COUNTIFS('一期·UV电访分配'!N:N,B30,'一期·UV电访分配'!Q:Q,"在读",'一期·UV电访分配'!P:P,"一期",'一期·UV电访分配'!A:A,"新宝利",'一期·UV电访分配'!BE:BE,"是") | U30: =IFERROR(T30/S30,0) | V30: =T30+Q30 | W30: =V30/E30
B31: 肖锐03 | C31: 英语 | D31: 2 | E31: =COUNTIFS('UV台帐'!AF:AF,B31,'UV台帐'!AK:AK,"在读",'UV台帐'!AJ:AJ,"一期") | F31: =E31/(D31*25) | G31: =SUMPRODUCT(('UV台帐'!AF:AF=B31)*('UV台帐'!AL:AL="是")*('UV台帐'!AJ:AJ="一期")) | H31: =G31/E31 | I31: =COUNTIFS('UV台帐'!AF:AF,B31,'UV台帐'!AK:AK,"课前退",'UV台帐'!AJ:AJ,"一期") | J31: =I31/(E31+I31) | K31: =COUNTIFS('肖锐03'!T:T,"是",'肖锐03'!B:B,"一期")/E31 | L31: =COUNTIFS('肖锐03'!U:U,"是",'肖锐03'!B:B,"一期")/E31 | M31: =COUNTIFS('肖锐03'!V:V,"是",'肖锐03'!B:B,"一期")/E31 | N31: =COUNTIFS('一期·UV电访分配'!N:N,B31,'一期·UV电访分配'!AY:AY,"是") | O31: =N31/E31 | P31: =COUNTIFS('一期·UV电访分配'!N:N,B31,'一期·UV电访分配'!Q:Q,"在读",'一期·UV电访分配'!P:P,"一期",'一期·UV电访分配'!A:A,"同创汇") | Q31: =COUNTIFS('一期·UV电访分配'!N:N,B31,'一期·UV电访分配'!Q:Q,"在读",'一期·UV电访分配'!P:P,"一期",'一期·UV电访分配'!A:A,"同创汇",'一期·UV电访分配'!BE:BE,"是") | R31: =IFERROR(Q31/P31,0) | S31: =COUNTIFS('一期·UV电访分配'!N:N,B31,'一期·UV电访分配'!Q:Q,"在读",'一期·UV电访分配'!P:P,"一期",'一期·UV电访分配'!A:A,"新宝利") | T31: =COUNTIFS('一期·UV电访分配'!N:N,B31,'一期·UV电访分配'!Q:Q,"在读",'一期·UV电访分配'!P:P,"一期",'一期·UV电访分配'!A:A,"新宝利",'一期·UV电访分配'!BE:BE,"是") | U31: =T31/S31 | V31: =T31+Q31 | W31: =V31/E31
B32: 高心怡04 | C32: 英语 | D32: 2 | E32: =COUNTIFS('UV台帐'!AF:AF,B32,'UV台帐'!AK:AK,"在读",'UV台帐'!AJ:AJ,"一期") | F32: =E32/(D32*25) | G32: =SUMPRODUCT(('UV台帐'!AF:AF=B32)*('UV台帐'!AL:AL="是")*('UV台帐'!AJ:AJ="一期")) | H32: =G32/E32 | I32: =COUNTIFS('UV台帐'!AF:AF,B32,'UV台帐'!AK:AK,"课前退",'UV台帐'!AJ:AJ,"一期") | J32: =I32/(E32+I32) | K32: =COUNTIFS('高心怡04'!T:T,"是",'高心怡04'!B:B,"一期")/E32 | L32: =COUNTIFS('高心怡04'!U:U,"是",'高心怡04'!B:B,"一期")/E32 | M32: =COUNTIFS('高心怡04'!V:V,"是",'高心怡04'!B:B,"一期")/E32 | N32: =COUNTIFS('一期·UV电访分配'!N:N,B32,'一期·UV电访分配'!AY:AY,"是") | O32: =N32/E32 | P32: =COUNTIFS('一期·UV电访分配'!N:N,B32,'一期·UV电访分配'!Q:Q,"在读",'一期·UV电访分配'!P:P,"一期",'一期·UV电访分配'!A:A,"同创汇") | Q32: =COUNTIFS('一期·UV电访分配'!N:N,B32,'一期·UV电访分配'!Q:Q,"在读",'一期·UV电访分配'!P:P,"一期",'一期·UV电访分配'!A:A,"同创汇",'一期·UV电访分配'!BE:BE,"是") | R32: =Q32/P32 | S32: =COUNTIFS('一期·UV电访分配'!N:N,B32,'一期·UV电访分配'!Q:Q,"在读",'一期·UV电访分配'!P:P,"一期",'一期·UV电访分配'!A:A,"新宝利") | T32: =COUNTIFS('一期·UV电访分配'!N:N,B32,'一期·UV电访分配'!Q:Q,"在读",'一期·UV电访分配'!P:P,"一期",'一期·UV电访分配'!A:A,"新宝利",'一期·UV电访分配'!BE:BE,"是") | U32: =IFERROR(T32/S32,0) | V32: =T32+Q32 | W32: =V32/E32
B33: 英语合计 | D33: =SUM(D30:D32) | E33: =SUM(E30:E32) | F33: =E33/(D33*25) | G33: =SUM(G30:G32) | H33: =G33/E33 | I33: =SUM(I30:I32) | J33: =I33/(E33+I33) | K33: =(K30*$E$54+K31*$E$55+K32*$E$56)/$E$57 | L33: =(L30*$E$54+L31*$E$55+L32*$E$56)/$E$57 | M33: =(M30*$E$54+M31*$E$55+M32*$E$56)/$E$57 | N33: =SUM(N30:N32) | O33: =N33/E33 | P33: =SUM(P30:P32) | Q33: =SUM(Q30:Q32) | R33: =Q33/P33 | S33: =SUM(S30:S32) | T33: =SUM(T30:T32) | U33: =T33/S33 | V33: =T33+Q33 | W33: =V33/E33
B35: 零期 | C35: 学员数 | E35: vip入群率 | F35: 课前家长会（UV） | H35: 课中家长会（UV） | J35: 转化率 （PV） | K35: 学员意向分层(PV)
B36: 校区 | C36: PV | D36: UV | F36: 课前诺访 | G36: 课前确访 | H36: 课中诺访 | I36: 课中确访 | K36: S | L36: 占比 | M36: A | N36: 占比 | O36: B | P36: 占比 | Q36: C | R36: 占比
B37: 天成大厦 | C37: =SUMIF('零期·UV电访分配'!A:A,B37,'零期·UV电访分配'!AS:AS) | D37: =COUNTIF('零期·UV电访分配'!A:A,B37) | E37: =IFERROR(COUNTIFS('零期·UV电访分配'!A:A,B37,'零期·UV电访分配'!AH:AH,"是")/D37,0) | F37: =IFERROR(COUNTIFS('零期·UV电访分配'!A:A,B37,'零期·UV电访分配'!S:S,"是")/D37,0) | G37: =IFERROR(COUNTIFS('零期·UV电访分配'!A:A,B37,'零期·UV电访分配'!T:T,"是")/D37,0) | H37: =IFERROR(COUNTIFS('零期·UV电访分配'!A:A,B37,'零期·UV电访分配'!AB:AB,"是")/D37,0) | I37: =IFERROR(COUNTIFS('零期·UV电访分配'!A:A,B37,'零期·UV电访分配'!AD:AD,"是")/D37,0) | J37: =IFERROR(SUMIF('零期·UV电访分配'!A:A,B37,'零期·UV电访分配'!AX:AX)/C37,0) | K37: =COUNTIFS('零期·UV电访分配'!A:A,B37,'零期·UV电访分配'!AM:AM,"S")+COUNTIFS('零期·UV电访分配'!A:A,B37,'零期·UV电访分配'!AN:AN,"S")+COUNTIFS('零期·UV电访分配'!A:A,B37,'零期·UV电访分配'!AO:AO,"S") | L37: =IFERROR(K37/C37,0) | M37: =COUNTIFS('零期·UV电访分配'!A:A,B37,'零期·UV电访分配'!AM:AM,"A")+COUNTIFS('零期·UV电访分配'!A:A,B37,'零期·UV电访分配'!AN:AN,"A")+COUNTIFS('零期·UV电访分配'!A:A,B37,'零期·UV电访分配'!AO:AO,"A") | N37: =IFERROR(M37/C37,0) | O37: =COUNTIFS('零期·UV电访分配'!A:A,B37,'零期·UV电访分配'!AM:AM,"B")+COUNTIFS('零期·UV电访分配'!A:A,B37,'零期·UV电访分配'!AN:AN,"B")+COUNTIFS('零期·UV电访分配'!A:A,B37,'零期·UV电访分配'!AO:AO,"B") | P37: =IFERROR(O37/C37,0) | Q37: =COUNTIFS('零期·UV电访分配'!A:A,B37,'零期·UV电访分配'!AM:AM,"C")+COUNTIFS('零期·UV电访分配'!A:A,B37,'零期·UV电访分配'!AN:AN,"C")+COUNTIFS('零期·UV电访分配'!A:A,B37,'零期·UV电访分配'!AO:AO,"C") | R37: =IFERROR(Q37/C37,0)
B38: 同创汇 | C38: =SUMIF('零期·UV电访分配'!A:A,B38,'零期·UV电访分配'!AS:AS) | D38: =COUNTIF('零期·UV电访分配'!A:A,B38) | E38: =COUNTIFS('零期·UV电访分配'!A:A,B38,'零期·UV电访分配'!AH:AH,"是")/D38 | F38: =COUNTIFS('零期·UV电访分配'!A:A,B38,'零期·UV电访分配'!S:S,"是")/D38 | G38: =COUNTIFS('零期·UV电访分配'!A:A,B38,'零期·UV电访分配'!T:T,"是")/D38 | H38: =COUNTIFS('零期·UV电访分配'!A:A,B38,'零期·UV电访分配'!AB:AB,"是")/D38 | I38: =COUNTIFS('零期·UV电访分配'!A:A,B38,'零期·UV电访分配'!AD:AD,"是")/D38 | J38: =SUMIF('零期·UV电访分配'!A:A,B38,'零期·UV电访分配'!AX:AX)/C38 | K38: =COUNTIFS('零期·UV电访分配'!A:A,B38,'零期·UV电访分配'!AM:AM,"S")+COUNTIFS('零期·UV电访分配'!A:A,B38,'零期·UV电访分配'!AN:AN,"S")+COUNTIFS('零期·UV电访分配'!A:A,B38,'零期·UV电访分配'!AO:AO,"S") | L38: =K38/C38 | M38: =COUNTIFS('零期·UV电访分配'!A:A,B38,'零期·UV电访分配'!AM:AM,"A")+COUNTIFS('零期·UV电访分配'!A:A,B38,'零期·UV电访分配'!AN:AN,"A")+COUNTIFS('零期·UV电访分配'!A:A,B38,'零期·UV电访分配'!AO:AO,"A") | N38: =M38/C38 | O38: =COUNTIFS('零期·UV电访分配'!A:A,B38,'零期·UV电访分配'!AM:AM,"B")+COUNTIFS('零期·UV电访分配'!A:A,B38,'零期·UV电访分配'!AN:AN,"B")+COUNTIFS('零期·UV电访分配'!A:A,B38,'零期·UV电访分配'!AO:AO,"B") | P38: =O38/C38 | Q38: =COUNTIFS('零期·UV电访分配'!A:A,B38,'零期·UV电访分配'!AM:AM,"C")+COUNTIFS('零期·UV电访分配'!A:A,B38,'零期·UV电访分配'!AN:AN,"C")+COUNTIFS('零期·UV电访分配'!A:A,B38,'零期·UV电访分配'!AO:AO,"C") | R38: =Q38/C38
B39: 新宝利 | C39: =SUMIF('零期·UV电访分配'!A:A,B39,'零期·UV电访分配'!AS:AS) | D39: =COUNTIF('零期·UV电访分配'!A:A,B39) | E39: =COUNTIFS('零期·UV电访分配'!A:A,B39,'零期·UV电访分配'!AH:AH,"是")/D39 | F39: =COUNTIFS('零期·UV电访分配'!A:A,B39,'零期·UV电访分配'!S:S,"是")/D39 | G39: =COUNTIFS('零期·UV电访分配'!A:A,B39,'零期·UV电访分配'!T:T,"是")/D39 | H39: =COUNTIFS('零期·UV电访分配'!A:A,B39,'零期·UV电访分配'!AB:AB,"是")/D39 | I39: =COUNTIFS('零期·UV电访分配'!A:A,B39,'零期·UV电访分配'!AD:AD,"是")/D39 | J39: =SUMIF('零期·UV电访分配'!A:A,B39,'零期·UV电访分配'!AX:AX)/C39 | K39: =COUNTIFS('零期·UV电访分配'!A:A,B39,'零期·UV电访分配'!AM:AM,"S")+COUNTIFS('零期·UV电访分配'!A:A,B39,'零期·UV电访分配'!AN:AN,"S")+COUNTIFS('零期·UV电访分配'!A:A,B39,'零期·UV电访分配'!AO:AO,"S") | L39: =K39/C39 | M39: =COUNTIFS('零期·UV电访分配'!A:A,B39,'零期·UV电访分配'!AM:AM,"A")+COUNTIFS('零期·UV电访分配'!A:A,B39,'零期·UV电访分配'!AN:AN,"A")+COUNTIFS('零期·UV电访分配'!A:A,B39,'零期·UV电访分配'!AO:AO,"A") | N39: =M39/C39 | O39: =COUNTIFS('零期·UV电访分配'!A:A,B39,'零期·UV电访分配'!AM:AM,"B")+COUNTIFS('零期·UV电访分配'!A:A,B39,'零期·UV电访分配'!AN:AN,"B")+COUNTIFS('零期·UV电访分配'!A:A,B39,'零期·UV电访分配'!AO:AO,"B") | P39: =O39/C39 | Q39: =COUNTIFS('零期·UV电访分配'!A:A,B39,'零期·UV电访分配'!AM:AM,"C")+COUNTIFS('零期·UV电访分配'!A:A,B39,'零期·UV电访分配'!AN:AN,"C")+COUNTIFS('零期·UV电访分配'!A:A,B39,'零期·UV电访分配'!AO:AO,"C") | R39: =Q39/C39
B40: 分校合计 | C40: =SUM(C37:C39) | D40: =SUM(D37:D39) | E40: =COUNTIF('零期·UV电访分配'!AH:AH,"是")/D40 | F40: =COUNTIF('零期·UV电访分配'!S:S,"是")/D40 | G40: =COUNTIF('零期·UV电访分配'!T:T,"是")/D40 | H40: =COUNTIF('零期·UV电访分配'!AB:AB,"是")/D40 | I40: =COUNTIF('零期·UV电访分配'!AD:AD,"是")/D40 | J40: ='零期·UV电访分配'!AX10/C40 | K40: =SUM(K37:K39) | L40: =K40/C40 | M40: =SUM(M37:M39) | N40: =M40/C40 | O40: =SUM(O37:O39) | P40: =O40/C40 | Q40: =SUM(Q37:Q39) | R40: =Q40/C40
B42: 零期汇总 | D42: 基础信息 | K42: 课前服务 | N42: 课中家长会
D43: =SUM(D45:D57)/2 | E43: =E49+E53+E57 | F43: =E43/(25*D43) | G43: =G49+G53+G57 | H43: =G43/E43 | I43: =SUM(I45:I57)/2 | J43: =I43/(E43+I43) | K43: =(K49*$E$49+K53*$E$53+K57*$E$57)/$E$43 | L43: =(L49*$E$49+L53*$E$53+L57*$E$57)/$E$43 | M43: =(M49*$E$49+M53*$E$53+M57*$E$57)/$E$43 | N43: =SUM(N45:N57)/2 | O43: =N43/E43 | P43: =SUM(P45:P57)/2 | Q43: =SUM(Q45:Q57)/2 | R43: =Q43/P43 | S43: =SUM(S45:S57)/2 | T43: =SUM(T45:T57)/2 | U43: =T43/S43 | V43: =SUM(V45:V57)/2 | W43: =V43/E43
B44: 老师看板 | C44: 学科 | D44: 班量 | E44: 在读PV | F44: 满班率 | G44: 暑续秋PV | H44: 转化率 | I44: 课前退PV | J44: 课前退率 | K44: 加微率 | L44: 首联率 | M44: vip入群率 | N44: 课中诺访 | O44: 诺访率PV | P44: 7月4日应到 | Q44: 7月4日实到 | R44: 到场率 | S44: 7月5日应到 | T44: 7月5日实到 | U44: 到场率 | V44: 整体到场 | W44: 到场率
B45: 陈中帅 | C45: 数学 | D45: 3 | E45: =COUNTIFS('UV台帐'!N:N,B45,'UV台帐'!S:S,"在读",'UV台帐'!R:R,"零期") | F45: =E45/(D45*25) | G45: =SUMPRODUCT(('UV台帐'!N:N=B45)*('UV台帐'!T:T="是")*('UV台帐'!R:R="零期")) | H45: =G45/E45 | I45: =COUNTIFS('UV台帐'!N:N,B45,'UV台帐'!S:S,"课前退",'UV台帐'!R:R,"零期") | J45: =I45/(E45+I45) | K45: =IFERROR(COUNTIFS('陈中帅'!T:T,"是",'陈中帅'!B:B,"零期")/E45,"") | L45: =COUNTIFS('陈中帅'!U:U,"是",'陈中帅'!B:B,"零期")/E45 | M45: =COUNTIFS('陈中帅'!V:V,"是",'陈中帅'!B:B,"零期")/E45 | N45: =COUNTIFS('零期·UV电访分配'!E:E,B45,'零期·UV电访分配'!AB:AB,"是") | O45: =N45/E45 | P45: =COUNTIFS('零期·UV电访分配'!E:E,B45,'零期·UV电访分配'!I:I,"在读",'零期·UV电访分配'!H:H,"零期",'零期·UV电访分配'!A:A,"同创汇") | Q45: =COUNTIFS('零期·UV电访分配'!E:E,B45,'零期·UV电访分配'!I:I,"在读",'零期·UV电访分配'!H:H,"零期",'零期·UV电访分配'!A:A,"同创汇",'零期·UV电访分配'!AD:AD,"是") | R45: =Q45/P45 | S45: =COUNTIFS('零期·UV电访分配'!E:E,B45,'零期·UV电访分配'!I:I,"在读",'零期·UV电访分配'!H:H,"零期",'零期·UV电访分配'!A:A,"新宝利") | T45: =COUNTIFS('零期·UV电访分配'!E:E,B45,'零期·UV电访分配'!I:I,"在读",'零期·UV电访分配'!H:H,"零期",'零期·UV电访分配'!A:A,"新宝利",'零期·UV电访分配'!AD:AD,"是") | U45: =T45/S45 | V45: =T45+Q45 | W45: =V45/E45
B46: 何咏04 | C46: 数学 | D46: 0 | E46: =COUNTIFS('UV台帐'!N:N,B46,'UV台帐'!S:S,"在读",'UV台帐'!R:R,"零期") | F46: =IFERROR(E46/(D46*25),"0") | G46: =SUMPRODUCT(('UV台帐'!N:N=B46)*('UV台帐'!T:T="是")*('UV台帐'!R:R="零期")) | H46: =IFERROR(G46/E46,"0") | I46: =COUNTIFS('UV台帐'!N:N,B46,'UV台帐'!S:S,"课前退",'UV台帐'!R:R,"零期") | J46: =IFERROR(I46/(E46+I46),"0") | K46: =IFERROR(COUNTIFS('何咏04'!T:T,"是",'何咏04'!B:B,"零期")/E46,"0") | L46: =IFERROR(COUNTIFS('何咏04'!U:U,"是",'何咏04'!B:B,"零期")/E46,"0") | M46: =IFERROR(COUNTIFS('何咏04'!V:V,"是",'何咏04'!B:B,"零期")/E46,"0") | N46: =COUNTIFS('零期·UV电访分配'!E:E,B46,'零期·UV电访分配'!AB:AB,"是") | O46: =IFERROR(N46/E46,0) | P46: =COUNTIFS('零期·UV电访分配'!E:E,B46,'零期·UV电访分配'!I:I,"在读",'零期·UV电访分配'!H:H,"零期",'零期·UV电访分配'!A:A,"同创汇") | Q46: =COUNTIFS('零期·UV电访分配'!E:E,B46,'零期·UV电访分配'!I:I,"在读",'零期·UV电访分配'!H:H,"零期",'零期·UV电访分配'!A:A,"同创汇",'零期·UV电访分配'!AD:AD,"是") | R46: =IFERROR(Q46/P46,0) | T46: 0 | U46: =IFERROR(T46/S46,0) | V46: =T46+Q46 | W46: =IFERROR(V46/E46,0)
B47: 田雨涵01 | C47: 数学 | D47: 2 | E47: =COUNTIFS('UV台帐'!N:N,B47,'UV台帐'!S:S,"在读",'UV台帐'!R:R,"零期") | F47: =E47/(D47*25) | G47: =SUMPRODUCT(('UV台帐'!N:N=B47)*('UV台帐'!T:T="是")*('UV台帐'!R:R="零期")) | H47: =G47/E47 | I47: =COUNTIFS('UV台帐'!N:N,B47,'UV台帐'!S:S,"课前退",'UV台帐'!R:R,"零期") | J47: =I47/(E47+I47) | K47: =COUNTIFS('田雨涵01'!T:T,"是",'田雨涵01'!B:B,"零期")/E47 | L47: =COUNTIFS('田雨涵01'!U:U,"是",'田雨涵01'!B:B,"零期")/E47 | M47: =COUNTIFS('田雨涵01'!V:V,"是",'田雨涵01'!B:B,"零期")/E47 | N47: =COUNTIFS('零期·UV电访分配'!E:E,B47,'零期·UV电访分配'!AB:AB,"是") | O47: =N47/E47 | P47: =COUNTIFS('零期·UV电访分配'!E:E,B47,'零期·UV电访分配'!I:I,"在读",'零期·UV电访分配'!H:H,"零期",'零期·UV电访分配'!A:A,"同创汇") | Q47: =COUNTIFS('零期·UV电访分配'!E:E,B47,'零期·UV电访分配'!I:I,"在读",'零期·UV电访分配'!H:H,"零期",'零期·UV电访分配'!A:A,"同创汇",'零期·UV电访分配'!AD:AD,"是") | R47: =Q47/P47 | S47: =COUNTIFS('零期·UV电访分配'!E:E,B47,'零期·UV电访分配'!I:I,"在读",'零期·UV电访分配'!H:H,"零期",'零期·UV电访分配'!A:A,"新宝利") | T47: =COUNTIFS('零期·UV电访分配'!E:E,B47,'零期·UV电访分配'!I:I,"在读",'零期·UV电访分配'!H:H,"零期",'零期·UV电访分配'!A:A,"新宝利",'零期·UV电访分配'!AD:AD,"是") | U47: =T47/S47 | V47: =T47+Q47 | W47: =V47/E47
B48: 宗志鹏 | C48: 数学 | D48: 0 | E48: =COUNTIFS('UV台帐'!N:N,B48,'UV台帐'!S:S,"在读",'UV台帐'!R:R,"零期") | F48: =IFERROR(E48/(D48*25),"0") | G48: =SUMPRODUCT(('UV台帐'!N:N=B48)*('UV台帐'!T:T="是")*('UV台帐'!R:R="零期")) | H48: =IFERROR(G48/E48,"0") | I48: =COUNTIFS('UV台帐'!N:N,B48,'UV台帐'!S:S,"课前退",'UV台帐'!R:R,"零期") | J48: =IFERROR(I48/(E48+I48),"0") | K48: =IFERROR(COUNTIFS('宗志鹏'!T:T,"是",'宗志鹏'!B:B,"零期")/E48,"0") | L48: =IFERROR(COUNTIFS('宗志鹏'!U:U,"是",'宗志鹏'!B:B,"零期")/E48,"0") | M48: =IFERROR(COUNTIFS('宗志鹏'!V:V,"是",'宗志鹏'!B:B,"零期")/E48,"0") | N48: =COUNTIFS('零期·UV电访分配'!E:E,B48,'零期·UV电访分配'!AB:AB,"是") | O48: =IFERROR(N48/E48,0) | P48: =COUNTIFS('零期·UV电访分配'!E:E,B48,'零期·UV电访分配'!I:I,"在读",'零期·UV电访分配'!H:H,"零期",'零期·UV电访分配'!A:A,"同创汇") | Q48: 0 | R48: =IFERROR(Q48/P48,0) | T48: 0 | U48: =IFERROR(T48/S48,0) | V48: =T48+Q48 | W48: =IFERROR(V48/E48,0)
B49: 数学合计 | D49: =SUM(D45:D48) | E49: =SUM(E45:E48) | F49: =E49/(D49*25) | G49: =SUM(G45:G48) | H49: =G49/E49 | I49: =SUM(I45:I48) | J49: =I49/(E49+I49) | K49: =(K45*$E$45+K46*$E$46+K47*$E$47+K48*$E$48)/$E$49 | L49: =(L45*$E$45+L46*$E$46+L47*$E$47+L48*$E$48)/$E$49 | M49: =(M45*$E$45+M46*$E$46+M47*$E$47+M48*$E$48)/$E$49 | N49: =SUM(N45:N47) | O49: =N49/E49 | P49: =SUM(P45:P47) | Q49: =SUM(Q45:Q47) | R49: =Q49/P49 | S49: =SUM(S45:S47) | T49: =SUM(T45:T47) | U49: =T49/S49 | V49: =T49+Q49 | W49: =V49/E49
B50: 黄铭怡 | C50: 语文 | D50: 2 | E50: =COUNTIFS('UV台帐'!W:W,B50,'UV台帐'!AB:AB,"在读",'UV台帐'!AA:AA,"零期") | F50: =E50/(D50*25) | G50: =SUMPRODUCT(('UV台帐'!W:W=B50)*('UV台帐'!AC:AC="是")*('UV台帐'!AA:AA="零期")) | H50: =G50/E50 | I50: =COUNTIFS('UV台帐'!W:W,B50,'UV台帐'!AB:AB,"课前退",'UV台帐'!AA:AA,"零期") | J50: =I50/(E50+I50) | K50: =COUNTIFS('黄铭怡'!T:T,"是",'黄铭怡'!B:B,"零期")/E50 | L50: =COUNTIFS('黄铭怡'!U:U,"是",'黄铭怡'!B:B,"零期")/E50 | M50: =COUNTIFS('黄铭怡'!V:V,"是",'黄铭怡'!B:B,"零期")/E50 | N50: =COUNTIFS('零期·UV电访分配'!J:J,B50,'零期·UV电访分配'!AB:AB,"是") | O50: =N50/E50 | P50: =COUNTIFS('零期·UV电访分配'!J:J,B50,'零期·UV电访分配'!M:M,"在读",'零期·UV电访分配'!L:L,"零期",'零期·UV电访分配'!A:A,"同创汇") | Q50: =COUNTIFS('零期·UV电访分配'!J:J,B50,'零期·UV电访分配'!M:M,"在读",'零期·UV电访分配'!L:L,"零期",'零期·UV电访分配'!A:A,"同创汇",'零期·UV电访分配'!AD:AD,"是") | R50: =Q50/P50 | S50: =COUNTIFS('零期·UV电访分配'!J:J,B50,'零期·UV电访分配'!M:M,"在读",'零期·UV电访分配'!L:L,"零期",'零期·UV电访分配'!A:A,"新宝利") | T50: =COUNTIFS('零期·UV电访分配'!J:J,B50,'零期·UV电访分配'!M:M,"在读",'零期·UV电访分配'!L:L,"零期",'零期·UV电访分配'!A:A,"新宝利",'零期·UV电访分配'!AD:AD,"是") | U50: =T50/S50 | V50: =T50+Q50 | W50: =V50/E50
B51: 李润 | C51: 语文 | D51: 2 | E51: =COUNTIFS('UV台帐'!W:W,B51,'UV台帐'!AB:AB,"在读",'UV台帐'!AA:AA,"零期") | F51: =E51/(D51*25) | G51: =SUMPRODUCT(('UV台帐'!W:W=B51)*('UV台帐'!AC:AC="是")*('UV台帐'!AA:AA="零期")) | H51: =G51/E51 | I51: =COUNTIFS('UV台帐'!W:W,B51,'UV台帐'!AB:AB,"课前退",'UV台帐'!AA:AA,"零期") | J51: =I51/(E51+I51) | K51: =COUNTIFS('李润'!T:T,"是",'李润'!B:B,"零期")/E51 | L51: =COUNTIFS('李润'!U:U,"是",'李润'!B:B,"零期")/E51 | M51: =COUNTIFS('李润'!V:V,"是",'李润'!B:B,"零期")/E51 | N51: =COUNTIFS('零期·UV电访分配'!J:J,B51,'零期·UV电访分配'!AB:AB,"是") | O51: =N51/E51 | P51: =COUNTIFS('零期·UV电访分配'!J:J,B51,'零期·UV电访分配'!M:M,"在读",'零期·UV电访分配'!L:L,"零期",'零期·UV电访分配'!A:A,"同创汇") | Q51: =COUNTIFS('零期·UV电访分配'!J:J,B51,'零期·UV电访分配'!M:M,"在读",'零期·UV电访分配'!L:L,"零期",'零期·UV电访分配'!A:A,"同创汇",'零期·UV电访分配'!AD:AD,"是") | R51: =Q51/P51 | S51: =COUNTIFS('零期·UV电访分配'!J:J,B51,'零期·UV电访分配'!M:M,"在读",'零期·UV电访分配'!L:L,"零期",'零期·UV电访分配'!A:A,"新宝利") | T51: =COUNTIFS('零期·UV电访分配'!J:J,B51,'零期·UV电访分配'!M:M,"在读",'零期·UV电访分配'!L:L,"零期",'零期·UV电访分配'!A:A,"新宝利",'零期·UV电访分配'!AD:AD,"是") | U51: =T51/S51 | V51: =T51+Q51 | W51: =V51/E51
B52: 陈南05 | C52: 语文 | D52: 1 | E52: =COUNTIFS('UV台帐'!W:W,B52,'UV台帐'!AB:AB,"在读",'UV台帐'!AA:AA,"零期") | F52: =E52/(D52*25) | G52: =SUMPRODUCT(('UV台帐'!W:W=B52)*('UV台帐'!AC:AC="是")*('UV台帐'!AA:AA="零期")) | H52: =G52/E52 | I52: =COUNTIFS('UV台帐'!W:W,B52,'UV台帐'!AB:AB,"课前退",'UV台帐'!AA:AA,"零期") | J52: =I52/(E52+I52) | K52: =COUNTIFS('陈南05'!T:T,"是",'陈南05'!B:B,"零期")/E52 | L52: =COUNTIFS('陈南05'!U:U,"是",'陈南05'!B:B,"零期")/E52 | M52: =COUNTIFS('陈南05'!V:V,"是",'陈南05'!B:B,"零期")/E52 | N52: =COUNTIFS('零期·UV电访分配'!J:J,B52,'零期·UV电访分配'!AB:AB,"是") | O52: =N52/E52 | P52: =COUNTIFS('零期·UV电访分配'!J:J,B52,'零期·UV电访分配'!M:M,"在读",'零期·UV电访分配'!L:L,"零期",'零期·UV电访分配'!A:A,"同创汇") | Q52: =COUNTIFS('零期·UV电访分配'!J:J,B52,'零期·UV电访分配'!M:M,"在读",'零期·UV电访分配'!L:L,"零期",'零期·UV电访分配'!A:A,"同创汇",'零期·UV电访分配'!AD:AD,"是") | R52: =Q52/P52 | S52: =COUNTIFS('零期·UV电访分配'!J:J,B52,'零期·UV电访分配'!M:M,"在读",'零期·UV电访分配'!L:L,"零期",'零期·UV电访分配'!A:A,"新宝利") | T52: =COUNTIFS('零期·UV电访分配'!J:J,B52,'零期·UV电访分配'!M:M,"在读",'零期·UV电访分配'!L:L,"零期",'零期·UV电访分配'!A:A,"新宝利",'零期·UV电访分配'!AD:AD,"是") | U52: =IFERROR(T52/S52,0) | V52: =T52+Q52 | W52: =V52/E52
B53: 语文合计 | D53: =SUM(D50:D52) | E53: =SUM(E50:E52) | F53: =E53/(D53*25) | G53: =SUM(G50:G52) | H53: =G53/E53 | I53: =SUM(I50:I52) | J53: =I53/(E53+I53) | K53: =(K50*$E$50+K51*$E$51+K52*$E$52)/$E$53 | L53: =(L50*$E$50+L51*$E$51+L52*$E$52)/$E$53 | M53: =(M50*$E$50+M51*$E$51+M52*$E$52)/$E$53 | N53: =SUM(N50:N52) | O53: =N53/E53 | P53: =SUM(P50:P52) | Q53: =SUM(Q50:Q52) | R53: =Q53/P53 | S53: =SUM(S50:S52) | T53: =SUM(T50:T52) | U53: =T53/S53 | V53: =T53+Q53 | W53: =V53/E53 | Y53: 校区 | Z53: 零期总PV | AA53: 已转PV | AB53: 应转PV | AC53: 转化目标 | AD53: 实际转化PV | AE53: 实际转化率 | AF53: 达成率
B54: 刘希子 | C54: 英语 | D54: 2 | E54: =COUNTIFS('UV台帐'!AF:AF,B54,'UV台帐'!AK:AK,"在读",'UV台帐'!AJ:AJ,"零期") | F54: =E54/(D54*25) | G54: =SUMPRODUCT(('UV台帐'!AF:AF=B54)*('UV台帐'!AL:AL="是")*('UV台帐'!AJ:AJ="零期")) | H54: =G54/E54 | I54: =COUNTIFS('UV台帐'!AF:AF,B54,'UV台帐'!AK:AK,"课前退",'UV台帐'!AJ:AJ,"零期") | J54: =I54/(E54+I54) | K54: =COUNTIFS('刘希子'!T:T,"是",'刘希子'!B:B,"零期")/E54 | L54: =COUNTIFS('刘希子'!U:U,"是",'刘希子'!B:B,"零期")/E54 | M54: =COUNTIFS('刘希子'!V:V,"是",'刘希子'!B:B,"零期")/E54 | N54: =COUNTIFS('零期·UV电访分配'!N:N,B54,'零期·UV电访分配'!AB:AB,"是") | O54: =N54/E54 | P54: =COUNTIFS('零期·UV电访分配'!N:N,B54,'零期·UV电访分配'!Q:Q,"在读",'零期·UV电访分配'!P:P,"零期",'零期·UV电访分配'!A:A,"同创汇") | Q54: =COUNTIFS('零期·UV电访分配'!N:N,B54,'零期·UV电访分配'!Q:Q,"在读",'零期·UV电访分配'!P:P,"零期",'零期·UV电访分配'!A:A,"同创汇",'零期·UV电访分配'!AD:AD,"是") | R54: =Q54/P54 | S54: =COUNTIFS('零期·UV电访分配'!N:N,B54,'零期·UV电访分配'!Q:Q,"在读",'零期·UV电访分配'!P:P,"零期",'零期·UV电访分配'!A:A,"新宝利") | T54: =COUNTIFS('零期·UV电访分配'!N:N,B54,'零期·UV电访分配'!Q:Q,"在读",'零期·UV电访分配'!P:P,"零期",'零期·UV电访分配'!A:A,"新宝利",'零期·UV电访分配'!AD:AD,"是") | U54: =IFERROR(T54/S54,0) | V54: =T54+Q54 | W54: =V54/E54 | Y54: 天成大厦 | Z54: =SUMIF('零期·UV电访分配'!A:A,Y54,'零期·UV电访分配'!AS:AS) | AA54: 0 | AB54: =Z54-AA54 | AC54: =AB54*55% | AD54: =SUMIF('零期·UV电访分配'!A:A,Y54,'零期·UV电访分配'!AX:AX)-AA54 | AE54: =IFERROR(AD54/AB54,0) | AF54: =IFERROR(AD54/AC54,0)
B55: 肖锐03 | C55: 英语 | D55: 2 | E55: =COUNTIFS('UV台帐'!AF:AF,B55,'UV台帐'!AK:AK,"在读",'UV台帐'!AJ:AJ,"零期") | F55: =E55/(D55*25) | G55: =SUMPRODUCT(('UV台帐'!AF:AF=B55)*('UV台帐'!AL:AL="是")*('UV台帐'!AJ:AJ="零期")) | H55: =G55/E55 | I55: =COUNTIFS('UV台帐'!AF:AF,B55,'UV台帐'!AK:AK,"课前退",'UV台帐'!AJ:AJ,"零期") | J55: =I55/(E55+I55) | K55: =COUNTIFS('肖锐03'!T:T,"是",'肖锐03'!B:B,"零期")/E55 | L55: =COUNTIFS('肖锐03'!U:U,"是",'肖锐03'!B:B,"零期")/E55 | M55: =COUNTIFS('肖锐03'!V:V,"是",'肖锐03'!B:B,"零期")/E55 | N55: =COUNTIFS('零期·UV电访分配'!N:N,B55,'零期·UV电访分配'!AB:AB,"是") | O55: =N55/E55 | P55: =COUNTIFS('零期·UV电访分配'!N:N,B55,'零期·UV电访分配'!Q:Q,"在读",'零期·UV电访分配'!P:P,"零期",'零期·UV电访分配'!A:A,"同创汇") | Q55: =COUNTIFS('零期·UV电访分配'!N:N,B55,'零期·UV电访分配'!Q:Q,"在读",'零期·UV电访分配'!P:P,"零期",'零期·UV电访分配'!A:A,"同创汇",'零期·UV电访分配'!AD:AD,"是") | R55: =IFERROR(Q55/P55,0) | S55: =COUNTIFS('零期·UV电访分配'!N:N,B55,'零期·UV电访分配'!Q:Q,"在读",'零期·UV电访分配'!P:P,"零期",'零期·UV电访分配'!A:A,"新宝利") | T55: =COUNTIFS('零期·UV电访分配'!N:N,B55,'零期·UV电访分配'!Q:Q,"在读",'零期·UV电访分配'!P:P,"零期",'零期·UV电访分配'!A:A,"新宝利",'零期·UV电访分配'!AD:AD,"是") | U55: =T55/S55 | V55: =T55+Q55 | W55: =V55/E55 | Y55: 同创汇 | Z55: =SUMIF('零期·UV电访分配'!A:A,Y55,'零期·UV电访分配'!AS:AS) | AA55: 28 | AB55: =Z55-AA55 | AC55: =AB55*55% | AD55: =SUMIF('零期·UV电访分配'!A:A,Y55,'零期·UV电访分配'!AX:AX)-AA55 | AE55: =AD55/AB55 | AF55: =AD55/AC55
B56: 高心怡04 | C56: 英语 | D56: 1 | E56: =COUNTIFS('UV台帐'!AF:AF,B56,'UV台帐'!AK:AK,"在读",'UV台帐'!AJ:AJ,"零期") | F56: =E56/(D56*25) | G56: =SUMPRODUCT(('UV台帐'!AF:AF=B56)*('UV台帐'!AL:AL="是")*('UV台帐'!AJ:AJ="零期")) | H56: =G56/E56 | I56: =COUNTIFS('UV台帐'!AF:AF,B56,'UV台帐'!AK:AK,"课前退",'UV台帐'!AJ:AJ,"零期") | J56: =I56/(E56+I56) | K56: =COUNTIFS('高心怡04'!T:T,"是",'高心怡04'!B:B,"零期")/E56 | L56: =COUNTIFS('高心怡04'!U:U,"是",'高心怡04'!B:B,"零期")/E56 | M56: =COUNTIFS('高心怡04'!V:V,"是",'高心怡04'!B:B,"零期")/E56 | N56: =COUNTIFS('零期·UV电访分配'!N:N,B56,'零期·UV电访分配'!AB:AB,"是") | O56: =N56/E56 | P56: =COUNTIFS('零期·UV电访分配'!N:N,B56,'零期·UV电访分配'!Q:Q,"在读",'零期·UV电访分配'!P:P,"零期",'零期·UV电访分配'!A:A,"同创汇") | Q56: =COUNTIFS('零期·UV电访分配'!N:N,B56,'零期·UV电访分配'!Q:Q,"在读",'零期·UV电访分配'!P:P,"零期",'零期·UV电访分配'!A:A,"同创汇",'零期·UV电访分配'!AD:AD,"是") | R56: =Q56/P56 | S56: =COUNTIFS('零期·UV电访分配'!N:N,B56,'零期·UV电访分配'!Q:Q,"在读",'零期·UV电访分配'!P:P,"零期",'零期·UV电访分配'!A:A,"新宝利") | T56: =COUNTIFS('零期·UV电访分配'!N:N,B56,'零期·UV电访分配'!Q:Q,"在读",'零期·UV电访分配'!P:P,"零期",'零期·UV电访分配'!A:A,"新宝利",'零期·UV电访分配'!AD:AD,"是") | U56: =IFERROR(T56/S56,0) | V56: =T56+Q56 | W56: =V56/E56 | Y56: 新宝利 | Z56: =SUMIF('零期·UV电访分配'!A:A,Y56,'零期·UV电访分配'!AS:AS) | AA56: 14 | AB56: =Z56-AA56 | AC56: =AB56*55% | AD56: =SUMIF('零期·UV电访分配'!A:A,Y56,'零期·UV电访分配'!AX:AX)-AA56 | AE56: =AD56/AB56 | AF56: =AD56/AC56
B57: 英语合计 | D57: =SUM(D54:D56) | E57: =SUM(E54:E56) | F57: =E57/(D57*25) | G57: =SUM(G54:G56) | H57: =G57/E57 | I57: =SUM(I54:I56) | J57: =I57/(E57+I57) | K57: =(K54*$E$54+K55*$E$55+K56*$E$56)/$E$57 | L57: =(L54*$E$54+L55*$E$55+L56*$E$56)/$E$57 | M57: =(M54*$E$54+M55*$E$55+M56*$E$56)/$E$57 | N57: =SUM(N54:N56) | O57: =N57/E57 | P57: =SUM(P54:P56) | Q57: =SUM(Q54:Q56) | R57: =Q57/P57 | S57: =SUM(S54:S56) | T57: =SUM(T54:T56) | U57: =T57/S57 | V57: =T57+Q57 | W57: =V57/E57 | Y57: 分校合计 | Z57: =SUM(Z54:Z56) | AA57: =SUM(AA54:AA56) | AB57: =Z57-AA57 | AC57: =AB57*55% | AD57: =SUM(AD54:AD56) | AE57: =AD57/AB57 | AF57: =AD57/AC57
B60: 班型 | C60: 分数段 | D60: 数学分层 | U60: 生源质量 | V60: 整体 | X60: 新宝利 | Z60: 同创汇 | AB60: 天成大厦
D61: 校区合计 | E61: 新宝利 | F61: 零期 | G61: 一期 | H61: 二期 | I61: 三期 | J61: 同创汇 | K61: 零期 | L61: 一期 | M61: 二期 | N61: 三期 | O61: 天成大厦 | P61: 零期 | Q61: 一期 | R61: 二期 | S61: 三期 | V61: UV | W61: 占比 | X61: UV | Y61: 占比 | Z61: UV | AA61: 占比 | AB61: UV | AC61: 占比
B62: 启能 | C62: 95-120 | D62: =E62+J62+O62 | E62: =COUNTIFS('UV台帐'!A:A,$E$61,'UV台帐'!L:L,">=95") | F62: =COUNTIFS('UV台帐'!A:A,$E$61,'UV台帐'!L:L,">=95",'UV台帐'!R:R,"零期") | G62: =COUNTIFS('UV台帐'!A:A,$E$61,'UV台帐'!L:L,">=95",'UV台帐'!R:R,"一期") | H62: =COUNTIFS('UV台帐'!A:A,$E$61,'UV台帐'!L:L,">=95",'UV台帐'!R:R,"二期") | I62: =COUNTIFS('UV台帐'!A:A,$E$61,'UV台帐'!L:L,">=95",'UV台帐'!R:R,"三期") | J62: =COUNTIFS('UV台帐'!A:A,$J$61,'UV台帐'!L:L,">=95") | K62: =COUNTIFS('UV台帐'!A:A,"同创汇",'UV台帐'!L:L,">=95",'UV台帐'!R:R,"零期") | L62: =COUNTIFS('UV台帐'!A:A,"同创汇",'UV台帐'!L:L,">=95",'UV台帐'!R:R,"一期") | M62: =COUNTIFS('UV台帐'!A:A,"同创汇",'UV台帐'!L:L,">=95",'UV台帐'!R:R,"二期") | N62: =COUNTIFS('UV台帐'!A:A,"同创汇",'UV台帐'!L:L,">=95",'UV台帐'!R:R,"三期") | O62: =COUNTIFS('UV台帐'!A:A,$O$61,'UV台帐'!L:L,">=95") | P62: =COUNTIFS('UV台帐'!A:A,"天成大厦",'UV台帐'!L:L,">=95",'UV台帐'!R:R,"零期") | Q62: =COUNTIFS('UV台帐'!A:A,"天成大厦",'UV台帐'!L:L,">=95",'UV台帐'!R:R,"一期") | R62: =COUNTIFS('UV台帐'!A:A,"天成大厦",'UV台帐'!L:L,">=95",'UV台帐'!R:R,"二期") | S62: =COUNTIFS('UV台帐'!A:A,"天成大厦",'UV台帐'!L:L,">=95",'UV台帐'!R:R,"三期") | U62: 纯拉新 | V62: =X62+Z62+AB62 | W62: =V62/$V$68 | X62: =COUNTIFS('UV台帐'!A:A,$X$60,'UV台帐'!E:E,U62) | Y62: =X62/$X$68 | Z62: =COUNTIFS('UV台帐'!A:A,$Z$60,'UV台帐'!E:E,U62) | AA62: =Z62/$Z$68 | AB62: =COUNTIFS('UV台帐'!A:A,$AB$60,'UV台帐'!E:E,U62) | AC62: =AB62/$AB$68
C63: 80-94 | D63: =E63+J63+O63 | E63: =COUNTIFS('UV台帐'!A:A,$E$61,'UV台帐'!L:L,">=80",'UV台帐'!L:L,"<95") | F63: =COUNTIFS('UV台帐'!A:A,$E$61,'UV台帐'!L:L,">=80",'UV台帐'!L:L,"<95",'UV台帐'!R:R,"零期") | G63: =COUNTIFS('UV台帐'!A:A,$E$61,'UV台帐'!L:L,">=80",'UV台帐'!L:L,"<95",'UV台帐'!R:R,"一期") | H63: =COUNTIFS('UV台帐'!A:A,$E$61,'UV台帐'!L:L,">=80",'UV台帐'!L:L,"<95",'UV台帐'!R:R,"二期") | I63: =COUNTIFS('UV台帐'!A:A,$E$61,'UV台帐'!L:L,">=80",'UV台帐'!L:L,"<95",'UV台帐'!R:R,"三期") | J63: =COUNTIFS('UV台帐'!A:A,$J$61,'UV台帐'!L:L,">=80",'UV台帐'!L:L,"<95") | K63: =COUNTIFS('UV台帐'!A:A,"同创汇",'UV台帐'!L:L,">=80",'UV台帐'!L:L,"<95",'UV台帐'!R:R,"零期") | L63: =COUNTIFS('UV台帐'!A:A,"同创汇",'UV台帐'!L:L,">=80",'UV台帐'!L:L,"<95",'UV台帐'!R:R,"一期") | M63: =COUNTIFS('UV台帐'!A:A,"同创汇",'UV台帐'!L:L,">=80",'UV台帐'!L:L,"<95",'UV台帐'!R:R,"二期") | N63: =COUNTIFS('UV台帐'!A:A,"同创汇",'UV台帐'!L:L,">=80",'UV台帐'!L:L,"<95",'UV台帐'!R:R,"三期") | O63: =COUNTIFS('UV台帐'!A:A,$O$61,'UV台帐'!L:L,">=80",'UV台帐'!L:L,"<95") | P63: =COUNTIFS('UV台帐'!A:A,"天成大厦",'UV台帐'!L:L,">=80",'UV台帐'!L:L,"<95",'UV台帐'!R:R,"零期") | Q63: =COUNTIFS('UV台帐'!A:A,"天成大厦",'UV台帐'!L:L,">=80",'UV台帐'!L:L,"<95",'UV台帐'!R:R,"一期") | R63: =COUNTIFS('UV台帐'!A:A,"天成大厦",'UV台帐'!L:L,">=80",'UV台帐'!L:L,"<95",'UV台帐'!R:R,"二期") | S63: =COUNTIFS('UV台帐'!A:A,"天成大厦",'UV台帐'!L:L,">=80",'UV台帐'!L:L,"<95",'UV台帐'!R:R,"三期") | U63: 春季在读老生 | V63: =X63+Z63+AB63 | W63: =V63/$V$68 | X63: =COUNTIFS('UV台帐'!A:A,$X$60,'UV台帐'!E:E,U63) | Y63: =X63/$X$68 | Z63: =COUNTIFS('UV台帐'!A:A,$Z$60,'UV台帐'!E:E,U63) | AA63: =Z63/$Z$68 | AB63: =COUNTIFS('UV台帐'!A:A,$AB$60,'UV台帐'!E:E,U63) | AC63: =AB63/$AB$68
B64: 潜能 | C64: 60-79 | D64: =E64+J64+O64 | E64: =COUNTIFS('UV台帐'!A:A,$E$61,'UV台帐'!L:L,">=60",'UV台帐'!L:L,"<80") | F64: =COUNTIFS('UV台帐'!A:A,$E$61,'UV台帐'!L:L,">=60",'UV台帐'!L:L,"<80",'UV台帐'!R:R,"零期") | G64: =COUNTIFS('UV台帐'!A:A,$E$61,'UV台帐'!L:L,">=60",'UV台帐'!L:L,"<80",'UV台帐'!R:R,"一期") | H64: =COUNTIFS('UV台帐'!A:A,$E$61,'UV台帐'!L:L,">=60",'UV台帐'!L:L,"<80",'UV台帐'!R:R,"二期") | I64: =COUNTIFS('UV台帐'!A:A,$E$61,'UV台帐'!L:L,">=60",'UV台帐'!L:L,"<80",'UV台帐'!R:R,"三期") | J64: =COUNTIFS('UV台帐'!A:A,$J$61,'UV台帐'!L:L,">=60",'UV台帐'!L:L,"<80") | K64: =COUNTIFS('UV台帐'!A:A,"同创汇",'UV台帐'!L:L,">=60",'UV台帐'!L:L,"<80",'UV台帐'!R:R,"零期") | L64: =COUNTIFS('UV台帐'!A:A,"同创汇",'UV台帐'!L:L,">=60",'UV台帐'!L:L,"<80",'UV台帐'!R:R,"一期") | M64: =COUNTIFS('UV台帐'!A:A,"同创汇",'UV台帐'!L:L,">=60",'UV台帐'!L:L,"<80",'UV台帐'!R:R,"二期") | N64: =COUNTIFS('UV台帐'!A:A,"同创汇",'UV台帐'!L:L,">=60",'UV台帐'!L:L,"<80",'UV台帐'!R:R,"三期") | O64: =COUNTIFS('UV台帐'!A:A,$O$61,'UV台帐'!L:L,">=60",'UV台帐'!L:L,"<80") | P64: =COUNTIFS('UV台帐'!A:A,"天成大厦",'UV台帐'!L:L,">=60",'UV台帐'!L:L,"<80",'UV台帐'!R:R,"零期") | Q64: =COUNTIFS('UV台帐'!A:A,"天成大厦",'UV台帐'!L:L,">=60",'UV台帐'!L:L,"<80",'UV台帐'!R:R,"一期") | R64: =COUNTIFS('UV台帐'!A:A,"天成大厦",'UV台帐'!L:L,">=60",'UV台帐'!L:L,"<80",'UV台帐'!R:R,"二期") | S64: =COUNTIFS('UV台帐'!A:A,"天成大厦",'UV台帐'!L:L,">=60",'UV台帐'!L:L,"<80",'UV台帐'!R:R,"三期") | U64: 老生转介绍 | V64: =X64+Z64+AB64 | W64: =V64/$V$68 | X64: =COUNTIFS('UV台帐'!A:A,$X$60,'UV台帐'!E:E,U64) | Y64: =X64/$X$68 | Z64: =COUNTIFS('UV台帐'!A:A,$Z$60,'UV台帐'!E:E,U64) | AA64: =Z64/$Z$68 | AB64: =COUNTIFS('UV台帐'!A:A,$AB$60,'UV台帐'!E:E,U64) | AC64: =AB64/$AB$68
B65: 启航 | C65: 40-59 | D65: =E65+J65+O65 | E65: =COUNTIFS('UV台帐'!A:A,$E$61,'UV台帐'!L:L,">=40",'UV台帐'!L:L,"<=59") | F65: =COUNTIFS('UV台帐'!A:A,$E$61,'UV台帐'!L:L,">=40",'UV台帐'!L:L,"<=59",'UV台帐'!R:R,"零期") | G65: =COUNTIFS('UV台帐'!A:A,$E$61,'UV台帐'!L:L,">=40",'UV台帐'!L:L,"<=59",'UV台帐'!R:R,"一期") | H65: =COUNTIFS('UV台帐'!A:A,$E$61,'UV台帐'!L:L,">=40",'UV台帐'!L:L,"<=59",'UV台帐'!R:R,"二期") | I65: =COUNTIFS('UV台帐'!A:A,$E$61,'UV台帐'!L:L,">=40",'UV台帐'!L:L,"<=59",'UV台帐'!R:R,"三期") | J65: =COUNTIFS('UV台帐'!A:A,$J$61,'UV台帐'!L:L,">=40",'UV台帐'!L:L,"<=59") | K65: =COUNTIFS('UV台帐'!A:A,"同创汇",'UV台帐'!L:L,">=40",'UV台帐'!L:L,"<=59",'UV台帐'!R:R,"零期") | L65: =COUNTIFS('UV台帐'!A:A,"同创汇",'UV台帐'!L:L,">=40",'UV台帐'!L:L,"<=59",'UV台帐'!R:R,"一期") | M65: =COUNTIFS('UV台帐'!A:A,"同创汇",'UV台帐'!L:L,">=40",'UV台帐'!L:L,"<=59",'UV台帐'!R:R,"二期") | N65: =COUNTIFS('UV台帐'!A:A,"同创汇",'UV台帐'!L:L,">=40",'UV台帐'!L:L,"<=59",'UV台帐'!R:R,"三期") | O65: =COUNTIFS('UV台帐'!A:A,$O$61,'UV台帐'!L:L,">=40",'UV台帐'!L:L,"<=59") | P65: =COUNTIFS('UV台帐'!A:A,"天成大厦",'UV台帐'!L:L,">=40",'UV台帐'!L:L,"<=59",'UV台帐'!R:R,"零期") | Q65: =COUNTIFS('UV台帐'!A:A,"天成大厦",'UV台帐'!L:L,">=40",'UV台帐'!L:L,"<=59",'UV台帐'!R:R,"一期") | R65: =COUNTIFS('UV台帐'!A:A,"天成大厦",'UV台帐'!L:L,">=40",'UV台帐'!L:L,"<=59",'UV台帐'!R:R,"二期") | S65: =COUNTIFS('UV台帐'!A:A,"天成大厦",'UV台帐'!L:L,">=40",'UV台帐'!L:L,"<=59",'UV台帐'!R:R,"三期") | U65: 新生转介绍 | V65: =X65+Z65+AB65 | W65: =V65/$V$68 | X65: =COUNTIFS('UV台帐'!A:A,$X$60,'UV台帐'!E:E,U65) | Y65: =X65/$X$68 | Z65: =COUNTIFS('UV台帐'!A:A,$Z$60,'UV台帐'!E:E,U65) | AA65: =Z65/$Z$68 | AB65: =COUNTIFS('UV台帐'!A:A,$AB$60,'UV台帐'!E:E,U65) | AC65: =AB65/$AB$68
C66: <39 | D66: =E66+J66+O66 | E66: =COUNTIFS('UV台帐'!A:A,$E$61,'UV台帐'!L:L,">1",'UV台帐'!L:L,"<=39") | F66: =COUNTIFS('UV台帐'!A:A,$E$61,'UV台帐'!L:L,">1",'UV台帐'!L:L,"<=39",'UV台帐'!R:R,"零期") | G66: =COUNTIFS('UV台帐'!A:A,$E$61,'UV台帐'!L:L,">1",'UV台帐'!L:L,"<=39",'UV台帐'!R:R,"一期") | H66: =COUNTIFS('UV台帐'!A:A,$E$61,'UV台帐'!L:L,">1",'UV台帐'!L:L,"<=39",'UV台帐'!R:R,"二期") | I66: =COUNTIFS('UV台帐'!A:A,$E$61,'UV台帐'!L:L,">1",'UV台帐'!L:L,"<=39",'UV台帐'!R:R,"三期") | J66: =COUNTIFS('UV台帐'!A:A,$J$61,'UV台帐'!L:L,">1",'UV台帐'!L:L,"<=39") | K66: =COUNTIFS('UV台帐'!A:A,"同创汇",'UV台帐'!L:L,">1",'UV台帐'!L:L,"<=39",'UV台帐'!R:R,"零期") | L66: =COUNTIFS('UV台帐'!A:A,"同创汇",'UV台帐'!L:L,">1",'UV台帐'!L:L,"<=39",'UV台帐'!R:R,"一期") | M66: =COUNTIFS('UV台帐'!A:A,"同创汇",'UV台帐'!L:L,">1",'UV台帐'!L:L,"<=39",'UV台帐'!R:R,"二期") | N66: =COUNTIFS('UV台帐'!A:A,"同创汇",'UV台帐'!L:L,">1",'UV台帐'!L:L,"<=39",'UV台帐'!R:R,"三期") | O66: =COUNTIFS('UV台帐'!A:A,$O$61,'UV台帐'!L:L,">1",'UV台帐'!L:L,"<=39") | P66: =COUNTIFS('UV台帐'!A:A,"天成大厦",'UV台帐'!L:L,">1",'UV台帐'!L:L,"<=39",'UV台帐'!R:R,"零期") | Q66: =COUNTIFS('UV台帐'!O:O,"天成大厦",'UV台帐'!L:L,">1",'UV台帐'!L:L,"<=39",'UV台帐'!R:R,"一期") | R66: =COUNTIFS('UV台帐'!O:O,"天成大厦",'UV台帐'!L:L,">1",'UV台帐'!L:L,"<=39",'UV台帐'!R:R,"二期") | S66: =COUNTIFS('UV台帐'!O:O,"天成大厦",'UV台帐'!L:L,">1",'UV台帐'!L:L,"<=39",'UV台帐'!R:R,"三期") | U66: 反复低价 | V66: =X66+Z66+AB66 | W66: =V66/$V$68 | X66: =COUNTIFS('UV台帐'!A:A,$X$60,'UV台帐'!E:E,U66) | Y66: =X66/$X$68 | Z66: =COUNTIFS('UV台帐'!A:A,$Z$60,'UV台帐'!E:E,U66) | AA66: =Z66/$Z$68 | AB66: =COUNTIFS('UV台帐'!A:A,$AB$60,'UV台帐'!E:E,U66) | AC66: =AB66/$AB$68
B67: 合计 | D67: =SUM(D62:D66) | E67: =SUM(E62:E66) | F67: =SUM(F62:F66) | G67: =SUM(G62:G66) | H67: =SUM(H62:H66) | I67: =SUM(I62:I66) | J67: =SUM(J62:J66) | K67: =SUM(K62:K66) | ... S67: =SUM(S62:S66) | U67: 断报老生 | V67: =X67+Z67+AB67 | W67: =V67/$V$68 | X67: =COUNTIFS('UV台帐'!A:A,$X$60,'UV台帐'!E:E,U67) | Y67: =X67/$X$68 | Z67: =COUNTIFS('UV台帐'!A:A,$Z$60,'UV台帐'!E:E,U67) | AA67: =Z67/$Z$68 | AB67: =COUNTIFS('UV台帐'!A:A,$AB$60,'UV台帐'!E:E,U67) | AC67: =AB67/$AB$68
U68: 合计 | V68: =X68+Z68+AB68 | W68: - | X68: =SUM(X62:X67) | Y68: - | Z68: =SUM(Z62:Z67) | AA68: - | AB68: =SUM(AB62:AB67) | AC68: -
B70: 校区看板 | C70: 在读UV | D70: 在读PV
D71: 整体在读 | E71: 暑续秋 | F71: PV续报率 | G71: 数学 | H71: 暑续秋 | I71: 转化率 | J71: 语文 | K71: 暑续秋 | L71: 转化率 | M71: 英语 | N71: 暑续秋 | O71: 转化率 | Q71: 成绩分类 | R71: 数学UV | S71: 占比 | T71: 新宝利 | U71: 同创汇 | V71: 天成大厦
B72: 新宝利 | C72: =COUNTIFS('UV台帐'!A:A,B72,'UV台帐'!H:H,"在读") | D72: =G72+J72+M72 | E72: =H72+K72+N72 | F72: =E72/D72 | G72: =COUNTIFS('UV台帐'!A:A,B72,'UV台帐'!S:S,"在读") | H72: =SUMPRODUCT(('UV台帐'!A:A=B72)*('UV台帐'!T$3:T528="是")) | I72: =H72/G72 | J72: =COUNTIFS('UV台帐'!A:A,B72,'UV台帐'!AB:AB,"在读") | K72: =SUMPRODUCT(('UV台帐'!A:A=B72)*('UV台帐'!AC$3:AC528="是")) | L72: =K72/J72 | M72: =COUNTIFS('UV台帐'!A:A,B72,'UV台帐'!AK:AK,"在读") | N72: =SUMPRODUCT(('UV台帐'!A:A=B72)*('UV台帐'!AL$3:AL528="是")) | O72: =N72/M72 | Q72: 老师预估 | R72: =COUNTIF('UV台帐'!K:K,"老师预估") | S72: =R72/$R$75 | T72: =COUNTIFS('UV台帐'!K:K,"老师预估",'UV台帐'!A:A,"新宝利") | U72: =COUNTIFS('UV台帐'!K:K,"老师预估",'UV台帐'!A:A,"同创汇") | V72: =COUNTIFS('UV台帐'!K:K,"老师预估",'UV台帐'!A:A,"天成大厦")
B73: 同创汇 | C73: =COUNTIFS('UV台帐'!A:A,B73,'UV台帐'!H:H,"在读") | D73: =G73+J73+M73 | E73: =H73+K73+N73 | F73: =E73/D73 | G73: =COUNTIFS('UV台帐'!A:A,B73,'UV台帐'!S:S,"在读") | H73: =SUMPRODUCT(('UV台帐'!A:A=B73)*('UV台帐'!T$3:T528="是")) | I73: =H73/G73 | J73: =COUNTIFS('UV台帐'!A:A,B73,'UV台帐'!AB:AB,"在读") | K73: =SUMPRODUCT(('UV台帐'!A:A=B73)*('UV台帐'!AC$3:AC528="是")) | L73: =K73/J73 | M73: =COUNTIFS('UV台帐'!A:A,B73,'UV台帐'!AK:AK,"在读") | N73: =SUMPRODUCT(('UV台帐'!A:A=B73)*('UV台帐'!AL$3:AL528="是")) | O73: =N73/M73 | Q73: 报前测成绩 | R73: =COUNTIF('UV台帐'!K:K,"报前测成绩") | S73: =R73/$R$75 | T73: =COUNTIFS('UV台帐'!K:K,"报前测成绩",'UV台帐'!A:A,"新宝利") | U73: =COUNTIFS('UV台帐'!K:K,"报前测成绩",'UV台帐'!A:A,"同创汇") | V73: =COUNTIFS('UV台帐'!K:K,"报前测成绩",'UV台帐'!A:A,"天成大厦")
B74: 天成大厦 | C74: =COUNTIFS('UV台帐'!A:A,B74,'UV台帐'!H:H,"在读") | D74: =G74+J74+M74 | E74: =H74+K74+N74 | F74: =E74/D74 | G74: =COUNTIFS('UV台帐'!A:A,B74,'UV台帐'!S:S,"在读") | H74: =SUMPRODUCT(('UV台帐'!A:A=B74)*('UV台帐'!T$3:T528="是")) | I74: =H74/G74 | J74: =COUNTIFS('UV台帐'!A:A,B74,'UV台帐'!AB:AB,"在读") | K74: =SUMPRODUCT(('UV台帐'!A:A=B74)*('UV台帐'!AC$3:AC528="是")) | L74: =K74/J74 | M74: =COUNTIFS('UV台帐'!A:A,B74,'UV台帐'!AK:AK,"在读") | N74: =SUMPRODUCT(('UV台帐'!A:A=B74)*('UV台帐'!AL$3:AL528="是")) | O74: =N74/M74 | Q74: 校内成绩 | R74: =COUNTIF('UV台帐'!K:K,"校内成绩") | S74: =R74/$R$75 | T74: =COUNTIFS('UV台帐'!K:K,"校内成绩",'UV台帐'!A:A,"新宝利") | U74: =COUNTIFS('UV台帐'!K:K,"校内成绩",'UV台帐'!A:A,"同创汇") | V74: =COUNTIFS('UV台帐'!K:K,"校内成绩",'UV台帐'!A:A,"天成大厦")
B75: 合计 | C75: =SUM(C72:C74) | D75: =SUM(D72:D74) | E75: =SUM(E72:E74) | F75: =E75/D75 | G75: =SUM(G72:G74) | H75: =SUM(H72:H74) | I75: =H75/G75 | J75: =SUM(J72:J74) | K75: =SUM(K72:K74) | L75: =K75/J75 | M75: =SUM(M72:M74) | N75: =SUM(N72:N74) | O75: =N75/M75 | Q75: 合计 | R75: =SUM(R72:R74) | S75: - | T75: =SUM(T72:T74) | U75: =SUM(U72:U74) | V75: =SUM(V72:V74)
P80: 零期 | Q80: UV | T80: PV
Q81: UV | R81: UV留存 | S81: 转率 | T81: 数学 | U81: 续报 | V81: 英语 | W81: 续报 | X81: 语文 | Y81: 续报 | Z81: 合计PV | AA81: 转化合计PV | AB81: PV转率
P82: 报前测 | Q82: 47 | R82: 15 | S82: =R82/Q82 | T82: 30 | U82: 15 | V82: 43 | W82: 9 | X82: 44 | Y82: 11 | Z82: =T82+V82+X82 | AA82: =U82+W82+Y82 | AB82: =AA82/Z82
C83: 拉新 | D83: 拉新占比 | E83: =E84/$J$84 | F83: =F84/$J$84 | G83: =G84/$J$84 | H83: =H84/$J$84 | I83: =I84/$J$84 | J83: 合计 | P83: 校内 | Q83: 37 | R83: 7 | S83: =R83/Q83 | T83: 38 | U83: 8 | V83: 40 | W83: 4 | X83: 39 | Y83: 7 | Z83: =T83+V83+X83 | AA83: =U83+W83+Y83 | AB83: =AA83/Z83
D84: PV | E84: =COUNTIFS('UV台帐'!AR:AR,"三月",'UV台帐'!E:E,"<>春季在读老生",'UV台帐'!S:S,"在读",'UV台帐'!R:R,"零期")+COUNTIFS('UV台帐'!AR:AR,"三月",'UV台帐'!E:E,"<>春季在读老生",'UV台帐'!AB:AB,"在读",'UV台帐'!AA:AA,"零期")+COUNTIFS('UV台帐'!AR:AR,"三月",'UV台帐'!E:E,"<>春季在读老生",'UV台帐'!AK:AK,"在读",'UV台帐'!AJ:AJ,"零期") | F84: =COUNTIFS('UV台帐'!AR:AR,"四月",'UV台帐'!E:E,"<>春季在读老生",'UV台帐'!S:S,"在读",'UV台帐'!R:R,"零期")+COUNTIFS('UV台帐'!AR:AR,"四月",'UV台帐'!E:E,"<>春季在读老生",'UV台帐'!AB:AB,"在读",'UV台帐'!AA:AA,"零期")+COUNTIFS('UV台帐'!AR:AR,"四月",'UV台帐'!E:E,"<>春季在读老生",'UV台帐'!AK:AK,"在读",'UV台帐'!AJ:AJ,"零期") | G84: =COUNTIFS('UV台帐'!AR:AR,"五月",'UV台帐'!E:E,"<>春季在读老生",'UV台帐'!S:S,"在读",'UV台帐'!R:R,"零期")+COUNTIFS('UV台帐'!AR:AR,"五月",'UV台帐'!E:E,"<>春季在读老生",'UV台帐'!AB:AB,"在读",'UV台帐'!AA:AA,"零期")+COUNTIFS('UV台帐'!AR:AR,"五月",'UV台帐'!E:E,"<>春季在读老生",'UV台帐'!AK:AK,"在读",'UV台帐'!AJ:AJ,"零期") | H84: =COUNTIFS('UV台帐'!AR:AR,"六月",'UV台帐'!E:E,"<>春季在读老生",'UV台帐'!S:S,"在读",'UV台帐'!R:R,"零期")+COUNTIFS('UV台帐'!AR:AR,"六月",'UV台帐'!E:E,"<>春季在读老生",'UV台帐'!AB:AB,"在读",'UV台帐'!AA:AA,"零期")+COUNTIFS('UV台帐'!AR:AR,"六月",'UV台帐'!E:E,"<>春季在读老生",'UV台帐'!AK:AK,"在读",'UV台帐'!AJ:AJ,"零期") | I84: =COUNTIFS('UV台帐'!AR:AR,"七月",'UV台帐'!E:E,"<>春季在读老生",'UV台帐'!S:S,"在读",'UV台帐'!R:R,"零期")+COUNTIFS('UV台帐'!AR:AR,"七月",'UV台帐'!E:E,"<>春季在读老生",'UV台帐'!AB:AB,"在读",'UV台帐'!AA:AA,"零期")+COUNTIFS('UV台帐'!AR:AR,"七月",'UV台帐'!E:E,"<>春季在读老生",'UV台帐'!AK:AK,"在读",'UV台帐'!AJ:AJ,"零期") | J84: =SUM(E84:I84)
D85: UV | E85: =COUNTIFS('UV台帐'!AR:AR,"三月",'UV台帐'!E:E,"<>春季在读老生",'UV台帐'!I:I,"*零期*") | F85: =COUNTIFS('UV台帐'!AR:AR,"四月",'UV台帐'!E:E,"<>春季在读老生",'UV台帐'!I:I,"*零期*") | G85: =COUNTIFS('UV台帐'!AR:AR,"五月",'UV台帐'!E:E,"<>春季在读老生",'UV台帐'!I:I,"*零期*") | H85: =COUNTIFS('UV台帐'!AR:AR,"六月",'UV台帐'!E:E,"<>春季在读老生",'UV台帐'!I:I,"*零期*") | I85: =COUNTIFS('UV台帐'!AR:AR,"七月",'UV台帐'!E:E,"<>春季在读老生",'UV台帐'!I:I,"*零期*") | J85: =SUM(E85:I85)
C86: 月份 | E86: 三月 | F86: 四月 | G86: 五月 | H86: 六月 | I86: 七月 | J86: 零期
C87: 转化 | D87: UV | E87: =COUNTIFS('UV台帐'!AR:AR,"三月",'UV台帐'!E:E,"<>春季在读老生",'UV台帐'!AS:AS,"是",'UV台帐'!I:I,"*零期*") | F87: =COUNTIFS('UV台帐'!AR:AR,"四月",'UV台帐'!E:E,"<>春季在读老生",'UV台帐'!AS:AS,"是",'UV台帐'!I:I,"*零期*") | G87: =COUNTIFS('UV台帐'!AR:AR,"五月",'UV台帐'!E:E,"<>春季在读老生",'UV台帐'!AS:AS,"是",'UV台帐'!I:I,"*零期*") | H87: =COUNTIFS('UV台帐'!AR:AR,"六月",'UV台帐'!E:E,"<>春季在读老生",'UV台帐'!AS:AS,"是",'UV台帐'!I:I,"*零期*") | I87: =COUNTIFS('UV台帐'!AR:AR,"七月",'UV台帐'!E:E,"<>春季在读老生",'UV台帐'!AS:AS,"是",'UV台帐'!I:I,"*零期*") | J87: =SUM(E87:I87)
D88: UV转化率 | E88: =E87/E85 | F88: =F87/F85 | G88: =G87/G85 | H88: =H87/H85 | I88: =IFERROR(I87/I85,0) | J88: =J87/J85
D89: PV | E89: =COUNTIFS('UV台帐'!AR:AR,"三月",'UV台帐'!E:E,"<>春季在读老生",'UV台帐'!AS:AS,"是",'UV台帐'!T:T,"是",'UV台帐'!R:R,"零期")+COUNTIFS('UV台帐'!AR:AR,"三月",'UV台帐'!E:E,"<>春季在读老生",'UV台帐'!AS:AS,"是",'UV台帐'!AC:AC,"是",'UV台帐'!AA:AA,"零期")+COUNTIFS('UV台帐'!AR:AR,"三月",'UV台帐'!E:E,"<>春季在读老生",'UV台帐'!AS:AS,"是",'UV台帐'!AL:AL,"是") | F89: =COUNTIFS('UV台帐'!AR:AR,"四月",'UV台帐'!E:E,"<>春季在读老生",'UV台帐'!AS:AS,"是",'UV台帐'!T:T,"是",'UV台帐'!R:R,"零期")+COUNTIFS('UV台帐'!AR:AR,"四月",'UV台帐'!E:E,"<>春季在读老生",'UV台帐'!AS:AS,"是",'UV台帐'!AC:AC,"是",'UV台帐'!AA:AA,"零期")+COUNTIFS('UV台帐'!AR:AR,"四月",'UV台帐'!E:E,"<>春季在读老生",'UV台帐'!AS:AS,"是",'UV台帐'!AL:AL,"是") | G89: =COUNTIFS('UV台帐'!AR:AR,"五月",'UV台帐'!E:E,"<>春季在读老生",'UV台帐'!AS:AS,"是",'UV台帐'!T:T,"是",'UV台帐'!R:R,"零期")+COUNTIFS('UV台帐'!AR:AR,"五月",'UV台帐'!E:E,"<>春季在读老生",'UV台帐'!AS:AS,"是",'UV台帐'!AC:AC,"是",'UV台帐'!AA:AA,"零期")+COUNTIFS('UV台帐'!AR:AR,"五月",'UV台帐'!E:E,"<>春季在读老生",'UV台帐'!AS:AS,"是",'UV台帐'!AL:AL,"是") | H89: =COUNTIFS('UV台帐'!AR:AR,"六月",'UV台帐'!E:E,"<>春季在读老生",'UV台帐'!AS:AS,"是",'UV台帐'!T:T,"是",'UV台帐'!R:R,"零期")+COUNTIFS('UV台帐'!AR:AR,"六月",'UV台帐'!E:E,"<>春季在读老生",'UV台帐'!AS:AS,"是",'UV台帐'!AC:AC,"是",'UV台帐'!AA:AA,"零期")+COUNTIFS('UV台帐'!AR:AR,"六月",'UV台帐'!E:E,"<>春季在读老生",'UV台帐'!AS:AS,"是",'UV台帐'!AL:AL,"是") | I89: =COUNTIFS('UV台帐'!AR:AR,"七月",'UV台帐'!E:E,"<>春季在读老生",'UV台帐'!AS:AS,"是",'UV台帐'!T:T,"是",'UV台帐'!R:R,"零期")+COUNTIFS('UV台帐'!AR:AR,"七月",'UV台帐'!E:E,"<>春季在读老生",'UV台帐'!AS:AS,"是",'UV台帐'!AC:AC,"是",'UV台帐'!AA:AA,"零期")+COUNTIFS('UV台帐'!AR:AR,"七月",'UV台帐'!E:E,"<>春季在读老生",'UV台帐'!AS:AS,"是",'UV台帐'!AL:AL,"是") | J89: =SUM(E89:I89)
D90: PV转化率 | E90: =E89/E84 | F90: =F89/F84 | G90: =G89/G84 | H90: =H89/H84 | I90: =IFERROR(I89/I84,0) | J90: =J89/J84

Sheet 一期·UV电访分配
A1: 教学点 | B1: 学生uid | C1: 学生姓名 | D1: 归属顾问 | E1: 雪球思维 | J1: 悦读创作 | N1: 双语素养 | R1: 课前电访-顾问（T-2） | AA1: 需求分析 | AD1: 具体需求（目标/学能/老师关注度） | AE1: 报名阈值 | AK1: 课前家长会-老师（T-2） | AN1: 首课电联-老师&顾问（U1～U5） | BD1: 课中家长会-老师&顾问（T4～T7） | BF1: 学员情况-顾问 | BI1: 首课电访（U1）-顾问 | BK1: 意向盘点（U3）-顾问&老师 | BP1: 满意度调查（U4）-顾问 | BQ1: 意向校准（U5）-顾问 | BR1: 在读 | BS1: 应续 | BT1: 数 | BU1: 语 | BV1: 英 | BW1: 已续 | BX1: 未续报卡点-顾问
E2: 主讲 | F2: 上课时段 | G2: 班型 | H2: 期次 | I2: 是否在读 | J2: 主讲 | K2: 上课时段 | L2: 期次 | M2: 是否在读 | N2: 主讲 | O2: 上课时段 | P2: 期次 | Q2: 是否在读 | R2: 是否VIP群 | S2: 意向盘点 | T2: 是否到店测试 | U2: 报读科目是否在同一期 | V2: 学校（小学/初中） | W2: 校内成绩 | X2: 学习习惯 | Y2: 报名初衷 | Z2: 电访记录（为什么报，校内成绩，学习习惯，学校） | AA2: 需求 | AB2: 沟通判定记录 | AC2: 需求学科 | AD2: 目标：提分、目标高中（公办）、自主、指标到校 学能：习惯、意愿、 老师关注度：课堂提问、给家长个性化反馈（互动）、多表扬、 | AE2: 需求紧迫性 | AF2: 付费能力 | AG2: 孩子意愿 | AH2: 家长认可度 | AI2: 家长意识 | AJ2: 意向判定 | AK2: 邀约人 | AL2: 课前诺访 | AM2: 课前确访 | AN2: 电联人（U1） | AO2: 是否完成 | AP2: 跟进记录 | AQ2: 电联人（U2） | AR2: 是否完成 | AS2: 跟进记录 | AT2: 电联人（U3） | AU2: 是否完成 | AV2: 跟进记录 | AW2: 电联人（U4） | AX2: 是否完成 | AY2: 课中诺访 | AZ2: 跟进记录 | BA2: 电联人（U5） | BB2: 是否完成 | BC2: 跟进记录 | BD2: 现场跟进人 | BE2: 课中确访 | BF2: 顾问 | BG2: 介绍人 | BH2: 中签学校 | BI2: 电访记录 | BJ2: 核心诉求 | BK2: 学员意向 | BL2: 数学 | BM2: 语文 | BN2: 英语 | BO2: 判定依据 | BP2: 是否参与 | BQ2: 校准依据 | BR2: =SUM(BR3:BR128) | BS2: =SUM(BS3:BS128) | BT2: =COUNTIF(BT3:BT128,"是") | BU2: =COUNTIF(BU3:BU128,"是") | BV2: =COUNTIF(BV3:BV128,"是") | BW2: =SUM(BW3:BW128) | BX2: （U3～U4） | BY2: （T6～T7） | BZ2: （U8～U10）
A3: 新宝利 | B3: 2341143960 | C3: =VLOOKUP(B3,'UV台帐'!B:AL,2,0) | D3: =VLOOKUP(B3,'UV台帐'!B:AL,3,0) | E3: =VLOOKUP(B3,'UV台帐'!B:AL,13,0) | F3: =VLOOKUP(B3,'UV台帐'!B:AL,15,0) | G3: =VLOOKUP(B3,'UV台帐'!B:AL,16,0) | H3: =VLOOKUP(B3,'UV台帐'!B:AL,17,0) | I3: =VLOOKUP(B3,'UV台帐'!B:AL,18,0) | J3: =VLOOKUP(B3,'UV台帐'!B:AL,22,0) | K3: =VLOOKUP(B3,'UV台帐'!B:AL,24,0) | L3: =VLOOKUP(B3,'UV台帐'!B:AL,26,0) | M3: =VLOOKUP(B3,'UV台帐'!B:AL,27,0) | N3: =VLOOKUP(B3,'UV台帐'!B:AL,31,0) | O3: =VLOOKUP(B3,'UV台帐'!B:AL,33,0) | P3: =VLOOKUP(B3,'UV台帐'!B:AL,35,0) | Q3: =VLOOKUP(B3,'UV台帐'!B:AL,36,0) | R3: 是 | S3: B | T3: 是 | U3: 否 | W3: 语文90，英语95 | X3: 学习习惯一般 | Y3: 小升初衔接 | Z3: 价格敏感型，开眼镜店最近生意不好，妈妈比较关注学习习惯，价格便宜可能会考虑。大概率后面会磨价格B，其他机构在读，语文和英语，报过价格，觉得贵。 | AA3: 明确需求 | AB3: 家长做门店生意，妈妈平时没时间过多关注孩子的学习情况，比较关注孩子学习效果和学习习惯改善，价格便宜可能会考虑，报过价格，觉得贵。 | AD3: 效果维度-提分,效果维度-抓习惯 | AE3: 1.不紧迫，觉得初一不需要学 | AF3: 1-无支付能力 | AG3: 2-一般 | AH3: 2-评价一般、无感 | AI3: 2-有意识无规划 | AJ3: C-小于8 | AK3: 陈南05 | AL3: 是 | BF3: 杨林33 | BG3: =VLOOKUP(B3,'UV台帐'!B:G,6,0) | BR3: =COUNTIFS(H3,"一期",I3,"在读")+COUNTIFS(L3,"一期",M3,"在读")+COUNTIFS(P3,"一期",Q3,"在读") | BS3: =BR3-BW3 | BT3: =VLOOKUP(B3,'UV台帐'!B:AL,19,0) | BU3: =VLOOKUP(B3,'UV台帐'!B:AL,28,0) | BV3: =VLOOKUP(B3,'UV台帐'!B:AL,37,0) | BW3: =COUNTIFS(H3,"一期",BT3,"是")+COUNTIFS(L3,"一期",BU3,"是")+COUNTIFS(P3,"一期",BV3,"是") | CA3: 2341143960
A4: 新宝利 | B4: 2649629431 | C4: =VLOOKUP(B4,'UV台帐'!B:AL,2,0) | D4: =VLOOKUP(B4,'UV台帐'!B:AL,3,0) | E4: =VLOOKUP(B4,'UV台帐'!B:AL,13,0) | F4: =VLOOKUP(B4,'UV台帐'!B:AL,15,0) | G4: =VLOOKUP(B4,'UV台帐'!B:AL,16,0) | H4: =VLOOKUP(B4,'UV台帐'!B:AL,17,0) | I4: =VLOOKUP(B4,'UV台帐'!B:AL,18,0) | J4: =VLOOKUP(B4,'UV台帐'!B:AL,22,0) | K4: =VLOOKUP(B4,'UV台帐'!B:AL,24,0) | L4: =VLOOKUP(B4,'UV台帐'!B:AL,26,0) | M4: =VLOOKUP(B4,'UV台帐'!B:AL,27,0) | N4: =VLOOKUP(B4,'UV台帐'!B:AL,31,0) | O4: =VLOOKUP(B4,'UV台帐'!B:AL,33,0) | P4: =VLOOKUP(B4,'UV台帐'!B:AL,35,0) | Q4: =VLOOKUP(B4,'UV台帐'!B:AL,36,0) | R4: 是 | S4: B | T4: 是 | U4: 是 | V4: 4小学，65中 | W4: 语文90，数学95，英语90 | Y4: 朋友介绍说有课一起学习感受一下 | Z4: 白云距离远，1小时通勤，过往补习经历卓越1-2年，B；6000/3课/30次课，寒暑。一个小时，转介绍。 | AA4: 明确需求 | AB4: 7月11日线下诊断面谈，语文，不稳定，阅读（家长关注，他其实不太清楚，希望老师分析什么薄弱），写作（关注孩子的框架老师说结构不好）， 英语成绩优异，学校，但是书面成绩好，口语不好，担心初中口语不行，重点关注口语读的模块，各方面的都不错英语。 数学是孩子最好的科目，基本95，诊断成绩也80+，没有明确太弱的模块，但是方程计算还是会出错。 对孩子的关注度可以的，家长讲了很多英语要会讲，孩子习惯方面一般重难点部分不爱圈重点，书面不错，家长还说了因为跨段上课，需要白老师 @林志豪01(白老师)协助中午午休后2点收一下孩子的电子产品，让他们把早上的数学和英语作业做了，如果语文作文课要求，留下做完走。沟通期间说过数学也有考虑，英语有明确的提升的需求。 | AC4: 英 | AD4: 效果维度-提分,效果维度-抓习惯 | AE4: 2-一般，对于目标需求一般 | AF4: 2-支付能力一般 | AG4: 2-一般 | AH4: 2-一般 | AI4: 2-有意识无规划 | AJ4: B-8-10 | AK4: 何咏04 | AL4: 是 | BF4: 林志豪01 | BG4: =VLOOKUP(B4,'UV台帐'!B:G,6,0) | BR4: =COUNTIFS(H4,"一期",I4,"在读")+COUNTIFS(L4,"一期",M4,"在读")+COUNTIFS(P4,"一期",Q4,"在读") | BS4: =BR4-BW4 | BT4: =VLOOKUP(B4,'UV台帐'!B:AL,19,0) | BU4: =VLOOKUP(B4,'UV台帐'!B:AL,28,0) | BV4: =VLOOKUP(B4,'UV台帐'!B:AL,37,0) | BW4: =COUNTIFS(H4,"一期",BT4,"是")+COUNTIFS(L4,"一期",BU4,"是")+COUNTIFS(P4,"一期",BV4,"是") | BX4: 语文，不稳定，阅读（关注，分析什么薄弱），写作（关注孩子的，框架），英语口语好重点关注。作文课留下来做完。 | CA4: 2649629431
A5: 新宝利 | B5: 2704638904 | C5: =VLOOKUP(B5,'UV台帐'!B:AL,2,0) | D5: =VLOOKUP(B5,'UV台帐'!B:AL,3,0) | E5: =VLOOKUP(B5,'UV台帐'!B:AL,13,0) | F5: =VLOOKUP(B5,'UV台帐'!B:AL,15,0) | G5: =VLOOKUP(B5,'UV台帐'!B:AL,16,0) | H5: =VLOOKUP(B5,'UV台帐'!B:AL,17,0) | I5: =VLOOKUP(B5,'UV台帐'!B:AL,18,0) | J5: =VLOOKUP(B5,'UV台帐'!B:AL,22,0) | K5: =VLOOKUP(B5,'UV台帐'!B:AL,24,0) | L5: =VLOOKUP(B5,'UV台帐'!B:AL,26,0) | M5: =VLOOKUP(B5,'UV台帐'!B:AL,27,0) | N5: =VLOOKUP(B5,'UV台帐'!B:AL,31,0) | O5: =VLOOKUP(B5,'UV台帐'!B:AL,33,0) | P5: =VLOOKUP(B5,'UV台帐'!B:AL,35,0) | Q5: =VLOOKUP(B5,'UV台帐'!B:AL,36,0) | R5: 是 | S5: B | T5: 是 | U5: 是 | V5: 4小学，65中 | W5: 语文85+，数学100，英语85+ | Y5: 找英语机构，价格贵 | Z5: 白云，距离远，1小时通勤，数学基本满分，语文英语弱，考虑过秋季，但是要好才可以，价格偏高.B，线下面谈，问过价格。4000价格。有报签测成绩，语文：阅读写作方法，写作，多互动，偏内向，背单词没办法。作文写完回去。 | AA5: 明确需求 | AB5: 7月初首次面谈，7月11日线下诊断面谈，家长虽然白云，但是配合度很高，详细沟通如下 7月初首次通过外呼激活，邀约线下，初次见面就带孩子来，了解了大纲，师资，秋季价格，初次沟通妈咪，说过在家有补课英语效果不好换机构，学的好考虑英语 7月11日沟通： 语文，孩子和华辰是朋友，语文阅读是差于华辰，具体在理解段落中心方面重视写不全，找不准，希望老师能给孩子一些好的方法能找到，作文内容可以的，但是校内老师说结构不好，没框架。 数学：数学孩子成绩很优秀基本100分校内，但是本次诊断错了一题方程，妈咪很诧异，因为孩子是参加过华新入学考，且考试难度高于诊断，觉得孩子总是出现低级错误。思维方面都很不错在几何方面。 英语：妈咪重点关注科目，孩子校内成绩是A，但是孩子这边平时看他测试和背书，完全没办法，尤其是单词模块，就是硬背，很担心孩子初中遇到长单词更难，口语太难，妈咪说学校不教口语模块，他的口语想一个个词读句子，太烂了，希望老师多让他开口读。 对孩子的关注度高，过了入学考的华新，但是最终选择65中MK过，因为民办太贵原因，孩子书写很大字，语文老师 @陈南05(陈南)家长希望能给些建议，该批评批评，知道这样中考书写太吃亏，家长还说了因为跨段上课，需要白老师协助中午午休后2点收一下孩子的电子产品，让他们把早上的数学和英语作业做了，如果语文作文课要求，留下做完走。沟通期间说过数学也有考虑，英语有明确的提升的需求 | AC5: 语,英 | AD5: 效果维度-提分,效果维度-抓习惯,沟通维度：老师有个性化,沟通维度：老师有关注度 | AE5: 3-非常紧迫，有短期目标和长期需求 | AF5: 2-支付能力一般 | AG5: 2-一般 | AH5: 2-评价一般、无感 | AI5: 3-有规划有意识 | AJ5: A-11-13 | AK5: 何咏04 | AL5: 是 | BF5: 林志豪01 | BG5: =VLOOKUP(B5,'UV台帐'!B:G,6,0) | BR5: =COUNTIFS(H5,"一期",I5,"在读")+COUNTIFS(L5,"一期",M5,"在读")+COUNTIFS(P5,"一期",Q5,"在读") | BS5: =BR5-BW5 | BT5: =VLOOKUP(B5,'UV台帐'!B:AL,19,0) | BU5: =VLOOKUP(B5,'UV台帐'!B:AL,28,0) | BV5: =VLOOKUP(B5,'UV台帐'!B:AL,37,0) | BW5: =COUNTIFS(H5,"一期",BT5,"是")+COUNTIFS(L5,"一期",BU5,"是")+COUNTIFS(P5,"一期",BV5,"是") | BX5: 语文：阅读写作方法，写作，多互动，偏内向，背单词没办法。作文写完回去。 | CA5: 2715584701
A6: 新宝利 | B6: 2260449861 | C6: =VLOOKUP(B6,'UV台帐'!B:AL,2,0) | D6: =VLOOKUP(B6,'UV台帐'!B:AL,3,0) | E6: =VLOOKUP(B6,'UV台帐'!B:AL,13,0) | F6: =VLOOKUP(B6,'UV台帐'!B:AL,15,0) | G6: =VLOOKUP(B6,'UV台帐'!B:AL,16,0) | H6: =VLOOKUP(B6,'UV台帐'!B:AL,17,0) | I6: =VLOOKUP(B6,'UV台帐'!B:AL,18,0) | J6: =VLOOKUP(B6,'UV台帐'!B:AL,22,0) | K6: =VLOOKUP(B6,'UV台帐'!B:AL,24,0) | L6: =VLOOKUP(B6,'UV台帐'!B:AL,26,0) | M6: =VLOOKUP(B6,'UV台帐'!B:AL,27,0) | N6: =VLOOKUP(B6,'UV台帐'!B:AL,31,0) | O6: =VLOOKUP(B6,'UV台帐'!B:AL,33,0) | P6: =VLOOKUP(B6,'UV台帐'!B:AL,35,0) | Q6: =VLOOKUP(B6,'UV台帐'!B:AL,36,0) | R6: 是 | S6: A | T6: 否 | U6: 是 | V6: 民德实验 | W6: 三科290,希望杯+PET | X6: 学习习惯良好 | Y6: 衔接初一内容，学的好可以秋季 | Z6: 主动询问秋季班的价格，有长期学的想法，之前有长期的补习经历，小奥有学。A，到店面谈了，校内学生手册成绩单进班，没有明显薄弱，英语过P，具体情况希望三科老师去评估 补习：爱普英语，进阶集训队340 3个半小时，语文也去卓越在学 暑假过来感受学习效果，学的好考虑长期学 | AA6: 明确需求 | AB6: 妈妈反馈没有明显知识薄弱，英语过P，具体学科情况等上暑假让三科老师去评估 补习经历：爱普英语，进阶集训队340 3个半小时，语文也去卓越在学 暑假过来感受整体的学习效果，学的好考虑长期学，目标是能跟得上名德重点班的学习难度。高中目标肯定是冲九大。 | AC6: 语,数 | AD6: 效果维度-提分,沟通维度：老师有关注度 | AE6: 2-一般，对于目标需求一般 | AF6: 2-支付能力一般 | AG6: 3-喜欢 | AH6: 2-评价一般、无感 | AI6: 3-有规划有意识 | AJ6: A-11-13 | AK6: 何咏04 | AL6: 是 | BF6: 杨林33 | BG6: =VLOOKUP(B6,'UV台帐'!B:G,6,0) | BH6: 三中 | BR6: =COUNTIFS(H6,"一期",I6,"在读")+COUNTIFS(L6,"一期",M6,"在读")+COUNTIFS(P6,"一期",Q6,"在读") | BS6: =BR6-BW6 | BT6: =VLOOKUP(B6,'UV台帐'!B:AL,19,0) | BU6: =VLOOKUP(B6,'UV台帐'!B:AL,28,0) | BV6: =VLOOKUP(B6,'UV台帐'!B:AL,37,0) | BW6: =COUNTIFS(H6,"一期",BT6,"是")+COUNTIFS(L6,"一期",BU6,"是")+COUNTIFS(P6,"一期",BV6,"是") | CA6: 4103453629
A7: 同创汇 | B7: 2715584701 | C7: =VLOOKUP(B7,'UV台帐'!B:AL,2,0) | D7: =VLOOKUP(B7,'UV台帐'!B:AL,3,0) | E7: =VLOOKUP(B7,'UV台帐'!B:AL,13,0) | F7: =VLOOKUP(B7,'UV台帐'!B:AL,15,0) | G7: =VLOOKUP(B7,'UV台帐'!B:AL,16,0) | H7: =VLOOKUP(B7,'UV台帐'!B:AL,17,0) | I7: =VLOOKUP(B7,'UV台帐'!B:AL,18,0) | J7: =VLOOKUP(B7,'UV台帐'!B:AL,22,0) | K7: =VLOOKUP(B7,'UV台帐'!B:AL,24,0) | L7: =VLOOKUP(B7,'UV台帐'!B:AL,26,0) | M7: =VLOOKUP(B7,'UV台帐'!B:AL,27,0) | N7: =VLOOKUP(B7,'UV台帐'!B:AL,31,0) | O7: =VLOOKUP(B7,'UV台帐'!B:AL,33,0) | P7: =VLOOKUP(B7,'UV台帐'!B:AL,35,0) | Q7: =VLOOKUP(B7,'UV台帐'!B:AL,36,0) | R7: 是 | S7: B | T7: 否 | U7: 否 | W7: 语文85+，数学95+，英语85+ | X7: 很好，孩子会有很多自己的想法 | Y7: 朋友推荐，一起来提前学新初一，暑假衔接 | Z7: 聊了之后孩子偏好动，多关注一下，聊了平时没有补课的习惯，暑假让他提前过度一下，B。线下聊过价格，校内成绩进班。 | AA7: 明确需求 | AB7: 7月8日沟通，电话沟通 语文：孩子阅读写作是薄弱的，语基部分平时捉的孩子背严格，但是感觉现在阅读和写作得不像当年难了 数学：孩子数学是没什么短板，成绩基本95+，学校考试基本就是计算或者粗心错几分，但是没有提前学 英语：孩子英语也比较稳定，单词会偶尔拼写错误，但整体还行，作文也还可以得，主要阅读和听力会稍微扣分多一些 孩子整体习惯偏好，妈咪说孩子坐久了会动，让助教老师可以在偏边关注一下，沟通暑假报名初衷，妈咪说今年分班，初一想往上冲冲，又因为没提前学，所以暑假找班学，长期规划看孩子意愿情况 | AC7: 语,英 | AD7: 效果维度-提分,效果维度-培优拓展/分班考 | AE7: 2-一般，对于目标需求一般 | AF7: 2-支付能力一般 | AG7: 2-一般 | AH7: 2-评价一般、无感 | AI7: 2-有意识无规划 | AJ7: B-8-10 | AK7: 何咏04 | AL7: 是 | BF7: 林志豪01 | BG7: =VLOOKUP(B7,'UV台帐'!B:G,6,0) | BH7: 三中/二中 | BR7: =COUNTIFS(H7,"一期",I7,"在读")+COUNTIFS(L7,"一期",M7,"在读")+COUNTIFS(P7,"一期",Q7,"在读") | BS7: =BR7-BW7 | BT7: =VLOOKUP(B7,'UV台帐'!B:AL,19,0) | BU7: =VLOOKUP(B7,'UV台帐'!B:AL,28,0) | BV7: =VLOOKUP(B7,'UV台帐'!B:AL,37,0) | BW7: =COUNTIFS(H7,"一期",BT7,"是")+COUNTIFS(L7,"一期",BU7,"是")+COUNTIFS(P7,"一期",BV7,"是") | CA7: 2489383127
A8: 同创汇 | B8: 2743981182 | C8: =VLOOKUP(B8,'UV台帐'!B:AL,2,0) | D8: =VLOOKUP(B8,'UV台帐'!B:AL,3,0) | E8: =VLOOKUP(B8,'UV台帐'!B:AL,13,0) | F8: =VLOOKUP(B8,'UV台帐'!B:AL,15,0) | G8: =VLOOKUP(B8,'UV台帐'!B:AL,16,0) | H8: =VLOOKUP(B8,'UV台帐'!B:AL,17,0) | I8: =VLOOKUP(B8,'UV台帐'!B:AL,18,0) | J8: =VLOOKUP(B8,'UV台帐'!B:AL,22,0) | K8: =VLOOKUP(B8,'UV台帐'!B:AL,24,0) | L8: =VLOOKUP(B8,'UV台帐'!B:AL,26,0) | M8: =VLOOKUP(B8,'UV台帐'!B:AL,27,0) | N8: =VLOOKUP(B8,'UV台帐'!B:AL,31,0) | O8: =VLOOKUP(B8,'UV台帐'!B:AL,33,0) | P8: =VLOOKUP(B8,'UV台帐'!B:AL,35,0) | Q8: =VLOOKUP(B8,'UV台帐'!B:AL,36,0) | R8: 是 | S8: B | T8: 否 | U8: 否 | W8: B | Y8: 端内线索，暑假体验下，后续上的好有计划跟着学 | Z8: 数学在其他机构上课，英语阅读和写作较弱，语文阅读较弱 | AA8: 明确需求 | AB8: 孩子小学三年级前学过KET，但是后面没有坚持，孩子词汇量不够，后面需要多加强词汇的积累。语文阅读较弱，课外读物比较少，需要提升孩子阅读答题技巧。孩子性格比较活泼一些，但不是那种捣蛋型的，有的时候静不下来，需要老师提要求，多监督 | AC8: 语,英 | AD8: 效果维度-提分,效果维度-抓习惯,沟通维度：老师有关注度 | AE8: 2-一般，对于目标需求一般 | AF8: 2-支付能力一般 | AG8: 2-一般 | AH8: 2-评价一般、无感 | AI8: 2-有意识无规划 | AJ8: B-8-10 | AK8: 陈南05 | BF8: 王丽 | BG8: =VLOOKUP(B8,'UV台帐'!B:G,6,0) | BH8: 广大附 | BR8: =COUNTIFS(H8,"一期",I8,"在读")+COUNTIFS(L8,"一期",M8,"在读")+COUNTIFS(P8,"一期",Q8,"在读") | BS8: =BR8-BW8 | BT8: =VLOOKUP(B8,'UV台帐'!B:AL,19,0) | BU8: =VLOOKUP(B8,'UV台帐'!B:AL,28,0) | BV8: =VLOOKUP(B8,'UV台帐'!B:AL,37,0) | BW8: =COUNTIFS(H8,"一期",BT8,"是")+COUNTIFS(L8,"一期",BU8,"是")+COUNTIFS(P8,"一期",BV8,"是") | CA8: 2554261157
A9: 同创汇 | B9: 4103453629 | C9: =VLOOKUP(B9,'UV台帐'!B:AL,2,0) | D9: =VLOOKUP(B9,'UV台帐'!B:AL,3,0) | E9: =VLOOKUP(B9,'UV台帐'!B:AL,13,0) | F9: =VLOOKUP(B9,'UV台帐'!B:AL,15,0) | G9: =VLOOKUP(B9,'UV台帐'!B:AL,16,0) | H9: =VLOOKUP(B9,'UV台帐'!B:AL,17,0) | I9: =VLOOKUP(B9,'UV台帐'!B:AL,18,0) | J9: =VLOOKUP(B9,'UV台帐'!B:AL,22,0) | K9: =VLOOKUP(B9,'UV台帐'!B:AL,24,0) | L9: =VLOOKUP(B9,'UV台帐'!B:AL,26,0) | M9: =VLOOKUP(B9,'UV台帐'!B:AL,27,0) | N9: =VLOOKUP(B9,'UV台帐'!B:AL,31,0) | O9: =VLOOKUP(B9,'UV台帐'!B:AL,33,0) | P9: =VLOOKUP(B9,'UV台帐'!B:AL,35,0) | Q9: =VLOOKUP(B9,'UV台帐'!B:AL,36,0) | R9: 是 | S9: B | T9: 否 | U9: 是 | V9: 天河中学猎德实验 | W9: 285 | X9: 学习态度：能自学 学习习惯：比较认真 性格：前期腼腆慢热 | Y9: 初中做好小升初衔接，想要冲重点班 | Z9: 摇中了猎德实验，有分层考，如有资料可以加餐 孩子性格：安静的性格，会举手回答老师问题，想要严格型的老师 报名是因为性价比高，前期对比了其他机构，认为咱教学大纲符合孩子的学习需求，前期问了我们要校内的电子版课本和分班考资料 妈妈问班容，问吃饭安排 | AA9: 明确需求 | AB9: 要冲天河中学猎德实验学校分层考 ，性格斯斯文文慢热型的孩子，需求是多鼓励和关注孩子 语文：字词、古诗文默写偶尔粗心丢分，文言文积累少，不会翻译，简单基础题无故丢分 数学：拓展综合题、几何模型丢分多 英语：听力，写作题型答题技巧需要帮助孩子提升 | AC9: 语,数,英 | AD9: 效果维度-提分,效果维度-抓习惯,效果维度-培优拓展/分班考,沟通维度：老师有个性化 | AE9: 2-一般，对于目标需求一般 | AF9: 2-支付能力一般 | AG9: 2-一般 | AH9: 2-评价一般、无感 | AI9: 2-有意识无规划 | AJ9: B-8-10 | AK9: 陈南05 | BF9: 苏丽婷 | BG9: =VLOOKUP(B9,'UV台帐'!B:G,6,0) | BH9: 猎德实验 | BR9: =COUNTIFS(H9,"一期",I9,"在读")+COUNTIFS(L9,"一期",M9,"在读")+COUNTIFS(P9,"一期",Q9,"在读") | BS9: =BR9-BW9 | BT9: =VLOOKUP(B9,'UV台帐'!B:AL,19,0) | BU9: =VLOOKUP(B9,'UV台帐'!B:AL,28,0) | BV9: =VLOOKUP(B9,'UV台帐'!B:AL,37,0) | BW9: =COUNTIFS(H9,"一期",BT9,"是")+COUNTIFS(L9,"一期",BU9,"是")+COUNTIFS(P9,"一期",BV9,"是") | CA9: 2579947640
A10: 同创汇 | B10: 2489383127 | C10: =VLOOKUP(B10,'UV台帐'!B:AL,2,0) | D10: =VLOOKUP(B10,'UV台帐'!B:AL,3,0) | E10: =VLOOKUP(B10,'UV台帐'!B:AL,13,0) | F10: =VLOOKUP(B10,'UV台帐'!B:AL,15,0) | G10: =VLOOKUP(B10,'UV台帐'!B:AL,16,0) | H10: =VLOOKUP(B10,'UV台帐'!B:AL,17,0) | I10: =VLOOKUP(B10,'UV台帐'!B:AL,18,0) | J10: =VLOOKUP(B10,'UV台帐'!B:AL,22,0) | K10: =VLOOKUP(B10,'UV台帐'!B:AL,24,0) | L10: =VLOOKUP(B10,'UV台帐'!B:AL,26,0) | M10: =VLOOKUP(B10,'UV台帐'!B:AL,27,0) | N10: =VLOOKUP(B10,'UV台帐'!B:AL,31,0) | O10: =VLOOKUP(B10,'UV台帐'!B:AL,33,0) | P10: =VLOOKUP(B10,'UV台帐'!B:AL,35,0) | Q10: =VLOOKUP(B10,'UV台帐'!B:AL,36,0) | R10: 是 | S10: B | T10: 否 | U10: 是 | W10: 语90，数90，英90 | X10: 数学压轴题要加强，希望老师梳理做题步骤，英语语法薄弱，语文字词粗心 | Y10: 1. 语文：基础字词容易粗心写错，希望课上加强生字默写、阅读理解答题方法指导，顺带积累作文短句素材； 2. 数学：压轴题他要加强，做题耐心不足，计算容易出错，麻烦老师帮孩子梳理审题步骤，纠正马虎的答题习惯； 3. 英语：语法知识点记不牢，麻烦老师用轻量化的练习巩固语法，顺带督促单词日常背诵。 | Z10: 没有线下课补习经历 孩子近视，需要助教老师注意下前面2讲铭牌放前面一点，也发了期望暑假学习孩子能有进步，解决某些问题。过往都是网课，家住白云距离远，可能有价格异议。比较晚报名，线上直收的，没有做入学测，家长愿意来线下，家长表示暑假学的好是可以考虑长期学的 | AA10: 明确需求 | AB10: 语数英都有薄弱点，期望老师解决孩子短板1. 语文：基础字词容易粗心写错，希望课上加强生字默写、阅读理解答题方法指导，顺带积累作文短句素材； 2. 数学：压轴题他要加强，做题耐心不足，计算容易出错，麻烦老师帮孩子梳理审题步骤，纠正马虎的答题习惯； 3. 英语：语法知识点记不牢，麻烦老师用轻量化的练习巩固语法，顺带督促单词日常背诵。孩子近视，需要助教老师注意下让孩子坐前排，也需求是是想奔着初中重点班去的（白云区的中学）但是担心孩子不太适应，没有补习经历，家长配合度挺高，表示暑假上的好，有需要是会考虑，距离较远 | AC10: 语,数,英 | AD10: 效果维度-提分,效果维度-抓习惯 | AE10: 2-一般，对于目标需求一般 | AF10: 2-支付能力一般 | AG10: 2-一般 | AH10: 2-评价一般、无感 | AI10: 2-有意识无规划 | AJ10: B-8-10 | AK10: 陈南05 | BF10: 张敏烨 | BG10: =VLOOKUP(B10,'UV台帐'!B:G,6,0) | BR10: =COUNTIFS(H10,"一期",I10,"在读")+COUNTIFS(L10,"一期",M10,"在读")+COUNTIFS(P10,"一期",Q10,"在读") | BS10: =BR10-BW10 | BT10: =VLOOKUP(B10,'UV台帐'!B:AL,19,0) | BU10: =VLOOKUP(B10,'UV台帐'!B:AL,28,0) | BV10: =VLOOKUP(B10,'UV台帐'!B:AL,37,0) | BW10: =COUNTIFS(H10,"一期",BT10,"是")+COUNTIFS(L10,"一期",BU10,"是")+COUNTIFS(P10,"一期",BV10,"是") | CA10: 2446527834
A11: 同创汇 | B11: 2554261157 | C11: =VLOOKUP(B11,'UV台帐'!B:AL,2,0) | D11: =VLOOKUP(B11,'UV台帐'!B:AL,3,0) | E11: =VLOOKUP(B11,'UV台帐'!B:AL,13,0) | F11: =VLOOKUP(B11,'UV台帐'!B:AL,15,0) | G11: =VLOOKUP(B11,'UV台帐'!B:AL,16,0) | H11: =VLOOKUP(B11,'UV台帐'!B:AL,17,0) | I11: =VLOOKUP(B11,'UV台帐'!B:AL,18,0) | J11: =VLOOKUP(B11,'UV台帐'!B:AL,22,0) | K11: =VLOOKUP(B11,'UV台帐'!B:AL,24,0) | L11: =VLOOKUP(B11,'UV台帐'!B:AL,26,0) | M11: =VLOOKUP(B11,'UV台帐'!B:AL,27,0) | N11: =VLOOKUP(B11,'UV台帐'!B:AL,31,0) | O11: =VLOOKUP(B11,'UV台帐'!B:AL,33,0) | P11: =VLOOKUP(B11,'UV台帐'!B:AL,35,0) | Q11: =VLOOKUP(B11,'UV台帐'!B:AL,36,0) | R11: 是 | S11: B | U11: 是 | V11: 五羊 | W11: 286 | X11: 数学好英语差点，语文一般，需要多鼓励 | Y11: 孩子奶奶报的，父母相送孩子去上一对一，但是奶奶认为孩子需要多接触，奶一直有说，没有伙伴想一起来上课，说明孩子比较内向，可以用班课上课形式来改善孩子，看到改变就可以报名 | Z11: 孩子奶奶交的费用，奶奶告知父母比较偏向让孩子上一对一，孩子小学三科A，之前在新东方上过课，孩子认可，后续会考虑在我们这边长期学，问了课程内容，上课形式，人数 | AA11: 明确需求 | AB11: 奶奶交的费用，父母想去一对一，但是奶奶认为可以让孩子来试一下，孩子学习比较懒散，需要人盯着，需要有老师给出孩子提升点和进步点，加强孩子自信心，给出明确初中学习规划 | AC11: 语,数,英 | AD11: 升学需求-保底本区公办高中,效果维度-提分,效果维度-抓习惯,沟通维度：老师有关注度 | AE11: 2-一般，对于目标需求一般 | AF11: 3-支付能力强 | AG11: 2-一般 | AH11: 1-有雷点、槽点 | AI11: 2-有意识无规划 | AJ11: B-8-10 | AK11: 陈南05 | BF11: 戎凯01 | BG11: =VLOOKUP(B11,'UV台帐'!B:G,6,0) | BR11: =COUNTIFS(H11,"一期",I11,"在读")+COUNTIFS(L11,"一期",M11,"在读")+COUNTIFS(P11,"一期",Q11,"在读") | BS11: =BR11-BW11 | BT11: =VLOOKUP(B11,'UV台帐'!B:AL,19,0) | BU11: =VLOOKUP(B11,'UV台帐'!B:AL,28,0) | BV11: =VLOOKUP(B11,'UV台帐'!B:AL,37,0) | BW11: =COUNTIFS(H11,"一期",BT11,"是")+COUNTIFS(L11,"一期",BU11,"是")+COUNTIFS(P11,"一期",BV11,"是") | CA11: 2519148407
A12: 新宝利 | B12: 4860505150 | C12: =VLOOKUP(B12,'UV台帐'!B:AL,2,0) | D12: =VLOOKUP(B12,'UV台帐'!B:AL,3,0) | E12: =VLOOKUP(B12,'UV台帐'!B:AL,13,0) | F12: =VLOOKUP(B12,'UV台帐'!B:AL,15,0) | G12: =VLOOKUP(B12,'UV台帐'!B:AL,16,0) | H12: =VLOOKUP(B12,'UV台帐'!B:AL,17,0) | I12: =VLOOKUP(B12,'UV台帐'!B:AL,18,0) | J12: =VLOOKUP(B12,'UV台帐'!B:AL,22,0) | K12: =VLOOKUP(B12,'UV台帐'!B:AL,24,0) | L12: =VLOOKUP(B12,'UV台帐'!B:AL,26,0) | M12: =VLOOKUP(B12,'UV台帐'!B:AL,27,0) | N12: =VLOOKUP(B12,'UV台帐'!B:AL,31,0) | O12: =VLOOKUP(B12,'UV台帐'!B:AL,33,0) | P12: =VLOOKUP(B12,'UV台帐'!B:AL,35,0) | Q12: =VLOOKUP(B12,'UV台帐'!B:AL,36,0) | R12: 是 | S12: S | T12: 否 | U12: 是 | V12: 回民小学/华侨 | W12: 280 | X12: 比较懒散，数学和英语偏弱 | Y12: 转介绍，家长觉得孩子成绩不行，自己又没时间管孩子，需要有课外机构进行保驾护航。 | Z12: 抓介绍，已面谈过。孩子成绩比较薄弱，妈妈对于孩子学习是比较着急的，但是比较理性。知道学习还是要靠课外机构提升。已明确续费意向。介绍人博睿三科报名；孩子是同学，母亲是闺蜜。 | AA12: 明确需求 | AB12: 基本情况：转介绍，孩子成绩比较薄弱，妈妈对于孩子学习是比较着急的，知道学习还是要靠课外机构提升。已明确续费意向。介绍人博睿三科报名；孩子是同学，母亲是好朋友。 需求判定：妈妈希望各科老师抓孩子的习惯，例如笔记字迹；学习主动性，特别是语文和英语。希望老师在前几次课多提问孩子，提升孩子投入度。 | AC12: 语,数,英 | AD12: 效果维度-抓习惯,沟通维度：老师有关注度 | AE12: 3-非常紧迫，有短期目标和长期需求 | AF12: 3-支付能力强 | AG12: 2-一般 | AH12: 3-有正面评价 | AI12: 3-有规划有意识 | AJ12: S-14-15 | AK12: 何咏04 | AL12: 是 | BF12: 陈亮延 | BG12: =VLOOKUP(B12,'UV台帐'!B:G,6,0) | BH12: 真光 | BR12: =COUNTIFS(H12,"一期",I12,"在读")+COUNTIFS(L12,"一期",M12,"在读")+COUNTIFS(P12,"一期",Q12,"在读") | BS12: =BR12-BW12 | BT12: =VLOOKUP(B12,'UV台帐'!B:AL,19,0) | BU12: =VLOOKUP(B12,'UV台帐'!B:AL,28,0) | BV12: =VLOOKUP(B12,'UV台帐'!B:AL,37,0) | BW12: =COUNTIFS(H12,"一期",BT12,"是")+COUNTIFS(L12,"一期",BU12,"是")+COUNTIFS(P12,"一期",BV12,"是") | CA12: 2524361673
A13: 同创汇 | B13: 2446527834 | C13: =VLOOKUP(B13,'UV台帐'!B:AL,2,0) | D13: =VLOOKUP(B13,'UV台帐'!B:AL,3,0) | E13: =VLOOKUP(B13,'UV台帐'!B:AL,13,0) | F13: =VLOOKUP(B13,'UV台帐'!B:AL,15,0) | G13: =VLOOKUP(B13,'UV台帐'!B:AL,16,0) | H13: =VLOOKUP(B13,'UV台帐'!B:AL,17,0) | I13: =VLOOKUP(B13,'UV台帐'!B:AL,18,0) | J13: =VLOOKUP(B13,'UV台帐'!B:AL,22,0) | K13: =VLOOKUP(B13,'UV台帐'!B:AL,24,0) | L13: =VLOOKUP(B13,'UV台帐'!B:AL,26,0) | M13: =VLOOKUP(B13,'UV台帐'!B:AL,27,0) | N13: =VLOOKUP(B13,'UV台帐'!B:AL,31,0) | O13: =VLOOKUP(B13,'UV台帐'!B:AL,33,0) | P13: =VLOOKUP(B13,'UV台帐'!B:AL,35,0) | Q13: =VLOOKUP(B13,'UV台帐'!B:AL,36,0) | R13: 是 | S13: B | U13: 是 | W13: 285-295 | Y13: 妈妈想在初中帮助孩子领跑在前面，应为现在还没上课，需要看情况，后续会考虑新宝利 | Z13: 妈妈感觉距离会有点远，后续可能考虑去新宝利上秋季课，先看暑秋上课情况 | AA13: 明确需求 | AB13: 意向校区在新宝利，出行比较方便，六下三科285期末，初中7中实验，小学沙头南，孩子有点懒，孩子愿意来上，需要改善孩子的学习习惯；希望去好的公办高中 2-3年级线上作业帮，4-6年没有补过课，家附近线下没有好的补课机构，希望老师多关注，帮助孩子改正习惯，需要看到习惯改变的效果 | AC13: 语,数,英 | AD13: 效果维度-提分,效果维度-抓习惯,沟通维度：老师有关注度 | AE13: 2-一般，对于目标需求一般 | AF13: 2-支付能力一般 | AG13: 3-喜欢 | AH13: 2-评价一般、无感 | AI13: 2-有意识无规划 | AJ13: B-8-10 | AK13: 陈南05 | BF13: 戎凯01 | BG13: =VLOOKUP(B13,'UV台帐'!B:G,6,0) | BR13: =COUNTIFS(H13,"一期",I13,"在读")+COUNTIFS(L13,"一期",M13,"在读")+COUNTIFS(P13,"一期",Q13,"在读") | BS13: =BR13-BW13 | BT13: =VLOOKUP(B13,'UV台帐'!B:AL,19,0) | BU13: =VLOOKUP(B13,'UV台帐'!B:AL,28,0) | BV13: =VLOOKUP(B13,'UV台帐'!B:AL,37,0) | BW13: =COUNTIFS(H13,"一期",BT13,"是")+COUNTIFS(L13,"一期",BU13,"是")+COUNTIFS(P13,"一期",BV13,"是") | CA13: 2578457931
A14: 同创汇 | B14: 4834944316 | C14: =VLOOKUP(B14,'UV台帐'!B:AL,2,0) | D14: =VLOOKUP(B14,'UV台帐'!B:AL,3,0) | E14: =VLOOKUP(B14,'UV台帐'!B:AL,13,0) | F14: =VLOOKUP(B14,'UV台帐'!B:AL,15,0) | G14: =VLOOKUP(B14,'UV台帐'!B:AL,16,0) | H14: =VLOOKUP(B14,'UV台帐'!B:AL,17,0) | I14: =VLOOKUP(B14,'UV台帐'!B:AL,18,0) | J14: =VLOOKUP(B14,'UV台帐'!B:AL,22,0) | K14: =VLOOKUP(B14,'UV台帐'!B:AL,24,0) | L14: =VLOOKUP(B14,'UV台帐'!B:AL,26,0) | M14: =VLOOKUP(B14,'UV台帐'!B:AL,27,0) | N14: =VLOOKUP(B14,'UV台帐'!B:AL,31,0) | O14: =VLOOKUP(B14,'UV台帐'!B:AL,33,0) | P14: =VLOOKUP(B14,'UV台帐'!B:AL,35,0) | Q14: =VLOOKUP(B14,'UV台帐'!B:AL,36,0) | R14: 是 | S14: A | T14: 否 | U14: 是 | V14: 省实越秀 | W14: 280-290 | X14: 语文很爱阅读。数学正常水平，高难度不行，不爱打草稿，绕弯的题目1-2个弯可以，第三个弯孩子就会畏难。性格是很好强。英语：幼儿阶段没开窍，但4-5年级去英孚学，现在还在英孚，ketPET,过了，是冲刺型选手 | Y14: 学校听了学校的家长会觉得新学期要给孩子补充，小宝有数学和语文的学习需求，大宝数学多学一个班是学而思，英语语文没有安排，打包一起报了 | Z14: 大宝：比较活泼开朗，高敏感孩子，喜欢被鼓励被看见，校内285+。语文很爱阅读。数学正常水平，高难度不行，不爱打草稿，很好强。英语：幼儿阶段没开窍，但4-5年级去英孚学，现在还在英孚，ketPET,过了，是冲刺型选手，基于孩子性格问题执信，二中没去，省市越秀摇中了，开学有分班考，要Top200名，孩子本身很想够上分班的资格，有学习主动性。 | AA14: 明确需求 | AB14: 谦谦性格：活泼开朗，高敏感孩子，喜欢被鼓励被看见，有学习主动性 校内成绩：校内285+ 语文：很爱阅读看书，但文言文课外拓展不足，阅读踩分点不太够的 数学：不爱打草稿，数学逻辑绕3个弯的题型有畏难情绪 英语：英孚拓展学过，KET/PET已通过，这个科目是冲刺型选手 初中学校：省实越秀，有分班考，孩子主动计划冲FC考（Top200名） | AC14: 语,数,英 | AD14: 效果维度-提分,效果维度-抓习惯,效果维度-培优拓展/分班考,沟通维度：老师有关注度 | AE14: 2-一般，对于目标需求一般 | AF14: 3-支付能力强 | AG14: 2-一般 | AH14: 2-评价一般、无感 | AI14: 3-有规划有意识 | AJ14: A-11-13 | AK14: 陈南05 | BF14: 苏丽婷 | BG14: =VLOOKUP(B14,'UV台帐'!B:G,6,0) | BH14: 省实越秀 | BR14: =COUNTIFS(H14,"一期",I14,"在读")+COUNTIFS(L14,"一期",M14,"在读")+COUNTIFS(P14,"一期",Q14,"在读") | BS14: =BR14-BW14 | BT14: =VLOOKUP(B14,'UV台帐'!B:AL,19,0) | BU14: =VLOOKUP(B14,'UV台帐'!B:AL,28,0) | BV14: =VLOOKUP(B14,'UV台帐'!B:AL,37,0) | BW14: =COUNTIFS(H14,"一期",BT14,"是")+COUNTIFS(L14,"一期",BU14,"是")+COUNTIFS(P14,"一期",BV14,"是") | CA14: 2937587526
A15: 同创汇 | B15: 2519148407 | C15: =VLOOKUP(B15,'UV台帐'!B:AL,2,0) | D15: =VLOOKUP(B15,'UV台帐'!B:AL,3,0) | E15: =VLOOKUP(B15,'UV台帐'!B:AL,13,0) | F15: =VLOOKUP(B15,'UV台帐'!B:AL,15,0) | G15: =VLOOKUP(B15,'UV台帐'!B:AL,16,0) | H15: =VLOOKUP(B15,'UV台帐'!B:AL,17,0) | I15: =VLOOKUP(B15,'UV台帐'!B:AL,18,0) | J15: =VLOOKUP(B15,'UV台帐'!B:AL,22,0) | K15: =VLOOKUP(B15,'UV台帐'!B:AL,24,0) | L15: =VLOOKUP(B15,'UV台帐'!B:AL,26,0) | M15: =VLOOKUP(B15,'UV台帐'!B:AL,27,0) | N15: =VLOOKUP(B15,'UV台帐'!B:AL,31,0) | O15: =VLOOKUP(B15,'UV台帐'!B:AL,33,0) | P15: =VLOOKUP(B15,'UV台帐'!B:AL,35,0) | Q15: =VLOOKUP(B15,'UV台帐'!B:AL,36,0) | R15: 是 | S15: B | T15: 否 | U15: 是 | V15: 10中 | W15: 数学语文A，英语B | X15: 面谈说语文不爱阅读，阅读理解最差，英语拼读没有技巧和方法，国际音标在线上学，还是不会运用 | Y15: 对比了很多家机构，最后家长和孩子选择了作业帮 | Z15: 面谈报的，看了环境还不错，现场也有老师在备课，姥姥和孩子现场都感到满意，说对比了几家机构这边便利和性价比高，现场给家长铺垫了暑假有效果一定要考虑秋季继续跟着学，铺垫了秋季的续班费用，教学内容的连贯性，家长觉得可以，会考虑。孩子性格是外向的，首课可能会有点胆怯，但也还好，摇中10中，想参加分层考，具体什么时间考不知道，暑假行课期间给孩子打印些分班考的卷子 | AA15: 明确需求 | AB15: 萱萱性格： 校内成绩： 数学语文是A 英语B 👋语文：不爱阅读，阅读理解最薄弱 ：读文浅，抓不住中心 👋数学：数学填空题错的最多，会理解错题目意思，其次是计算粗心大意的问题。 👋英语：英文背单词稍有困难，想要学音标，线上学过孩子不理解依然死记硬背，背单词需要花费2小时，背不扎实 初中学校：十中，分层考时间不明确，可提供分层真题练习 | AC15: 语,数,英 | AD15: 效果维度-提分,效果维度-抓习惯,效果维度-培优拓展/分班考,沟通维度：老师有个性化 | AE15: 2-一般，对于目标需求一般 | AF15: 2-支付能力一般 | AG15: 3-喜欢 | AH15: 3-有正面评价 | AI15: 2-有意识无规划 | AJ15: A-11-13 | AK15: 陈南05 | AL15: 是 | BF15: 苏丽婷 | BG15: =VLOOKUP(B15,'UV台帐'!B:G,6,0) | BH15: 十中 | BR15: =COUNTIFS(H15,"一期",I15,"在读")+COUNTIFS(L15,"一期",M15,"在读")+COUNTIFS(P15,"一期",Q15,"在读") | BS15: =BR15-BW15 | BT15: =VLOOKUP(B15,'UV台帐'!B:AL,19,0) | BU15: =VLOOKUP(B15,'UV台帐'!B:AL,28,0) | BV15: =VLOOKUP(B15,'UV台帐'!B:AL,37,0) | BW15: =COUNTIFS(H15,"一期",BT15,"是")+COUNTIFS(L15,"一期",BU15,"是")+COUNTIFS(P15,"一期",BV15,"是") | CA15: 4399390086
A16: 新宝利 | B16: 4156594850 | C16: =VLOOKUP(B16,'UV台帐'!B:AL,2,0) | D16: =VLOOKUP(B16,'UV台帐'!B:AL,3,0) | E16: =VLOOKUP(B16,'UV台帐'!B:AL,13,0) | F16: =VLOOKUP(B16,'UV台帐'!B:AL,15,0) | G16: =VLOOKUP(B16,'UV台帐'!B:AL,16,0) | H16: =VLOOKUP(B16,'UV台帐'!B:AL,17,0) | I16: =VLOOKUP(B16,'UV台帐'!B:AL,18,0) | J16: =VLOOKUP(B16,'UV台帐'!B:AL,22,0) | K16: =VLOOKUP(B16,'UV台帐'!B:AL,24,0) | L16: =VLOOKUP(B16,'UV台帐'!B:AL,26,0) | M16: =VLOOKUP(B16,'UV台帐'!B:AL,27,0) | N16: =VLOOKUP(B16,'UV台帐'!B:AL,31,0) | O16: =VLOOKUP(B16,'UV台帐'!B:AL,33,0) | P16: =VLOOKUP(B16,'UV台帐'!B:AL,35,0) | Q16: =VLOOKUP(B16,'UV台帐'!B:AL,36,0) | R16: 是 | S16: A | T16: 否 | U16: 是 | V16: 大南路，真光 | W16: 80+三科 | X16: 容易专注度不高，不爱做笔记 | Y16: 提前学初一，爸爸想找性价比高的机构 | Z16: 初中肯定学，孩子注意力不集中，之前学一对一一对二这种的，首次班课担心真的怕效果不好，最好前排多关注。有支付能力，担心课程效果和老师的关注度，爸爸考虑一对一。A，担心人多。三科80多分，孩子专注力差 | AA16: 明确需求 | AB16: 7月8日沟通，家长层面支付能力不错，之前都是家教的，价格都是500多一次课，支付能力强，爸爸妈妈知道孩子这个情况不补不行 孩子妈咪说孩子成绩一般，各个方面都一般（原话），本次来上课主要是想要是想要转大机构试试班课，但是同步很担心人多关注度不够，重点客户 @肖锐03(Jerry) @陈南05(陈南) @何咏04(何咏)，尽可能让孩子坐前排，关注孩子，平时孩子答题，互动一定要助教拍照做好正面反馈，多做正向反馈 | AC16: 语,数,英 | AD16: 升学需求-保底本区公办高中,效果维度-提分,效果维度-抓习惯,沟通维度：老师有个性化 | AE16: 2-一般，对于目标需求一般 | AF16: 3-支付能力强 | AG16: 2-一般 | AH16: 2-评价一般、无感 | AI16: 3-有规划有意识 | AJ16: A-11-13 | AK16: 何咏04 | AL16: 是 | BF16: 林志豪01 | BG16: =VLOOKUP(B16,'UV台帐'!B:G,6,0) | BR16: =COUNTIFS(H16,"一期",I16,"在读")+COUNTIFS(L16,"一期",M16,"在读")+COUNTIFS(P16,"一期",Q16,"在读") | BS16: =BR16-BW16 | BT16: =VLOOKUP(B16,'UV台帐'!B:AL,19,0) | BU16: =VLOOKUP(B16,'UV台帐'!B:AL,28,0) | BV16: =VLOOKUP(B16,'UV台帐'!B:AL,37,0) | BW16: =COUNTIFS(H16,"一期",BT16,"是")+COUNTIFS(L16,"一期",BU16,"是")+COUNTIFS(P16,"一期",BV16,"是") | CA16: 4850707583
A17: 同创汇 | B17: 2524361673 | C17: =VLOOKUP(B17,'UV台帐'!B:AL,2,0) | D17: =VLOOKUP(B17,'UV台帐'!B:AL,3,0) | E17: =VLOOKUP(B17,'UV台帐'!B:AL,13,0) | F17: =VLOOKUP(B17,'UV台帐'!B:AL,15,0) | G17: =VLOOKUP(B17,'UV台帐'!B:AL,16,0) | H17: =VLOOKUP(B17,'UV台帐'!B:AL,17,0) | I17: =VLOOKUP(B17,'UV台帐'!B:AL,18,0) | J17: =VLOOKUP(B17,'UV台帐'!B:AL,22,0) | K17: =VLOOKUP(B17,'UV台帐'!B:AL,24,0) | L17: =VLOOKUP(B17,'UV台帐'!B:AL,26,0) | M17: =VLOOKUP(B17,'UV台帐'!B:AL,27,0) | N17: =VLOOKUP(B17,'UV台帐'!B:AL,31,0) | O17: =VLOOKUP(B17,'UV台帐'!B:AL,33,0) | P17: =VLOOKUP(B17,'UV台帐'!B:AL,35,0) | Q17: =VLOOKUP(B17,'UV台帐'!B:AL,36,0) | R17: 是 | U17: 是 | AA17: 未明确需求 | AB17: 295，小学在小北路，初中未定，等补录（育才实验等四家） 补过课，品读行，之前在这学过正价，学过铭铭的课，孩子之前有上过一点初中内容，孩子自己也愿意在过一下。8月份上物理，已经报了！后面报名的卡点可能是在孩子已经学过了 | AC17: 语,数,英 | AD17: 升学需求-进九大or中上,效果维度-培优拓展/分班考,沟通维度：老师有个性化,沟通维度：老师有关注度 | AE17: 2-一般，对于目标需求一般 | AF17: 3-支付能力强 | AG17: 3-喜欢 | AH17: 3-有正面评价 | AI17: 2-有意识无规划 | AJ17: A-11-13 | AK17: 高心怡04 | AL17: 触达 | BF17: 戎凯01 | BG17: =VLOOKUP(B17,'UV台帐'!B:G,6,0) | BR17: =COUNTIFS(H17,"一期",I17,"在读")+COUNTIFS(L17,"一期",M17,"在读")+COUNTIFS(P17,"一期",Q17,"在读") | BS17: =BR17-BW17 | BT17: =VLOOKUP(B17,'UV台帐'!B:AL,19,0) | BU17: =VLOOKUP(B17,'UV台帐'!B:AL,28,0) | BV17: =VLOOKUP(B17,'UV台帐'!B:AL,37,0) | BW17: =COUNTIFS(H17,"一期",BT17,"是")+COUNTIFS(L17,"一期",BU17,"是")+COUNTIFS(P17,"一期",BV17,"是") | CA17: 4315733010
A18: 同创汇 | B18: 2578457931 | C18: =VLOOKUP(B18,'UV台帐'!B:AL,2,0) | D18: =VLOOKUP(B18,'UV台帐'!B:AL,3,0) | E18: =VLOOKUP(B18,'UV台帐'!B:AL,13,0) | F18: =VLOOKUP(B18,'UV台帐'!B:AL,15,0) | G18: =VLOOKUP(B18,'UV台帐'!B:AL,16,0) | H18: =VLOOKUP(B18,'UV台帐'!B:AL,17,0) | I18: =VLOOKUP(B18,'UV台帐'!B:AL,18,0) | J18: =VLOOKUP(B18,'UV台帐'!B:AL,22,0) | K18: =VLOOKUP(B18,'UV台帐'!B:AL,24,0) | L18: =VLOOKUP(B18,'UV台帐'!B:AL,26,0) | M18: =VLOOKUP(B18,'UV台帐'!B:AL,27,0) | N18: =VLOOKUP(B18,'UV台帐'!B:AL,31,0) | O18: =VLOOKUP(B18,'UV台帐'!B:AL,33,0) | P18: =VLOOKUP(B18,'UV台帐'!B:AL,35,0) | Q18: =VLOOKUP(B18,'UV台帐'!B:AL,36,0) | R18: 是 | S18: A | U18: 是 | W18: 语文英语都是A+，数学是A | X18: 粗心 | Y18: 刘亦馨转介绍来的，需要在一起上课，关系还是很好的，数学比较薄弱 | Z18: 刘亦馨转介绍来的，需要在一起上课，关系还是很好的 | AA18: 未明确需求 | AB18: 刘亦馨转介绍来的，报名是应为刘亦馨报名，妈妈在午休，不是很愿意沟通（这会在飞机上） | AC18: 语,数,英 | AD18: 升学需求-保底本区公办高中,沟通维度：老师有个性化 | AE18: 2-一般，对于目标需求一般 | AF18: 2-支付能力一般 | AG18: 2-一般 | AH18: 2-评价一般、无感 | AI18: 2-有意识无规划 | AJ18: B-8-10 | AK18: 高心怡04 | AL18: 触达 | BF18: 戎凯01 | BG18: =VLOOKUP(B18,'UV台帐'!B:G,6,0) | BH18: 铁一 | BR18: =COUNTIFS(H18,"一期",I18,"在读")+COUNTIFS(L18,"一期",M18,"在读")+COUNTIFS(P18,"一期",Q18,"在读") | BS18: =BR18-BW18 | BT18: =VLOOKUP(B18,'UV台帐'!B:AL,19,0) | BU18: =VLOOKUP(B18,'UV台帐'!B:AL,28,0) | BV18: =VLOOKUP(B18,'UV台帐'!B:AL,37,0) | BW18: =COUNTIFS(H18,"一期",BT18,"是")+COUNTIFS(L18,"一期",BU18,"是")+COUNTIFS(P18,"一期",BV18,"是") | CA18: 4843140524
A19: 同创汇 | B19: 2937587526 | C19: =VLOOKUP(B19,'UV台帐'!B:AL,2,0) | D19: =VLOOKUP(B19,'UV台帐'!B:AL,3,0) | E19: =VLOOKUP(B19,'UV台帐'!B:AL,13,0) | F19: =VLOOKUP(B19,'UV台帐'!B:AL,15,0) | G19: =VLOOKUP(B19,'UV台帐'!B:AL,16,0) | H19: =VLOOKUP(B19,'UV台帐'!B:AL,17,0) | I19: =VLOOKUP(B19,'UV台帐'!B:AL,18,0) | J19: =VLOOKUP(B19,'UV台帐'!B:AL,22,0) | K19: =VLOOKUP(B19,'UV台帐'!B:AL,24,0) | L19: =VLOOKUP(B19,'UV台帐'!B:AL,26,0) | M19: =VLOOKUP(B19,'UV台帐'!B:AL,27,0) | N19: =VLOOKUP(B19,'UV台帐'!B:AL,31,0) | O19: =VLOOKUP(B19,'UV台帐'!B:AL,33,0) | P19: =VLOOKUP(B19,'UV台帐'!B:AL,35,0) | Q19: =VLOOKUP(B19,'UV台帐'!B:AL,36,0) | U19: 是 | AA19: 未明确需求 | AJ19: C-小于8 | AK19: 高心怡04 | AL19: 触达 | BF19: 戎凯01 | BG19: =VLOOKUP(B19,'UV台帐'!B:G,6,0) | BR19: =COUNTIFS(H19,"一期",I19,"在读")+COUNTIFS(L19,"一期",M19,"在读")+COUNTIFS(P19,"一期",Q19,"在读") | BS19: =BR19-BW19 | BT19: =VLOOKUP(B19,'UV台帐'!B:AL,19,0) | BU19: =VLOOKUP(B19,'UV台帐'!B:AL,28,0) | BV19: =VLOOKUP(B19,'UV台帐'!B:AL,37,0) | BW19: =COUNTIFS(H19,"一期",BT19,"是")+COUNTIFS(L19,"一期",BU19,"是")+COUNTIFS(P19,"一期",BV19,"是") | CA19: 2544969370
A20: 同创汇 | B20: 4399390086 | C20: =VLOOKUP(B20,'UV台帐'!B:AL,2,0) | D20: =VLOOKUP(B20,'UV台帐'!B:AL,3,0) | E20: =VLOOKUP(B20,'UV台帐'!B:AL,13,0) | F20: =VLOOKUP(B20,'UV台帐'!B:AL,15,0) | G20: =VLOOKUP(B20,'UV台帐'!B:AL,16,0) | H20: =VLOOKUP(B20,'UV台帐'!B:AL,17,0) | I20: =VLOOKUP(B20,'UV台帐'!B:AL,18,0) | J20: =VLOOKUP(B20,'UV台帐'!B:AL,22,0) | K20: =VLOOKUP(B20,'UV台帐'!B:AL,24,0) | L20: =VLOOKUP(B20,'UV台帐'!B:AL,26,0) | M20: =VLOOKUP(B20,'UV台帐'!B:AL,27,0) | N20: =VLOOKUP(B20,'UV台帐'!B:AL,31,0) | O20: =VLOOKUP(B20,'UV台帐'!B:AL,33,0) | P20: =VLOOKUP(B20,'UV台帐'!B:AL,35,0) | Q20: =VLOOKUP(B20,'UV台帐'!B:AL,36,0) | R20: 是 | S20: B | T20: 否 | U20: 否 | W20: 三科成绩都九十多分，都是A | Y20: 电销，知道作业帮，报名我们的线下课试试 | Z20: 未接，微信沟通 | AA20: 未明确需求 | AB20: 希望暑假提前做好初中的预习，夯实好基础，妈妈说已经加上三位老师沟通，不愿意重复沟通 | AC20: 语,数,英 | AD20: 效果维度-提分,沟通维度：老师有关注度 | AE20: 2-一般，对于目标需求一般 | AF20: 2-支付能力一般 | AG20: 2-一般 | AH20: 2-评价一般、无感 | AI20: 2-有意识无规划 | AJ20: B-8-10 | AK20: 高心怡04 | AL20: 触达 | BF20: 王丽 | BG20: =VLOOKUP(B20,'UV台帐'!B:G,6,0) | BR20: =COUNTIFS(H20,"一期",I20,"在读")+COUNTIFS(L20,"一期",M20,"在读")+COUNTIFS(P20,"一期",Q20,"在读") | BS20: =BR20-BW20 | BT20: =VLOOKUP(B20,'UV台帐'!B:AL,19,0) | BU20: =VLOOKUP(B20,'UV台帐'!B:AL,28,0) | BV20: =VLOOKUP(B20,'UV台帐'!B:AL,37,0) | BW20: =COUNTIFS(H20,"一期",BT20,"是")+COUNTIFS(L20,"一期",BU20,"是")+COUNTIFS(P20,"一期",BV20,"是") | CA20: 4467119064
A21: 新宝利 | B21: 4850707583 | C21: =VLOOKUP(B21,'UV台帐'!B:AL,2,0) | D21: =VLOOKUP(B21,'UV台帐'!B:AL,3,0) | E21: =VLOOKUP(B21,'UV台帐'!B:AL,13,0) | F21: =VLOOKUP(B21,'UV台帐'!B:AL,15,0) | G21: =VLOOKUP(B21,'UV台帐'!B:AL,16,0) | H21: =VLOOKUP(B21,'UV台帐'!B:AL,17,0) | I21: =VLOOKUP(B21,'UV台帐'!B:AL,18,0) | J21: =VLOOKUP(B21,'UV台帐'!B:AL,22,0) | K21: =VLOOKUP(B21,'UV台帐'!B:AL,24,0) | L21: =VLOOKUP(B21,'UV台帐'!B:AL,26,0) | M21: =VLOOKUP(B21,'UV台帐'!B:AL,27,0) | N21: =VLOOKUP(B21,'UV台帐'!B:AL,31,0) | O21: =VLOOKUP(B21,'UV台帐'!B:AL,33,0) | P21: =VLOOKUP(B21,'UV台帐'!B:AL,35,0) | Q21: =VLOOKUP(B21,'UV台帐'!B:AL,36,0) | R21: 是 | S21: B | T21: 否 | U21: 是 | V21: 满小 | W21: 三科80-85 | X21: 专注度不太够，太粗心 | Y21: 过度初一的，不想天天玩，想给孩子英语方法提升的地方 | Z21: 多个关注就可以，尽可能分开，林骏锋，侯家聪和他，之前都是家教的，而且断断续续的，孩子态度问题，家长管不住。B-C；300/小时，支付能力OK。 | AA21: 明确需求 | AB21: 7月8日沟通，电话沟通 语文：孩子语言基础部分还可以，但是也会错在字词和拼音部分会多一些，阅读是孩子扣分严重得模块，孩子找不到关键，没怎么见过那过满分得阅读，多引导他怎么找到关键句子，理解含义 数学：孩子数学相对好一点不过也不是特别优秀，A-B徘徊，及时A也大概85-90，孩子计算和思维都不算特别优秀，平时计算总粗心，10-8=3都有出现过 英语：英语是最薄弱得科目，他们三个得英语都不好，相对家聪好一点的，我家孩子单词背的少，又不愿意自觉背，觉得阅读也差，不会用词写作文，整体偏弱 暑假报名过度初一的，不想天天玩，想给孩子英语方法提升的地方，但是孩子比较有性格，其实很早就想找机构补课了，但是孩子爱踢球，要搞孩子 | AC21: 英 | AD21: 效果维度-提分,效果维度-抓习惯,沟通维度：老师有个性化 | AE21: 2-一般，对于目标需求一般 | AF21: 2-支付能力一般 | AG21: 2-一般 | AH21: 2-一般 | AI21: 2-有意识无规划 | AJ21: B-8-10 | AK21: 何咏04 | AL21: 是 | BF21: 林志豪01 | BG21: =VLOOKUP(B21,'UV台帐'!B:G,6,0) | BR21: =COUNTIFS(H21,"一期",I21,"在读")+COUNTIFS(L21,"一期",M21,"在读")+COUNTIFS(P21,"一期",Q21,"在读") | BS21: =BR21-BW21 | BT21: =VLOOKUP(B21,'UV台帐'!B:AL,19,0) | BU21: =VLOOKUP(B21,'UV台帐'!B:AL,28,0) | BV21: =VLOOKUP(B21,'UV台帐'!B:AL,37,0) | BW21: =COUNTIFS(H21,"一期",BT21,"是")+COUNTIFS(L21,"一期",BU21,"是")+COUNTIFS(P21,"一期",BV21,"是") | CA21: 4070489080
A22: 同创汇 | B22: 2558217051 | C22: =VLOOKUP(B22,'UV台帐'!B:AL,2,0) | D22: =VLOOKUP(B22,'UV台帐'!B:AL,3,0) | E22: =VLOOKUP(B22,'UV台帐'!B:AL,13,0) | F22: =VLOOKUP(B22,'UV台帐'!B:AL,15,0) | G22: =VLOOKUP(B22,'UV台帐'!B:AL,16,0) | H22: =VLOOKUP(B22,'UV台帐'!B:AL,17,0) | I22: =VLOOKUP(B22,'UV台帐'!B:AL,18,0) | J22: =VLOOKUP(B22,'UV台帐'!B:AL,22,0) | K22: =VLOOKUP(B22,'UV台帐'!B:AL,24,0) | L22: =VLOOKUP(B22,'UV台帐'!B:AL,26,0) | M22: =VLOOKUP(B22,'UV台帐'!B:AL,27,0) | N22: =VLOOKUP(B22,'UV台帐'!B:AL,31,0) | O22: =VLOOKUP(B22,'UV台帐'!B:AL,33,0) | P22: =VLOOKUP(B22,'UV台帐'!B:AL,35,0) | Q22: =VLOOKUP(B22,'UV台帐'!B:AL,36,0) | R22: 是 | S22: B | U22: 是 | V22: 水荫路小学/摇中了7中 | W22: 语文88.5，数学92.5，英语88 | X22: 粗心，没有自驱力 | Y22: 摇到的学校比较好，妈妈也认识到需要给孩子加强假期学习，担心后续上学会跟不上 | Z22: 摇中了7中，可以正常来上课 | AA22: 明确需求 | AB22: 六下三科语文91英语83数学86，七中初中，水荫路小学，高中想去七中/好点高中 不知道分班情况，开学知道 之前在线下小机构补课，爸爸感觉还可以，理由是：成绩稳定有提升，行课中喜欢鼓励的老师，不要严格批评 选择机构的话，还是要看老师长期的规划，需要对应学校的进度，确保孩子可以跟得上七中的进度和平均分之上 | AC22: 语,数,英 | AD22: 升学需求-保底本区公办高中,效果维度-提分,效果维度-抓习惯,效果维度-培优拓展/分班考,沟通维度：老师有关注度 | AE22: 2-一般，对于目标需求一般 | AF22: 2-支付能力一般 | AG22: 2-一般 | AH22: 2-评价一般、无感 | AI22: 2-有意识无规划 | AJ22: B-8-10 | AK22: 陈南05 | BF22: 戎凯01 | BG22: =VLOOKUP(B22,'UV台帐'!B:G,6,0) | BH22: 7中 | BR22: =COUNTIFS(H22,"一期",I22,"在读")+COUNTIFS(L22,"一期",M22,"在读")+COUNTIFS(P22,"一期",Q22,"在读") | BS22: =BR22-BW22 | BT22: =VLOOKUP(B22,'UV台帐'!B:AL,19,0) | BU22: =VLOOKUP(B22,'UV台帐'!B:AL,28,0) | BV22: =VLOOKUP(B22,'UV台帐'!B:AL,37,0) | BW22: =COUNTIFS(H22,"一期",BT22,"是")+COUNTIFS(L22,"一期",BU22,"是")+COUNTIFS(P22,"一期",BV22,"是") | CA22: 4773663119
A23: 新宝利 | B23: 2563540579 | C23: =VLOOKUP(B23,'UV台帐'!B:AL,2,0) | D23: =VLOOKUP(B23,'UV台帐'!B:AL,3,0) | E23: =VLOOKUP(B23,'UV台帐'!B:AL,13,0) | F23: =VLOOKUP(B23,'UV台帐'!B:AL,15,0) | G23: =VLOOKUP(B23,'UV台帐'!B:AL,16,0) | H23: =VLOOKUP(B23,'UV台帐'!B:AL,17,0) | I23: =VLOOKUP(B23,'UV台帐'!B:AL,18,0) | J23: =VLOOKUP(B23,'UV台帐'!B:AL,22,0) | K23: =VLOOKUP(B23,'UV台帐'!B:AL,24,0) | L23: =VLOOKUP(B23,'UV台帐'!B:AL,26,0) | M23: =VLOOKUP(B23,'UV台帐'!B:AL,27,0) | N23: =VLOOKUP(B23,'UV台帐'!B:AL,31,0) | O23: =VLOOKUP(B23,'UV台帐'!B:AL,33,0) | P23: =VLOOKUP(B23,'UV台帐'!B:AL,35,0) | Q23: =VLOOKUP(B23,'UV台帐'!B:AL,36,0) | R23: 是 | S23: S | T23: 是 | U23: 是 | V23: 同福西路（中途合并为旧部前，华侨 | W23: ABA，但是妈咪说学校教的很简单 | X23: 孩子笔记，校内做题都不好 | Y23: 一开始想找一对一的，6升初一规划一对一讲得好觉得我们专业报名进来，想看我们教学能否也能帮助到孩子开开智 | Z23: 重点跟进客户，很重点，请各位老师重点关注，有正价课高意向，价格知道。S，何咏老师做诊断，有考虑现场报名，问了何咏老师一对一的价格 | AA23: 明确需求 | AB23: 家长来了很多次校区了， 语文本次期末考B，数学B，英语A，但是问具体什么情况，妈妈爸爸是挺懵得，对孩子具体哪些问题学校老师重来很模糊，甚至说期末考还给答案学员背（妈咪原话） 语文：孩子都不是特别优秀，尤其是阅读，数学是都薄弱，而且孩子不是特别聪明，之前一对一家教补，没有什么很好的效果，花了钱又浪费时间，补了一个学期。英语是孩子最好得科目基本90+孩子一般听力差一些 爸爸妈咪目标就是先普高，目前进了华侨，爸爸问了近几年得华侨升学都低于平均线，爸爸觉得天塌了，知道初一一定补如果，初一成绩不好，直接花大钱安排学习。 @何咏04(何咏) @陈南05(陈南) @肖锐03(Jerry)三科老师多多关注，课堂中可以让助教拍一些您辅导孩子得照片，孩子答题得情况，家长说让孩子做做第二排 家长来源。是认可我的专业度从一对一转来的，爸爸还说经常请我喝茶，妈咪对我也很满意，认可度专业度都拉满只要，老师端教学端ok，有好的规划，基本报名 | AC23: 语,数,英 | AD23: 升学需求-保底本区公办高中,效果维度-提分,效果维度-培优拓展/分班考,沟通维度：老师有个性化,沟通维度：老师有关注度 | AE23: 3-非常紧迫，有短期目标和长期需求 | AF23: 3-支付能力强 | AG23: 2-一般 | AH23: 3-有正面评价 | AI23: 3-有规划有意识 | AJ23: S-14-15 | AK23: 何咏04 | AL23: 是 | BF23: 林志豪01 | BG23: =VLOOKUP(B23,'UV台帐'!B:G,6,0) | BH23: 华侨中学 | BR23: =COUNTIFS(H23,"一期",I23,"在读")+COUNTIFS(L23,"一期",M23,"在读")+COUNTIFS(P23,"一期",Q23,"在读") | BS23: =BR23-BW23 | BT23: =VLOOKUP(B23,'UV台帐'!B:AL,19,0) | BU23: =VLOOKUP(B23,'UV台帐'!B:AL,28,0) | BV23: =VLOOKUP(B23,'UV台帐'!B:AL,37,0) | BW23: =COUNTIFS(H23,"一期",BT23,"是")+COUNTIFS(L23,"一期",BU23,"是")+COUNTIFS(P23,"一期",BV23,"是") | CA23: 4090630208
A24: 新宝利 | B24: 4847554796 | C24: =VLOOKUP(B24,'UV台帐'!B:AL,2,0) | D24: =VLOOKUP(B24,'UV台帐'!B:AL,3,0) | E24: =VLOOKUP(B24,'UV台帐'!B:AL,13,0) | F24: =VLOOKUP(B24,'UV台帐'!B:AL,15,0) | G24: =VLOOKUP(B24,'UV台帐'!B:AL,16,0) | H24: =VLOOKUP(B24,'UV台帐'!B:AL,17,0) | I24: =VLOOKUP(B24,'UV台帐'!B:AL,18,0) | J24: =VLOOKUP(B24,'UV台帐'!B:AL,22,0) | K24: =VLOOKUP(B24,'UV台帐'!B:AL,24,0) | L24: =VLOOKUP(B24,'UV台帐'!B:AL,26,0) | M24: =VLOOKUP(B24,'UV台帐'!B:AL,27,0) | N24: =VLOOKUP(B24,'UV台帐'!B:AL,31,0) | O24: =VLOOKUP(B24,'UV台帐'!B:AL,33,0) | P24: =VLOOKUP(B24,'UV台帐'!B:AL,35,0) | Q24: =VLOOKUP(B24,'UV台帐'!B:AL,36,0) | R24: 是 | S24: B | T24: 否 | U24: 是 | V24: 培英 | W24: 85-90之间 | X24: 不喜欢做课外作业，比较懒，学校老师反馈是比较乖，偶尔话多 | Y24: 是薄弱科目，所以要补，希望可以激发孩子兴趣 | Z24: 电访未接，地推9.9团报，暑假只报单科语文，没补过语文课，数学和英语已经学到八上内容，在楼上学，和皓霖柏霖皓轩建廷一起的，高中计划留在本校区，也是想冲击一二梯队学校，学习都是孩子自己搞定，偶尔爸爸会管一下，询问秋季是否跟着老师学，妈妈表示应该会，但是也会跟柏霖他们一起，关系比较好 | AA24: 明确需求 | AB24: 孩子情况：单报了一科语文，孩子比较懒，额外的作业不太愿意写，需要老师多督促下，孩子对语文科目喜欢度一般，期望暑假跟着老师学可以，平时作业都是孩子自己负责，偶尔爸爸会管一下 提高他语文学科的兴趣，学校评价孩子是挺乖的，但有时候话有点多，数学和英语报了楼上进阶，已经学到八上内容，秋季还没报，期望提高下语文成绩，怕孩子初中跟不上，和博霖皓霖皓轩建廷都是同学，一起补习的，是想去本校高中部，分数线要710，有铺垫过想达到这个分数线各科得达到多少分，妈妈是认可的，有想长期学的，但是表明也想知道学校安排之后在考虑，会和其他几位家长商量一下，拿名额学位截，初中不应该换老师，孩子还得重新适应， | AC24: 语 | AD24: 升学需求-保底本区公办高中,效果维度-提分,效果维度-培优拓展/分班考 | AE24: 2-一般，对于目标需求一般 | AF24: 3-支付能力强 | AG24: 1-抵触 | AH24: 2-评价一般、无感 | AI24: 3-有规划有意识 | AJ24: A-11-13 | AK24: 李润 | BF24: 张敏烨 | BG24: =VLOOKUP(B24,'UV台帐'!B:G,6,0) | BR24: =COUNTIFS(H24,"一期",I24,"在读")+COUNTIFS(L24,"一期",M24,"在读")+COUNTIFS(P24,"一期",Q24,"在读") | BS24: =BR24-BW24 | BT24: =VLOOKUP(B24,'UV台帐'!B:AL,19,0) | BU24: =VLOOKUP(B24,'UV台帐'!B:AL,28,0) | BV24: =VLOOKUP(B24,'UV台帐'!B:AL,37,0) | BW24: =COUNTIFS(H24,"一期",BT24,"是")+COUNTIFS(L24,"一期",BU24,"是")+COUNTIFS(P24,"一期",BV24,"是") | CA24: 2922308038
A25: 同创汇 | B25: 4315733010 | C25: =VLOOKUP(B25,'UV台帐'!B:AL,2,0) | D25: =VLOOKUP(B25,'UV台帐'!B:AL,3,0) | E25: =VLOOKUP(B25,'UV台帐'!B:AL,13,0) | F25: =VLOOKUP(B25,'UV台帐'!B:AL,15,0) | G25: =VLOOKUP(B25,'UV台帐'!B:AL,16,0) | H25: =VLOOKUP(B25,'UV台帐'!B:AL,17,0) | I25: =VLOOKUP(B25,'UV台帐'!B:AL,18,0) | J25: =VLOOKUP(B25,'UV台帐'!B:AL,22,0) | K25: =VLOOKUP(B25,'UV台帐'!B:AL,24,0) | L25: =VLOOKUP(B25,'UV台帐'!B:AL,26,0) | M25: =VLOOKUP(B25,'UV台帐'!B:AL,27,0) | N25: =VLOOKUP(B25,'UV台帐'!B:AL,31,0) | O25: =VLOOKUP(B25,'UV台帐'!B:AL,33,0) | P25: =VLOOKUP(B25,'UV台帐'!B:AL,35,0) | Q25: =VLOOKUP(B25,'UV台帐'!B:AL,36,0) | R25: 是 | S25: B | T25: 是 | U25: 是 | V25: 水荫路小学 | W25: 英语A；语文B；数学B | Y25: BMD，体验课期末复习课后报名 | Z25: 未接，微信沟通 | AA25: 明确需求 | AB25: 孩子爸爸管学习，孩子目前语文、数学两门学科基础较弱些，上课注意力有时候会不集中，个性有些散漫，希望老师们对她要求严格一些，及时纠正走神、松懈等不良状态，需要老师多监督，需要在行课中让家长感受到孩子变化，比如从上课专注力和作业完成情况来表现。在课后回访中，需要再下危机，让家长感受到初中的难度和孩子们之间的差异来进行收单 | AC25: 语,数,英 | AD25: 效果维度-提分,效果维度-抓习惯,沟通维度：老师有关注度 | AE25: 2-一般，对于目标需求一般 | AF25: 2-支付能力一般 | AG25: 2-一般 | AH25: 2-评价一般、无感 | AI25: 2-有意识无规划 | AJ25: B-8-10 | AK25: 陈南05 | BF25: 王丽 | BG25: =VLOOKUP(B25,'UV台帐'!B:G,6,0) | BR25: =COUNTIFS(H25,"一期",I25,"在读")+COUNTIFS(L25,"一期",M25,"在读")+COUNTIFS(P25,"一期",Q25,"在读") | BS25: =BR25-BW25 | BT25: =VLOOKUP(B25,'UV台帐'!B:AL,19,0) | BU25: =VLOOKUP(B25,'UV台帐'!B:AL,28,0) | BV25: =VLOOKUP(B25,'UV台帐'!B:AL,37,0) | BW25: =COUNTIFS(H25,"一期",BT25,"是")+COUNTIFS(L25,"一期",BU25,"是")+COUNTIFS(P25,"一期",BV25,"是") | CA25: 4060101914
A26: 同创汇 | B26: 4522580433 | C26: =VLOOKUP(B26,'UV台帐'!B:AL,2,0) | D26: =VLOOKUP(B26,'UV台帐'!B:AL,3,0) | E26: =VLOOKUP(B26,'UV台帐'!B:AL,13,0) | F26: =VLOOKUP(B26,'UV台帐'!B:AL,15,0) | G26: =VLOOKUP(B26,'UV台帐'!B:AL,16,0) | H26: =VLOOKUP(B26,'UV台帐'!B:AL,17,0) | I26: =VLOOKUP(B26,'UV台帐'!B:AL,18,0) | J26: =VLOOKUP(B26,'UV台帐'!B:AL,22,0) | K26: =VLOOKUP(B26,'UV台帐'!B:AL,24,0) | L26: =VLOOKUP(B26,'UV台帐'!B:AL,26,0) | M26: =VLOOKUP(B26,'UV台帐'!B:AL,27,0) | N26: =VLOOKUP(B26,'UV台帐'!B:AL,31,0) | O26: =VLOOKUP(B26,'UV台帐'!B:AL,33,0) | P26: =VLOOKUP(B26,'UV台帐'!B:AL,35,0) | Q26: =VLOOKUP(B26,'UV台帐'!B:AL,36,0) | R26: 是 | S26: A | T26: 是 | U26: 否 | V26: 省实越秀 | W26: 285-290 | X26: 能自主完成作业不用家长催，数学爱自己研究难度高的题型，孩子上课是很认真和积极互动的，腼腆小孩 | Y26: 试听了大帅老师的数学期末复习课，孩子喜欢，课后诊断卷现场思捷+大帅老师点评，家长觉得专业和满意 | Z26: 摇中学校：省越 孩子想要风格有趣些，孩子作业有惰性，有不懂的知识点要及时纠正，加强孩子的理解，座位往前坐 | AA26: 明确需求 | AB26: 明确要冲省实越秀开学分层考，但孩子作业有惰性，家长需求是加强孩子的知识理解和作业完成情况 | AC26: 语,数,英 | AD26: 升学需求-保底本区公办高中,效果维度-提分,效果维度-抓习惯,效果维度-培优拓展/分班考,沟通维度：老师有关注度 | AE26: 2-一般，对于目标需求一般 | AF26: 3-支付能力强 | AG26: 3-喜欢 | AH26: 3-有正面评价 | AI26: 2-有意识无规划 | AJ26: A-11-13 | AK26: 高心怡04 | AL26: 是 | BF26: 苏丽婷 | BG26: =VLOOKUP(B26,'UV台帐'!B:G,6,0) | BH26: 省实越秀 | BR26: =COUNTIFS(H26,"一期",I26,"在读")+COUNTIFS(L26,"一期",M26,"在读")+COUNTIFS(P26,"一期",Q26,"在读") | BS26: =BR26-BW26 | BT26: =VLOOKUP(B26,'UV台帐'!B:AL,19,0) | BU26: =VLOOKUP(B26,'UV台帐'!B:AL,28,0) | BV26: =VLOOKUP(B26,'UV台帐'!B:AL,37,0) | BW26: =COUNTIFS(H26,"一期",BT26,"是")+COUNTIFS(L26,"一期",BU26,"是")+COUNTIFS(P26,"一期",BV26,"是") | CA26: 2553608227
A27: 新宝利 | B27: 4016827369 | C27: =VLOOKUP(B27,'UV台帐'!B:AL,2,0) | D27: =VLOOKUP(B27,'UV台帐'!B:AL,3,0) | E27: =VLOOKUP(B27,'UV台帐'!B:AL,13,0) | F27: =VLOOKUP(B27,'UV台帐'!B:AL,15,0) | G27: =VLOOKUP(B27,'UV台帐'!B:AL,16,0) | H27: =VLOOKUP(B27,'UV台帐'!B:AL,17,0) | I27: =VLOOKUP(B27,'UV台帐'!B:AL,18,0) | J27: =VLOOKUP(B27,'UV台帐'!B:AL,22,0) | K27: =VLOOKUP(B27,'UV台帐'!B:AL,24,0) | L27: =VLOOKUP(B27,'UV台帐'!B:AL,26,0) | M27: =VLOOKUP(B27,'UV台帐'!B:AL,27,0) | N27: =VLOOKUP(B27,'UV台帐'!B:AL,31,0) | O27: =VLOOKUP(B27,'UV台帐'!B:AL,33,0) | P27: =VLOOKUP(B27,'UV台帐'!B:AL,35,0) | Q27: =VLOOKUP(B27,'UV台帐'!B:AL,36,0) | R27: 是 | S27: B | T27: 是 | U27: 是 | V27: 现在名德补录等结果 | W27: 三科平均90 | X27: 平时需要老师督促，孩子性格挺活泼，希望老师能多多提问，做题的时候会比较粗心，之前都是在线上学习； | Y27: 希望分班测取得一个不错排名 | Z27: 平时需要老师督促，孩子性格挺活泼，希望老师能多多提问，做题的时候会比较粗心，之前都是在线上学习；两科一期上，一科在二期 | AA27: 明确需求 | AB27: 孩子情况：孩子性格挺活泼，分数家长不太清晰， 一直都是a 。之前都是在线上学习，两科一期上，一科在二期 家长需求：家长说雅涵按照孩子的情况来安排就好 。数英方面雅涵就还好，语文的阅读和写作会比较弱， 做题的时候会比较粗心，平时需要老师督促，希望老师能多多提问。 补课经历：之前一直都在线上有补课，家长也有让孩子长期学习的打算，但是也要看:费用 目标：目前没有考虑那么长远，已经和家长说了我们的课程体系设定家长目标 目前等待名德补录，摇号的结果不行，家长说希望孩子有一个公办高中能上 | AC27: 语,数 | AD27: 升学需求-保底本区公办高中,效果维度-提分,效果维度-抓习惯,效果维度-培优拓展/分班考,沟通维度：老师有个性化,沟通维度：老师有关注度 | AE27: 2-一般，对于目标需求一般 | AF27: 2-支付能力一般 | AG27: 2-一般 | AH27: 2-评价一般、无感 | AI27: 2-有意识无规划 | AJ27: B-8-10 | AK27: 何咏04 | AL27: 是 | BF27: 沈思浩 | BG27: =VLOOKUP(B27,'UV台帐'!B:G,6,0) | BR27: =COUNTIFS(H27,"一期",I27,"在读")+COUNTIFS(L27,"一期",M27,"在读")+COUNTIFS(P27,"一期",Q27,"在读") | BS27: =BR27-BW27 | BT27: =VLOOKUP(B27,'UV台帐'!B:AL,19,0) | BU27: =VLOOKUP(B27,'UV台帐'!B:AL,28,0) | BV27: =VLOOKUP(B27,'UV台帐'!B:AL,37,0) | BW27: =COUNTIFS(H27,"一期",BT27,"是")+COUNTIFS(L27,"一期",BU27,"是")+COUNTIFS(P27,"一期",BV27,"是") | CA27: 4833286317
A28: 新宝利 | B28: 2501010500 | C28: =VLOOKUP(B28,'UV台帐'!B:AL,2,0) | D28: =VLOOKUP(B28,'UV台帐'!B:AL,3,0) | E28: =VLOOKUP(B28,'UV台帐'!B:AL,13,0) | F28: =VLOOKUP(B28,'UV台帐'!B:AL,15,0) | G28: =VLOOKUP(B28,'UV台帐'!B:AL,16,0) | H28: =VLOOKUP(B28,'UV台帐'!B:AL,17,0) | I28: =VLOOKUP(B28,'UV台帐'!B:AL,18,0) | J28: =VLOOKUP(B28,'UV台帐'!B:AL,22,0) | K28: =VLOOKUP(B28,'UV台帐'!B:AL,24,0) | L28: =VLOOKUP(B28,'UV台帐'!B:AL,26,0) | M28: =VLOOKUP(B28,'UV台帐'!B:AL,27,0) | N28: =VLOOKUP(B28,'UV台帐'!B:AL,31,0) | O28: =VLOOKUP(B28,'UV台帐'!B:AL,33,0) | P28: =VLOOKUP(B28,'UV台帐'!B:AL,35,0) | Q28: =VLOOKUP(B28,'UV台帐'!B:AL,36,0) | R28: 是 | S28: B | T28: 是 | U28: 是 | V28: 培英 | W28: A | X28: 阅读写作明显短板那 | Y28: 暑假提前做个预习 | Z28: 地推9.9团报，暑假只报单科语文，打电话未接，学校有提前学物理，想了解物理课；认可李润。 | AA28: 明确需求 | AB28: 孩子情况：单独报了一科语文，阅读没有技巧，想到啥写啥，偶尔会有字词写错，和皓霖是兄弟，妈妈理念是挺好的，会提前规划孩子学习，孩子自觉性很高，不需要怎么督促学习，之前上过李润的课，孩子对李润认可度高 @李润04(李润)但是试课的时候觉得校区比较吵，班级下课时间不一致，担心影响孩子上课，询问过秋季长期学的意向，但妈妈表示初中学校安排还没出来，等开学后看看，妈妈平时比较忙，晚上接通率会高一些，家长理念不错，支付能力OK | AC28: 语 | AD28: 效果维度-提分,效果维度-抓习惯 | AE28: 1.不紧迫，觉得初一不需要学 | AF28: 3-支付能力强 | AG28: 2-一般 | AH28: 1-有雷点、槽点 | AI28: 3-有规划有意识 | AJ28: B-8-10 | AK28: 李润 | BF28: 张敏烨 | BG28: =VLOOKUP(B28,'UV台帐'!B:G,6,0) | BR28: =COUNTIFS(H28,"一期",I28,"在读")+COUNTIFS(L28,"一期",M28,"在读")+COUNTIFS(P28,"一期",Q28,"在读") | BS28: =BR28-BW28 | BT28: =VLOOKUP(B28,'UV台帐'!B:AL,19,0) | BU28: =VLOOKUP(B28,'UV台帐'!B:AL,28,0) | BV28: =VLOOKUP(B28,'UV台帐'!B:AL,37,0) | BW28: =COUNTIFS(H28,"一期",BT28,"是")+COUNTIFS(L28,"一期",BU28,"是")+COUNTIFS(P28,"一期",BV28,"是") | CA28: 2472389311
A29: 新宝利 | B29: 4847695021 | C29: =VLOOKUP(B29,'UV台帐'!B:AL,2,0) | D29: =VLOOKUP(B29,'UV台帐'!B:AL,3,0) | E29: =VLOOKUP(B29,'UV台帐'!B:AL,13,0) | F29: =VLOOKUP(B29,'UV台帐'!B:AL,15,0) | G29: =VLOOKUP(B29,'UV台帐'!B:AL,16,0) | H29: =VLOOKUP(B29,'UV台帐'!B:AL,17,0) | I29: =VLOOKUP(B29,'UV台帐'!B:AL,18,0) | J29: =VLOOKUP(B29,'UV台帐'!B:AL,22,0) | K29: =VLOOKUP(B29,'UV台帐'!B:AL,24,0) | L29: =VLOOKUP(B29,'UV台帐'!B:AL,26,0) | M29: =VLOOKUP(B29,'UV台帐'!B:AL,27,0) | N29: =VLOOKUP(B29,'UV台帐'!B:AL,31,0) | O29: =VLOOKUP(B29,'UV台帐'!B:AL,33,0) | P29: =VLOOKUP(B29,'UV台帐'!B:AL,35,0) | Q29: =VLOOKUP(B29,'UV台帐'!B:AL,36,0) | R29: 是 | S29: B | T29: 是 | U29: 是 | V29: 培英 | W29: A | X29: 语文单科无明显薄弱项 | Y29: 暑假提前做个预习 | Z29: 地推9.9团报，暑假只报单科语文，打电话未接，学校有提前学物理，想了解物理课，认可李润 | AA29: 明确需求 | AB29: 单独报了一科语文，和皓霖是兄弟，妈妈理念是挺好的，会提前规划孩子学习，孩子自觉性很高，不需要怎么督促学习，之前上过李润的课，孩子对李润认可度高，但是试课的时候觉得校区比较吵，班级下课时间不一致，担心影响孩子上课，询问过秋季长期学的意向，但妈妈表示初中学校安排还没出来，等开学后看看，妈妈平时比较忙，晚上接通率会高一些 | AC29: 语 | AD29: 效果维度-提分,效果维度-抓习惯 | AE29: 1.不紧迫，觉得初一不需要学 | AF29: 3-支付能力强 | AG29: 2-一般 | AH29: 1-有雷点、槽点 | AI29: 3-有规划有意识 | AJ29: B-8-10 | AK29: 李润 | BF29: 张敏烨 | BG29: =VLOOKUP(B29,'UV台帐'!B:G,6,0) | BR29: =COUNTIFS(H29,"一期",I29,"在读")+COUNTIFS(L29,"一期",M29,"在读")+COUNTIFS(P29,"一期",Q29,"在读") | BS29: =BR29-BW29 | BT29: =VLOOKUP(B29,'UV台帐'!B:AL,19,0) | BU29: =VLOOKUP(B29,'UV台帐'!B:AL,28,0) | BV29: =VLOOKUP(B29,'UV台帐'!B:AL,37,0) | BW29: =COUNTIFS(H29,"一期",BT29,"是")+COUNTIFS(L29,"一期",BU29,"是")+COUNTIFS(P29,"一期",BV29,"是") | CA29: 4831171617
A30: 新宝利 | B30: 2401201374 | C30: =VLOOKUP(B30,'UV台帐'!B:AL,2,0) | D30: =VLOOKUP(B30,'UV台帐'!B:AL,3,0) | E30: =VLOOKUP(B30,'UV台帐'!B:AL,13,0) | F30: =VLOOKUP(B30,'UV台帐'!B:AL,15,0) | G30: =VLOOKUP(B30,'UV台帐'!B:AL,16,0) | H30: =VLOOKUP(B30,'UV台帐'!B:AL,17,0) | I30: =VLOOKUP(B30,'UV台帐'!B:AL,18,0) | J30: =VLOOKUP(B30,'UV台帐'!B:AL,22,0) | K30: =VLOOKUP(B30,'UV台帐'!B:AL,24,0) | L30: =VLOOKUP(B30,'UV台帐'!B:AL,26,0) | M30: =VLOOKUP(B30,'UV台帐'!B:AL,27,0) | N30: =VLOOKUP(B30,'UV台帐'!B:AL,31,0) | O30: =VLOOKUP(B30,'UV台帐'!B:AL,33,0) | P30: =VLOOKUP(B30,'UV台帐'!B:AL,35,0) | Q30: =VLOOKUP(B30,'UV台帐'!B:AL,36,0) | R30: 是 | S30: B | T30: 是 | U30: 是 | V30: 民办 | W30: A | X30: 阅读模块薄弱 | Y30: 暑假提前做个预习 | Z30: 地推9.9团报，暑假只报单科语文，打电话未接，认可李润 | AA30: 明确需求 | AB30: 单独报了一科语文，和博霖皓霖皓轩珉锐是同学，数学和英语在进阶学了，语文相对薄弱一些，希望老师讲授一些阅读技巧，写作方法之类的，地推9.9团报的，有铺垫过语文科目的重要性，妈妈是比较认可的，孩子也对李润认可度高，妈妈觉得还是看孩子自己，要学是5个同学一起的 | AC30: 语 | AD30: 效果维度-提分,效果维度-抓习惯 | AE30: 1.不紧迫，觉得初一不需要学 | AF30: 3-支付能力强 | AG30: 2-一般 | AH30: 1-有雷点、槽点 | AI30: 3-有规划有意识 | AJ30: B-8-10 | AK30: 李润 | BF30: 张敏烨 | BG30: =VLOOKUP(B30,'UV台帐'!B:G,6,0) | BR30: =COUNTIFS(H30,"一期",I30,"在读")+COUNTIFS(L30,"一期",M30,"在读")+COUNTIFS(P30,"一期",Q30,"在读") | BS30: =BR30-BW30 | BT30: =VLOOKUP(B30,'UV台帐'!B:AL,19,0) | BU30: =VLOOKUP(B30,'UV台帐'!B:AL,28,0) | BV30: =VLOOKUP(B30,'UV台帐'!B:AL,37,0) | BW30: =COUNTIFS(H30,"一期",BT30,"是")+COUNTIFS(L30,"一期",BU30,"是")+COUNTIFS(P30,"一期",BV30,"是") | CA30: 4255068106
A31: 新宝利 | B31: 2530543525 | C31: =VLOOKUP(B31,'UV台帐'!B:AL,2,0) | D31: =VLOOKUP(B31,'UV台帐'!B:AL,3,0) | E31: =VLOOKUP(B31,'UV台帐'!B:AL,13,0) | F31: =VLOOKUP(B31,'UV台帐'!B:AL,15,0) | G31: =VLOOKUP(B31,'UV台帐'!B:AL,16,0) | H31: =VLOOKUP(B31,'UV台帐'!B:AL,17,0) | I31: =VLOOKUP(B31,'UV台帐'!B:AL,18,0) | J31: =VLOOKUP(B31,'UV台帐'!B:AL,22,0) | K31: =VLOOKUP(B31,'UV台帐'!B:AL,24,0) | L31: =VLOOKUP(B31,'UV台帐'!B:AL,26,0) | M31: =VLOOKUP(B31,'UV台帐'!B:AL,27,0) | N31: =VLOOKUP(B31,'UV台帐'!B:AL,31,0) | O31: =VLOOKUP(B31,'UV台帐'!B:AL,33,0) | P31: =VLOOKUP(B31,'UV台帐'!B:AL,35,0) | Q31: =VLOOKUP(B31,'UV台帐'!B:AL,36,0) | R31: 是 | S31: B | T31: 是 | U31: 是 | W31: 95 | Y31: 衔接新初一，孩子语文弱，提升一下，数学有机构 | Z31: 团报，且之前沟通，有阅读补补需求，但是太看重孩子感受；意向一般，线下沟通，暑假衔接过度；语文单科。只认李润老师。 | AA31: 明确需求 | AB31: 7月线下面谈， 数学顶尖，我们得诊断卷子113，英语43，同步大纲觉得太简单，没报名暑假数学英语 孩子在进阶有数学课，语文诊断成绩也不错，30多分，但是孩子满意度高，喜欢语文李润老师授课风格，曾告知可以试试铭铭老师，他说孩子点名要跟李润，但是家长其实有一定槽点，曾说我们这里太吵了，管理不到位，且对大纲满意报名暑假的，妈妈几乎不跟你说很多关于孩子学校方面得。但是聊学习习惯，薄弱，提升很很认真听且配合度不错 | AC31: 语 | AD31: 升学需求-进九大or中上,效果维度-提分,效果维度-培优拓展/分班考 | AE31: 1.不紧迫，觉得初一不需要学 | AF31: 3-支付能力强 | AG31: 3-喜欢 | AH31: 1-有雷点、槽点 | AI31: 3-有规划有意识 | AJ31: B-8-10 | AK31: 李润 | BF31: 林志豪01 | BG31: =VLOOKUP(B31,'UV台帐'!B:G,6,0) | BR31: =COUNTIFS(H31,"一期",I31,"在读")+COUNTIFS(L31,"一期",M31,"在读")+COUNTIFS(P31,"一期",Q31,"在读") | BS31: =BR31-BW31 | BT31: =VLOOKUP(B31,'UV台帐'!B:AL,19,0) | BU31: =VLOOKUP(B31,'UV台帐'!B:AL,28,0) | BV31: =VLOOKUP(B31,'UV台帐'!B:AL,37,0) | BW31: =COUNTIFS(H31,"一期",BT31,"是")+COUNTIFS(L31,"一期",BU31,"是")+COUNTIFS(P31,"一期",BV31,"是") | CA31: 4050031794
A32: 同创汇 | B32: 2707561257 | C32: =VLOOKUP(B32,'UV台帐'!B:AL,2,0) | D32: =VLOOKUP(B32,'UV台帐'!B:AL,3,0) | E32: =VLOOKUP(B32,'UV台帐'!B:AL,13,0) | F32: =VLOOKUP(B32,'UV台帐'!B:AL,15,0) | G32: =VLOOKUP(B32,'UV台帐'!B:AL,16,0) | H32: =VLOOKUP(B32,'UV台帐'!B:AL,17,0) | I32: =VLOOKUP(B32,'UV台帐'!B:AL,18,0) | J32: =VLOOKUP(B32,'UV台帐'!B:AL,22,0) | K32: =VLOOKUP(B32,'UV台帐'!B:AL,24,0) | L32: =VLOOKUP(B32,'UV台帐'!B:AL,26,0) | M32: =VLOOKUP(B32,'UV台帐'!B:AL,27,0) | N32: =VLOOKUP(B32,'UV台帐'!B:AL,31,0) | O32: =VLOOKUP(B32,'UV台帐'!B:AL,33,0) | P32: =VLOOKUP(B32,'UV台帐'!B:AL,35,0) | Q32: =VLOOKUP(B32,'UV台帐'!B:AL,36,0) | R32: 是 | S32: A | T32: 否 | U32: 是 | W32: 语文93，英语数学100 | X32: 孩子自己比较喜欢数学，数学学了奥数，语文的阅读理解和写作框架技巧还是需要提升和关注的，前期会很慢热，不爱说话，后期会是话痨小男孩 | Y32: 妈妈认为孩子初中要学习的科目太多，前期要搞定三科，后面的精力放在理科上面，所以衔接课要学，离家近 | Z32: 孩子小学校内数学英语满分，认为小初衔接很有必要，离家近，孩子自己可以步行10分钟到校，上了期末复习课，英语觉得简单，数学语文老师关注度都有，而且有挑战，喜欢学，妈妈报名初衷是觉得初中学习节奏紧凑，现在语数英基础扎实，才能让孩子腾出更多时间放在理科上面，物理也有需求，但孩子现在不想一下子学很多。 | AA32: 明确需求 | AB32: 品希性格： 慢热型，好学型 校内成绩：语文93左右，数学100 语文：爱看书，文言文翻译和关注孩子的阅读理解 数学：比较喜欢数学，学过奥数，数学这个科目提前学，基础扎实后面腾时间学好物理化学 | AC32: 语,数 | AD32: 升学需求-保底本区公办高中,效果维度-培优拓展/分班考,沟通维度：老师有个性化 | AE32: 3-非常紧迫，有短期目标和长期需求 | AF32: 3-支付能力强 | AG32: 3-喜欢 | AH32: 3-有正面评价 | AI32: 3-有规划有意识 | AJ32: S-14-15 | AK32: 陈南05 | BF32: 苏丽婷 | BG32: =VLOOKUP(B32,'UV台帐'!B:G,6,0) | BR32: =COUNTIFS(H32,"一期",I32,"在读")+COUNTIFS(L32,"一期",M32,"在读")+COUNTIFS(P32,"一期",Q32,"在读") | BS32: =BR32-BW32 | BT32: =VLOOKUP(B32,'UV台帐'!B:AL,19,0) | BU32: =VLOOKUP(B32,'UV台帐'!B:AL,28,0) | BV32: =VLOOKUP(B32,'UV台帐'!B:AL,37,0) | BW32: =COUNTIFS(H32,"一期",BT32,"是")+COUNTIFS(L32,"一期",BU32,"是")+COUNTIFS(P32,"一期",BV32,"是") | CA32: 2573471597
A33: 天成大厦 | B33: 2616423670 | C33: =VLOOKUP(B33,'UV台帐'!B:AL,2,0) | D33: =VLOOKUP(B33,'UV台帐'!B:AL,3,0) | E33: =VLOOKUP(B33,'UV台帐'!B:AL,13,0) | F33: =VLOOKUP(B33,'UV台帐'!B:AL,15,0) | G33: =VLOOKUP(B33,'UV台帐'!B:AL,16,0) | H33: =VLOOKUP(B33,'UV台帐'!B:AL,17,0) | I33: =VLOOKUP(B33,'UV台帐'!B:AL,18,0) | J33: =VLOOKUP(B33,'UV台帐'!B:AL,22,0) | K33: =VLOOKUP(B33,'UV台帐'!B:AL,24,0) | L33: =VLOOKUP(B33,'UV台帐'!B:AL,26,0) | M33: =VLOOKUP(B33,'UV台帐'!B:AL,27,0) | N33: =VLOOKUP(B33,'UV台帐'!B:AL,31,0) | O33: =VLOOKUP(B33,'UV台帐'!B:AL,33,0) | P33: =VLOOKUP(B33,'UV台帐'!B:AL,35,0) | Q33: =VLOOKUP(B33,'UV台帐'!B:AL,36,0) | R33: 是 | S33: S | T33: 是 | U33: 是 | W33: 290 | X33: 孩子相对比较自满，好动 | Y33: 断报老生，认可机构教学，还是希望重新回来，特别是数学，但对机构管理还是存疑 | Z33: 断报老生，意向数学，上课时间没问题；数学S；寒春续报了，退费。5升6的妹妹，MK班 | AA33: 明确需求 | AB33: 基本情况：断报老生，意向数学，之前只是因为校区管理问题，家长一气之下退费了。另外两科要再看看，缺乏价值铺铺垫。学生意愿度：数学＞英语＞语文 需求判定：家长对于中考目前感觉不大，但是对于初中分班考还是与关注的，知道要上线高中，一定要往重点班冲刺。家长对于教学服务满意的，希望老师还是多抓孩子的学习习惯，孩子比较粗心浮躁，需要课上多提醒关注走神的问题。 | AC33: 数,英 | AD33: 升学需求-保底本区公办高中,效果维度-抓习惯 | AE33: 2-一般，对于目标需求一般 | AF33: 3-支付能力强 | AG33: 3-喜欢 | AH33: 3-有正面评价 | AI33: 3-有规划有意识 | AJ33: S-14-15 | AK33: 刘希子 | AL33: 是 | BF33: 陈亮延 | BG33: =VLOOKUP(B33,'UV台帐'!B:G,6,0) | BR33: =COUNTIFS(H33,"一期",I33,"在读")+COUNTIFS(L33,"一期",M33,"在读")+COUNTIFS(P33,"一期",Q33,"在读") | BS33: =BR33-BW33 | BT33: =VLOOKUP(B33,'UV台帐'!B:AL,19,0) | BU33: =VLOOKUP(B33,'UV台帐'!B:AL,28,0) | BV33: =VLOOKUP(B33,'UV台帐'!B:AL,37,0) | BW33: =COUNTIFS(H33,"一期",BT33,"是")+COUNTIFS(L33,"一期",BU33,"是")+COUNTIFS(P33,"一期",BV33,"是") | CA33: 2408937171
A34: 同创汇 | B34: 4845922736 | C34: =VLOOKUP(B34,'UV台帐'!B:AL,2,0) | D34: =VLOOKUP(B34,'UV台帐'!B:AL,3,0) | E34: =VLOOKUP(B34,'UV台帐'!B:AL,13,0) | F34: =VLOOKUP(B34,'UV台帐'!B:AL,15,0) | G34: =VLOOKUP(B34,'UV台帐'!B:AL,16,0) | H34: =VLOOKUP(B34,'UV台帐'!B:AL,17,0) | I34: =VLOOKUP(B34,'UV台帐'!B:AL,18,0) | J34: =VLOOKUP(B34,'UV台帐'!B:AL,22,0) | K34: =VLOOKUP(B34,'UV台帐'!B:AL,24,0) | L34: =VLOOKUP(B34,'UV台帐'!B:AL,26,0) | M34: =VLOOKUP(B34,'UV台帐'!B:AL,27,0) | N34: =VLOOKUP(B34,'UV台帐'!B:AL,31,0) | O34: =VLOOKUP(B34,'UV台帐'!B:AL,33,0) | P34: =VLOOKUP(B34,'UV台帐'!B:AL,35,0) | Q34: =VLOOKUP(B34,'UV台帐'!B:AL,36,0) | R34: 是 | S34: A | U34: 是 | W34: 6下292 | Y34: 数学有机构在学，妈妈最想补的是英语，后面加了语文（妈妈自主加的） | Z34: 六下三科，英语99.5，语文95，数学92（数学有点难），水荫路小学，16中，高中目标没有（需要看孩子的成绩） 期中考试来判断后续的分班授课， 之前没有补过课，孩子整体成绩还行，妈妈自我感觉良好 | AA34: 明确需求 | AB34: 妈妈有问过我们有没有小班课，数学明确说不报名，"六下三科，英语99.5，语文95，数学92（数学有点难），主要是题型见的不够多，孩子需要理解后才能只针对题型去答题。水荫路小学，16中，高中目标没有（需要看孩子的成绩来选择高中） 16中期中考试来判断后续的分班授课， 妈妈在这比较焦虑，担心孩子分不到好的班，影响后续升学 之前没有补过课，孩子整体成绩还行，妈妈自我感觉良好，认为孩子没有补课，校内还可以考这个分数 | AC34: 英 | AD34: 升学需求-保底本区公办高中,效果维度-培优拓展/分班考 | AE34: 2-一般，对于目标需求一般 | AF34: 3-支付能力强 | AG34: 2-一般 | AH34: 2-评价一般、无感 | AI34: 3-有规划有意识 | AJ34: A-11-13 | AK34: 陈南05 | BF34: 戎凯01 | BG34: =VLOOKUP(B34,'UV台帐'!B:G,6,0) | BH34: 16中 | BR34: =COUNTIFS(H34,"一期",I34,"在读")+COUNTIFS(L34,"一期",M34,"在读")+COUNTIFS(P34,"一期",Q34,"在读") | BS34: =BR34-BW34 | BT34: =VLOOKUP(B34,'UV台帐'!B:AL,19,0) | BU34: =VLOOKUP(B34,'UV台帐'!B:AL,28,0) | BV34: =VLOOKUP(B34,'UV台帐'!B:AL,37,0) | BW34: =COUNTIFS(H34,"一期",BT34,"是")+COUNTIFS(L34,"一期",BU34,"是")+COUNTIFS(P34,"一期",BV34,"是") | CA34: 4384813412
A35: 新宝利 | B35: 4843140524 | C35: =VLOOKUP(B35,'UV台帐'!B:AL,2,0) | D35: =VLOOKUP(B35,'UV台帐'!B:AL,3,0) | E35: =VLOOKUP(B35,'UV台帐'!B:AL,13,0) | F35: =VLOOKUP(B35,'UV台帐'!B:AL,15,0) | G35: =VLOOKUP(B35,'UV台帐'!B:AL,16,0) | H35: =VLOOKUP(B35,'UV台帐'!B:AL,17,0) | I35: =VLOOKUP(B35,'UV台帐'!B:AL,18,0) | J35: =VLOOKUP(B35,'UV台帐'!B:AL,22,0) | K35: =VLOOKUP(B35,'UV台帐'!B:AL,24,0) | L35: =VLOOKUP(B35,'UV台帐'!B:AL,26,0) | M35: =VLOOKUP(B35,'UV台帐'!B:AL,27,0) | N35: =VLOOKUP(B35,'UV台帐'!B:AL,31,0) | O35: =VLOOKUP(B35,'UV台帐'!B:AL,33,0) | P35: =VLOOKUP(B35,'UV台帐'!B:AL,35,0) | Q35: =VLOOKUP(B35,'UV台帐'!B:AL,36,0) | R35: 是 | S35: B | T35: 否 | U35: 是 | V35: 八一希望小学,知用 | W35: 3b | Y35: 报名暑假班是想给孩子做个过渡，提前接触初一内容，英语最薄弱，其次是数学 | Z35: 家长配合度低，打电话不接C；有一对一的家教辅导，希望提前适应初中衔接；未到过店，二次电联后家长表示一对一家教停掉了，孩子上的好，反馈好是可以考虑秋季的。 | AA35: 明确需求 | AB35: 比较关注数学和英语科目，不喜欢背单词，数学基础薄弱，担心孩子跟不上初中进度，数学审题不清晰，容易跳步骤，之前一直是一对一家教，现在都停掉了，孩子比较腼腆，基础相对薄弱些，需要老师多鼓励，电话是不接的，妈妈说有事线上沟通留言就好，期望初中孩子能是班上中上水平，觉得暑假先做个过渡，怕孩子初中跟不上，后续有想继续一对一家教，但是也有标明如果暑假孩子反馈比较好，跟得上，可以考虑秋季接着学 | AC35: 数,英 | AD35: 升学需求-保底本区公办高中,效果维度-提分,效果维度-抓习惯 | AE35: 1.不紧迫，觉得初一不需要学 | AF35: 2-支付能力一般 | AG35: 2-一般 | AH35: 2-评价一般、无感 | AI35: 1-无意识无规划 | AJ35: B-8-10 | AK35: 何咏04 | AL35: 是 | BF35: 张敏烨 | BG35: =VLOOKUP(B35,'UV台帐'!B:G,6,0) | BH35: 知用 | BR35: =COUNTIFS(H35,"一期",I35,"在读")+COUNTIFS(L35,"一期",M35,"在读")+COUNTIFS(P35,"一期",Q35,"在读") | BS35: =BR35-BW35 | BT35: =VLOOKUP(B35,'UV台帐'!B:AL,19,0) | BU35: =VLOOKUP(B35,'UV台帐'!B:AL,28,0) | BV35: =VLOOKUP(B35,'UV台帐'!B:AL,37,0) | BW35: =COUNTIFS(H35,"一期",BT35,"是")+COUNTIFS(L35,"一期",BU35,"是")+COUNTIFS(P35,"一期",BV35,"是") | CA35: 4218384525
A36: 新宝利 | B36: 4312380919 | C36: =VLOOKUP(B36,'UV台帐'!B:AL,2,0) | D36: =VLOOKUP(B36,'UV台帐'!B:AL,3,0) | E36: =VLOOKUP(B36,'UV台帐'!B:AL,13,0) | F36: =VLOOKUP(B36,'UV台帐'!B:AL,15,0) | G36: =VLOOKUP(B36,'UV台帐'!B:AL,16,0) | H36: =VLOOKUP(B36,'UV台帐'!B:AL,17,0) | I36: =VLOOKUP(B36,'UV台帐'!B:AL,18,0) | J36: =VLOOKUP(B36,'UV台帐'!B:AL,22,0) | K36: =VLOOKUP(B36,'UV台帐'!B:AL,24,0) | L36: =VLOOKUP(B36,'UV台帐'!B:AL,26,0) | M36: =VLOOKUP(B36,'UV台帐'!B:AL,27,0) | N36: =VLOOKUP(B36,'UV台帐'!B:AL,31,0) | O36: =VLOOKUP(B36,'UV台帐'!B:AL,33,0) | P36: =VLOOKUP(B36,'UV台帐'!B:AL,35,0) | Q36: =VLOOKUP(B36,'UV台帐'!B:AL,36,0) | R36: 是 | S36: A | T36: 否 | U36: 否 | V36: 二中 | W36: 三科平均90-95 | X36: 学习平时能独立完成作业，性格不是很主动，老师要多鼓励，二期有两天需要请假。 | Y36: 平时学习一半都是爸爸妈妈辅导，希望巩固课内之余提升思维 | Z36: 一半都是爸爸妈妈辅导，希望巩固课内之余提升思维，性格不是很主动，老师要多鼓励，二期有两天需要请假 | AA36: 明确需求 | AB36: 孩子性格：学习平时能独立完成作业，性格不是很主动，老师要多鼓励， 二期有两天需要请假。（现阶段是89节课请假，但是后期可能要调整请假日期） 学习情况：词汇量和语法比较弱，审题不太严谨，选择题时态弄混淆，需要题型打卡，音标方面的长音短音不太清晰，不同规则的发音比较弱。 家长需求：希望老师能够严格一点，妈妈们会实时跟进，需要每天的课后反馈，家长积极配合解决，计算有时候需要加强，孩子会比较粗心，赏罚分明。 家长说孩子对于课程方面的配合度很高，老师要求越高他完成度越好，孩子的抗压能力很好需要老师严格要求。家长还是有长期学习的意向的。希望三科能够均衡提升 规划：明白现在的学校升学压力大，只有50%的升学率，还主动说现在校内学番:茄炒蛋，考试考满汉全席希望孩子未来能有一个好的高中能上 | AC36: 语,数,英 | AD36: 升学需求-保底本区公办高中,效果维度-提分,效果维度-抓习惯,沟通维度：老师有个性化,沟通维度：老师有关注度 | AE36: 2-一般，对于目标需求一般 | AF36: 3-支付能力强 | AG36: 2-一般 | AH36: 3-有正面评价 | AI36: 2-有意识无规划 | AJ36: A-11-13 | AK36: 李润 | AL36: 是 | BF36: 沈思浩 | BG36: =VLOOKUP(B36,'UV台帐'!B:G,6,0) | BR36: =COUNTIFS(H36,"一期",I36,"在读")+COUNTIFS(L36,"一期",M36,"在读")+COUNTIFS(P36,"一期",Q36,"在读") | BS36: =BR36-BW36 | BT36: =VLOOKUP(B36,'UV台帐'!B:AL,19,0) | BU36: =VLOOKUP(B36,'UV台帐'!B:AL,28,0) | BV36: =VLOOKUP(B36,'UV台帐'!B:AL,37,0) | BW36: =COUNTIFS(H36,"一期",BT36,"是")+COUNTIFS(L36,"一期",BU36,"是")+COUNTIFS(P36,"一期",BV36,"是") | CA36: 4397457478
A37: 新宝利 | B37: 2544969370 | C37: =VLOOKUP(B37,'UV台帐'!B:AL,2,0) | D37: =VLOOKUP(B37,'UV台帐'!B:AL,3,0) | E37: =VLOOKUP(B37,'UV台帐'!B:AL,13,0) | F37: =VLOOKUP(B37,'UV台帐'!B:AL,15,0) | G37: =VLOOKUP(B37,'UV台帐'!B:AL,16,0) | H37: =VLOOKUP(B37,'UV台帐'!B:AL,17,0) | I37: =VLOOKUP(B37,'UV台帐'!B:AL,18,0) | J37: =VLOOKUP(B37,'UV台帐'!B:AL,22,0) | K37: =VLOOKUP(B37,'UV台帐'!B:AL,24,0) | L37: =VLOOKUP(B37,'UV台帐'!B:AL,26,0) | M37: =VLOOKUP(B37,'UV台帐'!B:AL,27,0) | N37: =VLOOKUP(B37,'UV台帐'!B:AL,31,0) | O37: =VLOOKUP(B37,'UV台帐'!B:AL,33,0) | P37: =VLOOKUP(B37,'UV台帐'!B:AL,35,0) | Q37: =VLOOKUP(B37,'UV台帐'!B:AL,36,0) | R37: 是 | S37: B | T37: 否 | U37: 是 | V37: 育才 | W37: 三科90左右 | Y37: BMD,知道线上作业帮，报名线下课体验下 | Z37: 有拓展过，但都是线上，感觉效果不太好 | AA37: 明确需求 | AB37: 暑假课进行小初衔接，孩子自控力比较差，喜欢偷懒，希望老师管严一点。之前上的线上课，整体学习效果达不到预期，所以当时没有继续学，需要这次从行课上看到孩子变化，孩子有学习意愿改变，学习习惯改善，比如笔记，作业完成情况，课前测来表现，孩子妈妈对于初中难度理解不够，在后续电聊需要再强调初中对于咱们家孩子来说，肯定会遇到的问题，让家长有危机意识 | AC37: 语,数,英 | AD37: 效果维度-提分,效果维度-抓习惯,沟通维度：老师有个性化,沟通维度：老师有关注度 | AE37: 2-一般，对于目标需求一般 | AF37: 2-支付能力一般 | AG37: 2-一般 | AH37: 2-评价一般、无感 | AI37: 2-有意识无规划 | AJ37: B-8-10 | AK37: 何咏04 | AL37: 是 | BF37: 王丽 | BG37: =VLOOKUP(B37,'UV台帐'!B:G,6,0) | BR37: =COUNTIFS(H37,"一期",I37,"在读")+COUNTIFS(L37,"一期",M37,"在读")+COUNTIFS(P37,"一期",Q37,"在读") | BS37: =BR37-BW37 | BT37: =VLOOKUP(B37,'UV台帐'!B:AL,19,0) | BU37: =VLOOKUP(B37,'UV台帐'!B:AL,28,0) | BV37: =VLOOKUP(B37,'UV台帐'!B:AL,37,0) | BW37: =COUNTIFS(H37,"一期",BT37,"是")+COUNTIFS(L37,"一期",BU37,"是")+COUNTIFS(P37,"一期",BV37,"是") | CA37: 4129826988
A38: 同创汇 | B38: 2714018258 | C38: =VLOOKUP(B38,'UV台帐'!B:AL,2,0) | D38: =VLOOKUP(B38,'UV台帐'!B:AL,3,0) | E38: =VLOOKUP(B38,'UV台帐'!B:AL,13,0) | F38: =VLOOKUP(B38,'UV台帐'!B:AL,15,0) | G38: =VLOOKUP(B38,'UV台帐'!B:AL,16,0) | H38: =VLOOKUP(B38,'UV台帐'!B:AL,17,0) | I38: =VLOOKUP(B38,'UV台帐'!B:AL,18,0) | J38: =VLOOKUP(B38,'UV台帐'!B:AL,22,0) | K38: =VLOOKUP(B38,'UV台帐'!B:AL,24,0) | L38: =VLOOKUP(B38,'UV台帐'!B:AL,26,0) | M38: =VLOOKUP(B38,'UV台帐'!B:AL,27,0) | N38: =VLOOKUP(B38,'UV台帐'!B:AL,31,0) | O38: =VLOOKUP(B38,'UV台帐'!B:AL,33,0) | P38: =VLOOKUP(B38,'UV台帐'!B:AL,35,0) | Q38: =VLOOKUP(B38,'UV台帐'!B:AL,36,0) | R38: 是 | S38: A | U38: 是 | W38: 语数英校内都95左右，数学好一点，98以上 | X38: 英语差一点，不爱读，这个学期好像经常93左右 | Y38: 秉谦妈妈推荐的，摇的学校不理想，需要走关系再来定学校 | Z38: 摇的学校不理想，妈妈还在想办法。秉谦妈妈推荐来的，后面又推荐了海洋来学习。 语数英三科都在95左右，数学好一点，98左右；英语差一点，孩子不爱读，六下的时候精彩93左右 上过辅导班，还是比较看重孩子的选择 | AA38: 明确需求 | AB38: 秉谦妈妈推荐来的，数学之前经常满分，这次94，语文英语98/97，这次数学有落差，失分在选择题，容易纠结，不会这么简单，所以失分 初中还没定，考虑补录，语文没上，英语新东方，数学独立老师一对二，语文和英语需要让孩子认识到初中的难度，数学需要让孩子不在纠结，妈妈认为数学还是很稳定的，但是没想到这次期末没考好。需要给孩子定目标和具体学习计划。 | AC38: 语,数,英 | AD38: 升学需求-保底本区公办高中,效果维度-培优拓展/分班考,沟通维度：老师有关注度 | AE38: 2-一般，对于目标需求一般 | AF38: 2-支付能力一般 | AG38: 2-一般 | AH38: 2-评价一般、无感 | AI38: 3-有规划有意识 | AJ38: A-11-13 | AK38: 高心怡04 | AL38: 是 | BF38: 戎凯01 | BG38: =VLOOKUP(B38,'UV台帐'!B:G,6,0) | BH38: 未定 | BR38: =COUNTIFS(H38,"一期",I38,"在读")+COUNTIFS(L38,"一期",M38,"在读")+COUNTIFS(P38,"一期",Q38,"在读") | BS38: =BR38-BW38 | BT38: =VLOOKUP(B38,'UV台帐'!B:AL,19,0) | BU38: =VLOOKUP(B38,'UV台帐'!B:AL,28,0) | BV38: =VLOOKUP(B38,'UV台帐'!B:AL,37,0) | BW38: =COUNTIFS(H38,"一期",BT38,"是")+COUNTIFS(L38,"一期",BU38,"是")+COUNTIFS(P38,"一期",BV38,"是") | CA38: 4817190059
A39: 天成大厦 | B39: 4442600800 | C39: =VLOOKUP(B39,'UV台帐'!B:AL,2,0) | D39: =VLOOKUP(B39,'UV台帐'!B:AL,3,0) | E39: =VLOOKUP(B39,'UV台帐'!B:AL,13,0) | F39: =VLOOKUP(B39,'UV台帐'!B:AL,15,0) | G39: =VLOOKUP(B39,'UV台帐'!B:AL,16,0) | H39: =VLOOKUP(B39,'UV台帐'!B:AL,17,0) | I39: =VLOOKUP(B39,'UV台帐'!B:AL,18,0) | J39: =VLOOKUP(B39,'UV台帐'!B:AL,22,0) | K39: =VLOOKUP(B39,'UV台帐'!B:AL,24,0) | L39: =VLOOKUP(B39,'UV台帐'!B:AL,26,0) | M39: =VLOOKUP(B39,'UV台帐'!B:AL,27,0) | N39: =VLOOKUP(B39,'UV台帐'!B:AL,31,0) | O39: =VLOOKUP(B39,'UV台帐'!B:AL,33,0) | P39: =VLOOKUP(B39,'UV台帐'!B:AL,35,0) | Q39: =VLOOKUP(B39,'UV台帐'!B:AL,36,0) | R39: 是 | S39: A | T39: 否 | U39: 否 | V39: 天河中学 | W39: 280 | X39: 家长反馈孩子比较内向，但是比较细心 | Y39: 转介绍，作业帮线上学员，考虑到初中课程难度，家长想转到线下。有长期学习的打算，特别是英语，价格可能是一个卡点。 | Z39: 在读转介绍，之前作业帮线上在读挺久的，现在初中想上线下课，上课时间没问题；英语S，黄杰转介绍，表姐是黄杰在读学员。孩子表示要上线下课，看孩子是否能坚持。6月14日谈过暑秋英语没拿下，有意愿。 | AA39: 明确需求 | AB39: 基本情况：转介绍家长，作业帮线上曾在读，现在初中想上线下课，意向英语，6月14日谈过暑秋英语没拿下，有意愿。家长表示线下课，看孩子是否能坚持（通勤）有亲属上了我们正价课程。有引导沟通分数和目标，家长反馈暂时没有这类规划。 需求判定：家长希望老师多去跟盯课清环节，提醒孩子多动笔。孩子习惯了线上课程，线下得适应。妈妈觉得线下有必要，希望老师也和孩子拉近关系，聊聊意愿度。 | AC39: 英 | AD39: 效果维度-抓习惯,沟通维度：老师有关注度 | AE39: 3-非常紧迫，有短期目标和长期需求 | AF39: 2-支付能力一般 | AG39: 2-一般 | AH39: 2-评价一般、无感 | AI39: 2-有意识无规划 | AJ39: A-11-13 | AK39: 刘希子 | AL39: 是 | BF39: 陈亮延 | BG39: =VLOOKUP(B39,'UV台帐'!B:G,6,0) | BR39: =COUNTIFS(H39,"一期",I39,"在读")+COUNTIFS(L39,"一期",M39,"在读")+COUNTIFS(P39,"一期",Q39,"在读") | BS39: =BR39-BW39 | BT39: =VLOOKUP(B39,'UV台帐'!B:AL,19,0) | BU39: =VLOOKUP(B39,'UV台帐'!B:AL,28,0) | BV39: =VLOOKUP(B39,'UV台帐'!B:AL,37,0) | BW39: =COUNTIFS(H39,"一期",BT39,"是")+COUNTIFS(L39,"一期",BU39,"是")+COUNTIFS(P39,"一期",BV39,"是") | CA39: 2529696621
A40: 新宝利 | B40: 4467119064 | C40: =VLOOKUP(B40,'UV台帐'!B:AL,2,0) | D40: =VLOOKUP(B40,'UV台帐'!B:AL,3,0) | E40: =VLOOKUP(B40,'UV台帐'!B:AL,13,0) | F40: =VLOOKUP(B40,'UV台帐'!B:AL,15,0) | G40: =VLOOKUP(B40,'UV台帐'!B:AL,16,0) | H40: =VLOOKUP(B40,'UV台帐'!B:AL,17,0) | I40: =VLOOKUP(B40,'UV台帐'!B:AL,18,0) | J40: =VLOOKUP(B40,'UV台帐'!B:AL,22,0) | K40: =VLOOKUP(B40,'UV台帐'!B:AL,24,0) | L40: =VLOOKUP(B40,'UV台帐'!B:AL,26,0) | M40: =VLOOKUP(B40,'UV台帐'!B:AL,27,0) | N40: =VLOOKUP(B40,'UV台帐'!B:AL,31,0) | O40: =VLOOKUP(B40,'UV台帐'!B:AL,33,0) | P40: =VLOOKUP(B40,'UV台帐'!B:AL,35,0) | Q40: =VLOOKUP(B40,'UV台帐'!B:AL,36,0) | R40: 是 | S40: B | T40: 否 | U40: 是 | V40: 南海中学 | W40: 语数英85 80 80 | X40: 一般 | Y40: 小升初衔接 | Z40: 数学：解题思路不够清晰，相对弱一点，方法技巧的讲解 英语：单词词汇语法，拼读 语文：阅读理解不够扎实，答题技巧掌握不好 期待值：暂时没有想法，随心随意，没有目标，上完再说。 过往补习：卓越数学英语 心田花开语文，英语还行，数学一般。人数比较多，老师关注不够，给孩子选择辅导班 参与过期末复习课，见过老师，对语文数学评价认可 | AA40: 明确需求 | AB40: 数学：解题思路不够清晰，主科里面属于相对弱一点，缺乏答题技巧和方法 英语：单词词汇语法薄弱，拼读存在短板 语文：阅读理解不够扎实，答题技巧掌握不好 期待值：暂时没有想法，随心随意，没有短期和长期的目标，上完再暑假课程说。 过往补习：卓越数学英语 心田花开语文，英语较满意，数学不太满意。担心班课人数比较多，老师关注不够 参与过期末复习课，见过老师，对语文数学评价是可以的 | AD40: 效果维度-提分 | AE40: 1.不紧迫，觉得初一不需要学 | AF40: 2-支付能力一般 | AG40: 2-一般 | AH40: 2-评价一般、无感 | AI40: 1-无意识无规划 | AJ40: B-8-10 | AK40: 何咏04 | AL40: 是 | BF40: 杨林33 | BG40: =VLOOKUP(B40,'UV台帐'!B:G,6,0) | BR40: =COUNTIFS(H40,"一期",I40,"在读")+COUNTIFS(L40,"一期",M40,"在读")+COUNTIFS(P40,"一期",Q40,"在读") | BS40: =BR40-BW40 | BT40: =VLOOKUP(B40,'UV台帐'!B:AL,19,0) | BU40: =VLOOKUP(B40,'UV台帐'!B:AL,28,0) | BV40: =VLOOKUP(B40,'UV台帐'!B:AL,37,0) | BW40: =COUNTIFS(H40,"一期",BT40,"是")+COUNTIFS(L40,"一期",BU40,"是")+COUNTIFS(P40,"一期",BV40,"是") | CA40: 4310026061
A41: 新宝利 | B41: 4070489080 | C41: =VLOOKUP(B41,'UV台帐'!B:AL,2,0) | D41: =VLOOKUP(B41,'UV台帐'!B:AL,3,0) | E41: =VLOOKUP(B41,'UV台帐'!B:AL,13,0) | F41: =VLOOKUP(B41,'UV台帐'!B:AL,15,0) | G41: =VLOOKUP(B41,'UV台帐'!B:AL,16,0) | H41: =VLOOKUP(B41,'UV台帐'!B:AL,17,0) | I41: =VLOOKUP(B41,'UV台帐'!B:AL,18,0) | J41: =VLOOKUP(B41,'UV台帐'!B:AL,22,0) | K41: =VLOOKUP(B41,'UV台帐'!B:AL,24,0) | L41: =VLOOKUP(B41,'UV台帐'!B:AL,26,0) | M41: =VLOOKUP(B41,'UV台帐'!B:AL,27,0) | N41: =VLOOKUP(B41,'UV台帐'!B:AL,31,0) | O41: =VLOOKUP(B41,'UV台帐'!B:AL,33,0) | P41: =VLOOKUP(B41,'UV台帐'!B:AL,35,0) | Q41: =VLOOKUP(B41,'UV台帐'!B:AL,36,0) | R41: 是 | S41: B | T41: 是 | U41: 是 | V41: 初中17中 | W41: A | X41: 应用题审题不清，粗心 | Y41: 希望通过我们提前学期中考试能分到a班 | Z41: 单科数学，过往没补习过，家住白云，到店咨询。C；语文和英语学得比较好；教育理念比较差。报暑假班是为了期中考试进到a班，有长期学的想法 | AA41: 明确需求 | AB41: 和欧阳紫晴是同学，上课比较活跃，单科数学，从来没有补习过，妈妈教育理念比较差，初中进到了17中，学校开家长会说期中考试会分ab班，希望孩子能去到a班，数学计算比较薄弱，会粗心，希望老师能多给一些习题打卡之类的，有讲过初中学校的普高率一般，孩子想去到a班数学得提高多少分，妈妈是认可的，但是支付能力偏弱一些，想看看孩子暑假上课的情况再决定 | AC41: 数 | AD41: 效果维度-提分,效果维度-抓习惯,效果维度-培优拓展/分班考 | AE41: 1.不紧迫，觉得初一不需要学 | AF41: 2-支付能力一般 | AG41: 2-一般 | AH41: 2-评价一般、无感 | AI41: 2-有意识无规划 | AJ41: B-8-10 | AK41: 何咏04 | AL41: 是 | BF41: 张敏烨 | BG41: =VLOOKUP(B41,'UV台帐'!B:G,6,0) | BH41: 17中 | BR41: =COUNTIFS(H41,"一期",I41,"在读")+COUNTIFS(L41,"一期",M41,"在读")+COUNTIFS(P41,"一期",Q41,"在读") | BS41: =BR41-BW41 | BT41: =VLOOKUP(B41,'UV台帐'!B:AL,19,0) | BU41: =VLOOKUP(B41,'UV台帐'!B:AL,28,0) | BV41: =VLOOKUP(B41,'UV台帐'!B:AL,37,0) | BW41: =COUNTIFS(H41,"一期",BT41,"是")+COUNTIFS(L41,"一期",BU41,"是")+COUNTIFS(P41,"一期",BV41,"是") | CA41: 2515578569
A42: 新宝利 | B42: 4838041163 | C42: =VLOOKUP(B42,'UV台帐'!B:AL,2,0) | D42: =VLOOKUP(B42,'UV台帐'!B:AL,3,0) | E42: =VLOOKUP(B42,'UV台帐'!B:AL,13,0) | F42: =VLOOKUP(B42,'UV台帐'!B:AL,15,0) | G42: =VLOOKUP(B42,'UV台帐'!B:AL,16,0) | H42: =VLOOKUP(B42,'UV台帐'!B:AL,17,0) | I42: =VLOOKUP(B42,'UV台帐'!B:AL,18,0) | J42: =VLOOKUP(B42,'UV台帐'!B:AL,22,0) | K42: =VLOOKUP(B42,'UV台帐'!B:AL,24,0) | L42: =VLOOKUP(B42,'UV台帐'!B:AL,26,0) | M42: =VLOOKUP(B42,'UV台帐'!B:AL,27,0) | N42: =VLOOKUP(B42,'UV台帐'!B:AL,31,0) | O42: =VLOOKUP(B42,'UV台帐'!B:AL,33,0) | P42: =VLOOKUP(B42,'UV台帐'!B:AL,35,0) | Q42: =VLOOKUP(B42,'UV台帐'!B:AL,36,0) | R42: 是 | S42: A | T42: 是 | U42: 是 | V42: 知用 | W42: 语85-90，数90，英80 | X42: 比较懒，拖拉，需要督促 | Y42: 正常公办高中，近一点，进A班 | Z42: 从未补过课，希望秋季价格优惠和暑假一样，已告知开窗期当日优惠最大，妈妈说暑假上着看一看，补是要补的，担心孩子适应不了一天三科，英语期望解决单词语法，孩子不爱背单词，数学需要提高做题思路，举一反三能力，数学是三科中比较好的，语文需要提升阅读理解 | AA42: 明确需求 | AB42: 和崔梓莹是同学，从来没补过课，三科都比较薄弱，孩子比较懒，写作业拖拉，需要家长督促，数学相对好一些，但是还是希望提高一下孩子应用计算问题，粗心，审题不清晰，语文科目期望在暑假的学习中学到一些阅读技巧，写作方法之类的，英语不爱背单词，语法差，期望可以提前学音标，目标正常公办离家近的高中就好，想进a班，但是知道是有难度的，有给家长讲过知用学校的普高率情况，让孩子做好提前学的准备，打好基础，初中才不会掉队，家长是认可的，有问过秋季价格是不是像暑假一样优惠，告知过秋季价格，家长说暑假看看孩子情况，不确定能不能适应得了，支付能力欠缺 | AC42: 数,英 | AD42: 升学需求-保底本区公办高中,效果维度-提分,效果维度-抓习惯,效果维度-培优拓展/分班考 | AE42: 2-一般，对于目标需求一般 | AF42: 2-支付能力一般 | AG42: 2-一般 | AH42: 2-评价一般、无感 | AI42: 2-有意识无规划 | AJ42: B-8-10 | AK42: 何咏04 | AL42: 是 | BF42: 张敏烨 | BG42: =VLOOKUP(B42,'UV台帐'!B:G,6,0) | BR42: =COUNTIFS(H42,"一期",I42,"在读")+COUNTIFS(L42,"一期",M42,"在读")+COUNTIFS(P42,"一期",Q42,"在读") | BS42: =BR42-BW42 | BT42: =VLOOKUP(B42,'UV台帐'!B:AL,19,0) | BU42: =VLOOKUP(B42,'UV台帐'!B:AL,28,0) | BV42: =VLOOKUP(B42,'UV台帐'!B:AL,37,0) | BW42: =COUNTIFS(H42,"一期",BT42,"是")+COUNTIFS(L42,"一期",BU42,"是")+COUNTIFS(P42,"一期",BV42,"是") | CA42: 4370732289
A43: 新宝利 | B43: 4836856814 | C43: =VLOOKUP(B43,'UV台帐'!B:AL,2,0) | D43: =VLOOKUP(B43,'UV台帐'!B:AL,3,0) | E43: =VLOOKUP(B43,'UV台帐'!B:AL,13,0) | F43: =VLOOKUP(B43,'UV台帐'!B:AL,15,0) | G43: =VLOOKUP(B43,'UV台帐'!B:AL,16,0) | H43: =VLOOKUP(B43,'UV台帐'!B:AL,17,0) | I43: =VLOOKUP(B43,'UV台帐'!B:AL,18,0) | J43: =VLOOKUP(B43,'UV台帐'!B:AL,22,0) | K43: =VLOOKUP(B43,'UV台帐'!B:AL,24,0) | L43: =VLOOKUP(B43,'UV台帐'!B:AL,26,0) | M43: =VLOOKUP(B43,'UV台帐'!B:AL,27,0) | N43: =VLOOKUP(B43,'UV台帐'!B:AL,31,0) | O43: =VLOOKUP(B43,'UV台帐'!B:AL,33,0) | P43: =VLOOKUP(B43,'UV台帐'!B:AL,35,0) | Q43: =VLOOKUP(B43,'UV台帐'!B:AL,36,0) | R43: 是 | S43: A | T43: 是 | U43: 是 | V43: 一中本部 | W43: 语文91 数学96 英语93 | X43: 学习习惯中等 | Y43: 提前学习新初一内容为主 | Z43: 妈妈做生意，支付能力没问题，过往有补习经历，对比学习效果。A，现场见面聊的；首课电访聊了10分钟，孩子学习需要督促，自觉性不高，孩子想学好，数学练习量不够，英语词汇量缺乏，秋季意向度上完看情况，会涉及机构对比，看重学习感受和学习效果，费用也在参考范围 | AA43: 明确需求 | AB43: 1.孩子作业方面需要督促，孩子内心是想学好的，自觉性不够，需要老师监督 2.数学基础掌握还可以，题目的练习量不够，英语主要是词汇量比较缺乏，语文阅读理解和作文平时有丢分 3.比较看重初一上的分层考，重点关注期中期末成绩，一中学校进度比较快 4.在其他机构长期补习数学和英语，因为这边性价比高才退了其他机构选择这边 5.后续学习的安排，比较看重三方面：上完看孩子的感受如何，看暑假的学习效果，费用也会在考虑的范围之内。明确需求就是初一上册的分层考，期中期末考试有好成绩，凭成绩分班 | AC43: 数,英 | AD43: 效果维度-抓习惯,效果维度-培优拓展/分班考 | AE43: 2-一般，对于目标需求一般 | AF43: 2-支付能力一般 | AG43: 2-一般 | AH43: 2-评价一般、无感 | AI43: 1-无意识无规划 | AJ43: B-8-10 | AK43: 何咏04 | AL43: 是 | BF43: 杨林33 | BG43: =VLOOKUP(B43,'UV台帐'!B:G,6,0) | BR43: =COUNTIFS(H43,"一期",I43,"在读")+COUNTIFS(L43,"一期",M43,"在读")+COUNTIFS(P43,"一期",Q43,"在读") | BS43: =BR43-BW43 | BT43: =VLOOKUP(B43,'UV台帐'!B:AL,19,0) | BU43: =VLOOKUP(B43,'UV台帐'!B:AL,28,0) | BV43: =VLOOKUP(B43,'UV台帐'!B:AL,37,0) | BW43: =COUNTIFS(H43,"一期",BT43,"是")+COUNTIFS(L43,"一期",BU43,"是")+COUNTIFS(P43,"一期",BV43,"是") | CA43: 4581996547
A44: 新宝利 | B44: 4486277372 | C44: =VLOOKUP(B44,'UV台帐'!B:AL,2,0) | D44: =VLOOKUP(B44,'UV台帐'!B:AL,3,0) | E44: =VLOOKUP(B44,'UV台帐'!B:AL,13,0) | F44: =VLOOKUP(B44,'UV台帐'!B:AL,15,0) | G44: =VLOOKUP(B44,'UV台帐'!B:AL,16,0) | H44: =VLOOKUP(B44,'UV台帐'!B:AL,17,0) | I44: =VLOOKUP(B44,'UV台帐'!B:AL,18,0) | J44: =VLOOKUP(B44,'UV台帐'!B:AL,22,0) | K44: =VLOOKUP(B44,'UV台帐'!B:AL,24,0) | L44: =VLOOKUP(B44,'UV台帐'!B:AL,26,0) | M44: =VLOOKUP(B44,'UV台帐'!B:AL,27,0) | N44: =VLOOKUP(B44,'UV台帐'!B:AL,31,0) | O44: =VLOOKUP(B44,'UV台帐'!B:AL,33,0) | P44: =VLOOKUP(B44,'UV台帐'!B:AL,35,0) | Q44: =VLOOKUP(B44,'UV台帐'!B:AL,36,0) | R44: 是 | S44: A | T44: 否 | U44: 是 | V44: 小北路小学，广附 | W44: 数98，语97.5，英97 | X44: 小粗心，英语听力薄弱 | Y44: 希望学些拓展知识，提前预习初一内容，和卓越作对比（主要对比课程体系和师资，教学，孩子的反馈）进华附重点班， | Z44: 支付能力没问题，有在读机构，没接。0期转1期，一年级到目前都有补，春季停的课，卓越学英语数学，暑假没报卓越，有做对比，卡点是知识可能偏简单。YMO三等奖，英语过了KET,PET没过 | AA44: 明确需求 | AB44: 孩子从一年级就开始校外补习，之前在卓越上，春季上完就没接着续，孩子自觉性是极强的，不需要家长怎么操心，数学考了ymo三等奖，红棉杯没考过，英语过了ket,pet没过，妈妈比较关注数学科目，孩子基础是没啥问题，希望数学学一些拓展知识，比如应用压轴题那些，提高举一反三能力，提前去预习初一内容，孩子是从0期调到一期的，上过中帅和肖锐的一节课，孩子表示还可以，就是觉得比较简单，秋季的课程也会考虑我们这边，报我们的暑假班也是想和卓越作对比（主要对比课程体系，师资，教学，孩子的反馈方面） | AC44: 数,英 | AD44: 升学需求-进九大or中上,效果维度-培优拓展/分班考,沟通维度：老师有个性化 | AE44: 3-非常紧迫，有短期目标和长期需求 | AF44: 3-支付能力强 | AG44: 2-一般 | AH44: 2-评价一般、无感 | AI44: 3-有规划有意识 | AJ44: A-11-13 | AK44: 何咏04 | BF44: 张敏烨 | BG44: =VLOOKUP(B44,'UV台帐'!B:G,6,0) | BR44: =COUNTIFS(H44,"一期",I44,"在读")+COUNTIFS(L44,"一期",M44,"在读")+COUNTIFS(P44,"一期",Q44,"在读") | BS44: =BR44-BW44 | BT44: =VLOOKUP(B44,'UV台帐'!B:AL,19,0) | BU44: =VLOOKUP(B44,'UV台帐'!B:AL,28,0) | BV44: =VLOOKUP(B44,'UV台帐'!B:AL,37,0) | BW44: =COUNTIFS(H44,"一期",BT44,"是")+COUNTIFS(L44,"一期",BU44,"是")+COUNTIFS(P44,"一期",BV44,"是") | CA44: 2577817187
A45: 新宝利 | B45: 4837163177 | C45: =VLOOKUP(B45,'UV台帐'!B:AL,2,0) | D45: =VLOOKUP(B45,'UV台帐'!B:AL,3,0) | E45: =VLOOKUP(B45,'UV台帐'!B:AL,13,0) | F45: =VLOOKUP(B45,'UV台帐'!B:AL,15,0) | G45: =VLOOKUP(B45,'UV台帐'!B:AL,16,0) | H45: =VLOOKUP(B45,'UV台帐'!B:AL,17,0) | I45: =VLOOKUP(B45,'UV台帐'!B:AL,18,0) | J45: =VLOOKUP(B45,'UV台帐'!B:AL,22,0) | K45: =VLOOKUP(B45,'UV台帐'!B:AL,24,0) | L45: =VLOOKUP(B45,'UV台帐'!B:AL,26,0) | M45: =VLOOKUP(B45,'UV台帐'!B:AL,27,0) | N45: =VLOOKUP(B45,'UV台帐'!B:AL,31,0) | O45: =VLOOKUP(B45,'UV台帐'!B:AL,33,0) | P45: =VLOOKUP(B45,'UV台帐'!B:AL,35,0) | Q45: =VLOOKUP(B45,'UV台帐'!B:AL,36,0) | R45: 是 | S45: A | T45: 是 | U45: 是 | V45: 知用 | W45: 语数英ABB | X45: 学习习惯不好，成绩中等 | Y45: 暑假提前学，学的好考虑秋季 | Z45: 数学：计算不扎实，上了几次复习课，数学期末考试有提升，孩子学习有信心，对老师认可。 语文：基础知识还可以，之前期末复习课答题标准有用到，觉得对学习有帮助，技巧和方法缺失 英语：音标和阅读理解，缺乏开口讲的勇气，不敢开口 初中：四中雁园 期待值：语数英110-120，普通班不掉队，前30% 校外补习：上过卓越的课程，学一科数学半年，服务反馈不够及时，对孩子关注没那么高 后续学习的想法：三科学的满意都考虑后面的学习 | AA45: 明确需求 | AB45: 数学：计算基础不过关，基础知识掌握一般，上了期末复习课，期末考试成绩有提升，对老师认可 语文：基础知识掌握还算可以，阅读缺乏答题技巧和方法 英语:音标没学，阅读理解答题技巧缺乏，得分率不高，缺乏开口的勇气，不敢开口读，需要老师多鼓励。 初中：四中雁园 目标：语数英三科110-120，普通班排名前30% 。 语文老师反馈：家长多次找老师沟通，孩子是比较内向的孩子，比较焦虑； | AC45: 语,数,英 | AD45: 效果维度-提分,效果维度-抓习惯,效果维度-培优拓展/分班考 | AE45: 3-非常紧迫，有短期目标和长期需求 | AF45: 2-支付能力一般 | AG45: 2-一般 | AH45: 3-有正面评价 | AI45: 3-有规划有意识 | AJ45: A-11-13 | AK45: 何咏04 | AL45: 是 | BF45: 杨林33 | BG45: =VLOOKUP(B45,'UV台帐'!B:G,6,0) | BH45: 四中雁园 | BR45: =COUNTIFS(H45,"一期",I45,"在读")+COUNTIFS(L45,"一期",M45,"在读")+COUNTIFS(P45,"一期",Q45,"在读") | BS45: =BR45-BW45 | BT45: =VLOOKUP(B45,'UV台帐'!B:AL,19,0) | BU45: =VLOOKUP(B45,'UV台帐'!B:AL,28,0) | BV45: =VLOOKUP(B45,'UV台帐'!B:AL,37,0) | BW45: =COUNTIFS(H45,"一期",BT45,"是")+COUNTIFS(L45,"一期",BU45,"是")+COUNTIFS(P45,"一期",BV45,"是") | CA45: 2717412875
A46: 新宝利 | B46: 4090630208 | C46: =VLOOKUP(B46,'UV台帐'!B:AL,2,0) | D46: =VLOOKUP(B46,'UV台帐'!B:AL,3,0) | E46: =VLOOKUP(B46,'UV台帐'!B:AL,13,0) | F46: =VLOOKUP(B46,'UV台帐'!B:AL,15,0) | G46: =VLOOKUP(B46,'UV台帐'!B:AL,16,0) | H46: =VLOOKUP(B46,'UV台帐'!B:AL,17,0) | I46: =VLOOKUP(B46,'UV台帐'!B:AL,18,0) | J46: =VLOOKUP(B46,'UV台帐'!B:AL,22,0) | K46: =VLOOKUP(B46,'UV台帐'!B:AL,24,0) | L46: =VLOOKUP(B46,'UV台帐'!B:AL,26,0) | M46: =VLOOKUP(B46,'UV台帐'!B:AL,27,0) | N46: =VLOOKUP(B46,'UV台帐'!B:AL,31,0) | O46: =VLOOKUP(B46,'UV台帐'!B:AL,33,0) | P46: =VLOOKUP(B46,'UV台帐'!B:AL,35,0) | Q46: =VLOOKUP(B46,'UV台帐'!B:AL,36,0) | R46: 是 | S46: B | T46: 否 | U46: 是 | Z46: 0期后五讲转过来，妈妈平时比较忙，电话有问秋季的课程大纲和费用。A | AA46: 明确需求 | AB46: 数学基础知识比较薄弱，特别是计算丢分比较多，混合运算也丢分，妈妈希望能够让孩子新初一基础知识点学扎实，在班级目标能够处于50%，其他科目在外面长期在学。 | AC46: 数 | AD46: 效果维度-培优拓展/分班考 | AE46: 2-一般，对于目标需求一般 | AF46: 2-支付能力一般 | AG46: 3-喜欢 | AH46: 3-有正面评价 | AI46: 2-有意识无规划 | AJ46: B-8-10 | AK46: 何咏04 | BF46: 杨林33 | BG46: =VLOOKUP(B46,'UV台帐'!B:G,6,0) | BR46: =COUNTIFS(H46,"一期",I46,"在读")+COUNTIFS(L46,"一期",M46,"在读")+COUNTIFS(P46,"一期",Q46,"在读") | BS46: =BR46-BW46 | BT46: =VLOOKUP(B46,'UV台帐'!B:AL,19,0) | BU46: =VLOOKUP(B46,'UV台帐'!B:AL,28,0) | BV46: =VLOOKUP(B46,'UV台帐'!B:AL,37,0) | BW46: =COUNTIFS(H46,"一期",BT46,"是")+COUNTIFS(L46,"一期",BU46,"是")+COUNTIFS(P46,"一期",BV46,"是") | CA46: 2579177783
A47: 新宝利 | B47: 2922308038 | C47: =VLOOKUP(B47,'UV台帐'!B:AL,2,0) | D47: =VLOOKUP(B47,'UV台帐'!B:AL,3,0) | E47: =VLOOKUP(B47,'UV台帐'!B:AL,13,0) | F47: =VLOOKUP(B47,'UV台帐'!B:AL,15,0) | G47: =VLOOKUP(B47,'UV台帐'!B:AL,16,0) | H47: =VLOOKUP(B47,'UV台帐'!B:AL,17,0) | I47: =VLOOKUP(B47,'UV台帐'!B:AL,18,0) | J47: =VLOOKUP(B47,'UV台帐'!B:AL,22,0) | K47: =VLOOKUP(B47,'UV台帐'!B:AL,24,0) | L47: =VLOOKUP(B47,'UV台帐'!B:AL,26,0) | M47: =VLOOKUP(B47,'UV台帐'!B:AL,27,0) | N47: =VLOOKUP(B47,'UV台帐'!B:AL,31,0) | O47: =VLOOKUP(B47,'UV台帐'!B:AL,33,0) | P47: =VLOOKUP(B47,'UV台帐'!B:AL,35,0) | Q47: =VLOOKUP(B47,'UV台帐'!B:AL,36,0) | R47: 是 | S47: B | T47: 是 | U47: 是 | V47: 三中实验 | W47: 3A | X47: 一般 | Y47: 小升初衔接 | Z47: 去的三中实验。对比我们的学习效果，校外有机构补习。支付能力可以。家长平时比较忙，回复消息不是很及时。B，新东方学习，没续费。 没有到过店，补测试成绩。打3次未接 | AA47: 明确需求 | AB47: 语数英三科成绩均衡，总分约285分（单科95分左右），之前在新东方一直学，效果不理想。孩子很有主见，是否报班以他的意愿为准。妈妈希望能给予更多课堂关注，帮助孩子扎实掌握知识点、真正提分。当前薄弱点是英语音标，其他科目具体薄弱点不了解，整体丢分不多，每日作业需要家长督促完成。 | AC47: 语,数,英 | AD47: 效果维度-提分,沟通维度：老师有关注度 | AE47: 2-一般，对于目标需求一般 | AF47: 2-支付能力一般 | AG47: 2-一般 | AH47: 2-评价一般、无感 | AI47: 3-有规划有意识 | AJ47: A-11-13 | AK47: 何咏04 | AL47: 是 | BF47: 杨林33 | BG47: =VLOOKUP(B47,'UV台帐'!B:G,6,0) | BH47: 三中实验 | BR47: =COUNTIFS(H47,"一期",I47,"在读")+COUNTIFS(L47,"一期",M47,"在读")+COUNTIFS(P47,"一期",Q47,"在读") | BS47: =BR47-BW47 | BT47: =VLOOKUP(B47,'UV台帐'!B:AL,19,0) | BU47: =VLOOKUP(B47,'UV台帐'!B:AL,28,0) | BV47: =VLOOKUP(B47,'UV台帐'!B:AL,37,0) | BW47: =COUNTIFS(H47,"一期",BT47,"是")+COUNTIFS(L47,"一期",BU47,"是")+COUNTIFS(P47,"一期",BV47,"是") | CA47: 2457332134
A48: 天成大厦 | B48: 4060101914 | C48: =VLOOKUP(B48,'UV台帐'!B:AL,2,0) | D48: =VLOOKUP(B48,'UV台帐'!B:AL,3,0) | E48: =VLOOKUP(B48,'UV台帐'!B:AL,13,0) | F48: =VLOOKUP(B48,'UV台帐'!B:AL,15,0) | G48: =VLOOKUP(B48,'UV台帐'!B:AL,16,0) | H48: =VLOOKUP(B48,'UV台帐'!B:AL,17,0) | I48: =VLOOKUP(B48,'UV台帐'!B:AL,18,0) | J48: =VLOOKUP(B48,'UV台帐'!B:AL,22,0) | K48: =VLOOKUP(B48,'UV台帐'!B:AL,24,0) | L48: =VLOOKUP(B48,'UV台帐'!B:AL,26,0) | M48: =VLOOKUP(B48,'UV台帐'!B:AL,27,0) | N48: =VLOOKUP(B48,'UV台帐'!B:AL,31,0) | O48: =VLOOKUP(B48,'UV台帐'!B:AL,33,0) | P48: =VLOOKUP(B48,'UV台帐'!B:AL,35,0) | Q48: =VLOOKUP(B48,'UV台帐'!B:AL,36,0) | R48: 是 | S48: B | T48: 是 | U48: 是 | W48: 295 | X48: 转介绍学员，家长很忙，没怎么深入沟通 | Y48: 转介绍学员，家长很忙，没怎么深入沟通，有课外辅导经历 | Z48: 转介绍学员，家长很忙，上课时间没问题；校内成绩295，一直以微信沟通为主，妈妈从事保险行业。支付能力还可以。 | AA48: 未沟通 | AB48: 转介绍家长，家长做保险的，很忙，电话基本不接，微信也很少回，7.10电话未接，7.11电话未接 | AE48: 2-一般，对于目标需求一般 | AF48: 2-支付能力一般 | AG48: 2-一般 | AH48: 2-评价一般、无感 | AI48: 2-有意识无规划 | AJ48: B-8-10 | AK48: 刘希子 | AL48: 是 | BF48: 陈亮延 | BG48: =VLOOKUP(B48,'UV台帐'!B:G,6,0) | BR48: =COUNTIFS(H48,"一期",I48,"在读")+COUNTIFS(L48,"一期",M48,"在读")+COUNTIFS(P48,"一期",Q48,"在读") | BS48: =BR48-BW48 | BT48: =VLOOKUP(B48,'UV台帐'!B:AL,19,0) | BU48: =VLOOKUP(B48,'UV台帐'!B:AL,28,0) | BV48: =VLOOKUP(B48,'UV台帐'!B:AL,37,0) | BW48: =COUNTIFS(H48,"一期",BT48,"是")+COUNTIFS(L48,"一期",BU48,"是")+COUNTIFS(P48,"一期",BV48,"是") | CA48: 4108975188
A49: 新宝利 | B49: 2516986556 | C49: =VLOOKUP(B49,'UV台帐'!B:AL,2,0) | D49: =VLOOKUP(B49,'UV台帐'!B:AL,3,0) | E49: =VLOOKUP(B49,'UV台帐'!B:AL,13,0) | F49: =VLOOKUP(B49,'UV台帐'!B:AL,15,0) | G49: =VLOOKUP(B49,'UV台帐'!B:AL,16,0) | H49: =VLOOKUP(B49,'UV台帐'!B:AL,17,0) | I49: =VLOOKUP(B49,'UV台帐'!B:AL,18,0) | J49: =VLOOKUP(B49,'UV台帐'!B:AL,22,0) | K49: =VLOOKUP(B49,'UV台帐'!B:AL,24,0) | L49: =VLOOKUP(B49,'UV台帐'!B:AL,26,0) | M49: =VLOOKUP(B49,'UV台帐'!B:AL,27,0) | N49: =VLOOKUP(B49,'UV台帐'!B:AL,31,0) | O49: =VLOOKUP(B49,'UV台帐'!B:AL,33,0) | P49: =VLOOKUP(B49,'UV台帐'!B:AL,35,0) | Q49: =VLOOKUP(B49,'UV台帐'!B:AL,36,0) | R49: 是 | S49: A | T49: 是 | U49: 否 | V49: 三中 | W49: 三科平均90，跟子慧差不多 | X49: 写作文大部分都是凑字数流水账，并且孩子性格不是属于勤奋那种，对学习成绩不紧不慢，反而是妈妈着急比较多 | Y49: 语文不扎实，妈妈觉得语文方面还缺少完整的学习体系，希望老师能激发学习的欲望 | Z49: 作业会比较拖拉，主要看后面衔接的效果；团长，家长奔着分班测来的，聊过暑秋，现场会销。 | AA49: 明确需求 | AB49: 孩子情况：语文方面一直比较薄弱需要有个系统性学习，分班测转化的学员，长对于分班测需求很大 家长补课意识：之前咨询过秋季课的价格，家长紧迫感比较高对于孩子学习非常焦虑，但是孩子比较佛 需求：希望老师能够严一点，多多关注一下孩子的上课表现，让孩子有目标感 目标：最后希望孩子保底是有公办的高中上 | AC49: 语,数,英 | AD49: 升学需求-保底本区公办高中,效果维度-提分,效果维度-抓习惯,沟通维度：老师有关注度 | AE49: 2-一般，对于目标需求一般 | AF49: 3-支付能力强 | AG49: 3-喜欢 | AH49: 3-有正面评价 | AI49: 2-有意识无规划 | AJ49: S-14-15 | AK49: 李润 | AL49: 是 | BF49: 沈思浩 | BG49: =VLOOKUP(B49,'UV台帐'!B:G,6,0) | BR49: =COUNTIFS(H49,"一期",I49,"在读")+COUNTIFS(L49,"一期",M49,"在读")+COUNTIFS(P49,"一期",Q49,"在读") | BS49: =BR49-BW49 | BT49: =VLOOKUP(B49,'UV台帐'!B:AL,19,0) | BU49: =VLOOKUP(B49,'UV台帐'!B:AL,28,0) | BV49: =VLOOKUP(B49,'UV台帐'!B:AL,37,0) | BW49: =COUNTIFS(H49,"一期",BT49,"是")+COUNTIFS(L49,"一期",BU49,"是")+COUNTIFS(P49,"一期",BV49,"是") | CA49: 4380980083
A50: 新宝利 | B50: 2500666341 | C50: =VLOOKUP(B50,'UV台帐'!B:AL,2,0) | D50: =VLOOKUP(B50,'UV台帐'!B:AL,3,0) | E50: =VLOOKUP(B50,'UV台帐'!B:AL,13,0) | F50: =VLOOKUP(B50,'UV台帐'!B:AL,15,0) | G50: =VLOOKUP(B50,'UV台帐'!B:AL,16,0) | H50: =VLOOKUP(B50,'UV台帐'!B:AL,17,0) | I50: =VLOOKUP(B50,'UV台帐'!B:AL,18,0) | J50: =VLOOKUP(B50,'UV台帐'!B:AL,22,0) | K50: =VLOOKUP(B50,'UV台帐'!B:AL,24,0) | L50: =VLOOKUP(B50,'UV台帐'!B:AL,26,0) | M50: =VLOOKUP(B50,'UV台帐'!B:AL,27,0) | N50: =VLOOKUP(B50,'UV台帐'!B:AL,31,0) | O50: =VLOOKUP(B50,'UV台帐'!B:AL,33,0) | P50: =VLOOKUP(B50,'UV台帐'!B:AL,35,0) | Q50: =VLOOKUP(B50,'UV台帐'!B:AL,36,0) | R50: 是 | S50: A | T50: 是 | U50: 是 | V50: 初中侨中 | W50: 数95，语94，英94 | X50: 会走神，上课必须和陈泊儒分开坐 | Y50: 数学是要长期学的，很少上班课，希望孩子可以适应 | Z50: 有长期学的想法，知道秋季价格，秋季大概率考虑数学。A，单科需求，线下沟通过，有做报前测；启能班能力，线上语文课在上 | AA50: 明确需求 | AB50: 孩子会走神，和陈泊儒是好朋友，上课一定要和陈泊儒分开坐，语文一直学的猿辅导线上课，数学没有补习过，家长觉得数学是要长期学的，孩子习惯不好，容易接话，审题不清晰，不检查，需要老师纠正下习惯，知道秋季价格，最后一节课3.30下，下课后要去参加考级比赛，希望尽量不拖堂 | AC50: 数 | AD50: 升学需求-保底本区公办高中,效果维度-提分,效果维度-抓习惯 | AE50: 3-非常紧迫，有短期目标和长期需求 | AF50: 2-支付能力一般 | AG50: 3-喜欢 | AH50: 3-有正面评价 | AI50: 2-有意识无规划 | AJ50: A-11-13 | AK50: 何咏04 | AL50: 是 | BF50: 张敏烨 | BG50: =VLOOKUP(B50,'UV台帐'!B:G,6,0) | BR50: =COUNTIFS(H50,"一期",I50,"在读")+COUNTIFS(L50,"一期",M50,"在读")+COUNTIFS(P50,"一期",Q50,"在读") | BS50: =BR50-BW50 | BT50: =VLOOKUP(B50,'UV台帐'!B:AL,19,0) | BU50: =VLOOKUP(B50,'UV台帐'!B:AL,28,0) | BV50: =VLOOKUP(B50,'UV台帐'!B:AL,37,0) | BW50: =COUNTIFS(H50,"一期",BT50,"是")+COUNTIFS(L50,"一期",BU50,"是")+COUNTIFS(P50,"一期",BV50,"是") | CA50: 4827301500
A51: 新宝利 | B51: 2553608227 | C51: =VLOOKUP(B51,'UV台帐'!B:AL,2,0) | D51: =VLOOKUP(B51,'UV台帐'!B:AL,3,0) | E51: =VLOOKUP(B51,'UV台帐'!B:AL,13,0) | F51: =VLOOKUP(B51,'UV台帐'!B:AL,15,0) | G51: =VLOOKUP(B51,'UV台帐'!B:AL,16,0) | H51: =VLOOKUP(B51,'UV台帐'!B:AL,17,0) | I51: =VLOOKUP(B51,'UV台帐'!B:AL,18,0) | J51: =VLOOKUP(B51,'UV台帐'!B:AL,22,0) | K51: =VLOOKUP(B51,'UV台帐'!B:AL,24,0) | L51: =VLOOKUP(B51,'UV台帐'!B:AL,26,0) | M51: =VLOOKUP(B51,'UV台帐'!B:AL,27,0) | N51: =VLOOKUP(B51,'UV台帐'!B:AL,31,0) | O51: =VLOOKUP(B51,'UV台帐'!B:AL,33,0) | P51: =VLOOKUP(B51,'UV台帐'!B:AL,35,0) | Q51: =VLOOKUP(B51,'UV台帐'!B:AL,36,0) | R51: 是 | S51: B | T51: 是 | U51: 是 | V51: 初中13中 | W51: 3A | X51: 自觉，喜欢上课，不爱写作业 | Y51: 解决孩子数学计算，应用压轴题，英语单词语法，语文阅读写作 | Z51: 只上过猿辅导线上语文课，没有上过线下课，有意向秋季接着上线下，但是表示要等开学后看看孩子情况，妈妈已经停掉线上语文课 | AA51: 明确需求 | AB51: 只上过猿辅导线上语文课，没有上过线下课，但心孩子一天上三科会不适应，妈妈是护士，会比较忙，经常打着电话说要去忙工作了就挂了，孩子不爱背单词，语法偏弱，数学提高应用拔高题的解题步骤，关注数学，期望初中稳定在重点班，不被淘汰，希望有个好点高中上，13中直升也可以接受，老师可以布置些作业在校区完成后再走 | AC51: 数 | AD51: 升学需求-保底本区公办高中,效果维度-提分,效果维度-抓习惯 | AE51: 2-一般，对于目标需求一般 | AF51: 1-无支付能力 | AG51: 3-喜欢 | AH51: 3-有正面评价 | AI51: 2-有意识无规划 | AJ51: B-8-10 | AK51: 何咏04 | AL51: 是 | BF51: 张敏烨 | BG51: =VLOOKUP(B51,'UV台帐'!B:G,6,0) | BH51: 13中 | BR51: =COUNTIFS(H51,"一期",I51,"在读")+COUNTIFS(L51,"一期",M51,"在读")+COUNTIFS(P51,"一期",Q51,"在读") | BS51: =BR51-BW51 | BT51: =VLOOKUP(B51,'UV台帐'!B:AL,19,0) | BU51: =VLOOKUP(B51,'UV台帐'!B:AL,28,0) | BV51: =VLOOKUP(B51,'UV台帐'!B:AL,37,0) | BW51: =COUNTIFS(H51,"一期",BT51,"是")+COUNTIFS(L51,"一期",BU51,"是")+COUNTIFS(P51,"一期",BV51,"是")
A52: 新宝利 | B52: 4357245184 | C52: =VLOOKUP(B52,'UV台帐'!B:AL,2,0) | D52: =VLOOKUP(B52,'UV台帐'!B:AL,3,0) | E52: =VLOOKUP(B52,'UV台帐'!B:AL,13,0) | F52: =VLOOKUP(B52,'UV台帐'!B:AL,15,0) | G52: =VLOOKUP(B52,'UV台帐'!B:AL,16,0) | H52: =VLOOKUP(B52,'UV台帐'!B:AL,17,0) | I52: =VLOOKUP(B52,'UV台帐'!B:AL,18,0) | J52: =VLOOKUP(B52,'UV台帐'!B:AL,22,0) | K52: =VLOOKUP(B52,'UV台帐'!B:AL,24,0) | L52: =VLOOKUP(B52,'UV台帐'!B:AL,26,0) | M52: =VLOOKUP(B52,'UV台帐'!B:AL,27,0) | N52: =VLOOKUP(B52,'UV台帐'!B:AL,31,0) | O52: =VLOOKUP(B52,'UV台帐'!B:AL,33,0) | P52: =VLOOKUP(B52,'UV台帐'!B:AL,35,0) | Q52: =VLOOKUP(B52,'UV台帐'!B:AL,36,0) | R52: 是 | S52: B | T52: 否 | U52: 是 | V52: 中二小， | W52: 都进满分 | X52: 很好 | Y52: 想看我们的教学质量和规划是否能承接 | Z52: 比较重点学员，妈妈很重视教学和老师，有正价需求，有支付能力，孩子很优秀希望杯一等奖，可能会遇到授课难度偏低的风险，希望课堂不要太吵闹。PET优秀\希望杯一等奖，是否学过新初一。 | AA52: 明确需求 | AB52: 语文校内情况90+，阅读是薄弱得点，书写习惯都不错。数学：希望杯一等奖，考试基本满分，偶尔错一两题 家长是我很早一批的暑假学员，曾经是有报过课，且明确需求数学满意就报名，之前因为数学老师原因对我们教学失望过，初中孩子很想再上一层，明确好会考虑，但是符合孩子掌握情况，老师明确规划。数学进度学到了绝对值那一章节。 | AC52: 数 | AD52: 效果维度-培优拓展/分班考,沟通维度：老师有个性化,沟通维度：老师有关注度 | AE52: 2-一般，对于目标需求一般 | AF52: 3-支付能力强 | AG52: 3-喜欢 | AH52: 1-有雷点、槽点 | AI52: 3-有规划有意识 | AJ52: A-11-13 | AK52: 何咏04 | BF52: 林志豪01 | BG52: =VLOOKUP(B52,'UV台帐'!B:G,6,0) | BR52: =COUNTIFS(H52,"一期",I52,"在读")+COUNTIFS(L52,"一期",M52,"在读")+COUNTIFS(P52,"一期",Q52,"在读") | BS52: =BR52-BW52 | BT52: =VLOOKUP(B52,'UV台帐'!B:AL,19,0) | BU52: =VLOOKUP(B52,'UV台帐'!B:AL,28,0) | BV52: =VLOOKUP(B52,'UV台帐'!B:AL,37,0) | BW52: =COUNTIFS(H52,"一期",BT52,"是")+COUNTIFS(L52,"一期",BU52,"是")+COUNTIFS(P52,"一期",BV52,"是")
A53: 同创汇 | B53: 4303763811 | C53: =VLOOKUP(B53,'UV台帐'!B:AL,2,0) | D53: =VLOOKUP(B53,'UV台帐'!B:AL,3,0) | E53: =VLOOKUP(B53,'UV台帐'!B:AL,13,0) | F53: =VLOOKUP(B53,'UV台帐'!B:AL,15,0) | G53: =VLOOKUP(B53,'UV台帐'!B:AL,16,0) | H53: =VLOOKUP(B53,'UV台帐'!B:AL,17,0) | I53: =VLOOKUP(B53,'UV台帐'!B:AL,18,0) | J53: =VLOOKUP(B53,'UV台帐'!B:AL,22,0) | K53: =VLOOKUP(B53,'UV台帐'!B:AL,24,0) | L53: =VLOOKUP(B53,'UV台帐'!B:AL,26,0) | M53: =VLOOKUP(B53,'UV台帐'!B:AL,27,0) | N53: =VLOOKUP(B53,'UV台帐'!B:AL,31,0) | O53: =VLOOKUP(B53,'UV台帐'!B:AL,33,0) | P53: =VLOOKUP(B53,'UV台帐'!B:AL,35,0) | Q53: =VLOOKUP(B53,'UV台帐'!B:AL,36,0) | R53: 是 | S53: A | U53: 是 | V53: 大沙头小学/培正 | W53: 三科90左右 | Y53: 黄靖柔介绍来的，关系很好，全部摇中了培正，虽然在海珠，但是妈妈认为初中还是要抓一下学习 | Z53: 妈妈认为上初中要开始补课了，黄靖柔介绍； | AA53: 明确需求 | AB53: 黄靖柔推荐来就直接报名了，英语B数学语文A，大沙头，摇培正中学；高中目标没有（需要看孩子的成绩） 之前补课，没有效果，需要结果，猿辅导补数学，英语线下 妈妈很重视，看孩子的结果，只要有结果，肯定能报名 | AC53: 语,数,英 | AD53: 升学需求-进九大or中上,升学需求-保底本区公办高中,效果维度-提分,效果维度-抓习惯,效果维度-培优拓展/分班考,沟通维度：老师有关注度 | AE53: 3-非常紧迫，有短期目标和长期需求 | AF53: 3-支付能力强 | AG53: 2-一般 | AH53: 2-评价一般、无感 | AI53: 3-有规划有意识 | AJ53: A-11-13 | AK53: 高心怡04 | AL53: 触达 | BF53: 戎凯01 | BG53: =VLOOKUP(B53,'UV台帐'!B:G,6,0) | BH53: 培正 | BR53: =COUNTIFS(H53,"一期",I53,"在读")+COUNTIFS(L53,"一期",M53,"在读")+COUNTIFS(P53,"一期",Q53,"在读") | BS53: =BR53-BW53 | BT53: =VLOOKUP(B53,'UV台帐'!B:AL,19,0) | BU53: =VLOOKUP(B53,'UV台帐'!B:AL,28,0) | BV53: =VLOOKUP(B53,'UV台帐'!B:AL,37,0) | BW53: =COUNTIFS(H53,"一期",BT53,"是")+COUNTIFS(L53,"一期",BU53,"是")+COUNTIFS(P53,"一期",BV53,"是")
A54: 新宝利 | B54: 4833286317 | C54: =VLOOKUP(B54,'UV台帐'!B:AL,2,0) | D54: =VLOOKUP(B54,'UV台帐'!B:AL,3,0) | E54: =VLOOKUP(B54,'UV台帐'!B:AL,13,0) | F54: =VLOOKUP(B54,'UV台帐'!B:AL,15,0) | G54: =VLOOKUP(B54,'UV台帐'!B:AL,16,0) | H54: =VLOOKUP(B54,'UV台帐'!B:AL,17,0) | I54: =VLOOKUP(B54,'UV台帐'!B:AL,18,0) | J54: =VLOOKUP(B54,'UV台帐'!B:AL,22,0) | K54: =VLOOKUP(B54,'UV台帐'!B:AL,24,0) | L54: =VLOOKUP(B54,'UV台帐'!B:AL,26,0) | M54: =VLOOKUP(B54,'UV台帐'!B:AL,27,0) | N54: =VLOOKUP(B54,'UV台帐'!B:AL,31,0) | O54: =VLOOKUP(B54,'UV台帐'!B:AL,33,0) | P54: =VLOOKUP(B54,'UV台帐'!B:AL,35,0) | Q54: =VLOOKUP(B54,'UV台帐'!B:AL,36,0) | R54: 是 | S54: B | T54: 否 | U54: 是 | V54: 西小，西文 | W54: 语文80，数学90，英语80 | X54: 很好，但是做题总找不到重点 | Y54: 对比我们线下线上的区别，想改变孩子的思维找到方法 | Z54: 孩子习惯不是特别好，胆小不爱问,B；孩子成绩一般，妈妈一直在作业帮线上课程，对品牌认可。 | AA54: 明确需求 | AB54: 7月8日沟通，电话沟通 孩子做过诊断，孩子得情况比较中规中矩，情况如下 语文：孩子阅读是很薄弱得，说特别梳理文段理解段落中心方面特别弱，每次都要扣10来分，觉得很弱 数学：数学情况是相对可以得，但是思维也弱，妈妈说孩子几何题，简单得都可以，但是延申综合性强得题目就很容易出错，多引导引导难题，给一些做题方法 英语：孩子英语是最差得，80左右时不时70多都有，单词很弱，因为之前4年级换老师后，孩子就一直掉，一直也是我们线上补课得，但是效果也提不上来。严格捉捉孩子英语背诵，就是懒不背 孩子目前去到了不好的学校加上孩子本身不是特别拔尖的孩子，她觉得孩子需要提升的，是线上学员，但是明确讲过价格，妈咪说有一点点压力觉得。 | AC54: 数,英 | AD54: 效果维度-提分,效果维度-抓习惯,沟通维度：老师有个性化,沟通维度：老师有关注度 | AE54: 2-一般，对于目标需求一般 | AF54: 1-无支付能力 | AG54: 2-一般 | AH54: 2-评价一般、无感 | AI54: 3-有规划有意识 | AJ54: C-小于8 | AK54: 何咏04 | BF54: 林志豪01 | BG54: =VLOOKUP(B54,'UV台帐'!B:G,6,0) | BR54: =COUNTIFS(H54,"一期",I54,"在读")+COUNTIFS(L54,"一期",M54,"在读")+COUNTIFS(P54,"一期",Q54,"在读") | BS54: =BR54-BW54 | BT54: =VLOOKUP(B54,'UV台帐'!B:AL,19,0) | BU54: =VLOOKUP(B54,'UV台帐'!B:AL,28,0) | BV54: =VLOOKUP(B54,'UV台帐'!B:AL,37,0) | BW54: =COUNTIFS(H54,"一期",BT54,"是")+COUNTIFS(L54,"一期",BU54,"是")+COUNTIFS(P54,"一期",BV54,"是")
A55: 新宝利 | B55: 4100299520 | C55: =VLOOKUP(B55,'UV台帐'!B:AL,2,0) | D55: =VLOOKUP(B55,'UV台帐'!B:AL,3,0) | E55: =VLOOKUP(B55,'UV台帐'!B:AL,13,0) | F55: =VLOOKUP(B55,'UV台帐'!B:AL,15,0) | G55: =VLOOKUP(B55,'UV台帐'!B:AL,16,0) | H55: =VLOOKUP(B55,'UV台帐'!B:AL,17,0) | I55: =VLOOKUP(B55,'UV台帐'!B:AL,18,0) | J55: =VLOOKUP(B55,'UV台帐'!B:AL,22,0) | K55: =VLOOKUP(B55,'UV台帐'!B:AL,24,0) | L55: =VLOOKUP(B55,'UV台帐'!B:AL,26,0) | M55: =VLOOKUP(B55,'UV台帐'!B:AL,27,0) | N55: =VLOOKUP(B55,'UV台帐'!B:AL,31,0) | O55: =VLOOKUP(B55,'UV台帐'!B:AL,33,0) | P55: =VLOOKUP(B55,'UV台帐'!B:AL,35,0) | Q55: =VLOOKUP(B55,'UV台帐'!B:AL,36,0) | R55: 是 | S55: A | T55: 是 | U55: 否 | V55: 侨小翠园/广附 | W55: 290 | X55: 孩子细心扎实，就是有点胆小，不太主动 | Y55: 家长希望做机构对比，觉得这边的课程优惠，试错成本低，觉得ok九转机构，有长期学习的打算 | Z55: 零期在读英语和语文，比较忙；会销进来的，单独聊过2小时，爸爸当时说上完暑假再安排，数学科目在沃伦学习，床上四件套外贸。 | AA55: 明确需求 | AB55: 基本情况：孩子目前有稳定的数学学科辅导（沃伦），家长明确想了解语文英语的课程，也想孩子体验暑假课程，对比机构的教学服务，结合孩子意愿度做长期学习的规划。零期上了语文和英语，妈妈觉得课程还可以，需要结合一期的数学课程再做决定。 需求判定：孩子初中在广附，妈妈虽然没有明确的学校想法，但希望能去到九大校。分析了孩子目前可能是语文偏弱，在数学科目上希望老师能多给一些课外的习题，让孩子多做补充。孩子比较胆小，需要老师多关注，可以提提问，或者课后面谈。 | AC55: 语,英 | AD55: 升学需求-进九大or中上,效果维度-培优拓展/分班考,沟通维度：老师有个性化 | AE55: 3-非常紧迫，有短期目标和长期需求 | AF55: 3-支付能力强 | AG55: 2-一般 | AH55: 2-评价一般、无感 | AI55: 3-有规划有意识 | AJ55: A-11-13 | AK55: 何咏04 | AL55: 是 | BF55: 陈亮延 | BG55: =VLOOKUP(B55,'UV台帐'!B:G,6,0) | BH55: 广附 | BR55: =COUNTIFS(H55,"一期",I55,"在读")+COUNTIFS(L55,"一期",M55,"在读")+COUNTIFS(P55,"一期",Q55,"在读") | BS55: =BR55-BW55 | BT55: =VLOOKUP(B55,'UV台帐'!B:AL,19,0) | BU55: =VLOOKUP(B55,'UV台帐'!B:AL,28,0) | BV55: =VLOOKUP(B55,'UV台帐'!B:AL,37,0) | BW55: =COUNTIFS(H55,"一期",BT55,"是")+COUNTIFS(L55,"一期",BU55,"是")+COUNTIFS(P55,"一期",BV55,"是")
A56: 新宝利 | B56: 2958659528 | C56: =VLOOKUP(B56,'UV台帐'!B:AL,2,0) | D56: =VLOOKUP(B56,'UV台帐'!B:AL,3,0) | E56: =VLOOKUP(B56,'UV台帐'!B:AL,13,0) | F56: =VLOOKUP(B56,'UV台帐'!B:AL,15,0) | G56: =VLOOKUP(B56,'UV台帐'!B:AL,16,0) | H56: =VLOOKUP(B56,'UV台帐'!B:AL,17,0) | I56: =VLOOKUP(B56,'UV台帐'!B:AL,18,0) | J56: =VLOOKUP(B56,'UV台帐'!B:AL,22,0) | K56: =VLOOKUP(B56,'UV台帐'!B:AL,24,0) | L56: =VLOOKUP(B56,'UV台帐'!B:AL,26,0) | M56: =VLOOKUP(B56,'UV台帐'!B:AL,27,0) | N56: =VLOOKUP(B56,'UV台帐'!B:AL,31,0) | O56: =VLOOKUP(B56,'UV台帐'!B:AL,33,0) | P56: =VLOOKUP(B56,'UV台帐'!B:AL,35,0) | Q56: =VLOOKUP(B56,'UV台帐'!B:AL,36,0) | R56: 是 | S56: A | U56: 是 | V56: 初中广大附 | W56: AAA | X56: 学习态度良好 | Y56: 初中分班测分层测，8月广大附开家长会 | Z56: 五年级开始上数学英语一对一，孩子爸爸觉得费用高，并且不利于孩子学习能力的提升，想要提高孩子学习态度，让孩子能够自主学习，孩子爸爸管学习，平时关注各科进程，也关注分班测，会销进来，课程价格是了解，孩子自己比较有主见，孩子有在了解高中，想要进入一所比较好的高中 | AA56: 明确需求 | AB56: 补习经历：五年级开始上数学英语一对一，孩子爸爸觉得费用高，并且不利于孩子学习能力的提升，希望老师能培养孩子的自主学习能力以及学习态度，孩子爸爸管学习，关注分班测，孩子摇号中了广大附，学校对于理科要求比较高，如果想要进到重点班，对于数学单科提分必要性强；希望老师课后能反馈孩子课堂表现，有没有小动作，走神什么的需要及时沟通。孩子自己比较有主见，孩子有在了解高中，想要进入一所比较好的区属高中。 | AC56: 数,英 | AD56: 升学需求-保底本区公办高中,效果维度-抓习惯,效果维度-培优拓展/分班考,沟通维度：老师有个性化 | AE56: 2-一般，对于目标需求一般 | AF56: 3-支付能力强 | AG56: 2-一般 | AH56: 2-评价一般、无感 | AI56: 2-有意识无规划 | AJ56: A-11-13 | AK56: 何咏04 | AL56: 是 | BF56: 王达04 | BG56: =VLOOKUP(B56,'UV台帐'!B:G,6,0) | BR56: =COUNTIFS(H56,"一期",I56,"在读")+COUNTIFS(L56,"一期",M56,"在读")+COUNTIFS(P56,"一期",Q56,"在读") | BS56: =BR56-BW56 | BT56: =VLOOKUP(B56,'UV台帐'!B:AL,19,0) | BU56: =VLOOKUP(B56,'UV台帐'!B:AL,28,0) | BV56: =VLOOKUP(B56,'UV台帐'!B:AL,37,0) | BW56: =COUNTIFS(H56,"一期",BT56,"是")+COUNTIFS(L56,"一期",BU56,"是")+COUNTIFS(P56,"一期",BV56,"是")
A57: 同创汇 | B57: 2472389311 | C57: =VLOOKUP(B57,'UV台帐'!B:AL,2,0) | D57: =VLOOKUP(B57,'UV台帐'!B:AL,3,0) | E57: =VLOOKUP(B57,'UV台帐'!B:AL,13,0) | F57: =VLOOKUP(B57,'UV台帐'!B:AL,15,0) | G57: =VLOOKUP(B57,'UV台帐'!B:AL,16,0) | H57: =VLOOKUP(B57,'UV台帐'!B:AL,17,0) | I57: =VLOOKUP(B57,'UV台帐'!B:AL,18,0) | J57: =VLOOKUP(B57,'UV台帐'!B:AL,22,0) | K57: =VLOOKUP(B57,'UV台帐'!B:AL,24,0) | L57: =VLOOKUP(B57,'UV台帐'!B:AL,26,0) | M57: =VLOOKUP(B57,'UV台帐'!B:AL,27,0) | N57: =VLOOKUP(B57,'UV台帐'!B:AL,31,0) | O57: =VLOOKUP(B57,'UV台帐'!B:AL,33,0) | P57: =VLOOKUP(B57,'UV台帐'!B:AL,35,0) | Q57: =VLOOKUP(B57,'UV台帐'!B:AL,36,0) | R57: 是 | S57: B | V57: 东风东 | W57: 285六下 | X57: 内向，不爱说话，需要老师引导，孩子比较认老师 | Y57: 讲座来进行的转化，这次摇号不理想，需要确定初中（考虑民办）会应为学校选择搬家，目前零期语文还没报名原因也是这个 | Z57: 零期语文还没报名，妈妈之前有说要考虑搬家的问题，主要是初中学校还没定，所以妈妈这边下不来决定 | AA57: 明确需求 | AB57: 零期上的语文，孩子点名上的小润的课，目前没有报名是应为初中还没确定，需要考虑搬家，现在没办法确定补课机构，也需要看孩子意愿和对老师认可度 主要是孩子比较内向，很挑老师，孩子确定，妈妈这边会选择报名 | AC57: 语,数,英 | AD57: 升学需求-保底本区公办高中,沟通维度：老师有个性化,沟通维度：老师有关注度 | AE57: 2-一般，对于目标需求一般 | AF57: 3-支付能力强 | AG57: 2-一般 | AH57: 3-有正面评价 | AI57: 2-有意识无规划 | AJ57: A-11-13 | AK57: 高心怡04 | AL57: 触达 | BF57: 戎凯01 | BG57: =VLOOKUP(B57,'UV台帐'!B:G,6,0) | BH57: 未定 | BR57: =COUNTIFS(H57,"一期",I57,"在读")+COUNTIFS(L57,"一期",M57,"在读")+COUNTIFS(P57,"一期",Q57,"在读") | BS57: =BR57-BW57 | BT57: =VLOOKUP(B57,'UV台帐'!B:AL,19,0) | BU57: =VLOOKUP(B57,'UV台帐'!B:AL,28,0) | BV57: =VLOOKUP(B57,'UV台帐'!B:AL,37,0) | BW57: =COUNTIFS(H57,"一期",BT57,"是")+COUNTIFS(L57,"一期",BU57,"是")+COUNTIFS(P57,"一期",BV57,"是")
A58: 新宝利 | B58: 4193294263 | C58: =VLOOKUP(B58,'UV台帐'!B:AL,2,0) | D58: =VLOOKUP(B58,'UV台帐'!B:AL,3,0) | E58: =VLOOKUP(B58,'UV台帐'!B:AL,13,0) | F58: =VLOOKUP(B58,'UV台帐'!B:AL,15,0) | G58: =VLOOKUP(B58,'UV台帐'!B:AL,16,0) | H58: =VLOOKUP(B58,'UV台帐'!B:AL,17,0) | I58: =VLOOKUP(B58,'UV台帐'!B:AL,18,0) | J58: =VLOOKUP(B58,'UV台帐'!B:AL,22,0) | K58: =VLOOKUP(B58,'UV台帐'!B:AL,24,0) | L58: =VLOOKUP(B58,'UV台帐'!B:AL,26,0) | M58: =VLOOKUP(B58,'UV台帐'!B:AL,27,0) | N58: =VLOOKUP(B58,'UV台帐'!B:AL,31,0) | O58: =VLOOKUP(B58,'UV台帐'!B:AL,33,0) | P58: =VLOOKUP(B58,'UV台帐'!B:AL,35,0) | Q58: =VLOOKUP(B58,'UV台帐'!B:AL,36,0) | R58: 是 | S58: S | T58: 是 | U58: 是 | V58: 天元府，南武中学 | W58: 85+ | X58: 好动，外向，做题习惯不错 | Y58: 了解英语 | Z58: 在读学员扩科，英语有需求，效果能好就能报，需要老师重点关注和服务。S | AA58: 明确需求 | AB58: 7月8日沟通，老学员，数学大帅班在读很久的，孩子很喜欢大帅，觉得我们这里教的好，而且志愿填报给了很好的建议，去到自己的学校很满意。 英语：英语还是85+，还是想她再进一步，语法词汇多捉捉，希望能像大帅老师一样严格要求孩子， @肖锐03(Jerry)明确英语满意就报名，申请回3400就行 语文：成绩基本90+妈妈说都还不错的，不考虑的，多了也累 | AC58: 英 | AD58: 效果维度-抓习惯,沟通维度：老师有个性化,沟通维度：老师有关注度 | AE58: 3-非常紧迫，有短期目标和长期需求 | AF58: 2-支付能力一般 | AG58: 3-喜欢 | AH58: 3-有正面评价 | AI58: 3-有规划有意识 | AJ58: S-14-15 | AK58: 李润 | BF58: 林志豪01 | BG58: =VLOOKUP(B58,'UV台帐'!B:G,6,0) | BR58: =COUNTIFS(H58,"一期",I58,"在读")+COUNTIFS(L58,"一期",M58,"在读")+COUNTIFS(P58,"一期",Q58,"在读") | BS58: =BR58-BW58 | BT58: =VLOOKUP(B58,'UV台帐'!B:AL,19,0) | BU58: =VLOOKUP(B58,'UV台帐'!B:AL,28,0) | BV58: =VLOOKUP(B58,'UV台帐'!B:AL,37,0) | BW58: =COUNTIFS(H58,"一期",BT58,"是")+COUNTIFS(L58,"一期",BU58,"是")+COUNTIFS(P58,"一期",BV58,"是")
A59: 同创汇 | B59: 4829563345 | C59: =VLOOKUP(B59,'UV台帐'!B:AL,2,0) | D59: =VLOOKUP(B59,'UV台帐'!B:AL,3,0) | E59: =VLOOKUP(B59,'UV台帐'!B:AL,13,0) | F59: =VLOOKUP(B59,'UV台帐'!B:AL,15,0) | G59: =VLOOKUP(B59,'UV台帐'!B:AL,16,0) | H59: =VLOOKUP(B59,'UV台帐'!B:AL,17,0) | I59: =VLOOKUP(B59,'UV台帐'!B:AL,18,0) | J59: =VLOOKUP(B59,'UV台帐'!B:AL,22,0) | K59: =VLOOKUP(B59,'UV台帐'!B:AL,24,0) | L59: =VLOOKUP(B59,'UV台帐'!B:AL,26,0) | M59: =VLOOKUP(B59,'UV台帐'!B:AL,27,0) | N59: =VLOOKUP(B59,'UV台帐'!B:AL,31,0) | O59: =VLOOKUP(B59,'UV台帐'!B:AL,33,0) | P59: =VLOOKUP(B59,'UV台帐'!B:AL,35,0) | Q59: =VLOOKUP(B59,'UV台帐'!B:AL,36,0) | R59: 是 | S59: S | T59: 是 | U59: 是 | V59: 水荫路小学 | W59: 三科90左右 | Y59: 在读老生转介绍，之前知道作业帮，体验线下课 | Z59: 有两节课调课到一期，语数英已续报 | AA59: 明确需求 | AB59: 语数英已续报 | AC59: 语,数,英 | AK59: 陈南05 | AL59: 0期已开 | BF59: 王丽 | BG59: =VLOOKUP(B59,'UV台帐'!B:G,6,0) | BR59: =COUNTIFS(H59,"一期",I59,"在读")+COUNTIFS(L59,"一期",M59,"在读")+COUNTIFS(P59,"一期",Q59,"在读") | BS59: =BR59-BW59 | BT59: =VLOOKUP(B59,'UV台帐'!B:AL,19,0) | BU59: =VLOOKUP(B59,'UV台帐'!B:AL,28,0) | BV59: =VLOOKUP(B59,'UV台帐'!B:AL,37,0) | BW59: =COUNTIFS(H59,"一期",BT59,"是")+COUNTIFS(L59,"一期",BU59,"是")+COUNTIFS(P59,"一期",BV59,"是")
A60: 新宝利 | B60: 4831171617 | C60: =VLOOKUP(B60,'UV台帐'!B:AL,2,0) | D60: =VLOOKUP(B60,'UV台帐'!B:AL,3,0) | E60: =VLOOKUP(B60,'UV台帐'!B:AL,13,0) | F60: =VLOOKUP(B60,'UV台帐'!B:AL,15,0) | G60: =VLOOKUP(B60,'UV台帐'!B:AL,16,0) | H60: =VLOOKUP(B60,'UV台帐'!B:AL,17,0) | I60: =VLOOKUP(B60,'UV台帐'!B:AL,18,0) | J60: =VLOOKUP(B60,'UV台帐'!B:AL,22,0) | K60: =VLOOKUP(B60,'UV台帐'!B:AL,24,0) | L60: =VLOOKUP(B60,'UV台帐'!B:AL,26,0) | M60: =VLOOKUP(B60,'UV台帐'!B:AL,27,0) | N60: =VLOOKUP(B60,'UV台帐'!B:AL,31,0) | O60: =VLOOKUP(B60,'UV台帐'!B:AL,33,0) | P60: =VLOOKUP(B60,'UV台帐'!B:AL,35,0) | Q60: =VLOOKUP(B60,'UV台帐'!B:AL,36,0) | R60: 是 | S60: B | T60: 是 | U60: 是 | V60: 名德 | W60: 数94，语93，英90 | X60: 喜欢画画，跳舞，孩子自觉，省心，不用操作，作业自己搞定 | Y60: 提前学初一内容，打好基础 | Z60: 孩子上过期末复习课觉得不错，很有趣，之前上过猿辅导数学课，画画跳舞网课都停掉了，家里有个大的，妈妈不想卷，是想等孩子到初一看看情况再报秋季，不想给孩子压力 | AA60: 明确需求 | AB60: 孩子喜欢画画跳舞，自觉性高，学习不需要家长管的，作业都是自己搞定的，家里做生意的，平时白天会很忙，之前私自调课家长对此比较有意见，觉得我们没提前告知，甚至想退费，和郭诗颖是朋友，之前上过期末复习课，孩子觉得线下课很有意思，之前只上过猿辅导数学线上课，摇中的学校不好，花钱去了名德，家里有个大的哥哥，妈妈不想那么卷，不想给孩子那么多压力，也是知道初中会有压力，报我们这边是想提前做个初一预习，做个衔接，孩子暑假体验感不错，秋季开学后会考虑哪科薄弱补哪一科 | AC60: 数 | AD60: 升学需求-保底本区公办高中,效果维度-培优拓展/分班考 | AE60: 2-一般，对于目标需求一般 | AF60: 2-支付能力一般 | AG60: 2-一般 | AH60: 1-有雷点、槽点 | AI60: 2-有意识无规划 | AJ60: B-8-10 | AK60: 何咏04 | AL60: 是 | BF60: 张敏烨 | BG60: =VLOOKUP(B60,'UV台帐'!B:G,6,0) | BR60: =COUNTIFS(H60,"一期",I60,"在读")+COUNTIFS(L60,"一期",M60,"在读")+COUNTIFS(P60,"一期",Q60,"在读") | BS60: =BR60-BW60 | BT60: =VLOOKUP(B60,'UV台帐'!B:AL,19,0) | BU60: =VLOOKUP(B60,'UV台帐'!B:AL,28,0) | BV60: =VLOOKUP(B60,'UV台帐'!B:AL,37,0) | BW60: =COUNTIFS(H60,"一期",BT60,"是")+COUNTIFS(L60,"一期",BU60,"是")+COUNTIFS(P60,"一期",BV60,"是")
A61: 天成大厦 | B61: 2514140816 | C61: =VLOOKUP(B61,'UV台帐'!B:AL,2,0) | D61: =VLOOKUP(B61,'UV台帐'!B:AL,3,0) | E61: =VLOOKUP(B61,'UV台帐'!B:AL,13,0) | F61: =VLOOKUP(B61,'UV台帐'!B:AL,15,0) | G61: =VLOOKUP(B61,'UV台帐'!B:AL,16,0) | H61: =VLOOKUP(B61,'UV台帐'!B:AL,17,0) | I61: =VLOOKUP(B61,'UV台帐'!B:AL,18,0) | J61: =VLOOKUP(B61,'UV台帐'!B:AL,22,0) | K61: =VLOOKUP(B61,'UV台帐'!B:AL,24,0) | L61: =VLOOKUP(B61,'UV台帐'!B:AL,26,0) | M61: =VLOOKUP(B61,'UV台帐'!B:AL,27,0) | N61: =VLOOKUP(B61,'UV台帐'!B:AL,31,0) | O61: =VLOOKUP(B61,'UV台帐'!B:AL,33,0) | P61: =VLOOKUP(B61,'UV台帐'!B:AL,35,0) | Q61: =VLOOKUP(B61,'UV台帐'!B:AL,36,0) | R61: 是 | S61: A | T61: 是 | U61: 是 | V61: 没有摇到公办，等民办补录 | W61: 250-260之间 | X61: 孩子内向一点，需要老师督促，会有点畏难，平时做作业是比较及时的，但是错题率比较高 | Y61: 正价断报老生，换师退费，之前数学正价在读。目前想加强分班测 | Z61: 孩子内向一点，需要老师督促；参加过测试，正价断报老生，换师退费，数学正价在读。 | AA61: 明确需求 | AB61: 孩子情况：孩子内向一点，需要老师督促;参加过测试，之前数学的正价断报老生。目前孩子语文a，数学英语b，希望能够巩固好基础:孩子缺乏目标感，孩子回到家不会主动复习。之前有上过大班课:。 需求：孩子对校内老师没好感所以缺乏对学习的兴趣，校内老师是用学习排名进行区别对待，所以想咱们这边能给孩子更多的关注，平时希望老师们督促，能够奖罚分明去激励孩子，让孩子学习更有动力 ，孩子对于课程安排没太大意见，家长希望老师能够严厉一点，说孩子就是缺乏人去督促，但是太过严厉孩子会有抗拒的感觉 规划：目前家长没有规划，还是希望能上一个高中的 | AC61: 语,数,英 | AD61: 升学需求-保底本区公办高中,效果维度-提分,效果维度-抓习惯,效果维度-培优拓展/分班考,沟通维度：老师有个性化,沟通维度：老师有关注度 | AE61: 2-一般，对于目标需求一般 | AF61: 2-支付能力一般 | AG61: 2-一般 | AH61: 2-评价一般、无感 | AI61: 2-有意识无规划 | AJ61: B-8-10 | AK61: 刘希子 | AL61: 是 | BF61: 沈思浩 | BG61: =VLOOKUP(B61,'UV台帐'!B:G,6,0) | BR61: =COUNTIFS(H61,"一期",I61,"在读")+COUNTIFS(L61,"一期",M61,"在读")+COUNTIFS(P61,"一期",Q61,"在读") | BS61: =BR61-BW61 | BT61: =VLOOKUP(B61,'UV台帐'!B:AL,19,0) | BU61: =VLOOKUP(B61,'UV台帐'!B:AL,28,0) | BV61: =VLOOKUP(B61,'UV台帐'!B:AL,37,0) | BW61: =COUNTIFS(H61,"一期",BT61,"是")+COUNTIFS(L61,"一期",BU61,"是")+COUNTIFS(P61,"一期",BV61,"是")
A62: 天成大厦 | B62: 4373949634 | C62: =VLOOKUP(B62,'UV台帐'!B:AL,2,0) | D62: =VLOOKUP(B62,'UV台帐'!B:AL,3,0) | E62: =VLOOKUP(B62,'UV台帐'!B:AL,13,0) | F62: =VLOOKUP(B62,'UV台帐'!B:AL,15,0) | G62: =VLOOKUP(B62,'UV台帐'!B:AL,16,0) | H62: =VLOOKUP(B62,'UV台帐'!B:AL,17,0) | I62: =VLOOKUP(B62,'UV台帐'!B:AL,18,0) | J62: =VLOOKUP(B62,'UV台帐'!B:AL,22,0) | K62: =VLOOKUP(B62,'UV台帐'!B:AL,24,0) | L62: =VLOOKUP(B62,'UV台帐'!B:AL,26,0) | M62: =VLOOKUP(B62,'UV台帐'!B:AL,27,0) | N62: =VLOOKUP(B62,'UV台帐'!B:AL,31,0) | O62: =VLOOKUP(B62,'UV台帐'!B:AL,33,0) | P62: =VLOOKUP(B62,'UV台帐'!B:AL,35,0) | Q62: =VLOOKUP(B62,'UV台帐'!B:AL,36,0) | R62: 是 | S62: S | T62: 是 | U62: 是 | V62: 广中直升 | W62: 280 | Y62: 妈妈说孩子上的好就报名，数学语文是已经续费了 | Z62: 续报老生，零期一科在读，没问题正常上课 | AA62: 明确需求 | AB62: 孩子情况：老生扩科，英语的词汇语法比较弱 补课需求：妈妈说学完这几节课后看看孩子感受怎么样在考虑报名秋季班。期末成绩出来之后家长感觉孩子成绩下滑严重，需要老师重新根据报前测在分析一次孩子情况，并且给解决方案，已经同步给希子。家长在广中之前适合他聊过分班测的事情，希望老师在课堂上面多多关注一些，孩子成绩中等需要系统性地学，所以家长要求老师可以加一些额外的词汇打卡。 意向判断：之前开语文家长会家长明确说，孩子上课喜欢老师并且语法方面有提高就报名 | AC62: 英 | AD62: 效果维度-提分,效果维度-培优拓展/分班考,沟通维度：老师有个性化,沟通维度：老师有关注度 | AE62: 3-非常紧迫，有短期目标和长期需求 | AF62: 3-支付能力强 | AG62: 3-喜欢 | AH62: 3-有正面评价 | AI62: 3-有规划有意识 | AJ62: S-14-15 | AK62: 刘希子 | AL62: 是 | BF62: 沈思浩 | BG62: =VLOOKUP(B62,'UV台帐'!B:G,6,0) | BR62: =COUNTIFS(H62,"一期",I62,"在读")+COUNTIFS(L62,"一期",M62,"在读")+COUNTIFS(P62,"一期",Q62,"在读") | BS62: =BR62-BW62 | BT62: =VLOOKUP(B62,'UV台帐'!B:AL,19,0) | BU62: =VLOOKUP(B62,'UV台帐'!B:AL,28,0) | BV62: =VLOOKUP(B62,'UV台帐'!B:AL,37,0) | BW62: =COUNTIFS(H62,"一期",BT62,"是")+COUNTIFS(L62,"一期",BU62,"是")+COUNTIFS(P62,"一期",BV62,"是")
A63: 同创汇 | B63: 2181270054 | C63: =VLOOKUP(B63,'UV台帐'!B:AL,2,0) | D63: =VLOOKUP(B63,'UV台帐'!B:AL,3,0) | E63: =VLOOKUP(B63,'UV台帐'!B:AL,13,0) | F63: =VLOOKUP(B63,'UV台帐'!B:AL,15,0) | G63: =VLOOKUP(B63,'UV台帐'!B:AL,16,0) | H63: =VLOOKUP(B63,'UV台帐'!B:AL,17,0) | I63: =VLOOKUP(B63,'UV台帐'!B:AL,18,0) | J63: =VLOOKUP(B63,'UV台帐'!B:AL,22,0) | K63: =VLOOKUP(B63,'UV台帐'!B:AL,24,0) | L63: =VLOOKUP(B63,'UV台帐'!B:AL,26,0) | M63: =VLOOKUP(B63,'UV台帐'!B:AL,27,0) | N63: =VLOOKUP(B63,'UV台帐'!B:AL,31,0) | O63: =VLOOKUP(B63,'UV台帐'!B:AL,33,0) | P63: =VLOOKUP(B63,'UV台帐'!B:AL,35,0) | Q63: =VLOOKUP(B63,'UV台帐'!B:AL,36,0) | R63: 是 | S63: A | T63: 是 | U63: 是 | V63: 先烈东，直升75中 | W63: 校内90多 | Y63: 在读老生扩科 | Z63: 未接，微信留言 | AA63: 明确需求 | AB63: 数学春季在读老生，扩科语文英语暑假。希望把基础打好，期待孩子可以改正学习态度，孩子自驱力不强，希望授课老师能多耐心引导、正向鼓励，调动孩子积极性。家长报名意愿没问题，主要需要看孩子对于老师的认可程度。和温静仪一起的，是好朋友 | AC63: 语,数,英 | AD63: 效果维度-提分,效果维度-抓习惯,沟通维度：老师有关注度 | AE63: 2-一般，对于目标需求一般 | AF63: 3-支付能力强 | AG63: 2-一般 | AH63: 3-有正面评价 | AI63: 2-有意识无规划 | AJ63: A-11-13 | AK63: 高心怡04 | AL63: 是 | BF63: 王丽 | BG63: =VLOOKUP(B63,'UV台帐'!B:G,6,0) | BR63: =COUNTIFS(H63,"一期",I63,"在读")+COUNTIFS(L63,"一期",M63,"在读")+COUNTIFS(P63,"一期",Q63,"在读") | BS63: =BR63-BW63 | BT63: =VLOOKUP(B63,'UV台帐'!B:AL,19,0) | BU63: =VLOOKUP(B63,'UV台帐'!B:AL,28,0) | BV63: =VLOOKUP(B63,'UV台帐'!B:AL,37,0) | BW63: =COUNTIFS(H63,"一期",BT63,"是")+COUNTIFS(L63,"一期",BU63,"是")+COUNTIFS(P63,"一期",BV63,"是")
A64: 同创汇 | B64: 4050031794 | C64: =VLOOKUP(B64,'UV台帐'!B:AL,2,0) | D64: =VLOOKUP(B64,'UV台帐'!B:AL,3,0) | E64: =VLOOKUP(B64,'UV台帐'!B:AL,13,0) | F64: =VLOOKUP(B64,'UV台帐'!B:AL,15,0) | G64: =VLOOKUP(B64,'UV台帐'!B:AL,16,0) | H64: =VLOOKUP(B64,'UV台帐'!B:AL,17,0) | I64: =VLOOKUP(B64,'UV台帐'!B:AL,18,0) | J64: =VLOOKUP(B64,'UV台帐'!B:AL,22,0) | K64: =VLOOKUP(B64,'UV台帐'!B:AL,24,0) | L64: =VLOOKUP(B64,'UV台帐'!B:AL,26,0) | M64: =VLOOKUP(B64,'UV台帐'!B:AL,27,0) | N64: =VLOOKUP(B64,'UV台帐'!B:AL,31,0) | O64: =VLOOKUP(B64,'UV台帐'!B:AL,33,0) | P64: =VLOOKUP(B64,'UV台帐'!B:AL,35,0) | Q64: =VLOOKUP(B64,'UV台帐'!B:AL,36,0) | R64: 是 | S64: A | U64: 否 | V64: 育才/育才 | W64: 289.5 | X64: 孩子比较有性格 | Y64: 数学没报名，只报名了英语，后面加了语文，分2期上课，妈妈很懂教培行业和教学工作，在卓越有了解过，目前零期英语未转，已经了解过价格 | Z64: 零期英语还没报名，一期上语文 | AA64: 明确需求 | AB64: 推荐了3个妈妈来，零期英语还没报名，妈妈说需要看孩子意愿，妈妈家长会和铭铭沟通过，老师也确认需要和孩子沟通达成共识，零期已经沟通过价格，主要看语文上完课，孩子这边认可，就可以2科一起报名 | AC64: 语,英 | AD64: 升学需求-保底本区公办高中,沟通维度：老师有个性化,沟通维度：老师有关注度 | AE64: 2-一般，对于目标需求一般 | AF64: 2-支付能力一般 | AG64: 1-抵触 | AH64: 3-有正面评价 | AI64: 2-有意识无规划 | AJ64: B-8-10 | AK64: 黄铭怡 | BF64: 戎凯01 | BG64: =VLOOKUP(B64,'UV台帐'!B:G,6,0) | BR64: =COUNTIFS(H64,"一期",I64,"在读")+COUNTIFS(L64,"一期",M64,"在读")+COUNTIFS(P64,"一期",Q64,"在读") | BS64: =BR64-BW64 | BT64: =VLOOKUP(B64,'UV台帐'!B:AL,19,0) | BU64: =VLOOKUP(B64,'UV台帐'!B:AL,28,0) | BV64: =VLOOKUP(B64,'UV台帐'!B:AL,37,0) | BW64: =COUNTIFS(H64,"一期",BT64,"是")+COUNTIFS(L64,"一期",BU64,"是")+COUNTIFS(P64,"一期",BV64,"是")
A65: 同创汇 | B65: 2573471597 | C65: =VLOOKUP(B65,'UV台帐'!B:AL,2,0) | D65: =VLOOKUP(B65,'UV台帐'!B:AL,3,0) | E65: =VLOOKUP(B65,'UV台帐'!B:AL,13,0) | F65: =VLOOKUP(B65,'UV台帐'!B:AL,15,0) | G65: =VLOOKUP(B65,'UV台帐'!B:AL,16,0) | H65: =VLOOKUP(B65,'UV台帐'!B:AL,17,0) | I65: =VLOOKUP(B65,'UV台帐'!B:AL,18,0) | J65: =VLOOKUP(B65,'UV台帐'!B:AL,22,0) | K65: =VLOOKUP(B65,'UV台帐'!B:AL,24,0) | L65: =VLOOKUP(B65,'UV台帐'!B:AL,26,0) | M65: =VLOOKUP(B65,'UV台帐'!B:AL,27,0) | N65: =VLOOKUP(B65,'UV台帐'!B:AL,31,0) | O65: =VLOOKUP(B65,'UV台帐'!B:AL,33,0) | P65: =VLOOKUP(B65,'UV台帐'!B:AL,35,0) | Q65: =VLOOKUP(B65,'UV台帐'!B:AL,36,0) | R65: 是 | S65: B | U65: 是 | V65: 农林下/明德 | W65: 280-290之间 | X65: 孩子比较内向 | Y65: 妈妈去年有了解过我们，没有来上过课，这次第一次来体验，之前一直有补课 | Z65: 妈妈比较理性，需要看效果 | AA65: 明确需求 | AB65: 原先有了解过作业帮，但是没有来上过课，平时妈妈比较谨慎选择机构，英语数学老师都联系，语文还没联系，数学比较薄弱，在题型上还是比较生疏，语英还行，孩子文科学习比较容易拿分。这次期末没有去考试。行课座位安排不要在空调底下 小学农林下，初中在明德，3个重点班，3个非重点班，只是做了一下报道，还没进班，具体分班不明确 | AC65: 语,数,英 | AD65: 升学需求-保底本区公办高中,效果维度-提分,效果维度-抓习惯,沟通维度：老师有关注度 | AE65: 2-一般，对于目标需求一般 | AF65: 2-支付能力一般 | AG65: 2-一般 | AH65: 2-评价一般、无感 | AI65: 2-有意识无规划 | AJ65: B-8-10 | AK65: 高心怡04 | AL65: 触达 | BF65: 戎凯01 | BG65: =VLOOKUP(B65,'UV台帐'!B:G,6,0) | BH65: 明德 | BR65: =COUNTIFS(H65,"一期",I65,"在读")+COUNTIFS(L65,"一期",M65,"在读")+COUNTIFS(P65,"一期",Q65,"在读") | BS65: =BR65-BW65 | BT65: =VLOOKUP(B65,'UV台帐'!B:AL,19,0) | BU65: =VLOOKUP(B65,'UV台帐'!B:AL,28,0) | BV65: =VLOOKUP(B65,'UV台帐'!B:AL,37,0) | BW65: =COUNTIFS(H65,"一期",BT65,"是")+COUNTIFS(L65,"一期",BU65,"是")+COUNTIFS(P65,"一期",BV65,"是")
A66: 天成大厦 | B66: 4720146806 | C66: =VLOOKUP(B66,'UV台帐'!B:AL,2,0) | D66: =VLOOKUP(B66,'UV台帐'!B:AL,3,0) | E66: =VLOOKUP(B66,'UV台帐'!B:AL,13,0) | F66: =VLOOKUP(B66,'UV台帐'!B:AL,15,0) | G66: =VLOOKUP(B66,'UV台帐'!B:AL,16,0) | H66: =VLOOKUP(B66,'UV台帐'!B:AL,17,0) | I66: =VLOOKUP(B66,'UV台帐'!B:AL,18,0) | J66: =VLOOKUP(B66,'UV台帐'!B:AL,22,0) | K66: =VLOOKUP(B66,'UV台帐'!B:AL,24,0) | L66: =VLOOKUP(B66,'UV台帐'!B:AL,26,0) | M66: =VLOOKUP(B66,'UV台帐'!B:AL,27,0) | N66: =VLOOKUP(B66,'UV台帐'!B:AL,31,0) | O66: =VLOOKUP(B66,'UV台帐'!B:AL,33,0) | P66: =VLOOKUP(B66,'UV台帐'!B:AL,35,0) | Q66: =VLOOKUP(B66,'UV台帐'!B:AL,36,0) | R66: 是 | S66: S | U66: 是 | Z66: 在读老生 | AK66: 陈中帅 | BF66: 龙倩敏 | BG66: =VLOOKUP(B66,'UV台帐'!B:G,6,0) | BR66: =COUNTIFS(H66,"一期",I66,"在读")+COUNTIFS(L66,"一期",M66,"在读")+COUNTIFS(P66,"一期",Q66,"在读") | BS66: =BR66-BW66 | BT66: =VLOOKUP(B66,'UV台帐'!B:AL,19,0) | BU66: =VLOOKUP(B66,'UV台帐'!B:AL,28,0) | BV66: =VLOOKUP(B66,'UV台帐'!B:AL,37,0) | BW66: =COUNTIFS(H66,"一期",BT66,"是")+COUNTIFS(L66,"一期",BU66,"是")+COUNTIFS(P66,"一期",BV66,"是")
A67: 新宝利 | B67: 2748308649 | C67: =VLOOKUP(B67,'UV台帐'!B:AL,2,0) | D67: =VLOOKUP(B67,'UV台帐'!B:AL,3,0) | E67: =VLOOKUP(B67,'UV台帐'!B:AL,13,0) | F67: =VLOOKUP(B67,'UV台帐'!B:AL,15,0) | G67: =VLOOKUP(B67,'UV台帐'!B:AL,16,0) | H67: =VLOOKUP(B67,'UV台帐'!B:AL,17,0) | I67: =VLOOKUP(B67,'UV台帐'!B:AL,18,0) | J67: =VLOOKUP(B67,'UV台帐'!B:AL,22,0) | K67: =VLOOKUP(B67,'UV台帐'!B:AL,24,0) | L67: =VLOOKUP(B67,'UV台帐'!B:AL,26,0) | M67: =VLOOKUP(B67,'UV台帐'!B:AL,27,0) | N67: =VLOOKUP(B67,'UV台帐'!B:AL,31,0) | O67: =VLOOKUP(B67,'UV台帐'!B:AL,33,0) | P67: =VLOOKUP(B67,'UV台帐'!B:AL,35,0) | Q67: =VLOOKUP(B67,'UV台帐'!B:AL,36,0) | R67: 是 | S67: A | T67: 是 | U67: 是 | V67: 南五附属 | W67: 数90，英90 | X67: 自觉性一般，妈妈不怎么管孩子，靠孩子自己 | Y67: 住海珠，希望和韵晞卿子惠一起上课，提前做预习 | Z67: 数学春季在读老生，从来没补习过，妈妈认为补习效果是老师方法和孩子接受度2方共同协作的，问过孩子3次暑假上完要不要接着上，孩子说上完暑假再说，要看孩子接受度，因为换了老师 | AA67: 明确需求 | AB67: 春季在读老生，续了单科数学，扩科英语2期上，和周炜婷卿子惠是同学，住海珠，初中南五附属中学，从来没补过课，报名我们也是炜婷妈妈推荐的，比较关注数学和英语科目，对孩子学习不是很了解。问过孩子之后才知道数学薄弱点是选择题，填空题容易错，英语的完型填空有待提高，单词积累量不够，妈妈觉得选择一家机构主要是老师的教学方法以及孩子吸收程度双方共同配合，暑假数学换了老师孩子需要重新适应，问过三次孩子暑假学完秋季要不要接着学，孩子表示上完暑假再说，孩子比较挑老师 | AC67: 数,英 | AD67: 升学需求-保底本区公办高中,效果维度-提分,效果维度-抓习惯,效果维度-培优拓展/分班考,沟通维度：老师有个性化 | AE67: 2-一般，对于目标需求一般 | AF67: 2-支付能力一般 | AG67: 2-一般 | AH67: 3-有正面评价 | AI67: 2-有意识无规划 | AJ67: A-11-13 | AK67: 何咏04 | BF67: 张敏烨 | BG67: =VLOOKUP(B67,'UV台帐'!B:G,6,0) | BR67: =COUNTIFS(H67,"一期",I67,"在读")+COUNTIFS(L67,"一期",M67,"在读")+COUNTIFS(P67,"一期",Q67,"在读") | BS67: =BR67-BW67 | BT67: =VLOOKUP(B67,'UV台帐'!B:AL,19,0) | BU67: =VLOOKUP(B67,'UV台帐'!B:AL,28,0) | BV67: =VLOOKUP(B67,'UV台帐'!B:AL,37,0) | BW67: =COUNTIFS(H67,"一期",BT67,"是")+COUNTIFS(L67,"一期",BU67,"是")+COUNTIFS(P67,"一期",BV67,"是")
A68: 新宝利 | B68: 2780082407 | C68: =VLOOKUP(B68,'UV台帐'!B:AL,2,0) | D68: =VLOOKUP(B68,'UV台帐'!B:AL,3,0) | E68: =VLOOKUP(B68,'UV台帐'!B:AL,13,0) | F68: =VLOOKUP(B68,'UV台帐'!B:AL,15,0) | G68: =VLOOKUP(B68,'UV台帐'!B:AL,16,0) | H68: =VLOOKUP(B68,'UV台帐'!B:AL,17,0) | I68: =VLOOKUP(B68,'UV台帐'!B:AL,18,0) | J68: =VLOOKUP(B68,'UV台帐'!B:AL,22,0) | K68: =VLOOKUP(B68,'UV台帐'!B:AL,24,0) | L68: =VLOOKUP(B68,'UV台帐'!B:AL,26,0) | M68: =VLOOKUP(B68,'UV台帐'!B:AL,27,0) | N68: =VLOOKUP(B68,'UV台帐'!B:AL,31,0) | O68: =VLOOKUP(B68,'UV台帐'!B:AL,33,0) | P68: =VLOOKUP(B68,'UV台帐'!B:AL,35,0) | Q68: =VLOOKUP(B68,'UV台帐'!B:AL,36,0) | R68: 是 | S68: A | T68: 否 | U68: 是 | V68: 白云广附 | W68: 250左右 | X68: 孩子习惯比较差懒散，平时自主学习能力一般，需要老师督促，希望老师能改掉小学的懒散毛病 | Y68: 希望提高学习兴趣学习习惯，语文阅读理解，数学思维拓展，英语语法巩固，新东方渠道负责人。推荐过来亲戚，亲戚直接报了我初二物理。 | Z68: 希望提高学习兴趣学习习惯，语文阅读理解，数学思维拓展，英语语法巩固，新东方渠道负责人。推荐过来亲戚，亲戚直接报了我初二物理。 | AA68: 明确需求 | AB68: 孩子情况：语数英都是B，孩子学习动力不是很够，孩子初中靠关系进白云广附， 家长需求：希望提高学习兴趣学习习惯，语文阅读理解，数学思维拓展，英语语法巩固，都有薄弱的地方 补课规划：秋季报名要看一下时间安排，学校压力大而且不明确秋季放假是在周五还是周六。 意向判断：B，主要因为初中的住宿安排还没确定，所以秋季周末排期可能是未来的卡点，优势是有支付能力，家长本干新东方的渠道负责人，很懂得机构运营规则，之前和何咏老师沟通过，家长说不用跟我说太多，直接介绍你能给我孩子带来什么帮助。推荐过来亲戚，亲戚直接报了初二物理正价。 | AC68: 语,数,英 | AD68: 升学需求-保底本区公办高中,效果维度-提分,效果维度-抓习惯,效果维度-培优拓展/分班考,沟通维度：老师有个性化,沟通维度：老师有关注度 | AE68: 2-一般，对于目标需求一般 | AF68: 3-支付能力强 | AG68: 1-抵触 | AH68: 2-评价一般、无感 | AI68: 2-有意识无规划 | AJ68: C-小于8 | AK68: 何咏04 | AL68: 是 | BF68: 沈思浩 | BG68: =VLOOKUP(B68,'UV台帐'!B:G,6,0) | BR68: =COUNTIFS(H68,"一期",I68,"在读")+COUNTIFS(L68,"一期",M68,"在读")+COUNTIFS(P68,"一期",Q68,"在读") | BS68: =BR68-BW68 | BT68: =VLOOKUP(B68,'UV台帐'!B:AL,19,0) | BU68: =VLOOKUP(B68,'UV台帐'!B:AL,28,0) | BV68: =VLOOKUP(B68,'UV台帐'!B:AL,37,0) | BW68: =COUNTIFS(H68,"一期",BT68,"是")+COUNTIFS(L68,"一期",BU68,"是")+COUNTIFS(P68,"一期",BV68,"是")
A69: 新宝利 | B69: 2562161214 | C69: =VLOOKUP(B69,'UV台帐'!B:AL,2,0) | D69: =VLOOKUP(B69,'UV台帐'!B:AL,3,0) | E69: =VLOOKUP(B69,'UV台帐'!B:AL,13,0) | F69: =VLOOKUP(B69,'UV台帐'!B:AL,15,0) | G69: =VLOOKUP(B69,'UV台帐'!B:AL,16,0) | H69: =VLOOKUP(B69,'UV台帐'!B:AL,17,0) | I69: =VLOOKUP(B69,'UV台帐'!B:AL,18,0) | J69: =VLOOKUP(B69,'UV台帐'!B:AL,22,0) | K69: =VLOOKUP(B69,'UV台帐'!B:AL,24,0) | L69: =VLOOKUP(B69,'UV台帐'!B:AL,26,0) | M69: =VLOOKUP(B69,'UV台帐'!B:AL,27,0) | N69: =VLOOKUP(B69,'UV台帐'!B:AL,31,0) | O69: =VLOOKUP(B69,'UV台帐'!B:AL,33,0) | P69: =VLOOKUP(B69,'UV台帐'!B:AL,35,0) | Q69: =VLOOKUP(B69,'UV台帐'!B:AL,36,0) | R69: 是 | S69: B | T69: 是 | U69: 是 | V69: 东风西小学/省实越秀 | W69: 285 | X69: 孩子学习习惯良好，就是数学不太爱做草稿 | Y69: 转介绍，作业帮线上学员，考虑到初中课程难度，家长想转到线下。有长期学习的打算 | Z69: 课前有问过秋季课程，作业帮线上在读，上课时间没问题，会销现场进来，现场沟通过暑秋。 | AA69: 明确需求 | AB69: 基本情况：会销现场沟通过暑秋三科。校内基础挺好的3A。没有系统的线下补课经历，孩子没有接触过校外知识。后面家长需要让孩子先上课后再做决定（卡点通勤问题，孩子需要走过来） 需求判定：孩子有点信心不足，需要老师多提问鼓励。数学需要养成打草稿的习惯。 | AC69: 语,数 | AD69: 效果维度-抓习惯,沟通维度：老师有关注度 | AE69: 2-一般，对于目标需求一般 | AF69: 2-支付能力一般 | AG69: 2-一般 | AH69: 2-评价一般、无感 | AI69: 2-有意识无规划 | AJ69: B-8-10 | AK69: 何咏04 | AL69: 是 | BF69: 陈亮延 | BG69: =VLOOKUP(B69,'UV台帐'!B:G,6,0) | BR69: =COUNTIFS(H69,"一期",I69,"在读")+COUNTIFS(L69,"一期",M69,"在读")+COUNTIFS(P69,"一期",Q69,"在读") | BS69: =BR69-BW69 | BT69: =VLOOKUP(B69,'UV台帐'!B:AL,19,0) | BU69: =VLOOKUP(B69,'UV台帐'!B:AL,28,0) | BV69: =VLOOKUP(B69,'UV台帐'!B:AL,37,0) | BW69: =COUNTIFS(H69,"一期",BT69,"是")+COUNTIFS(L69,"一期",BU69,"是")+COUNTIFS(P69,"一期",BV69,"是")
A70: 新宝利 | B70: 2284879023 | C70: =VLOOKUP(B70,'UV台帐'!B:AL,2,0) | D70: =VLOOKUP(B70,'UV台帐'!B:AL,3,0) | E70: =VLOOKUP(B70,'UV台帐'!B:AL,13,0) | F70: =VLOOKUP(B70,'UV台帐'!B:AL,15,0) | G70: =VLOOKUP(B70,'UV台帐'!B:AL,16,0) | H70: =VLOOKUP(B70,'UV台帐'!B:AL,17,0) | I70: =VLOOKUP(B70,'UV台帐'!B:AL,18,0) | J70: =VLOOKUP(B70,'UV台帐'!B:AL,22,0) | K70: =VLOOKUP(B70,'UV台帐'!B:AL,24,0) | L70: =VLOOKUP(B70,'UV台帐'!B:AL,26,0) | M70: =VLOOKUP(B70,'UV台帐'!B:AL,27,0) | N70: =VLOOKUP(B70,'UV台帐'!B:AL,31,0) | O70: =VLOOKUP(B70,'UV台帐'!B:AL,33,0) | P70: =VLOOKUP(B70,'UV台帐'!B:AL,35,0) | Q70: =VLOOKUP(B70,'UV台帐'!B:AL,36,0) | R70: 是 | S70: A | T70: 是 | U70: 是 | V70: 海珠中路、七中实验重点班，择班到重A，高中目标七中本部 | W70: 295 | X70: 孩子是学校班长，大队长，学习习惯很好 | Y70: 想要孩子提前学初中的内容，目标高中（全校前50可进七中本部）七中本部，目前在七中实验重点班（重点班2个班孩子在A班） | Z70: 会销进来，考了课前诊断；现场给了暑秋价格；有长期学规划，目标校内前50，偏向理科多一些，数学英语，主要爸爸抓学习 | AA70: 明确需求 | AB70: 孩子在学校是班长和大队长，衔接初中学科，现在校内成绩290-295，目前没有学科短板；目标高中（全校前50可进七中本部）七中本部，目前在七中实验重点班（重点班2个班孩子在A班），校内已经同步校内前50可以进，孩子爸爸关注学科重要程度数学＞英语＞语文 | AC70: 数,英 | AD70: 升学需求-保底本区公办高中 | AE70: 2-一般，对于目标需求一般 | AF70: 3-支付能力强 | AG70: 2-一般 | AH70: 2-评价一般、无感 | AI70: 2-有意识无规划 | AJ70: A-11-13 | AK70: 何咏04 | AL70: 是 | BF70: 王达04 | BG70: =VLOOKUP(B70,'UV台帐'!B:G,6,0) | BR70: =COUNTIFS(H70,"一期",I70,"在读")+COUNTIFS(L70,"一期",M70,"在读")+COUNTIFS(P70,"一期",Q70,"在读") | BS70: =BR70-BW70 | BT70: =VLOOKUP(B70,'UV台帐'!B:AL,19,0) | BU70: =VLOOKUP(B70,'UV台帐'!B:AL,28,0) | BV70: =VLOOKUP(B70,'UV台帐'!B:AL,37,0) | BW70: =COUNTIFS(H70,"一期",BT70,"是")+COUNTIFS(L70,"一期",BU70,"是")+COUNTIFS(P70,"一期",BV70,"是")
A71: 新宝利 | B71: 4823986037 | C71: =VLOOKUP(B71,'UV台帐'!B:AL,2,0) | D71: =VLOOKUP(B71,'UV台帐'!B:AL,3,0) | E71: =VLOOKUP(B71,'UV台帐'!B:AL,13,0) | F71: =VLOOKUP(B71,'UV台帐'!B:AL,15,0) | G71: =VLOOKUP(B71,'UV台帐'!B:AL,16,0) | H71: =VLOOKUP(B71,'UV台帐'!B:AL,17,0) | I71: =VLOOKUP(B71,'UV台帐'!B:AL,18,0) | J71: =VLOOKUP(B71,'UV台帐'!B:AL,22,0) | K71: =VLOOKUP(B71,'UV台帐'!B:AL,24,0) | L71: =VLOOKUP(B71,'UV台帐'!B:AL,26,0) | M71: =VLOOKUP(B71,'UV台帐'!B:AL,27,0) | N71: =VLOOKUP(B71,'UV台帐'!B:AL,31,0) | O71: =VLOOKUP(B71,'UV台帐'!B:AL,33,0) | P71: =VLOOKUP(B71,'UV台帐'!B:AL,35,0) | Q71: =VLOOKUP(B71,'UV台帐'!B:AL,36,0) | R71: 是 | S71: A | T71: 是 | U71: 是 | V71: 海印实验 | W71: 数95，英96，语94 | X71: 孩子吸收很快，自觉性很高 | Y71: 从没补过课，希望暑假孩子提前学点进入初中可以提前适应 | Z71: 没有补习经历，知道秋季价格，有打算长期学，看孩子意愿度。A，线下沟通，家长了解知道价格。何咏老师线下聊过，爸爸说秋季需要配合的直接说 | AA71: 明确需求 | AB71: 和林钰琪是好朋友，从未补过课，孩子学习习惯很好，家长不需要操心，作业都是自己搞定的，性格比较内向，熟了之后能聊得来，比较听话的类型，初中花钱去了海印实验，何咏老师和爸爸面聊过，比较关注数学科目，高中目标是一梯队的学校，家长觉得小学成绩没啥问题了，期末数学考了100分，期望学些拓展知识，能去到重点班，家长表示后续需要长期学可以跟他讲，全力配合，还可以协调时间，爸爸是中大毕业的，比较高知，已经在给孩子预习过语文英语了，初中数学理科强 | AC71: 数,英 | AD71: 升学需求-进九大or中上,效果维度-培优拓展/分班考 | AE71: 3-非常紧迫，有短期目标和长期需求 | AF71: 2-支付能力一般 | AG71: 2-一般 | AH71: 3-有正面评价 | AI71: 3-有规划有意识 | AJ71: S-14-15 | AK71: 何咏04 | AL71: 是 | BF71: 张敏烨 | BG71: =VLOOKUP(B71,'UV台帐'!B:G,6,0) | BH71: 3中实验 | BR71: =COUNTIFS(H71,"一期",I71,"在读")+COUNTIFS(L71,"一期",M71,"在读")+COUNTIFS(P71,"一期",Q71,"在读") | BS71: =BR71-BW71 | BT71: =VLOOKUP(B71,'UV台帐'!B:AL,19,0) | BU71: =VLOOKUP(B71,'UV台帐'!B:AL,28,0) | BV71: =VLOOKUP(B71,'UV台帐'!B:AL,37,0) | BW71: =COUNTIFS(H71,"一期",BT71,"是")+COUNTIFS(L71,"一期",BU71,"是")+COUNTIFS(P71,"一期",BV71,"是")
A72: 同创汇 | B72: 2946163107 | C72: =VLOOKUP(B72,'UV台帐'!B:AL,2,0) | D72: =VLOOKUP(B72,'UV台帐'!B:AL,3,0) | E72: =VLOOKUP(B72,'UV台帐'!B:AL,13,0) | F72: =VLOOKUP(B72,'UV台帐'!B:AL,15,0) | G72: =VLOOKUP(B72,'UV台帐'!B:AL,16,0) | H72: =VLOOKUP(B72,'UV台帐'!B:AL,17,0) | I72: =VLOOKUP(B72,'UV台帐'!B:AL,18,0) | J72: =VLOOKUP(B72,'UV台帐'!B:AL,22,0) | K72: =VLOOKUP(B72,'UV台帐'!B:AL,24,0) | L72: =VLOOKUP(B72,'UV台帐'!B:AL,26,0) | M72: =VLOOKUP(B72,'UV台帐'!B:AL,27,0) | N72: =VLOOKUP(B72,'UV台帐'!B:AL,31,0) | O72: =VLOOKUP(B72,'UV台帐'!B:AL,33,0) | P72: =VLOOKUP(B72,'UV台帐'!B:AL,35,0) | Q72: =VLOOKUP(B72,'UV台帐'!B:AL,36,0) | R72: 是 | S72: S | U72: 否 | Y72: 在读老生，目前只有英语没报名，上完课以后可以报 | Z72: 语数秋季已经报名 | AA72: 明确需求 | AB72: 在读老生，扩科英语，爸妈都有教育意识和支付能力，需要告知学生明确的初中学习难度和学习方法 | AC72: 英 | AD72: 升学需求-保底本区公办高中,效果维度-培优拓展/分班考,沟通维度：老师有个性化,沟通维度：老师有关注度 | AE72: 3-非常紧迫，有短期目标和长期需求 | AF72: 3-支付能力强 | AG72: 2-一般 | AH72: 3-有正面评价 | AI72: 3-有规划有意识 | AJ72: S-14-15 | AK72: 高心怡04 | AL72: 是 | BF72: 戎凯01 | BG72: =VLOOKUP(B72,'UV台帐'!B:G,6,0) | BR72: =COUNTIFS(H72,"一期",I72,"在读")+COUNTIFS(L72,"一期",M72,"在读")+COUNTIFS(P72,"一期",Q72,"在读") | BS72: =BR72-BW72 | BT72: =VLOOKUP(B72,'UV台帐'!B:AL,19,0) | BU72: =VLOOKUP(B72,'UV台帐'!B:AL,28,0) | BV72: =VLOOKUP(B72,'UV台帐'!B:AL,37,0) | BW72: =COUNTIFS(H72,"一期",BT72,"是")+COUNTIFS(L72,"一期",BU72,"是")+COUNTIFS(P72,"一期",BV72,"是")
A73: 同创汇 | B73: 2731869099 | C73: =VLOOKUP(B73,'UV台帐'!B:AL,2,0) | D73: =VLOOKUP(B73,'UV台帐'!B:AL,3,0) | E73: =VLOOKUP(B73,'UV台帐'!B:AL,13,0) | F73: =VLOOKUP(B73,'UV台帐'!B:AL,15,0) | G73: =VLOOKUP(B73,'UV台帐'!B:AL,16,0) | H73: =VLOOKUP(B73,'UV台帐'!B:AL,17,0) | I73: =VLOOKUP(B73,'UV台帐'!B:AL,18,0) | J73: =VLOOKUP(B73,'UV台帐'!B:AL,22,0) | K73: =VLOOKUP(B73,'UV台帐'!B:AL,24,0) | L73: =VLOOKUP(B73,'UV台帐'!B:AL,26,0) | M73: =VLOOKUP(B73,'UV台帐'!B:AL,27,0) | N73: =VLOOKUP(B73,'UV台帐'!B:AL,31,0) | O73: =VLOOKUP(B73,'UV台帐'!B:AL,33,0) | P73: =VLOOKUP(B73,'UV台帐'!B:AL,35,0) | Q73: =VLOOKUP(B73,'UV台帐'!B:AL,36,0) | R73: 是 | S73: S | U73: 是 | Y73: 三科已经报名 | Z73: 语数英三科秋季已经报名 | AB73: 语数英三科秋季已经报名 | AK73: 高心怡04 | AL73: 是 | BF73: 戎凯01 | BG73: =VLOOKUP(B73,'UV台帐'!B:G,6,0) | BR73: =COUNTIFS(H73,"一期",I73,"在读")+COUNTIFS(L73,"一期",M73,"在读")+COUNTIFS(P73,"一期",Q73,"在读") | BS73: =BR73-BW73 | BT73: =VLOOKUP(B73,'UV台帐'!B:AL,19,0) | BU73: =VLOOKUP(B73,'UV台帐'!B:AL,28,0) | BV73: =VLOOKUP(B73,'UV台帐'!B:AL,37,0) | BW73: =COUNTIFS(H73,"一期",BT73,"是")+COUNTIFS(L73,"一期",BU73,"是")+COUNTIFS(P73,"一期",BV73,"是")
A74: 新宝利 | B74: 2408937171 | C74: =VLOOKUP(B74,'UV台帐'!B:AL,2,0) | D74: =VLOOKUP(B74,'UV台帐'!B:AL,3,0) | E74: =VLOOKUP(B74,'UV台帐'!B:AL,13,0) | F74: =VLOOKUP(B74,'UV台帐'!B:AL,15,0) | G74: =VLOOKUP(B74,'UV台帐'!B:AL,16,0) | H74: =VLOOKUP(B74,'UV台帐'!B:AL,17,0) | I74: =VLOOKUP(B74,'UV台帐'!B:AL,18,0) | J74: =VLOOKUP(B74,'UV台帐'!B:AL,22,0) | K74: =VLOOKUP(B74,'UV台帐'!B:AL,24,0) | L74: =VLOOKUP(B74,'UV台帐'!B:AL,26,0) | M74: =VLOOKUP(B74,'UV台帐'!B:AL,27,0) | N74: =VLOOKUP(B74,'UV台帐'!B:AL,31,0) | O74: =VLOOKUP(B74,'UV台帐'!B:AL,33,0) | P74: =VLOOKUP(B74,'UV台帐'!B:AL,35,0) | Q74: =VLOOKUP(B74,'UV台帐'!B:AL,36,0) | R74: 是 | S74: C | T74: 否 | U74: 否 | V74: 番禺直升 | W74: 数95，英91，语90.5 | Y74: 一般寒暑假会提前学 | Z74: 不接，番禺直升，概率考虑暑假。C；只上寒暑短期课程，早上7:50的课也是能接受的。线上收单，端内资源。 | AA74: 明确需求 | AB74: 家长电话是不接的，线上留言过，学习靠孩子自己，希望老师严格点，字词基础薄弱，爱打游戏，电子设备管的不多，语文是最弱科目，阅读很少，素材积累不多，暑假住江南西，秋季搬回番禺。番禺直升。有住宿，一般寒暑假会提前学做个预习，数学在三科中是比较好的，关注语文科目，英语有学过ket内容，孩子是比较调皮的，偶尔会走神，需要老师多互动下，妈妈比较冷淡 | AC74: 数 | AD74: 效果维度-提分,效果维度-抓习惯 | AE74: 2-一般，对于目标需求一般 | AF74: 2-支付能力一般 | AG74: 2-一般 | AH74: 2-评价一般、无感 | AI74: 1-无意识无规划 | AJ74: C-小于8 | AK74: 何咏04 | BF74: 张敏烨 | BG74: =VLOOKUP(B74,'UV台帐'!B:G,6,0) | BR74: =COUNTIFS(H74,"一期",I74,"在读")+COUNTIFS(L74,"一期",M74,"在读")+COUNTIFS(P74,"一期",Q74,"在读") | BS74: =BR74-BW74 | BT74: =VLOOKUP(B74,'UV台帐'!B:AL,19,0) | BU74: =VLOOKUP(B74,'UV台帐'!B:AL,28,0) | BV74: =VLOOKUP(B74,'UV台帐'!B:AL,37,0) | BW74: =COUNTIFS(H74,"一期",BT74,"是")+COUNTIFS(L74,"一期",BU74,"是")+COUNTIFS(P74,"一期",BV74,"是")
A75: 新宝利 | B75: 4384813412 | C75: =VLOOKUP(B75,'UV台帐'!B:AL,2,0) | D75: =VLOOKUP(B75,'UV台帐'!B:AL,3,0) | E75: =VLOOKUP(B75,'UV台帐'!B:AL,13,0) | F75: =VLOOKUP(B75,'UV台帐'!B:AL,15,0) | G75: =VLOOKUP(B75,'UV台帐'!B:AL,16,0) | H75: =VLOOKUP(B75,'UV台帐'!B:AL,17,0) | I75: =VLOOKUP(B75,'UV台帐'!B:AL,18,0) | J75: =VLOOKUP(B75,'UV台帐'!B:AL,22,0) | K75: =VLOOKUP(B75,'UV台帐'!B:AL,24,0) | L75: =VLOOKUP(B75,'UV台帐'!B:AL,26,0) | M75: =VLOOKUP(B75,'UV台帐'!B:AL,27,0) | N75: =VLOOKUP(B75,'UV台帐'!B:AL,31,0) | O75: =VLOOKUP(B75,'UV台帐'!B:AL,33,0) | P75: =VLOOKUP(B75,'UV台帐'!B:AL,35,0) | Q75: =VLOOKUP(B75,'UV台帐'!B:AL,36,0) | R75: 是 | S75: B | T75: 是 | U75: 是 | V75: 建设大马路,13中 | W75: AAB | X75: 书写不好 ，不自觉，做题不圈画重点，阅读/语法较差 | Y75: 讲座转化，知道线上作业帮 | Z75: 建设大马路小学的，摇到13中，数学英语无拓展，学武术有武术奖项，之前一直在作业帮线上学 | AA75: 明确需求 | AB75: 孩子成绩一般，摇中13中，目标普高，孩子学习不够自觉，容易偷懒，需要老师多督促，老师们可以严厉一些。之前报名的是作业帮线上课，第一次来线下上课，会存在对比的情况。爸爸来听过讲座，对于初中学习难度认识还需要加强，比如数学计算量的增大，英语语法的学习。孩子需要在新初一养成好的习惯，确保能顺利升入普高，课后首通需要告知家长普高往年分数线，再下一次危机 | AC75: 语,数,英 | AD75: 升学需求-保底本区公办高中,效果维度-提分,效果维度-抓习惯,沟通维度：老师有关注度 | AE75: 2-一般，对于目标需求一般 | AF75: 2-支付能力一般 | AG75: 2-一般 | AH75: 2-评价一般、无感 | AI75: 2-有意识无规划 | AJ75: B-8-10 | AK75: 何咏04 | AL75: 是 | BF75: 王丽 | BG75: =VLOOKUP(B75,'UV台帐'!B:G,6,0) | BH75: 十三中 | BR75: =COUNTIFS(H75,"一期",I75,"在读")+COUNTIFS(L75,"一期",M75,"在读")+COUNTIFS(P75,"一期",Q75,"在读") | BS75: =BR75-BW75 | BT75: =VLOOKUP(B75,'UV台帐'!B:AL,19,0) | BU75: =VLOOKUP(B75,'UV台帐'!B:AL,28,0) | BV75: =VLOOKUP(B75,'UV台帐'!B:AL,37,0) | BW75: =COUNTIFS(H75,"一期",BT75,"是")+COUNTIFS(L75,"一期",BU75,"是")+COUNTIFS(P75,"一期",BV75,"是")
A76: 同创汇 | B76: 4481410838 | C76: =VLOOKUP(B76,'UV台帐'!B:AL,2,0) | D76: =VLOOKUP(B76,'UV台帐'!B:AL,3,0) | E76: =VLOOKUP(B76,'UV台帐'!B:AL,13,0) | F76: =VLOOKUP(B76,'UV台帐'!B:AL,15,0) | G76: =VLOOKUP(B76,'UV台帐'!B:AL,16,0) | H76: =VLOOKUP(B76,'UV台帐'!B:AL,17,0) | I76: =VLOOKUP(B76,'UV台帐'!B:AL,18,0) | J76: =VLOOKUP(B76,'UV台帐'!B:AL,22,0) | K76: =VLOOKUP(B76,'UV台帐'!B:AL,24,0) | L76: =VLOOKUP(B76,'UV台帐'!B:AL,26,0) | M76: =VLOOKUP(B76,'UV台帐'!B:AL,27,0) | N76: =VLOOKUP(B76,'UV台帐'!B:AL,31,0) | O76: =VLOOKUP(B76,'UV台帐'!B:AL,33,0) | P76: =VLOOKUP(B76,'UV台帐'!B:AL,35,0) | Q76: =VLOOKUP(B76,'UV台帐'!B:AL,36,0) | R76: 是 | S76: A | T76: 是 | U76: 是 | V76: 育才，16中 | W76: 校内90+ | X76: 语文阅读较弱，数学程度还可以，没有拓展 | Y76: 讲座转化，知道线上作业帮 | Z76: 孩子爸爸接的，把爸妈都拉进群 | AA76: 明确需求 | AB76: 孩子写字需要加强，数学作业要写清楚步骤，孩子喜欢跳步骤，需要老师多关注下。家长也希望老师可以及时反馈孩子的课堂情况 | AC76: 语,数,英 | AD76: 效果维度-抓习惯,沟通维度：老师有个性化,沟通维度：老师有关注度 | AE76: 2-一般，对于目标需求一般 | AF76: 3-支付能力强 | AG76: 2-一般 | AH76: 2-评价一般、无感 | AI76: 2-有意识无规划 | AJ76: A-11-13 | AK76: 高心怡04 | AL76: 是 | BF76: 王丽 | BG76: =VLOOKUP(B76,'UV台帐'!B:G,6,0) | BR76: =COUNTIFS(H76,"一期",I76,"在读")+COUNTIFS(L76,"一期",M76,"在读")+COUNTIFS(P76,"一期",Q76,"在读") | BS76: =BR76-BW76 | BT76: =VLOOKUP(B76,'UV台帐'!B:AL,19,0) | BU76: =VLOOKUP(B76,'UV台帐'!B:AL,28,0) | BV76: =VLOOKUP(B76,'UV台帐'!B:AL,37,0) | BW76: =COUNTIFS(H76,"一期",BT76,"是")+COUNTIFS(L76,"一期",BU76,"是")+COUNTIFS(P76,"一期",BV76,"是")
A77: 新宝利 | B77: 4825766381 | C77: =VLOOKUP(B77,'UV台帐'!B:AL,2,0) | D77: =VLOOKUP(B77,'UV台帐'!B:AL,3,0) | E77: =VLOOKUP(B77,'UV台帐'!B:AL,13,0) | F77: =VLOOKUP(B77,'UV台帐'!B:AL,15,0) | G77: =VLOOKUP(B77,'UV台帐'!B:AL,16,0) | H77: =VLOOKUP(B77,'UV台帐'!B:AL,17,0) | I77: =VLOOKUP(B77,'UV台帐'!B:AL,18,0) | J77: =VLOOKUP(B77,'UV台帐'!B:AL,22,0) | K77: =VLOOKUP(B77,'UV台帐'!B:AL,24,0) | L77: =VLOOKUP(B77,'UV台帐'!B:AL,26,0) | M77: =VLOOKUP(B77,'UV台帐'!B:AL,27,0) | N77: =VLOOKUP(B77,'UV台帐'!B:AL,31,0) | O77: =VLOOKUP(B77,'UV台帐'!B:AL,33,0) | P77: =VLOOKUP(B77,'UV台帐'!B:AL,35,0) | Q77: =VLOOKUP(B77,'UV台帐'!B:AL,36,0) | R77: 是 | S77: A | T77: 是 | U77: 是 | V77: 西菜 | W77: 95+ | X77: 专心，不爱问 | Y77: 过度初一，女孩子理科思维怕跟不上初中 | Z77: 看孩子接受程度，之前在学而思学过，有正价补习经历，孩子会挑老师的授课风格，家长有规划长期学习。A，做过线下诊断 | AA77: 明确需求 | AB77: 家长主动说的，孩子数学思维弱，初中想提升中难度及压轴题的解题思维，以往学而思在读，所以证明支付能力不差，西彩的重点班，怕拖后腿所以选择暑假报名单科，孩子几何题掌握较弱，计算能力不错。只要孩子愿意跟着老师学，喜欢老师，并且确实能够在日常学习中反馈到孩子的进步，家长有意愿并且有能力转化。爸爸是房产经纪的团队长，时间较为充裕，收入不错。 | AC77: 数 | AD77: 效果维度-提分,效果维度-抓习惯,沟通维度：老师有个性化,沟通维度：老师有关注度 | AE77: 2-一般，对于目标需求一般 | AF77: 2-支付能力一般 | AG77: 2-一般 | AH77: 3-有正面评价 | AI77: 3-有规划有意识 | AJ77: A-11-13 | AK77: 何咏04 | AL77: 是 | BF77: 林志豪01 | BG77: =VLOOKUP(B77,'UV台帐'!B:G,6,0) | BH77: 彩虹桥 | BR77: =COUNTIFS(H77,"一期",I77,"在读")+COUNTIFS(L77,"一期",M77,"在读")+COUNTIFS(P77,"一期",Q77,"在读") | BS77: =BR77-BW77 | BT77: =VLOOKUP(B77,'UV台帐'!B:AL,19,0) | BU77: =VLOOKUP(B77,'UV台帐'!B:AL,28,0) | BV77: =VLOOKUP(B77,'UV台帐'!B:AL,37,0) | BW77: =COUNTIFS(H77,"一期",BT77,"是")+COUNTIFS(L77,"一期",BU77,"是")+COUNTIFS(P77,"一期",BV77,"是")
A78: 新宝利 | B78: 2112208710 | C78: =VLOOKUP(B78,'UV台帐'!B:AL,2,0) | D78: =VLOOKUP(B78,'UV台帐'!B:AL,3,0) | E78: =VLOOKUP(B78,'UV台帐'!B:AL,13,0) | F78: =VLOOKUP(B78,'UV台帐'!B:AL,15,0) | G78: =VLOOKUP(B78,'UV台帐'!B:AL,16,0) | H78: =VLOOKUP(B78,'UV台帐'!B:AL,17,0) | I78: =VLOOKUP(B78,'UV台帐'!B:AL,18,0) | J78: =VLOOKUP(B78,'UV台帐'!B:AL,22,0) | K78: =VLOOKUP(B78,'UV台帐'!B:AL,24,0) | L78: =VLOOKUP(B78,'UV台帐'!B:AL,26,0) | M78: =VLOOKUP(B78,'UV台帐'!B:AL,27,0) | N78: =VLOOKUP(B78,'UV台帐'!B:AL,31,0) | O78: =VLOOKUP(B78,'UV台帐'!B:AL,33,0) | P78: =VLOOKUP(B78,'UV台帐'!B:AL,35,0) | Q78: =VLOOKUP(B78,'UV台帐'!B:AL,36,0) | R78: 是 | S78: S | T78: 是 | U78: 否 | W78: 英82，数90，语85 | X78: 孩子懒，对英会比较抵触 | Y78: 对孩子期望值比较高，只要孩子愿意学，秋季报名没问题 | Z78: 语文复习课体验感很好，妈妈说只要孩子愿意上，秋季续报是没问题的。S，陈楠老师的体验课。数学暑秋连报，英语在2期。 | AA78: 明确需求 | AB78: 三科都挺薄弱，怕孩子初中跟不上，数学已经续报，知道秋季价格，妈妈表示只要孩子愿意学，秋季报名是没问题的，孩子比较拘谨，之前一直是线上用户，上过陈南的期末复习课，孩子感受非常棒，英语在二期 | AC78: 语,英 | AD78: 效果维度-提分,效果维度-抓习惯,沟通维度：老师有个性化,沟通维度：老师有关注度 | AE78: 3-非常紧迫，有短期目标和长期需求 | AF78: 3-支付能力强 | AG78: 2-一般 | AH78: 3-有正面评价 | AI78: 3-有规划有意识 | AJ78: S-14-15 | AK78: 何咏04 | BF78: 张敏烨 | BG78: =VLOOKUP(B78,'UV台帐'!B:G,6,0) | BR78: =COUNTIFS(H78,"一期",I78,"在读")+COUNTIFS(L78,"一期",M78,"在读")+COUNTIFS(P78,"一期",Q78,"在读") | BS78: =BR78-BW78 | BT78: =VLOOKUP(B78,'UV台帐'!B:AL,19,0) | BU78: =VLOOKUP(B78,'UV台帐'!B:AL,28,0) | BV78: =VLOOKUP(B78,'UV台帐'!B:AL,37,0) | BW78: =COUNTIFS(H78,"一期",BT78,"是")+COUNTIFS(L78,"一期",BU78,"是")+COUNTIFS(P78,"一期",BV78,"是")
A79: 天成大厦 | B79: 4218384525 | C79: =VLOOKUP(B79,'UV台帐'!B:AL,2,0) | D79: =VLOOKUP(B79,'UV台帐'!B:AL,3,0) | E79: =VLOOKUP(B79,'UV台帐'!B:AL,13,0) | F79: =VLOOKUP(B79,'UV台帐'!B:AL,15,0) | G79: =VLOOKUP(B79,'UV台帐'!B:AL,16,0) | H79: =VLOOKUP(B79,'UV台帐'!B:AL,17,0) | I79: =VLOOKUP(B79,'UV台帐'!B:AL,18,0) | J79: =VLOOKUP(B79,'UV台帐'!B:AL,22,0) | K79: =VLOOKUP(B79,'UV台帐'!B:AL,24,0) | L79: =VLOOKUP(B79,'UV台帐'!B:AL,26,0) | M79: =VLOOKUP(B79,'UV台帐'!B:AL,27,0) | N79: =VLOOKUP(B79,'UV台帐'!B:AL,31,0) | O79: =VLOOKUP(B79,'UV台帐'!B:AL,33,0) | P79: =VLOOKUP(B79,'UV台帐'!B:AL,35,0) | Q79: =VLOOKUP(B79,'UV台帐'!B:AL,36,0) | R79: 是 | S79: B | T79: 否 | U79: 是 | V79: 中学清湾，高中目标省实 | W79: 语90+数90+英90+ | X79: 专注度不够，粗心 | Y79: 学习态度改观，学习笔记工整，多提问孩子孩子易走神 | Z79: 诉求：对孩子要求学习态度改观，学习笔记工整，多提问孩子孩子易走神，孩子课堂内容课堂完成不想让孩子带回家，回家做作业孩子很被动，之前有在线上学过，但是到初中妈妈想让孩子到线下，有氛围有监督，目标高中省实 | AA79: 明确需求 | AB79: 对孩子要求学习态度改观，学习笔记工整，多提问孩子孩子易走神，孩子课堂内容课堂完成不想让孩子带回家（当堂完成，校区完成），回家做作业孩子很被动，之前有在线上学过，但是到初中妈妈想让孩子到线下，有氛围有监督， 目前中学：清湾附中，说只分了行政班，开学后会测试分层，关注分班测。学校侧重点数英。 目标高中省实 | AC79: 语,数,英 | AD79: 升学需求-保底本区公办高中,效果维度-抓习惯,沟通维度：老师有个性化 | AE79: 2-一般，对于目标需求一般 | AF79: 2-支付能力一般 | AG79: 2-一般 | AH79: 2-评价一般、无感 | AI79: 2-有意识无规划 | AJ79: B-8-10 | AK79: 刘希子 | AL79: 是 | BF79: 王达04 | BG79: =VLOOKUP(B79,'UV台帐'!B:G,6,0) | BR79: =COUNTIFS(H79,"一期",I79,"在读")+COUNTIFS(L79,"一期",M79,"在读")+COUNTIFS(P79,"一期",Q79,"在读") | BS79: =BR79-BW79 | BT79: =VLOOKUP(B79,'UV台帐'!B:AL,19,0) | BU79: =VLOOKUP(B79,'UV台帐'!B:AL,28,0) | BV79: =VLOOKUP(B79,'UV台帐'!B:AL,37,0) | BW79: =COUNTIFS(H79,"一期",BT79,"是")+COUNTIFS(L79,"一期",BU79,"是")+COUNTIFS(P79,"一期",BV79,"是")
A80: 新宝利 | B80: 2580537342 | C80: =VLOOKUP(B80,'UV台帐'!B:AL,2,0) | D80: =VLOOKUP(B80,'UV台帐'!B:AL,3,0) | E80: =VLOOKUP(B80,'UV台帐'!B:AL,13,0) | F80: =VLOOKUP(B80,'UV台帐'!B:AL,15,0) | G80: =VLOOKUP(B80,'UV台帐'!B:AL,16,0) | H80: =VLOOKUP(B80,'UV台帐'!B:AL,17,0) | I80: =VLOOKUP(B80,'UV台帐'!B:AL,18,0) | J80: =VLOOKUP(B80,'UV台帐'!B:AL,22,0) | K80: =VLOOKUP(B80,'UV台帐'!B:AL,24,0) | L80: =VLOOKUP(B80,'UV台帐'!B:AL,26,0) | M80: =VLOOKUP(B80,'UV台帐'!B:AL,27,0) | N80: =VLOOKUP(B80,'UV台帐'!B:AL,31,0) | O80: =VLOOKUP(B80,'UV台帐'!B:AL,33,0) | P80: =VLOOKUP(B80,'UV台帐'!B:AL,35,0) | Q80: =VLOOKUP(B80,'UV台帐'!B:AL,36,0) | R80: 是 | S80: A | T80: 是 | U80: 是 | V80: 西雅大坦沙 | W80: 3A | X80: 一般 | Y80: 小升初衔接 | Z80: 讲座现场报名，西雅大坦沙，学校学习压力还是有的，有危机感。教育理念还可以。A | AA80: 明确需求 | AB80: 妈妈诉求考上高中，孩子在班级里面能跟得上，初中西雅大坦沙学校，妈妈觉得学习压力还是有的，有升学的危机感。学科上妈妈对孩子具体的薄弱点了解不是很清楚，意思让老师通过暑假课去关注孩子具体的问题，再看情况去解决。【外化习惯上的效果变化，围绕孩子意愿提升做功】 | AC80: 语,数 | AD80: 升学需求-保底本区公办高中,效果维度-培优拓展/分班考 | AE80: 3-非常紧迫，有短期目标和长期需求 | AF80: 3-支付能力强 | AG80: 2-一般 | AH80: 2-评价一般、无感 | AI80: 3-有规划有意识 | AJ80: A-11-13 | AK80: 何咏04 | AL80: 是 | BF80: 杨林33 | BG80: =VLOOKUP(B80,'UV台帐'!B:G,6,0) | BR80: =COUNTIFS(H80,"一期",I80,"在读")+COUNTIFS(L80,"一期",M80,"在读")+COUNTIFS(P80,"一期",Q80,"在读") | BS80: =BR80-BW80 | BT80: =VLOOKUP(B80,'UV台帐'!B:AL,19,0) | BU80: =VLOOKUP(B80,'UV台帐'!B:AL,28,0) | BV80: =VLOOKUP(B80,'UV台帐'!B:AL,37,0) | BW80: =COUNTIFS(H80,"一期",BT80,"是")+COUNTIFS(L80,"一期",BU80,"是")+COUNTIFS(P80,"一期",BV80,"是")
A81: 天成大厦 | B81: 4397457478 | C81: =VLOOKUP(B81,'UV台帐'!B:AL,2,0) | D81: =VLOOKUP(B81,'UV台帐'!B:AL,3,0) | E81: =VLOOKUP(B81,'UV台帐'!B:AL,13,0) | F81: =VLOOKUP(B81,'UV台帐'!B:AL,15,0) | G81: =VLOOKUP(B81,'UV台帐'!B:AL,16,0) | H81: =VLOOKUP(B81,'UV台帐'!B:AL,17,0) | I81: =VLOOKUP(B81,'UV台帐'!B:AL,18,0) | J81: =VLOOKUP(B81,'UV台帐'!B:AL,22,0) | K81: =VLOOKUP(B81,'UV台帐'!B:AL,24,0) | L81: =VLOOKUP(B81,'UV台帐'!B:AL,26,0) | M81: =VLOOKUP(B81,'UV台帐'!B:AL,27,0) | N81: =VLOOKUP(B81,'UV台帐'!B:AL,31,0) | O81: =VLOOKUP(B81,'UV台帐'!B:AL,33,0) | P81: =VLOOKUP(B81,'UV台帐'!B:AL,35,0) | Q81: =VLOOKUP(B81,'UV台帐'!B:AL,36,0) | R81: 是 | S81: A | U81: 是 | V81: 广中 | W81: 240左右 | X81: 学习习惯比较差，断保老生，小宝在咱们学正价 | Y81: 加强分班测 | Z81: 没问题正常上课；姐姐是正价学员。 | AA81: 明确需求 | AB81: 孩子情况：广中240左右，学习习惯比较差，断保老生， 小宝在咱们学正价，没问题正常上课;妹妹是正价学员。英语80+数学90+，孩子英语语法非常薄弱，单词也非常的差，在56年级妈妈开始抓才开始提升 需求:注意孩子上课的注意力专注度、多鼓励孩子、孩子有点叛逆(关注孩子下午英语课到课情况，孩子中午在校区) 补课经历:有长期学习规划，孩子小学一直在 卓越上数学，因为老师不交初中才选择换机构，妈妈在外面不方便沟通 | AC81: 数 | AD81: 效果维度-提分,效果维度-抓习惯,沟通维度：老师有个性化,沟通维度：老师有关注度 | AE81: 2-一般，对于目标需求一般 | AF81: 2-支付能力一般 | AG81: 2-一般 | AH81: 2-评价一般、无感 | AI81: 2-有意识无规划 | AJ81: B-8-10 | AK81: 陈中帅 | AL81: 是 | BF81: 沈思浩 | BG81: =VLOOKUP(B81,'UV台帐'!B:G,6,0) | BR81: =COUNTIFS(H81,"一期",I81,"在读")+COUNTIFS(L81,"一期",M81,"在读")+COUNTIFS(P81,"一期",Q81,"在读") | BS81: =BR81-BW81 | BT81: =VLOOKUP(B81,'UV台帐'!B:AL,19,0) | BU81: =VLOOKUP(B81,'UV台帐'!B:AL,28,0) | BV81: =VLOOKUP(B81,'UV台帐'!B:AL,37,0) | BW81: =COUNTIFS(H81,"一期",BT81,"是")+COUNTIFS(L81,"一期",BU81,"是")+COUNTIFS(P81,"一期",BV81,"是")
A82: 天成大厦 | B82: 4129826988 | C82: =VLOOKUP(B82,'UV台帐'!B:AL,2,0) | D82: =VLOOKUP(B82,'UV台帐'!B:AL,3,0) | E82: =VLOOKUP(B82,'UV台帐'!B:AL,13,0) | F82: =VLOOKUP(B82,'UV台帐'!B:AL,15,0) | G82: =VLOOKUP(B82,'UV台帐'!B:AL,16,0) | H82: =VLOOKUP(B82,'UV台帐'!B:AL,17,0) | I82: =VLOOKUP(B82,'UV台帐'!B:AL,18,0) | J82: =VLOOKUP(B82,'UV台帐'!B:AL,22,0) | K82: =VLOOKUP(B82,'UV台帐'!B:AL,24,0) | L82: =VLOOKUP(B82,'UV台帐'!B:AL,26,0) | M82: =VLOOKUP(B82,'UV台帐'!B:AL,27,0) | N82: =VLOOKUP(B82,'UV台帐'!B:AL,31,0) | O82: =VLOOKUP(B82,'UV台帐'!B:AL,33,0) | P82: =VLOOKUP(B82,'UV台帐'!B:AL,35,0) | Q82: =VLOOKUP(B82,'UV台帐'!B:AL,36,0) | R82: 是 | S82: A | T82: 否 | U82: 否 | W82: 数A英B 语文A | X82: 专注度不够，粗心 | Y82: 之前沟通的不多，校内数学，语文基础都在90左右徘徊，英语80希望暑假学习态度需要做下调整，孩子不主动学习，，这几天电话微信都没接，在群里有回复老师 | Z82: 之前沟通的不多，校内数学，语文基础都在90左右徘徊，英语80希望暑假学习态度需要做下调整，孩子不主动学习，，这几天电话微信都没接，在群里有回复老师 | AA82: 未沟通 | AB82: 之前沟通的不多，校内数学，语文基础都在90左右徘徊，英语80希望暑假学习态度需要做下调整，孩子不主动学习，妈妈家政行业，有问过价格，这几天电话微信都没接，在群里有回复老师 | AC82: 数,英 | AE82: 2-一般，对于目标需求一般 | AF82: 2-支付能力一般 | AG82: 2-一般 | AH82: 2-评价一般、无感 | AI82: 3-有规划有意识 | AJ82: A-11-13 | AK82: 陈中帅 | AL82: 是 | BF82: 王达04 | BG82: =VLOOKUP(B82,'UV台帐'!B:G,6,0) | BR82: =COUNTIFS(H82,"一期",I82,"在读")+COUNTIFS(L82,"一期",M82,"在读")+COUNTIFS(P82,"一期",Q82,"在读") | BS82: =BR82-BW82 | BT82: =VLOOKUP(B82,'UV台帐'!B:AL,19,0) | BU82: =VLOOKUP(B82,'UV台帐'!B:AL,28,0) | BV82: =VLOOKUP(B82,'UV台帐'!B:AL,37,0) | BW82: =COUNTIFS(H82,"一期",BT82,"是")+COUNTIFS(L82,"一期",BU82,"是")+COUNTIFS(P82,"一期",BV82,"是")
A83: 新宝利 | B83: 4635810658 | C83: =VLOOKUP(B83,'UV台帐'!B:AL,2,0) | D83: =VLOOKUP(B83,'UV台帐'!B:AL,3,0) | E83: =VLOOKUP(B83,'UV台帐'!B:AL,13,0) | F83: =VLOOKUP(B83,'UV台帐'!B:AL,15,0) | G83: =VLOOKUP(B83,'UV台帐'!B:AL,16,0) | H83: =VLOOKUP(B83,'UV台帐'!B:AL,17,0) | I83: =VLOOKUP(B83,'UV台帐'!B:AL,18,0) | J83: =VLOOKUP(B83,'UV台帐'!B:AL,22,0) | K83: =VLOOKUP(B83,'UV台帐'!B:AL,24,0) | L83: =VLOOKUP(B83,'UV台帐'!B:AL,26,0) | M83: =VLOOKUP(B83,'UV台帐'!B:AL,27,0) | N83: =VLOOKUP(B83,'UV台帐'!B:AL,31,0) | O83: =VLOOKUP(B83,'UV台帐'!B:AL,33,0) | P83: =VLOOKUP(B83,'UV台帐'!B:AL,35,0) | Q83: =VLOOKUP(B83,'UV台帐'!B:AL,36,0) | R83: 是 | S83: S | T83: 是 | U83: 否 | V83: 八一希望小学 | W83: 语95数95英95 | X83: 已报 | Z83: 零期学员已续报 | AA83: 明确需求 | AB83: 已续费 | AC83: 数 | AD83: 升学需求-进九大or中上,升学需求-保底本区公办高中 | AE83: 3-非常紧迫，有短期目标和长期需求 | AF83: 3-支付能力强 | AG83: 3-喜欢 | AH83: 3-有正面评价 | AI83: 3-有规划有意识 | AJ83: S-14-15 | AK83: 何咏04 | AL83: 是 | BF83: 王达04 | BG83: =VLOOKUP(B83,'UV台帐'!B:G,6,0) | BR83: =COUNTIFS(H83,"一期",I83,"在读")+COUNTIFS(L83,"一期",M83,"在读")+COUNTIFS(P83,"一期",Q83,"在读") | BS83: =BR83-BW83 | BT83: =VLOOKUP(B83,'UV台帐'!B:AL,19,0) | BU83: =VLOOKUP(B83,'UV台帐'!B:AL,28,0) | BV83: =VLOOKUP(B83,'UV台帐'!B:AL,37,0) | BW83: =COUNTIFS(H83,"一期",BT83,"是")+COUNTIFS(L83,"一期",BU83,"是")+COUNTIFS(P83,"一期",BV83,"是")
A84: 新宝利 | B84: 4240904687 | C84: =VLOOKUP(B84,'UV台帐'!B:AL,2,0) | D84: =VLOOKUP(B84,'UV台帐'!B:AL,3,0) | E84: =VLOOKUP(B84,'UV台帐'!B:AL,13,0) | F84: =VLOOKUP(B84,'UV台帐'!B:AL,15,0) | G84: =VLOOKUP(B84,'UV台帐'!B:AL,16,0) | H84: =VLOOKUP(B84,'UV台帐'!B:AL,17,0) | I84: =VLOOKUP(B84,'UV台帐'!B:AL,18,0) | J84: =VLOOKUP(B84,'UV台帐'!B:AL,22,0) | K84: =VLOOKUP(B84,'UV台帐'!B:AL,24,0) | L84: =VLOOKUP(B84,'UV台帐'!B:AL,26,0) | M84: =VLOOKUP(B84,'UV台帐'!B:AL,27,0) | N84: =VLOOKUP(B84,'UV台帐'!B:AL,31,0) | O84: =VLOOKUP(B84,'UV台帐'!B:AL,33,0) | P84: =VLOOKUP(B84,'UV台帐'!B:AL,35,0) | Q84: =VLOOKUP(B84,'UV台帐'!B:AL,36,0) | R84: 是 | S84: B | U84: 是 | V84: 三中 | W84: 270 | X84: 语文基础很一般，阅读理解需要体系化，写作都会用到ai，英语基础最差的，时态人称最基本的容易弄混淆，数学还不错，更多希望拓展，孩子六年级下册的英语退步了，做功课比较拖拉，审题单位换算容易忽略，需要圈画一些关键词，养成好学习习惯， | Y84: 看课程是否适合孩子。不是冲着价格优惠报进来的。 | Z84: 语文基础很一般，阅读理解需要体系化，写作都会用到ai，英语基础最差的，时态人称最基本的容易弄混淆，数学还不错，更多希望拓展，孩子六年级下册的英语退步了，做功课比较拖拉，审题单位换算容易忽略，需要圈画一些关键词，养成好学习习惯，看课程是否适合孩子。不是冲着价格优惠报进来的。 | AA84: 明确需求 | AB84: 学习情况：语文基础很一般，写作都会用到ai，英语基础最差的，时态人称最基本的容易弄混淆，数学还不错，孩子六年级下册的英语退步了，做功课比较拖拉，审题单位换算容易忽略 家长的需求：更多希望数学思维拓展，阅读理解需要体系化，需要圈画一些关键词，养成好学习习惯 意向判断：A;有意向长期学习，但是家长想多观望对比，所以续费周期可能比较长，之前是讲座转化的低价课，家长犹豫了很久，不是说价格低就马上报名占名额的，后面也问了秋季价格 规划：目前暂时没有明确升学思路，期望公立高中做保底 | AC84: 语,数,英 | AD84: 升学需求-保底本区公办高中,效果维度-提分,效果维度-抓习惯,效果维度-培优拓展/分班考,沟通维度：老师有个性化,沟通维度：老师有关注度 | AE84: 2-一般，对于目标需求一般 | AF84: 2-支付能力一般 | AG84: 3-喜欢 | AH84: 2-评价一般、无感 | AI84: 2-有意识无规划 | AJ84: A-11-13 | AK84: 何咏04 | AL84: 是 | BF84: 沈思浩 | BG84: =VLOOKUP(B84,'UV台帐'!B:G,6,0) | BR84: =COUNTIFS(H84,"一期",I84,"在读")+COUNTIFS(L84,"一期",M84,"在读")+COUNTIFS(P84,"一期",Q84,"在读") | BS84: =BR84-BW84 | BT84: =VLOOKUP(B84,'UV台帐'!B:AL,19,0) | BU84: =VLOOKUP(B84,'UV台帐'!B:AL,28,0) | BV84: =VLOOKUP(B84,'UV台帐'!B:AL,37,0) | BW84: =COUNTIFS(H84,"一期",BT84,"是")+COUNTIFS(L84,"一期",BU84,"是")+COUNTIFS(P84,"一期",BV84,"是")
A85: 新宝利 | B85: 4817190059 | C85: =VLOOKUP(B85,'UV台帐'!B:AL,2,0) | D85: =VLOOKUP(B85,'UV台帐'!B:AL,3,0) | E85: =VLOOKUP(B85,'UV台帐'!B:AL,13,0) | F85: =VLOOKUP(B85,'UV台帐'!B:AL,15,0) | G85: =VLOOKUP(B85,'UV台帐'!B:AL,16,0) | H85: =VLOOKUP(B85,'UV台帐'!B:AL,17,0) | I85: =VLOOKUP(B85,'UV台帐'!B:AL,18,0) | J85: =VLOOKUP(B85,'UV台帐'!B:AL,22,0) | K85: =VLOOKUP(B85,'UV台帐'!B:AL,24,0) | L85: =VLOOKUP(B85,'UV台帐'!B:AL,26,0) | M85: =VLOOKUP(B85,'UV台帐'!B:AL,27,0) | N85: =VLOOKUP(B85,'UV台帐'!B:AL,31,0) | O85: =VLOOKUP(B85,'UV台帐'!B:AL,33,0) | P85: =VLOOKUP(B85,'UV台帐'!B:AL,35,0) | Q85: =VLOOKUP(B85,'UV台帐'!B:AL,36,0) | R85: 是 | S85: B | T85: 是 | U85: 是 | V85: 满族小学/华侨 | W85: 250 | X85: 孩子学习全方位薄弱 | Y85: 家长前期教育意识比较淡薄，只是觉得初中要给孩子找个辅导班尝试一下，没有长期学习的打算。 | Z85: 家长前期教育意识比较淡薄，孩子程度薄弱。通过讲座认识到差距，课前有聊过暑秋的数学；问过价格。老人负责学习。考了课前诊断。 | AA85: 明确需求 | AB85: 基本情况：家长前期教育意识比较淡薄，没有课外辅导经历，孩子程度薄弱，特别是英语。目前对于升学没有想法，一步一步来。通过讲座认识到差距，课前有聊过暑秋的数学；问过价格。爸爸好像是纹身师还是酒吧老板。 需求判定：希望孩子来这里，提升孩子专注力，还有学生的字迹。希望课程过后，孩子第一次考试有理想发挥。数学科目相对孩子比较感兴趣，家长希望老师能提醒孩子勤思考。 | AC85: 数 | AD85: 效果维度-提分,效果维度-抓习惯,沟通维度：老师有关注度 | AE85: 2-一般，对于目标需求一般 | AF85: 2-支付能力一般 | AG85: 2-一般 | AH85: 2-评价一般、无感 | AI85: 1-无意识无规划 | AJ85: C-小于8 | AK85: 何咏04 | AL85: 是 | BF85: 陈亮延 | BG85: =VLOOKUP(B85,'UV台帐'!B:G,6,0) | BH85: 华侨中学 | BR85: =COUNTIFS(H85,"一期",I85,"在读")+COUNTIFS(L85,"一期",M85,"在读")+COUNTIFS(P85,"一期",Q85,"在读") | BS85: =BR85-BW85 | BT85: =VLOOKUP(B85,'UV台帐'!B:AL,19,0) | BU85: =VLOOKUP(B85,'UV台帐'!B:AL,28,0) | BV85: =VLOOKUP(B85,'UV台帐'!B:AL,37,0) | BW85: =COUNTIFS(H85,"一期",BT85,"是")+COUNTIFS(L85,"一期",BU85,"是")+COUNTIFS(P85,"一期",BV85,"是")
A86: 新宝利 | B86: 2529696621 | C86: =VLOOKUP(B86,'UV台帐'!B:AL,2,0) | D86: =VLOOKUP(B86,'UV台帐'!B:AL,3,0) | E86: =VLOOKUP(B86,'UV台帐'!B:AL,13,0) | F86: =VLOOKUP(B86,'UV台帐'!B:AL,15,0) | G86: =VLOOKUP(B86,'UV台帐'!B:AL,16,0) | H86: =VLOOKUP(B86,'UV台帐'!B:AL,17,0) | I86: =VLOOKUP(B86,'UV台帐'!B:AL,18,0) | J86: =VLOOKUP(B86,'UV台帐'!B:AL,22,0) | K86: =VLOOKUP(B86,'UV台帐'!B:AL,24,0) | L86: =VLOOKUP(B86,'UV台帐'!B:AL,26,0) | M86: =VLOOKUP(B86,'UV台帐'!B:AL,27,0) | N86: =VLOOKUP(B86,'UV台帐'!B:AL,31,0) | O86: =VLOOKUP(B86,'UV台帐'!B:AL,33,0) | P86: =VLOOKUP(B86,'UV台帐'!B:AL,35,0) | Q86: =VLOOKUP(B86,'UV台帐'!B:AL,36,0) | R86: 是 | S86: B | T86: 否 | U86: 是 | V86: 初中南海中学 | W86: 语80数90 | X86: 粗心，少阅读 | Y86: 重视初中难度，提前衔接 | Z86: 孩子奶奶，孩子爸爸一起负责孩子的学习，数学线上学猿辅导，语文猿辅导没效果，语文英语六上都是A,六下下滑到B了，英语听力不好，主要解决背单词听力的提升，语文孩子阅读差，没有阅读习惯。 | AA86: 明确需求 | AB86: 线上网课猿辅导，数学在学，学的不错所以没报数学，语文效果不好 学习负责人奶奶和爸爸，电话是奶奶的，群里拉了爸爸和孩子。 ，希望老师能多督促多要求，学习配合度高，但是提问不要太多正常好，孩子挺高大，就是不自信，回答问题会支支吾吾，希望通过更多的正面鼓励，改变孩子对单学科的信心，有利于孩子对于单学科的投入度，可以更好地促进续班转化。 语文英语六上都是A,六下下滑到B了，在家基本不背单词，不做语文阅读，英语听力不好，主要解决背单词听力的提升，语文孩子阅读差，没有阅读习惯。老师可以针对单词、语文的阅读单独做工，孩子有进步，及时提醒家长，并且同步我，我也去给家长做相应反馈，增加家长的体感和认可度 需要明确付费家长，跟爸爸沟通还是跟奶奶沟通。 | AC86: 语,英 | AD86: 效果维度-提分,效果维度-抓习惯 | AE86: 2-一般，对于目标需求一般 | AF86: 1-无支付能力 | AG86: 2-一般 | AH86: 2-评价一般、无感 | AI86: 2-有意识无规划 | AJ86: C-小于8 | AK86: 李润 | AL86: 是 | BF86: 王达04 | BG86: =VLOOKUP(B86,'UV台帐'!B:G,6,0) | BR86: =COUNTIFS(H86,"一期",I86,"在读")+COUNTIFS(L86,"一期",M86,"在读")+COUNTIFS(P86,"一期",Q86,"在读") | BS86: =BR86-BW86 | BT86: =VLOOKUP(B86,'UV台帐'!B:AL,19,0) | BU86: =VLOOKUP(B86,'UV台帐'!B:AL,28,0) | BV86: =VLOOKUP(B86,'UV台帐'!B:AL,37,0) | BW86: =COUNTIFS(H86,"一期",BT86,"是")+COUNTIFS(L86,"一期",BU86,"是")+COUNTIFS(P86,"一期",BV86,"是")
A87: 同创汇 | B87: 2163375170 | C87: =VLOOKUP(B87,'UV台帐'!B:AL,2,0) | D87: =VLOOKUP(B87,'UV台帐'!B:AL,3,0) | E87: =VLOOKUP(B87,'UV台帐'!B:AL,13,0) | F87: =VLOOKUP(B87,'UV台帐'!B:AL,15,0) | G87: =VLOOKUP(B87,'UV台帐'!B:AL,16,0) | H87: =VLOOKUP(B87,'UV台帐'!B:AL,17,0) | I87: =VLOOKUP(B87,'UV台帐'!B:AL,18,0) | J87: =VLOOKUP(B87,'UV台帐'!B:AL,22,0) | K87: =VLOOKUP(B87,'UV台帐'!B:AL,24,0) | L87: =VLOOKUP(B87,'UV台帐'!B:AL,26,0) | M87: =VLOOKUP(B87,'UV台帐'!B:AL,27,0) | N87: =VLOOKUP(B87,'UV台帐'!B:AL,31,0) | O87: =VLOOKUP(B87,'UV台帐'!B:AL,33,0) | P87: =VLOOKUP(B87,'UV台帐'!B:AL,35,0) | Q87: =VLOOKUP(B87,'UV台帐'!B:AL,36,0) | R87: 是 | S87: A | T87: 是 | U87: 否 | W87: 校内90+ | X87: 孩子比较懒，需要老师督促，妈妈几乎全程陪伴孩子上课 | Y87: 在读老生扩科 | Z87: 0期上数学语文，1期上英语，数学语文已续报 | AA87: 明确需求 | AB87: 暑假做小初衔接，孩子容易懒惰，自律性差，需要老师多监督，多关注，家长比较认老师，合适就会长期跟着学，目前语文数学已经报名秋季。英语老师多关注孩子上课听课情况，提醒孩子背单词，表现出负责，关爱，专业，妈妈经常都在校区陪孩子上课，可以多和家长面聊 | AC87: 语,数,英 | AD87: 效果维度-提分,效果维度-抓习惯,沟通维度：老师有个性化,沟通维度：老师有关注度 | AE87: 2-一般，对于目标需求一般 | AF87: 2-支付能力一般 | AG87: 2-一般 | AH87: 3-有正面评价 | AI87: 2-有意识无规划 | AJ87: A-11-13 | AK87: 高心怡04 | AL87: 0期已开 | BF87: 王丽 | BG87: =VLOOKUP(B87,'UV台帐'!B:G,6,0) | BR87: =COUNTIFS(H87,"一期",I87,"在读")+COUNTIFS(L87,"一期",M87,"在读")+COUNTIFS(P87,"一期",Q87,"在读") | BS87: =BR87-BW87 | BT87: =VLOOKUP(B87,'UV台帐'!B:AL,19,0) | BU87: =VLOOKUP(B87,'UV台帐'!B:AL,28,0) | BV87: =VLOOKUP(B87,'UV台帐'!B:AL,37,0) | BW87: =COUNTIFS(H87,"一期",BT87,"是")+COUNTIFS(L87,"一期",BU87,"是")+COUNTIFS(P87,"一期",BV87,"是")
A88: 天成大厦 | B88: 2226829869 | C88: =VLOOKUP(B88,'UV台帐'!B:AL,2,0) | D88: =VLOOKUP(B88,'UV台帐'!B:AL,3,0) | E88: =VLOOKUP(B88,'UV台帐'!B:AL,13,0) | F88: =VLOOKUP(B88,'UV台帐'!B:AL,15,0) | G88: =VLOOKUP(B88,'UV台帐'!B:AL,16,0) | H88: =VLOOKUP(B88,'UV台帐'!B:AL,17,0) | I88: =VLOOKUP(B88,'UV台帐'!B:AL,18,0) | J88: =VLOOKUP(B88,'UV台帐'!B:AL,22,0) | K88: =VLOOKUP(B88,'UV台帐'!B:AL,24,0) | L88: =VLOOKUP(B88,'UV台帐'!B:AL,26,0) | M88: =VLOOKUP(B88,'UV台帐'!B:AL,27,0) | N88: =VLOOKUP(B88,'UV台帐'!B:AL,31,0) | O88: =VLOOKUP(B88,'UV台帐'!B:AL,33,0) | P88: =VLOOKUP(B88,'UV台帐'!B:AL,35,0) | Q88: =VLOOKUP(B88,'UV台帐'!B:AL,36,0) | R88: 是 | S88: S | U88: 是 | V88: 龙口西帝景校区、广中 | W88: 270 hh | X88: 做题习惯不好，易粗心 | Y88: 做好衔接，逐步提升成绩 | Z88: 在读老生，暑秋联报英语、数学 | AC88: 数,英 | AK88: 陈中帅 | AL88: 是 | BF88: 龙倩敏 | BG88: =VLOOKUP(B88,'UV台帐'!B:G,6,0) | BR88: =COUNTIFS(H88,"一期",I88,"在读")+COUNTIFS(L88,"一期",M88,"在读")+COUNTIFS(P88,"一期",Q88,"在读") | BS88: =BR88-BW88 | BT88: =VLOOKUP(B88,'UV台帐'!B:AL,19,0) | BU88: =VLOOKUP(B88,'UV台帐'!B:AL,28,0) | BV88: =VLOOKUP(B88,'UV台帐'!B:AL,37,0) | BW88: =COUNTIFS(H88,"一期",BT88,"是")+COUNTIFS(L88,"一期",BU88,"是")+COUNTIFS(P88,"一期",BV88,"是")
A89: 天成大厦 | B89: 4050255637 | C89: =VLOOKUP(B89,'UV台帐'!B:AL,2,0) | D89: =VLOOKUP(B89,'UV台帐'!B:AL,3,0) | E89: =VLOOKUP(B89,'UV台帐'!B:AL,13,0) | F89: =VLOOKUP(B89,'UV台帐'!B:AL,15,0) | G89: =VLOOKUP(B89,'UV台帐'!B:AL,16,0) | H89: =VLOOKUP(B89,'UV台帐'!B:AL,17,0) | I89: =VLOOKUP(B89,'UV台帐'!B:AL,18,0) | J89: =VLOOKUP(B89,'UV台帐'!B:AL,22,0) | K89: =VLOOKUP(B89,'UV台帐'!B:AL,24,0) | L89: =VLOOKUP(B89,'UV台帐'!B:AL,26,0) | M89: =VLOOKUP(B89,'UV台帐'!B:AL,27,0) | N89: =VLOOKUP(B89,'UV台帐'!B:AL,31,0) | O89: =VLOOKUP(B89,'UV台帐'!B:AL,33,0) | P89: =VLOOKUP(B89,'UV台帐'!B:AL,35,0) | Q89: =VLOOKUP(B89,'UV台帐'!B:AL,36,0) | R89: 是 | S89: S | U89: 是 | Z89: 在读老生 | AK89: 陈中帅 | AL89: 是 | BF89: 王达04 | BG89: =VLOOKUP(B89,'UV台帐'!B:G,6,0) | BR89: =COUNTIFS(H89,"一期",I89,"在读")+COUNTIFS(L89,"一期",M89,"在读")+COUNTIFS(P89,"一期",Q89,"在读") | BS89: =BR89-BW89 | BT89: =VLOOKUP(B89,'UV台帐'!B:AL,19,0) | BU89: =VLOOKUP(B89,'UV台帐'!B:AL,28,0) | BV89: =VLOOKUP(B89,'UV台帐'!B:AL,37,0) | BW89: =COUNTIFS(H89,"一期",BT89,"是")+COUNTIFS(L89,"一期",BU89,"是")+COUNTIFS(P89,"一期",BV89,"是")
A90: 同创汇 | B90: 4310026061 | C90: =VLOOKUP(B90,'UV台帐'!B:AL,2,0) | D90: =VLOOKUP(B90,'UV台帐'!B:AL,3,0) | E90: =VLOOKUP(B90,'UV台帐'!B:AL,13,0) | F90: =VLOOKUP(B90,'UV台帐'!B:AL,15,0) | G90: =VLOOKUP(B90,'UV台帐'!B:AL,16,0) | H90: =VLOOKUP(B90,'UV台帐'!B:AL,17,0) | I90: =VLOOKUP(B90,'UV台帐'!B:AL,18,0) | J90: =VLOOKUP(B90,'UV台帐'!B:AL,22,0) | K90: =VLOOKUP(B90,'UV台帐'!B:AL,24,0) | L90: =VLOOKUP(B90,'UV台帐'!B:AL,26,0) | M90: =VLOOKUP(B90,'UV台帐'!B:AL,27,0) | N90: =VLOOKUP(B90,'UV台帐'!B:AL,31,0) | O90: =VLOOKUP(B90,'UV台帐'!B:AL,33,0) | P90: =VLOOKUP(B90,'UV台帐'!B:AL,35,0) | Q90: =VLOOKUP(B90,'UV台帐'!B:AL,36,0) | R90: 是 | S90: B | T90: 是 | U90: 是 | W90: 语文97.5,数学95，英语97.5 | X90: 孩子自驱力还可以，校内作业都能自觉完成 | Y90: 听了升学政策，认为孩子新初一衔接得学，想冲铁一中学的分层考 | Z90: 家长觉得没开课已经有5、6位老师找家长沟通了解情况了（0期转一期，加上前面的期末复习课等等原因），觉得流程很繁琐和复杂，家长沟通已经有情绪了，还说晚上12点还在反馈跟进，很打扰。行课期间三位主教老师和家长沟通反馈尽量早些哈，电访同一天不要三位老师同时找家长沟通咯。 | AA90: 未明确需求 | AB90: 孩子爸爸抗拒沟通 | AC90: 语,数,英 | AD90: 升学需求-保底本区公办高中,效果维度-培优拓展/分班考,沟通维度：老师有关注度 | AE90: 2-一般，对于目标需求一般 | AF90: 2-支付能力一般 | AG90: 2-一般 | AH90: 1-有雷点、槽点 | AI90: 2-有意识无规划 | AJ90: B-8-10 | AK90: 陈南05 | AL90: 是 | BF90: 苏丽婷 | BG90: =VLOOKUP(B90,'UV台帐'!B:G,6,0) | BR90: =COUNTIFS(H90,"一期",I90,"在读")+COUNTIFS(L90,"一期",M90,"在读")+COUNTIFS(P90,"一期",Q90,"在读") | BS90: =BR90-BW90 | BT90: =VLOOKUP(B90,'UV台帐'!B:AL,19,0) | BU90: =VLOOKUP(B90,'UV台帐'!B:AL,28,0) | BV90: =VLOOKUP(B90,'UV台帐'!B:AL,37,0) | BW90: =COUNTIFS(H90,"一期",BT90,"是")+COUNTIFS(L90,"一期",BU90,"是")+COUNTIFS(P90,"一期",BV90,"是")
A91: 新宝利 | B91: 2515578569 | C91: =VLOOKUP(B91,'UV台帐'!B:AL,2,0) | D91: =VLOOKUP(B91,'UV台帐'!B:AL,3,0) | E91: =VLOOKUP(B91,'UV台帐'!B:AL,13,0) | F91: =VLOOKUP(B91,'UV台帐'!B:AL,15,0) | G91: =VLOOKUP(B91,'UV台帐'!B:AL,16,0) | H91: =VLOOKUP(B91,'UV台帐'!B:AL,17,0) | I91: =VLOOKUP(B91,'UV台帐'!B:AL,18,0) | J91: =VLOOKUP(B91,'UV台帐'!B:AL,22,0) | K91: =VLOOKUP(B91,'UV台帐'!B:AL,24,0) | L91: =VLOOKUP(B91,'UV台帐'!B:AL,26,0) | M91: =VLOOKUP(B91,'UV台帐'!B:AL,27,0) | N91: =VLOOKUP(B91,'UV台帐'!B:AL,31,0) | O91: =VLOOKUP(B91,'UV台帐'!B:AL,33,0) | P91: =VLOOKUP(B91,'UV台帐'!B:AL,35,0) | Q91: =VLOOKUP(B91,'UV台帐'!B:AL,36,0) | R91: 是 | S91: C | T91: 是 | U91: 否 | V91: 三中 | W91: 3a | X91: 孩子对知识理解，但是不爱做题，家里有点放养式的 | Y91: 提前学应对三中的分层 | Z91: 孩子发烧，从0期调过来的，配合度不高，不怎么管孩子。C，想暑假当个托管。 | AA91: 明确需求 | AB91: 孩子成绩一般，比较调皮，从0期转到一期的，只上了4节课，上课不积极，家长也不怎么管孩子学习，课堂纪律也不太好，妈妈觉得孩子报课就是让老师全权负责的，妈妈是希望孩子自己能意识到学习的重要性，之前第5讲邀约过线下家长会，家长情绪比较激动。说没时间参加，线上不可以吗，搞这么麻烦，说在开车就挂了，知道秋季价格，表示贵 | AC91: 数,英 | AD91: 效果维度-提分,效果维度-抓习惯,沟通维度：老师有个性化 | AE91: 2-一般，对于目标需求一般 | AF91: 1-无支付能力 | AG91: 1-抵触 | AH91: 1-有雷点、槽点 | AI91: 2-有意识无规划 | AJ91: C-小于8 | AK91: 李润 | BF91: 张敏烨 | BG91: =VLOOKUP(B91,'UV台帐'!B:G,6,0) | BR91: =COUNTIFS(H91,"一期",I91,"在读")+COUNTIFS(L91,"一期",M91,"在读")+COUNTIFS(P91,"一期",Q91,"在读") | BS91: =BR91-BW91 | BT91: =VLOOKUP(B91,'UV台帐'!B:AL,19,0) | BU91: =VLOOKUP(B91,'UV台帐'!B:AL,28,0) | BV91: =VLOOKUP(B91,'UV台帐'!B:AL,37,0) | BW91: =COUNTIFS(H91,"一期",BT91,"是")+COUNTIFS(L91,"一期",BU91,"是")+COUNTIFS(P91,"一期",BV91,"是")
